Workbook

Sheet 1-10
A2: i Wall@
A3: SharpSing Limited
A4: Room 1609, 16/F., Golden Era Plaza, No. 39 Sai Yee Street, Mongkok, KLN. Tel:35868635 Fax:31889330
B6: =Total!$A$2 -> 2026 Jun Century Field Promoter Salary Summary
B8: Name/姓名 | C8: =Total!$E$8 -> Tan Xing Fang | D8: {=INDEX(Total!$D$8:$D$31,MATCH($C8&$G8,Total!$E$8:$E$31&Total!#REF!,0))} -> #REF! | F8: CQ NO. | G8: =Total!#REF! -> #REF!
B10: Job Detail | E10: Content
B11: Job Categories/工作類別 | E11: Promoter
B12: Location/工作地點 | E12: {=INDEX(Total!$F$8:$F$31,MATCH($C8&$G8,Total!$E$8:$E$31&Total!#REF!,0))} -> #REF!
B13: Period/工作日子 | E13: {=INDEX(Total!$G$8:$G$31,MATCH($C8&$G8,Total!$E$8:$E$31&Total!#REF!,0))} -> #REF!
B14: Reg.Day/工作日數 | E14: {=INDEX(Total!$H$8:$H$31,MATCH($C8&$G8,Total!$E$8:$E$31&Total!#REF!,0))} -> #REF!
B15: Reg.Hour/工作時數 | E15: {=INDEX(Total!$I$8:$I$31,MATCH($C8&$G8,Total!$E$8:$E$31&Total!#REF!,0))} -> #REF!
B16: HK$/時薪 | E16: {=INDEX(Total!$J$8:$J$31,MATCH($C8&$G8,Total!$E$8:$E$31&Total!#REF!,0))} -> #REF!
B17: Sales Record/銷售紀錄 | E17: {=INDEX(Total!$L$8:$L$31,MATCH($C8&$G8,Total!$E$8:$E$31&Total!#REF!,0))} -> #REF!
C19: Salary Detail | F19: Sub. Total
C20: Basic/酬金 | G20: {=INDEX(Total!$K$8:$K$31,MATCH($C8&$G8,Total!$E$8:$E$31&Total!#REF!,0))} -> #REF!
C21: Attendance/出勤 | G21: {=INDEX(Total!$Q$8:$Q$31,MATCH($C8&$G8,Total!$E$8:$E$31&Total!#REF!,0))} -> #REF!
C22: Commission/佣金 | G22: =Total!N8 -> 3675.186
C23: Allowance/津貼 | G23: {=INDEX(Total!$R$8:$R$31,MATCH($C8&$G8,Total!$E$8:$E$31&Total!#REF!,0))} -> #REF!
C24: Award/獎金 | G24: {=INDEX(Total!#REF!,MATCH($C8&$G8,Total!$E$8:$E$31&Total!#REF!,0))} -> #REF!
C25: Expenses/支出 | G25: {=INDEX(Total!$S$8:$S$31,MATCH($C8&$G8,Total!$E$8:$E$31&Total!#REF!,0))} -> #REF!
C26: Other/其他 | G26: {=INDEX(Total!#REF!,MATCH($C8&$G8,Total!$E$8:$E$31&Total!#REF!,0))} -> #REF!
C27: Adjustment/調整 | G27: {=INDEX(Total!$T$8:$T$31,MATCH($C8&$G8,Total!$E$8:$E$31&Total!#REF!,0))} -> #REF!
C28: MPF/強積金** | G28: {=-INDEX(Total!$U$8:$U$31,MATCH($C8&$G8,Total!$E$8:$E$31&Total!#REF!,0))} -> #REF!
E29: Total | F29: =SUM($G20:$G28) -> #REF! | J29: {=INDEX(Total!$W$8:$W$31,MATCH($C8&$G8,Total!$E$8:$E$31&Total!#REF!,0))} -> #REF!
B31: **如屬自僱人仕必須自行購買勞工保險及強積金；
B32: 註 1：如所支付之金額有錯誤，請在兩天內提出；
B33: 註 2：請自行核對清楚支票上的姓名及金額；
E34: Promoter 確認簽名 :
F36: I.D. Card No. :
A39: i Wall@
A40: SharpSing Limited
A41: Room 1609, 16/F., Golden Era Plaza, No. 39 Sai Yee Street, Mongkok, KLN. Tel:35868635 Fax:31889330
B43: =Total!$A$2 -> 2026 Jun Century Field Promoter Salary Summary
B45: Name/姓名 | C45: =Total!$E$9 -> Yuen Maria Wing Yan | D45: {=INDEX(Total!$D$8:$D$31,MATCH($C45&$G45,Total!$E$8:$E$31&Total!#REF!,0))} -> #REF! | F45: CQ NO. | G45: =Total!#REF! -> #REF!
B47: Job Detail | E47: Content
B48: Job Categories/工作類別 | E48: Promoter
B49: Location/工作地點 | E49: {=INDEX(Total!$F$8:$F$31,MATCH($C45&$G45,Total!$E$8:$E$31&Total!#REF!,0))} -> #REF!
B50: Period/工作日子 | E50: {=INDEX(Total!$G$8:$G$31,MATCH($C45&$G45,Total!$E$8:$E$31&Total!#REF!,0))} -> #REF!
B51: Reg.Day/工作日數 | E51: {=INDEX(Total!$H$8:$H$31,MATCH($C45&$G45,Total!$E$8:$E$31&Total!#REF!,0))} -> #REF!
B52: Reg.Hour/工作時數 | E52: {=INDEX(Total!$I$8:$I$31,MATCH($C45&$G45,Total!$E$8:$E$31&Total!#REF!,0))} -> #REF!
B53: HK$/時薪 | E53: {=INDEX(Total!$J$8:$J$31,MATCH($C45&$G45,Total!$E$8:$E$31&Total!#REF!,0))} -> #REF!
B54: Sales Record/銷售紀錄 | E54: {=INDEX(Total!$L$8:$L$31,MATCH($C45&$G45,Total!$E$8:$E$31&Total!#REF!,0))} -> #REF!
C56: Salary Detail | F56: Sub. Total
C57: Basic/酬金 | G57: {=INDEX(Total!$K$8:$K$31,MATCH($C45&$G45,Total!$E$8:$E$31&Total!#REF!,0))} -> #REF!
C58: Attendance/出勤 | G58: {=INDEX(Total!$Q$8:$Q$31,MATCH($C45&$G45,Total!$E$8:$E$31&Total!#REF!,0))} -> #REF!
C59: Commission/佣金 | G59: {=INDEX(Total!$N$8:$N$31,MATCH($C45&$G45,Total!$E$8:$E$31&Total!#REF!,0))} -> #REF!
C60: Allowance/津貼 | G60: {=INDEX(Total!$R$8:$R$31,MATCH($C45&$G45,Total!$E$8:$E$31&Total!#REF!,0))} -> #REF!
C61: Award/獎金 | G61: {=INDEX(Total!#REF!,MATCH($C45&$G45,Total!$E$8:$E$31&Total!#REF!,0))} -> #REF!
C62: Expenses/支出 | G62: {=INDEX(Total!$S$8:$S$31,MATCH($C45&$G45,Total!$E$8:$E$31&Total!#REF!,0))} -> #REF!
C63: Other/其他 | G63: {=INDEX(Total!#REF!,MATCH($C45&$G45,Total!$E$8:$E$31&Total!#REF!,0))} -> #REF!
C64: Adjustment/調整 | G64: {=INDEX(Total!$T$8:$T$31,MATCH($C45&$G45,Total!$E$8:$E$31&Total!#REF!,0))} -> #REF!
C65: MPF/強積金** | G65: {=-INDEX(Total!$U$8:$U$31,MATCH($C45&$G45,Total!$E$8:$E$31&Total!#REF!,0))} -> #REF!
E66: Total | F66: =SUM($G57:$G65) -> #REF! | J66: {=INDEX(Total!$W$8:$W$31,MATCH($C45&$G45,Total!$E$8:$E$31&Total!#REF!,0))} -> #REF!
B68: **如屬自僱人仕必須自行購買勞工保險及強積金；
B69: 註 1：如所支付之金額有錯誤，請在兩天內提出；
B70: 註 2：請自行核對清楚支票上的姓名及金額；
E71: Promoter 確認簽名 :
F73: I.D. Card No. :
A76: i Wall@
A77: SharpSing Limited
A78: Room 1609, 16/F., Golden Era Plaza, No. 39 Sai Yee Street, Mongkok, KLN. Tel:35868635 Fax:31889330
B80: =Total!$A$2 -> 2026 Jun Century Field Promoter Salary Summary
B82: Name/姓名 | C82: =Total!$E$10 -> Lo Chun Wah | D82: {=INDEX(Total!$D$8:$D$31,MATCH($C82&$G82,Total!$E$8:$E$31&Total!#REF!,0))} -> #REF! | F82: CQ NO. | G82: =Total!#REF! -> #REF!
B84: Job Detail | E84: Content
B85: Job Categories/工作類別 | E85: Promoter
B86: Location/工作地點 | E86: {=INDEX(Total!$F$8:$F$31,MATCH($C82&$G82,Total!$E$8:$E$31&Total!#REF!,0))} -> #REF!
B87: Period/工作日子 | E87: {=INDEX(Total!$G$8:$G$31,MATCH($C82&$G82,Total!$E$8:$E$31&Total!#REF!,0))} -> #REF!
B88: Reg.Day/工作日數 | E88: {=INDEX(Total!$H$8:$H$31,MATCH($C82&$G82,Total!$E$8:$E$31&Total!#REF!,0))} -> #REF!
B89: Reg.Hour/工作時數 | E89: {=INDEX(Total!$I$8:$I$31,MATCH($C82&$G82,Total!$E$8:$E$31&Total!#REF!,0))} -> #REF!
B90: HK$/時薪 | E90: {=INDEX(Total!$J$8:$J$31,MATCH($C82&$G82,Total!$E$8:$E$31&Total!#REF!,0))} -> #REF!
B91: Sales Record/銷售紀錄 | E91: {=INDEX(Total!$L$8:$L$31,MATCH($C82&$G82,Total!$E$8:$E$31&Total!#REF!,0))} -> #REF!
C93: Salary Detail | F93: Sub. Total
C94: Basic/酬金 | G94: {=INDEX(Total!$K$8:$K$31,MATCH($C82&$G82,Total!$E$8:$E$31&Total!#REF!,0))} -> #REF!
C95: Attendance/出勤 | G95: {=INDEX(Total!$Q$8:$Q$31,MATCH($C82&$G82,Total!$E$8:$E$31&Total!#REF!,0))} -> #REF!
C96: Commission/佣金 | G96: {=INDEX(Total!$N$8:$N$31,MATCH($C82&$G82,Total!$E$8:$E$31&Total!#REF!,0))} -> #REF!
C97: Allowance/津貼 | G97: {=INDEX(Total!$R$8:$R$31,MATCH($C82&$G82,Total!$E$8:$E$31&Total!#REF!,0))} -> #REF!
C98: Award/獎金 | G98: {=INDEX(Total!#REF!,MATCH($C82&$G82,Total!$E$8:$E$31&Total!#REF!,0))} -> #REF!
C99: Expenses/支出 | G99: {=INDEX(Total!$S$8:$S$31,MATCH($C82&$G82,Total!$E$8:$E$31&Total!#REF!,0))} -> #REF!
C100: Other/其他 | G100: {=INDEX(Total!#REF!,MATCH($C82&$G82,Total!$E$8:$E$31&Total!#REF!,0))} -> #REF!
C101: Adjustment/調整 | G101: {=INDEX(Total!$T$8:$T$31,MATCH($C82&$G82,Total!$E$8:$E$31&Total!#REF!,0))} -> #REF!
C102: MPF/強積金** | G102: {=-INDEX(Total!$U$8:$U$31,MATCH($C82&$G82,Total!$E$8:$E$31&Total!#REF!,0))} -> #REF!
E103: Total | F103: =SUM($G94:$G102) -> #REF! | J103: {=INDEX(Total!$W$8:$W$31,MATCH($C82&$G82,Total!$E$8:$E$31&Total!#REF!,0))} -> #REF!
B105: **如屬自僱人仕必須自行購買勞工保險及強積金；
B106: 註 1：如所支付之金額有錯誤，請在兩天內提出；
B107: 註 2：請自行核對清楚支票上的姓名及金額；
E108: Promoter 確認簽名 :
F110: I.D. Card No. :
A113: i Wall@
A114: SharpSing Limited
A115: Room 1609, 16/F., Golden Era Plaza, No. 39 Sai Yee Street, Mongkok, KLN. Tel:35868635 Fax:31889330
B117: =Total!$A$2 -> 2026 Jun Century Field Promoter Salary Summary
B119: Name/姓名 | C119: =Total!$E$11 -> Lok Yin Ling | D119: {=INDEX(Total!$D$8:$D$31,MATCH($C119&$G119,Total!$E$8:$E$31&Total!#REF!,0))} -> #REF! | F119: CQ NO. | G119: =Total!#REF! -> #REF!
B121: Job Detail | E121: Content
B122: Job Categories/工作類別 | E122: Promoter
B123: Location/工作地點 | E123: {=INDEX(Total!$F$8:$F$31,MATCH($C119&$G119,Total!$E$8:$E$31&Total!#REF!,0))} -> #REF!
B124: Period/工作日子 | E124: {=INDEX(Total!$G$8:$G$31,MATCH($C119&$G119,Total!$E$8:$E$31&Total!#REF!,0))} -> #REF!
B125: Reg.Day/工作日數 | E125: {=INDEX(Total!$H$8:$H$31,MATCH($C119&$G119,Total!$E$8:$E$31&Total!#REF!,0))} -> #REF!
B126: Reg.Hour/工作時數 | E126: {=INDEX(Total!$I$8:$I$31,MATCH($C119&$G119,Total!$E$8:$E$31&Total!#REF!,0))} -> #REF!
B127: HK$/時薪 | E127: {=INDEX(Total!$J$8:$J$31,MATCH($C119&$G119,Total!$E$8:$E$31&Total!#REF!,0))} -> #REF!
B128: Sales Record/銷售紀錄 | E128: {=INDEX(Total!$L$8:$L$31,MATCH($C119&$G119,Total!$E$8:$E$31&Total!#REF!,0))} -> #REF!
...

Sheet 11-20
A2: i Wall@
A3: SharpSing Limited
A4: Room 1609, 16/F., Golden Era Plaza, No. 39 Sai Yee Street, Mongkok, KLN. Tel:35868635 Fax:31889330
B6: =Total!$A$2 -> 2026 Jun Century Field Promoter Salary Summary
B8: Name/姓名 | C8: =Total!E15 -> Siu Wai Ling | D8: =Total!D15 -> Margaret | F8: CQ NO. | G8: =Total!#REF! -> #REF!
B10: Job Detail | E10: Content
B11: Job Categories/工作類別 | E11: Promoter
B12: Location/工作地點 | E12: =Total!#REF! -> #REF!
B13: Period/工作日子 | E13: =Total!G15 -> 5,6,7,12,13,14,19,20,21,25,29/Jun
B14: Reg.Day/工作日數 | E14: =Total!H15 -> 11
B15: Reg.Hour/工作時數 | E15: =Total!I15 -> 88
B16: HK$/時薪 | E16: =Total!J15 -> 56.25
B17: Sales Record/銷售紀錄 | E17: =Total!L15 -> 159644
C19: Salary Detail | F19: Sub. Total
C20: Basic/酬金 | G20: =Total!K15 -> 4950
C21: Attendance/出勤 | G21: =Total!Q15 -> 0
C22: Commission/佣金 | G22: =Total!N15 -> 4789.32
C23: Allowance/津貼 | G23: =Total!R15 -> 0
C24: Award/獎金 | G24: =Total!#REF! -> #REF!
C25: Expenses/支出 | G25: =Total!S15 -> 0
C26: Other/其他 | G26: =Total!#REF! -> #REF!
C27: Adjustment/調整 | G27: =Total!T15 -> 0
C28: MPF/強積金** | G28: =Total!U15 -> 0
E29: Total | F29: =SUM(G20:G27)-G28 -> #REF! | J29: =Total!V15 -> 9739.32
B31: **如屬自僱人仕必須自行購買勞工保險及強積金；
B32: 註 1：如所支付之金額有錯誤，請在兩天內提出；
B33: 註 2：請自行核對清楚支票上的姓名及金額；
E34: Promoter 確認簽名 :
F36: I.D. Card No. :
A39: i Wall@
A40: SharpSing Limited
A41: Room 1609, 16/F., Golden Era Plaza, No. 39 Sai Yee Street, Mongkok, KLN. Tel:35868635 Fax:31889330
B43: =Total!$A$2 -> 2026 Jun Century Field Promoter Salary Summary
B45: Name/姓名 | C45: =Total!E16 -> Siu Wai Ling | D45: =Total!D16 -> Margaret | F45: CQ NO. | G45: =Total!#REF! -> #REF!
B47: Job Detail | E47: Content
B48: Job Categories/工作類別 | E48: Promoter
B49: Location/工作地點 | E49: =Total!G16 -> 1,2,8,9,15,22,23/Jun
B50: Period/工作日子 | E50: =Total!#REF! -> #REF!
B51: Reg.Day/工作日數 | E51: =Total!H16 -> 7
B52: Reg.Hour/工作時數 | E52: =Total!I16 -> 56
B53: HK$/時薪 | E53: =Total!J16 -> 56.25
B54: Sales Record/銷售紀錄 | E54: =Total!L16 -> 55390
C56: Salary Detail | F56: Sub. Total
C57: Basic/酬金 | G57: =Total!K16 -> 3150
C58: Attendance/出勤 | G58: =Total!Q16 -> 0
C59: Commission/佣金 | G59: =Total!N16 -> 1661.7
C60: Allowance/津貼 | G60: =Total!R16 -> 0
C61: Award/獎金 | G61: =Total!#REF! -> #REF!
C62: Expenses/支出 | G62: =Total!S16 -> 0
C63: Other/其他 | G63: =Total!#REF! -> #REF!
C64: Adjustment/調整 | G64: =Total!T16 -> 0
C65: MPF/強積金** | G65: =Total!U16 -> 0
E66: Total | F66: =SUM(G57:G64)-G65 -> #REF! | J66: =Total!V16 -> 4811.7
B68: **如屬自僱人仕必須自行購買勞工保險及強積金；
B69: 註 1：如所支付之金額有錯誤，請在兩天內提出；
B70: 註 2：請自行核對清楚支票上的姓名及金額；
E71: Promoter 確認簽名 :
F73: I.D. Card No. :
A76: i Wall@
A77: SharpSing Limited
A78: Room 1609, 16/F., Golden Era Plaza, No. 39 Sai Yee Street, Mongkok, KLN. Tel:35868635 Fax:31889330
B80: =Total!$A$2 -> 2026 Jun Century Field Promoter Salary Summary
B82: Name/姓名 | C82: =Total!E29 -> 0 | D82: =Total!D29 -> 0 | F82: CQ NO. | G82: =Total!#REF! -> #REF!
B84: Job Detail | E84: Content
B85: Job Categories/工作類別 | E85: Promoter
B86: Location/工作地點 | E86: =Total!F17 -> 21191
B87: Period/工作日子 | E87: =Total!#REF! -> #REF!
B88: Reg.Day/工作日數 | E88: =Total!H29 -> 0
B89: Reg.Hour/工作時數 | E89: =Total!I29 -> 0
B90: HK$/時薪 | E90: =Total!J29 -> 0
B91: Sales Record/銷售紀錄 | E91: =Total!L29 -> 0
C93: Salary Detail | F93: Sub. Total
C94: Basic/酬金 | G94: =Total!K29 -> 0
C95: Attendance/出勤 | G95: =Total!Q29 -> 0
C96: Commission/佣金 | G96: =Total!N29 -> 0
C97: Allowance/津貼 | G97: =Total!R29 -> 0
C98: Award/獎金 | G98: =Total!#REF! -> #REF!
C99: Expenses/支出 | G99: =Total!S29 -> 0
C100: Other/其他 | G100: =Total!#REF! -> #REF!
C101: Adjustment/調整 | G101: =Total!T29 -> 0
C102: MPF/強積金** | G102: =Total!U29 -> 0
E103: Total | F103: =SUM(G94:G101)-G102 -> #REF! | J103: =Total!V29 -> 0
B105: **如屬自僱人仕必須自行購買勞工保險及強積金；
B106: 註 1：如所支付之金額有錯誤，請在兩天內提出；
B107: 註 2：請自行核對清楚支票上的姓名及金額；
E108: Promoter 確認簽名 :
F110: I.D. Card No. :
A113: i Wall@
A114: SharpSing Limited
A115: Room 1609, 16/F., Golden Era Plaza, No. 39 Sai Yee Street, Mongkok, KLN. Tel:35868635 Fax:31889330
B117: =Total!$A$2 -> 2026 Jun Century Field Promoter Salary Summary
B119: Name/姓名 | C119: =Total!E30 -> 0 | D119: =Total!D30 -> 0 | F119: CQ NO. | G119: =Total!#REF! -> #REF!
B121: Job Detail | E121: Content
B122: Job Categories/工作類別 | E122: Promoter
B123: Location/工作地點 | E123: =Total!F29 -> 0
B124: Period/工作日子 | E124: =Total!G30 -> 0
B125: Reg.Day/工作日數 | E125: =Total!H30 -> 0
B126: Reg.Hour/工作時數 | E126: =Total!I30 -> 0
B127: HK$/時薪 | E127: =Total!J30 -> 0
B128: Sales Record/銷售紀錄 | E128: =Total!L30 -> 0
...

Sheet Roster
A1: 要入當月1號日期>>>>> | B1: 46174 | C1: =YEAR(B1) -> 2026 | D1: =MONTH(B1) -> 6
A4: 保護工作表PW:1234 | AH4: Man Day | AI4: Hours
B5: 2026 Jun | AH5: =SUBTOTAL(9,AH8:AH31) -> 155 | AI5: =SUBTOTAL(9,AI8:AI31) -> 1240 | AL5: =B5 -> 2026 Jun
C6: =TEXT($C$1&"/"&$D$1&"/"&C7,"ddd") -> Mon | D6: =TEXT($C$1&"/"&$D$1&"/"&D7,"ddd") -> Tue | E6: =TEXT($C$1&"/"&$D$1&"/"&E7,"ddd") -> Wed | F6: =TEXT($C$1&"/"&$D$1&"/"&F7,"ddd") -> Thu | G6: =TEXT($C$1&"/"&$D$1&"/"&G7,"ddd") -> Fri | H6: =TEXT($C$1&"/"&$D$1&"/"&H7,"ddd") -> Sat | I6: =TEXT($C$1&"/"&$D$1&"/"&I7,"ddd") -> Sun | J6: =TEXT($C$1&"/"&$D$1&"/"&J7,"ddd") -> Mon | ... AG6: =TEXT($C$1&"/"&$D$1&"/"&AG7,"ddd") -> 2026/6/31 | AM6: =C6 -> Mon | AN6: =D6 -> Tue | AO6: =E6 -> Wed | AP6: =F6 -> Thu | AQ6: =G6 -> Fri | AR6: =H6 -> Sat | AS6: =I6 -> Sun | AT6: =J6 -> Mon | ... BQ6: =AG6 -> 2026/6/31 | BR6: =#REF! -> #REF! | BS6: =#REF! -> #REF!
A7: 以下溢出代表時間表個頁相同location n date,不同人 | B7: 以下不用入location… | C7: =DAY(B1) -> 1 | D7: =C7+1 -> 2 | E7: =D7+1 -> 3 | F7: =E7+1 -> 4 | G7: =F7+1 -> 5 | H7: =G7+1 -> 6 | I7: =H7+1 -> 7 | J7: =I7+1 -> 8 | K7: =J7+1 -> 9 | ... AG7: =AF7+1 -> 31 | AM7: =C7 -> 1 | AN7: =D7 -> 2 | AO7: =E7 -> 3 | AP7: =F7 -> 4 | AQ7: =G7 -> 5 | AR7: =H7 -> 6 | AS7: =I7 -> 7 | AT7: =J7 -> 8 | ... BQ7: =AG7 -> 31 | BR7: =#REF! -> #REF! | BS7: =#REF! -> #REF!
A8: {=_xlfn.LET( _xlpm.data, C8:AG8, _xlpm.removeList, {" off","."," SL","xxx"}, _xlpm.cleaned, TRIM(_xlfn.REDUCE(_xlpm.data, _xlpm.removeList, _xlfn.LAMBDA(_xlpm.arr,_xlpm.str, SUBSTITUTE(_xlpm.arr, _xlpm.str, "")))), _xlpm.first, _xlfn._xlws.FILTER(_xlpm.cleaned, _xlpm.cleaned <> ""), INDEX(_xlpm.first, 1) )} -> Margaret | B8: {=_xlfn.ANCHORARRAY('Name List'!$K$3)} -> Central Fortress | C8: {=_xlfn.LET( _xlpm.data, 表格3_5[[Date]:[Location]], _xlpm.date_col, INDEX(_xlpm.data, , 1), _xlpm.name_col, INDEX(_xlpm.data, , 2), _xlpm.loc_col, INDEX(_xlpm.data, , 3), _xlpm.target_date, DATE(YEAR($B$1), MONTH($B$1), C$7), _xlpm.filtered, _xlfn._xlws.FILTER(_xlpm.name_col, (_xlpm.date_col = _xlpm.target_date) * (_xlpm.loc_col =$B8), ""), IF(_xlpm.filtered="", "", _xlpm.filtered) )} -> Margaret | D8: {=_xlfn.LET( _xlpm.data, 表格3_5[[Date]:[Location]], _xlpm.date_col, INDEX(_xlpm.data, , 1), _xlpm.name_col, INDEX(_xlpm.data, , 2), _xlpm.loc_col, INDEX(_xlpm.data, , 3), _xlpm.target_date, DATE(YEAR($B$1), MONTH($B$1), D$7), _xlpm.filtered, _xlfn._xlws.FILTER(_xlpm.name_col, (_xlpm.date_col = _xlpm.target_date) * (_xlpm.loc_col =$B8), ""), IF(_xlpm.filtered="", "", _xlpm.filtered) )} -> Margaret | E8: {=_xlfn.LET( _xlpm.data, 表格3_5[[Date]:[Location]], _xlpm.date_col, INDEX(_xlpm.data, , 1), _xlpm.name_col, INDEX(_xlpm.data, , 2), _xlpm.loc_col, INDEX(_xlpm.data, , 3), _xlpm.target_date, DATE(YEAR($B$1), MONTH($B$1), E$7), _xlpm.filtered, _xlfn._xlws.FILTER(_xlpm.name_col, (_xlpm.date_col = _xlpm.target_date) * (_xlpm.loc_col =$B8), ""), IF(_xlpm.filtered="", "", _xlpm.filtered) )} | F8: {=_xlfn.LET( _xlpm.data, 表格3_5[[Date]:[Location]], _xlpm.date_col, INDEX(_xlpm.data, , 1), _xlpm.name_col, INDEX(_xlpm.data, , 2), _xlpm.loc_col, INDEX(_xlpm.data, , 3), _xlpm.target_date, DATE(YEAR($B$1), MONTH($B$1), F$7), _xlpm.filtered, _xlfn._xlws.FILTER(_xlpm.name_col, (_xlpm.date_col = _xlpm.target_date) * (_xlpm.loc_col =$B8), ""), IF(_xlpm.filtered="", "", _xlpm.filtered) )} | G8: {=_xlfn.LET( _xlpm.data, 表格3_5[[Date]:[Location]], _xlpm.date_col, INDEX(_xlpm.data, , 1), _xlpm.name_col, INDEX(_xlpm.data, , 2), _xlpm.loc_col, INDEX(_xlpm.data, , 3), _xlpm.target_date, DATE(YEAR($B$1), MONTH($B$1), G$7), _xlpm.filtered, _xlfn._xlws.FILTER(_xlpm.name_col, (_xlpm.date_col = _xlpm.target_date) * (_xlpm.loc_col =$B8), ""), IF(_xlpm.filtered="", "", _xlpm.filtered) )} | H8: {=_xlfn.LET( _xlpm.data, 表格3_5[[Date]:[Location]], _xlpm.date_col, INDEX(_xlpm.data, , 1), _xlpm.name_col, INDEX(_xlpm.data, , 2), _xlpm.loc_col, INDEX(_xlpm.data, , 3), _xlpm.target_date, DATE(YEAR($B$1), MONTH($B$1), H$7), _xlpm.filtered, _xlfn._xlws.FILTER(_xlpm.name_col, (_xlpm.date_col = _xlpm.target_date) * (_xlpm.loc_col =$B8), ""), IF(_xlpm.filtered="", "", _xlpm.filtered) )} | I8: {=_xlfn.LET( _xlpm.data, 表格3_5[[Date]:[Location]], _xlpm.date_col, INDEX(_xlpm.data, , 1), _xlpm.name_col, INDEX(_xlpm.data, , 2), _xlpm.loc_col, INDEX(_xlpm.data, , 3), _xlpm.target_date, DATE(YEAR($B$1), MONTH($B$1), I$7), _xlpm.filtered, _xlfn._xlws.FILTER(_xlpm.name_col, (_xlpm.date_col = _xlpm.target_date) * (_xlpm.loc_col =$B8), ""), IF(_xlpm.filtered="", "", _xlpm.filtered) )} | J8: {=_xlfn.LET( _xlpm.data, 表格3_5[[Date]:[Location]], _xlpm.date_col, INDEX(_xlpm.data, , 1), _xlpm.name_col, INDEX(_xlpm.data, , 2), _xlpm.loc_col, INDEX(_xlpm.data, , 3), _xlpm.target_date, DATE(YEAR($B$1), MONTH($B$1), J$7), _xlpm.filtered, _xlfn._xlws.FILTER(_xlpm.name_col, (_xlpm.date_col = _xlpm.target_date) * (_xlpm.loc_col =$B8), ""), IF(_xlpm.filtered="", "", _xlpm.filtered) )} -> Margaret | ... AG8: {=_xlfn.LET( _xlpm.data, 表格3_5[[Date]:[Location]], _xlpm.date_col, INDEX(_xlpm.data, , 1), _xlpm.name_col, INDEX(_xlpm.data, , 2), _xlpm.loc_col, INDEX(_xlpm.data, , 3), _xlpm.target_date, DATE(YEAR($B$1), MONTH($B$1), AG$7), _xlpm.filtered, _xlfn._xlws.FILTER(_xlpm.name_col, (_xlpm.date_col = _xlpm.target_date) * (_xlpm.loc_col =$B8), ""), IF(_xlpm.filtered="", "", _xlpm.filtered) )} | AH8: =COUNTIF(C8:AG8,"?*") -> 7 | AI8: =AH8*8 -> 56 | AL8: =B8 -> Central Fortress | AM8: =IF(C8=".",C8,IF(VLOOKUP($AL8&C$1+#REF!&C8, 工作表1!$C:$V,1,) > 0,C8,"ERROR")) -> #REF! | AN8: =IF(D8=".",D8,IF(VLOOKUP($AL8&D$1+#REF!&D8, 工作表1!$C:$V,1,) > 0,D8,"ERROR")) -> #REF! | AO8: =IF(E8=".",E8,IF(VLOOKUP($AL8&E$1+#REF!&E8, 工作表1!$C:$V,1,) > 0,E8,"ERROR")) -> #REF! | AP8: =IF(F8=".",F8,IF(VLOOKUP($AL8&F$1+#REF!&F8, 工作表1!$C:$V,1,) > 0,F8,"ERROR")) -> #REF! | AQ8: =IF(G8=".",G8,IF(VLOOKUP($AL8&G$1+#REF!&G8, 工作表1!$C:$V,1,) > 0,G8,"ERROR")) -> #REF! | AR8: =IF(H8=".",H8,IF(VLOOKUP($AL8&H$1+#REF!&H8, 工作表1!$C:$V,1,) > 0,H8,"ERROR")) -> #REF! | AS8: =IF(I8=".",I8,IF(VLOOKUP($AL8&I$1+#REF!&I8, 工作表1!$C:$V,1,) > 0,I8,"ERROR")) -> #REF! | AT8: =IF(J8=".",J8,IF(VLOOKUP($AL8&J$1+#REF!&J8, 工作表1!$C:$V,1,) > 0,J8,"ERROR")) -> #REF! | ... BQ8: =IF(AG8=".",AG8,IF(VLOOKUP($AL8&AG$1+#REF!&AG8, 工作表1!$C:$V,1,) > 0,AG8,"ERROR")) -> #REF! | BR8: =IF(#REF!=".",#REF!,IF(VLOOKUP($AL8&#REF!+#REF!&#REF!, 工作表1!$C:$V,1,) > 0,#REF!,"ERROR")) -> #REF! | BS8: =IF(#REF!=".",#REF!,IF(VLOOKUP($AL8&#REF!+#REF!&#REF!, 工作表1!$C:$V,1,) > 0,#REF!,"ERROR")) -> #REF!
A9: {=_xlfn.LET( _xlpm.data, C9:AG9, _xlpm.removeList, {" off","."," SL","xxx"}, _xlpm.cleaned, TRIM(_xlfn.REDUCE(_xlpm.data, _xlpm.removeList, _xlfn.LAMBDA(_xlpm.arr,_xlpm.str, SUBSTITUTE(_xlpm.arr, _xlpm.str, "")))), _xlpm.first, _xlfn._xlws.FILTER(_xlpm.cleaned, _xlpm.cleaned <> ""), INDEX(_xlpm.first, 1) )} -> Shirley | B9: Festival Walk Fortress | C9: {=_xlfn.LET( _xlpm.data, 表格3_5[[Date]:[Location]], _xlpm.date_col, INDEX(_xlpm.data, , 1), _xlpm.name_col, INDEX(_xlpm.data, , 2), _xlpm.loc_col, INDEX(_xlpm.data, , 3), _xlpm.target_date, DATE(YEAR($B$1), MONTH($B$1), C$7), _xlpm.filtered, _xlfn._xlws.FILTER(_xlpm.name_col, (_xlpm.date_col = _xlpm.target_date) * (_xlpm.loc_col =$B9), ""), IF(_xlpm.filtered="", "", _xlpm.filtered) )} | D9: {=_xlfn.LET( _xlpm.data, 表格3_5[[Date]:[Location]], _xlpm.date_col, INDEX(_xlpm.data, , 1), _xlpm.name_col, INDEX(_xlpm.data, , 2), _xlpm.loc_col, INDEX(_xlpm.data, , 3), _xlpm.target_date, DATE(YEAR($B$1), MONTH($B$1), D$7), _xlpm.filtered, _xlfn._xlws.FILTER(_xlpm.name_col, (_xlpm.date_col = _xlpm.target_date) * (_xlpm.loc_col =$B9), ""), IF(_xlpm.filtered="", "", _xlpm.filtered) )} | E9: {=_xlfn.LET( _xlpm.data, 表格3_5[[Date]:[Location]], _xlpm.date_col, INDEX(_xlpm.data, , 1), _xlpm.name_col, INDEX(_xlpm.data, , 2), _xlpm.loc_col, INDEX(_xlpm.data, , 3), _xlpm.target_date, DATE(YEAR($B$1), MONTH($B$1), E$7), _xlpm.filtered, _xlfn._xlws.FILTER(_xlpm.name_col, (_xlpm.date_col = _xlpm.target_date) * (_xlpm.loc_col =$B9), ""), IF(_xlpm.filtered="", "", _xlpm.filtered) )} | F9: {=_xlfn.LET( _xlpm.data, 表格3_5[[Date]:[Location]], _xlpm.date_col, INDEX(_xlpm.data, , 1), _xlpm.name_col, INDEX(_xlpm.data, , 2), _xlpm.loc_col, INDEX(_xlpm.data, , 3), _xlpm.target_date, DATE(YEAR($B$1), MONTH($B$1), F$7), _xlpm.filtered, _xlfn._xlws.FILTER(_xlpm.name_col, (_xlpm.date_col = _xlpm.target_date) * (_xlpm.loc_col =$B9), ""), IF(_xlpm.filtered="", "", _xlpm.filtered) )} | G9: {=_xlfn.LET( _xlpm.data, 表格3_5[[Date]:[Location]], _xlpm.date_col, INDEX(_xlpm.data, , 1), _xlpm.name_col, INDEX(_xlpm.data, , 2), _xlpm.loc_col, INDEX(_xlpm.data, , 3), _xlpm.target_date, DATE(YEAR($B$1), MONTH($B$1), G$7), _xlpm.filtered, _xlfn._xlws.FILTER(_xlpm.name_col, (_xlpm.date_col = _xlpm.target_date) * (_xlpm.loc_col =$B9), ""), IF(_xlpm.filtered="", "", _xlpm.filtered) )} -> Shirley | H9: {=_xlfn.LET( _xlpm.data, 表格3_5[[Date]:[Location]], _xlpm.date_col, INDEX(_xlpm.data, , 1), _xlpm.name_col, INDEX(_xlpm.data, , 2), _xlpm.loc_col, INDEX(_xlpm.data, , 3), _xlpm.target_date, DATE(YEAR($B$1), MONTH($B$1), H$7), _xlpm.filtered, _xlfn._xlws.FILTER(_xlpm.name_col, (_xlpm.date_col = _xlpm.target_date) * (_xlpm.loc_col =$B9), ""), IF(_xlpm.filtered="", "", _xlpm.filtered) )} -> Shirley | I9: {=_xlfn.LET( _xlpm.data, 表格3_5[[Date]:[Location]], _xlpm.date_col, INDEX(_xlpm.data, , 1), _xlpm.name_col, INDEX(_xlpm.data, , 2), _xlpm.loc_col, INDEX(_xlpm.data, , 3), _xlpm.target_date, DATE(YEAR($B$1), MONTH($B$1), I$7), _xlpm.filtered, _xlfn._xlws.FILTER(_xlpm.name_col, (_xlpm.date_col = _xlpm.target_date) * (_xlpm.loc_col =$B9), ""), IF(_xlpm.filtered="", "", _xlpm.filtered) )} -> Shirley | J9: {=_xlfn.LET( _xlpm.data, 表格3_5[[Date]:[Location]], _xlpm.date_col, INDEX(_xlpm.data, , 1), _xlpm.name_col, INDEX(_xlpm.data, , 2), _xlpm.loc_col, INDEX(_xlpm.data, , 3), _xlpm.target_date, DATE(YEAR($B$1), MONTH($B$1), J$7), _xlpm.filtered, _xlfn._xlws.FILTER(_xlpm.name_col, (_xlpm.date_col = _xlpm.target_date) * (_xlpm.loc_col =$B9), ""), IF(_xlpm.filtered="", "", _xlpm.filtered) )} | ... AG9: {=_xlfn.LET( _xlpm.data, 表格3_5[[Date]:[Location]], _xlpm.date_col, INDEX(_xlpm.data, , 1), _xlpm.name_col, INDEX(_xlpm.data, , 2), _xlpm.loc_col, INDEX(_xlpm.data, , 3), _xlpm.target_date, DATE(YEAR($B$1), MONTH($B$1), AG$7), _xlpm.filtered, _xlfn._xlws.FILTER(_xlpm.name_col, (_xlpm.date_col = _xlpm.target_date) * (_xlpm.loc_col =$B9), ""), IF(_xlpm.filtered="", "", _xlpm.filtered) )} | AH9: =COUNTIF(C9:AG9,"?*") -> 3 | AI9: =AH9*8 -> 24 | AL9: =B9 -> Festival Walk Fortress | AM9: =IF(C9=".",C9,IF(VLOOKUP($AL9&C$1+C4&C9, 工作表1!$C:$V,1,) > 0,C9,"ERROR")) -> #N/A | AN9: =IF(D9=".",D9,IF(VLOOKUP($AL9&D$1+D4&D9, 工作表1!$C:$V,1,) > 0,D9,"ERROR")) -> #N/A | AO9: =IF(E9=".",E9,IF(VLOOKUP($AL9&E$1+E4&E9, 工作表1!$C:$V,1,) > 0,E9,"ERROR")) -> #N/A | AP9: =IF(F9=".",F9,IF(VLOOKUP($AL9&F$1+F4&F9, 工作表1!$C:$V,1,) > 0,F9,"ERROR")) -> #N/A | AQ9: =IF(G9=".",G9,IF(VLOOKUP($AL9&G$1+G4&G9, 工作表1!$C:$V,1,) > 0,G9,"ERROR")) -> #N/A | AR9: =IF(H9=".",H9,IF(VLOOKUP($AL9&H$1+H4&H9, 工作表1!$C:$V,1,) > 0,H9,"ERROR")) -> #N/A | AS9: =IF(I9=".",I9,IF(VLOOKUP($AL9&I$1+I4&I9, 工作表1!$C:$V,1,) > 0,I9,"ERROR")) -> #N/A | AT9: =IF(J9=".",J9,IF(VLOOKUP($AL9&J$1+J4&J9, 工作表1!$C:$V,1,) > 0,J9,"ERROR")) -> #N/A | ... BQ9: =IF(AG9=".",AG9,IF(VLOOKUP($AL9&AG$1+AG4&AG9, 工作表1!$C:$V,1,) > 0,AG9,"ERROR")) -> #N/A | BR9: =IF(#REF!=".",#REF!,IF(VLOOKUP($AL9&#REF!+#REF!&#REF!, 工作表1!$C:$V,1,) > 0,#REF!,"ERROR")) -> #REF! | BS9: =IF(#REF!=".",#REF!,IF(VLOOKUP($AL9&#REF!+#REF!&#REF!, 工作表1!$C:$V,1,) > 0,#REF!,"ERROR")) -> #REF!
A10: {=_xlfn.LET( _xlpm.data, C10:AG10, _xlpm.removeList, {" off","."," SL","xxx"}, _xlpm.cleaned, TRIM(_xlfn.REDUCE(_xlpm.data, _xlpm.removeList, _xlfn.LAMBDA(_xlpm.arr,_xlpm.str, SUBSTITUTE(_xlpm.arr, _xlpm.str, "")))), _xlpm.first, _xlfn._xlws.FILTER(_xlpm.cleaned, _xlpm.cleaned <> ""), INDEX(_xlpm.first, 1) )} -> Jenny P | B10: In - Home Expo | C10: {=_xlfn.LET( _xlpm.data, 表格3_5[[Date]:[Location]], _xlpm.date_col, INDEX(_xlpm.data, , 1), _xlpm.name_col, INDEX(_xlpm.data, , 2), _xlpm.loc_col, INDEX(_xlpm.data, , 3), _xlpm.target_date, DATE(YEAR($B$1), MONTH($B$1), C$7), _xlpm.filtered, _xlfn._xlws.FILTER(_xlpm.name_col, (_xlpm.date_col = _xlpm.target_date) * (_xlpm.loc_col =$B10), ""), IF(_xlpm.filtered="", "", _xlpm.filtered) )} | D10: {=_xlfn.LET( _xlpm.data, 表格3_5[[Date]:[Location]], _xlpm.date_col, INDEX(_xlpm.data, , 1), _xlpm.name_col, INDEX(_xlpm.data, , 2), _xlpm.loc_col, INDEX(_xlpm.data, , 3), _xlpm.target_date, DATE(YEAR($B$1), MONTH($B$1), D$7), _xlpm.filtered, _xlfn._xlws.FILTER(_xlpm.name_col, (_xlpm.date_col = _xlpm.target_date) * (_xlpm.loc_col =$B10), ""), IF(_xlpm.filtered="", "", _xlpm.filtered) )} | E10: {=_xlfn.LET( _xlpm.data, 表格3_5[[Date]:[Location]], _xlpm.date_col, INDEX(_xlpm.data, , 1), _xlpm.name_col, INDEX(_xlpm.data, , 2), _xlpm.loc_col, INDEX(_xlpm.data, , 3), _xlpm.target_date, DATE(YEAR($B$1), MONTH($B$1), E$7), _xlpm.filtered, _xlfn._xlws.FILTER(_xlpm.name_col, (_xlpm.date_col = _xlpm.target_date) * (_xlpm.loc_col =$B10), ""), IF(_xlpm.filtered="", "", _xlpm.filtered) )} | F10: {=_xlfn.LET( _xlpm.data, 表格3_5[[Date]:[Location]], _xlpm.date_col, INDEX(_xlpm.data, , 1), _xlpm.name_col, INDEX(_xlpm.data, , 2), _xlpm.loc_col, INDEX(_xlpm.data, , 3), _xlpm.target_date, DATE(YEAR($B$1), MONTH($B$1), F$7), _xlpm.filtered, _xlfn._xlws.FILTER(_xlpm.name_col, (_xlpm.date_col = _xlpm.target_date) * (_xlpm.loc_col =$B10), ""), IF(_xlpm.filtered="", "", _xlpm.filtered) )} | G10: {=_xlfn.LET( _xlpm.data, 表格3_5[[Date]:[Location]], _xlpm.date_col, INDEX(_xlpm.data, , 1), _xlpm.name_col, INDEX(_xlpm.data, , 2), _xlpm.loc_col, INDEX(_xlpm.data, , 3), _xlpm.target_date, DATE(YEAR($B$1), MONTH($B$1), G$7), _xlpm.filtered, _xlfn._xlws.FILTER(_xlpm.name_col, (_xlpm.date_col = _xlpm.target_date) * (_xlpm.loc_col =$B10), ""), IF(_xlpm.filtered="", "", _xlpm.filtered) )} | H10: {=_xlfn.LET( _xlpm.data, 表格3_5[[Date]:[Location]], _xlpm.date_col, INDEX(_xlpm.data, , 1), _xlpm.name_col, INDEX(_xlpm.data, , 2), _xlpm.loc_col, INDEX(_xlpm.data, , 3), _xlpm.target_date, DATE(YEAR($B$1), MONTH($B$1), H$7), _xlpm.filtered, _xlfn._xlws.FILTER(_xlpm.name_col, (_xlpm.date_col = _xlpm.target_date) * (_xlpm.loc_col =$B10), ""), IF(_xlpm.filtered="", "", _xlpm.filtered) )} | I10: {=_xlfn.LET( _xlpm.data, 表格3_5[[Date]:[Location]], _xlpm.date_col, INDEX(_xlpm.data, , 1), _xlpm.name_col, INDEX(_xlpm.data, , 2), _xlpm.loc_col, INDEX(_xlpm.data, , 3), _xlpm.target_date, DATE(YEAR($B$1), MONTH($B$1), I$7), _xlpm.filtered, _xlfn._xlws.FILTER(_xlpm.name_col, (_xlpm.date_col = _xlpm.target_date) * (_xlpm.loc_col =$B10), ""), IF(_xlpm.filtered="", "", _xlpm.filtered) )} | J10: {=_xlfn.LET( _xlpm.data, 表格3_5[[Date]:[Location]], _xlpm.date_col, INDEX(_xlpm.data, , 1), _xlpm.name_col, INDEX(_xlpm.data, , 2), _xlpm.loc_col, INDEX(_xlpm.data, , 3), _xlpm.target_date, DATE(YEAR($B$1), MONTH($B$1), J$7), _xlpm.filtered, _xlfn._xlws.FILTER(_xlpm.name_col, (_xlpm.date_col = _xlpm.target_date) * (_xlpm.loc_col =$B10), ""), IF(_xlpm.filtered="", "", _xlpm.filtered) )} | ... AG10: {=_xlfn.LET( _xlpm.data, 表格3_5[[Date]:[Location]], _xlpm.date_col, INDEX(_xlpm.data, , 1), _xlpm.name_col, INDEX(_xlpm.data, , 2), _xlpm.loc_col, INDEX(_xlpm.data, , 3), _xlpm.target_date, DATE(YEAR($B$1), MONTH($B$1), AG$7), _xlpm.filtered, _xlfn._xlws.FILTER(_xlpm.name_col, (_xlpm.date_col = _xlpm.target_date) * (_xlpm.loc_col =$B10), ""), IF(_xlpm.filtered="", "", _xlpm.filtered) )} | AH10: =COUNTIF(C10:AG10,"?*") -> 4 | AI10: =AH10*8 -> 32 | AL10: =B10 -> In - Home Expo | AM10: =IF(C10=".",C10,IF(VLOOKUP($AL10&C$1+C5&C10, 工作表1!$C:$V,1,) > 0,C10,"ERROR")) -> #N/A | AN10: =IF(D10=".",D10,IF(VLOOKUP($AL10&D$1+D5&D10, 工作表1!$C:$V,1,) > 0,D10,"ERROR")) -> #N/A | AO10: =IF(E10=".",E10,IF(VLOOKUP($AL10&E$1+E5&E10, 工作表1!$C:$V,1,) > 0,E10,"ERROR")) -> #N/A | AP10: =IF(F10=".",F10,IF(VLOOKUP($AL10&F$1+F5&F10, 工作表1!$C:$V,1,) > 0,F10,"ERROR")) -> #N/A | AQ10: =IF(G10=".",G10,IF(VLOOKUP($AL10&G$1+G5&G10, 工作表1!$C:$V,1,) > 0,G10,"ERROR")) -> #N/A | AR10: =IF(H10=".",H10,IF(VLOOKUP($AL10&H$1+H5&H10, 工作表1!$C:$V,1,) > 0,H10,"ERROR")) -> #N/A | AS10: =IF(I10=".",I10,IF(VLOOKUP($AL10&I$1+I5&I10, 工作表1!$C:$V,1,) > 0,I10,"ERROR")) -> #N/A | AT10: =IF(J10=".",J10,IF(VLOOKUP($AL10&J$1+J5&J10, 工作表1!$C:$V,1,) > 0,J10,"ERROR")) -> #N/A | ... BQ10: =IF(AG10=".",AG10,IF(VLOOKUP($AL10&AG$1+AG5&AG10, 工作表1!$C:$V,1,) > 0,AG10,"ERROR")) -> #N/A | BR10: =IF(#REF!=".",#REF!,IF(VLOOKUP($AL10&#REF!+#REF!&#REF!, 工作表1!$C:$V,1,) > 0,#REF!,"ERROR")) -> #REF! | BS10: =IF(#REF!=".",#REF!,IF(VLOOKUP($AL10&#REF!+#REF!&#REF!, 工作表1!$C:$V,1,) > 0,#REF!,"ERROR")) -> #REF!
A11: {=_xlfn.LET( _xlpm.data, C11:AG11, _xlpm.removeList, {" off","."," SL","xxx"}, _xlpm.cleaned, TRIM(_xlfn.REDUCE(_xlpm.data, _xlpm.removeList, _xlfn.LAMBDA(_xlpm.arr,_xlpm.str, SUBSTITUTE(_xlpm.arr, _xlpm.str, "")))), _xlpm.first, _xlfn._xlws.FILTER(_xlpm.cleaned, _xlpm.cleaned <> ""), INDEX(_xlpm.first, 1) )} -> Margaret | B11: In - Home Expo 2 | C11: {=_xlfn.LET( _xlpm.data, 表格3_5[[Date]:[Location]], _xlpm.date_col, INDEX(_xlpm.data, , 1), _xlpm.name_col, INDEX(_xlpm.data, , 2), _xlpm.loc_col, INDEX(_xlpm.data, , 3), _xlpm.target_date, DATE(YEAR($B$1), MONTH($B$1), C$7), _xlpm.filtered, _xlfn._xlws.FILTER(_xlpm.name_col, (_xlpm.date_col = _xlpm.target_date) * (_xlpm.loc_col =$B11), ""), IF(_xlpm.filtered="", "", _xlpm.filtered) )} | D11: {=_xlfn.LET( _xlpm.data, 表格3_5[[Date]:[Location]], _xlpm.date_col, INDEX(_xlpm.data, , 1), _xlpm.name_col, INDEX(_xlpm.data, , 2), _xlpm.loc_col, INDEX(_xlpm.data, , 3), _xlpm.target_date, DATE(YEAR($B$1), MONTH($B$1), D$7), _xlpm.filtered, _xlfn._xlws.FILTER(_xlpm.name_col, (_xlpm.date_col = _xlpm.target_date) * (_xlpm.loc_col =$B11), ""), IF(_xlpm.filtered="", "", _xlpm.filtered) )} | E11: {=_xlfn.LET( _xlpm.data, 表格3_5[[Date]:[Location]], _xlpm.date_col, INDEX(_xlpm.data, , 1), _xlpm.name_col, INDEX(_xlpm.data, , 2), _xlpm.loc_col, INDEX(_xlpm.data, , 3), _xlpm.target_date, DATE(YEAR($B$1), MONTH($B$1), E$7), _xlpm.filtered, _xlfn._xlws.FILTER(_xlpm.name_col, (_xlpm.date_col = _xlpm.target_date) * (_xlpm.loc_col =$B11), ""), IF(_xlpm.filtered="", "", _xlpm.filtered) )} | F11: {=_xlfn.LET( _xlpm.data, 表格3_5[[Date]:[Location]], _xlpm.date_col, INDEX(_xlpm.data, , 1), _xlpm.name_col, INDEX(_xlpm.data, , 2), _xlpm.loc_col, INDEX(_xlpm.data, , 3), _xlpm.target_date, DATE(YEAR($B$1), MONTH($B$1), F$7), _xlpm.filtered, _xlfn._xlws.FILTER(_xlpm.name_col, (_xlpm.date_col = _xlpm.target_date) * (_xlpm.loc_col =$B11), ""), IF(_xlpm.filtered="", "", _xlpm.filtered) )} | G11: {=_xlfn.LET( _xlpm.data, 表格3_5[[Date]:[Location]], _xlpm.date_col, INDEX(_xlpm.data, , 1), _xlpm.name_col, INDEX(_xlpm.data, , 2), _xlpm.loc_col, INDEX(_xlpm.data, , 3), _xlpm.target_date, DATE(YEAR($B$1), MONTH($B$1), G$7), _xlpm.filtered, _xlfn._xlws.FILTER(_xlpm.name_col, (_xlpm.date_col = _xlpm.target_date) * (_xlpm.loc_col =$B11), ""), IF(_xlpm.filtered="", "", _xlpm.filtered) )} | H11: {=_xlfn.LET( _xlpm.data, 表格3_5[[Date]:[Location]], _xlpm.date_col, INDEX(_xlpm.data, , 1), _xlpm.name_col, INDEX(_xlpm.data, , 2), _xlpm.loc_col, INDEX(_xlpm.data, , 3), _xlpm.target_date, DATE(YEAR($B$1), MONTH($B$1), H$7), _xlpm.filtered, _xlfn._xlws.FILTER(_xlpm.name_col, (_xlpm.date_col = _xlpm.target_date) * (_xlpm.loc_col =$B11), ""), IF(_xlpm.filtered="", "", _xlpm.filtered) )} | I11: {=_xlfn.LET( _xlpm.data, 表格3_5[[Date]:[Location]], _xlpm.date_col, INDEX(_xlpm.data, , 1), _xlpm.name_col, INDEX(_xlpm.data, , 2), _xlpm.loc_col, INDEX(_xlpm.data, , 3), _xlpm.target_date, DATE(YEAR($B$1), MONTH($B$1), I$7), _xlpm.filtered, _xlfn._xlws.FILTER(_xlpm.name_col, (_xlpm.date_col = _xlpm.target_date) * (_xlpm.loc_col =$B11), ""), IF(_xlpm.filtered="", "", _xlpm.filtered) )} | J11: {=_xlfn.LET( _xlpm.data, 表格3_5[[Date]:[Location]], _xlpm.date_col, INDEX(_xlpm.data, , 1), _xlpm.name_col, INDEX(_xlpm.data, , 2), _xlpm.loc_col, INDEX(_xlpm.data, , 3), _xlpm.target_date, DATE(YEAR($B$1), MONTH($B$1), J$7), _xlpm.filtered, _xlfn._xlws.FILTER(_xlpm.name_col, (_xlpm.date_col = _xlpm.target_date) * (_xlpm.loc_col =$B11), ""), IF(_xlpm.filtered="", "", _xlpm.filtered) )} | ... AG11: {=_xlfn.LET( _xlpm.data, 表格3_5[[Date]:[Location]], _xlpm.date_col, INDEX(_xlpm.data, , 1), _xlpm.name_col, INDEX(_xlpm.data, , 2), _xlpm.loc_col, INDEX(_xlpm.data, , 3), _xlpm.target_date, DATE(YEAR($B$1), MONTH($B$1), AG$7), _xlpm.filtered, _xlfn._xlws.FILTER(_xlpm.name_col, (_xlpm.date_col = _xlpm.target_date) * (_xlpm.loc_col =$B11), ""), IF(_xlpm.filtered="", "", _xlpm.filtered) )} | AH11: =COUNTIF(C11:AG11,"?*") -> 2 | AI11: =AH11*8 -> 16 | AL11: =B11 -> In - Home Expo 2 | AM11: =IF(C11=".",C11,IF(VLOOKUP($AL11&C$1+C6&C11, 工作表1!$C:$V,1,) > 0,C11,"ERROR")) -> #VALUE! | AN11: =IF(D11=".",D11,IF(VLOOKUP($AL11&D$1+D6&D11, 工作表1!$C:$V,1,) > 0,D11,"ERROR")) -> #VALUE! | AO11: =IF(E11=".",E11,IF(VLOOKUP($AL11&E$1+E6&E11, 工作表1!$C:$V,1,) > 0,E11,"ERROR")) -> #VALUE! | AP11: =IF(F11=".",F11,IF(VLOOKUP($AL11&F$1+F6&F11, 工作表1!$C:$V,1,) > 0,F11,"ERROR")) -> #VALUE! | AQ11: =IF(G11=".",G11,IF(VLOOKUP($AL11&G$1+G6&G11, 工作表1!$C:$V,1,) > 0,G11,"ERROR")) -> #VALUE! | AR11: =IF(H11=".",H11,IF(VLOOKUP($AL11&H$1+H6&H11, 工作表1!$C:$V,1,) > 0,H11,"ERROR")) -> #VALUE! | AS11: =IF(I11=".",I11,IF(VLOOKUP($AL11&I$1+I6&I11, 工作表1!$C:$V,1,) > 0,I11,"ERROR")) -> #VALUE! | AT11: =IF(J11=".",J11,IF(VLOOKUP($AL11&J$1+J6&J11, 工作表1!$C:$V,1,) > 0,J11,"ERROR")) -> #VALUE! | ... BQ11: =IF(AG11=".",AG11,IF(VLOOKUP($AL11&AG$1+AG6&AG11, 工作表1!$C:$V,1,) > 0,AG11,"ERROR")) -> #VALUE! | BR11: =IF(#REF!=".",#REF!,IF(VLOOKUP($AL11&#REF!+#REF!&#REF!, 工作表1!$C:$V,1,) > 0,#REF!,"ERROR")) -> #REF! | BS11: =IF(#REF!=".",#REF!,IF(VLOOKUP($AL11&#REF!+#REF!&#REF!, 工作表1!$C:$V,1,) > 0,#REF!,"ERROR")) -> #REF!
A12: {=_xlfn.LET( _xlpm.data, C12:AG12, _xlpm.removeList, {" off","."," SL","xxx"}, _xlpm.cleaned, TRIM(_xlfn.REDUCE(_xlpm.data, _xlpm.removeList, _xlfn.LAMBDA(_xlpm.arr,_xlpm.str, SUBSTITUTE(_xlpm.arr, _xlpm.str, "")))), _xlpm.first, _xlfn._xlws.FILTER(_xlpm.cleaned, _xlpm.cleaned <> ""), INDEX(_xlpm.first, 1) )} -> Wah | B12: Kowloon Bay Fortress | C12: {=_xlfn.LET( _xlpm.data, 表格3_5[[Date]:[Location]], _xlpm.date_col, INDEX(_xlpm.data, , 1), _xlpm.name_col, INDEX(_xlpm.data, , 2), _xlpm.loc_col, INDEX(_xlpm.data, , 3), _xlpm.target_date, DATE(YEAR($B$1), MONTH($B$1), C$7), _xlpm.filtered, _xlfn._xlws.FILTER(_xlpm.name_col, (_xlpm.date_col = _xlpm.target_date) * (_xlpm.loc_col =$B12), ""), IF(_xlpm.filtered="", "", _xlpm.filtered) )} | D12: {=_xlfn.LET( _xlpm.data, 表格3_5[[Date]:[Location]], _xlpm.date_col, INDEX(_xlpm.data, , 1), _xlpm.name_col, INDEX(_xlpm.data, , 2), _xlpm.loc_col, INDEX(_xlpm.data, , 3), _xlpm.target_date, DATE(YEAR($B$1), MONTH($B$1), D$7), _xlpm.filtered, _xlfn._xlws.FILTER(_xlpm.name_col, (_xlpm.date_col = _xlpm.target_date) * (_xlpm.loc_col =$B12), ""), IF(_xlpm.filtered="", "", _xlpm.filtered) )} | E12: {=_xlfn.LET( _xlpm.data, 表格3_5[[Date]:[Location]], _xlpm.date_col, INDEX(_xlpm.data, , 1), _xlpm.name_col, INDEX(_xlpm.data, , 2), _xlpm.loc_col, INDEX(_xlpm.data, , 3), _xlpm.target_date, DATE(YEAR($B$1), MONTH($B$1), E$7), _xlpm.filtered, _xlfn._xlws.FILTER(_xlpm.name_col, (_xlpm.date_col = _xlpm.target_date) * (_xlpm.loc_col =$B12), ""), IF(_xlpm.filtered="", "", _xlpm.filtered) )} | F12: {=_xlfn.LET( _xlpm.data, 表格3_5[[Date]:[Location]], _xlpm.date_col, INDEX(_xlpm.data, , 1), _xlpm.name_col, INDEX(_xlpm.data, , 2), _xlpm.loc_col, INDEX(_xlpm.data, , 3), _xlpm.target_date, DATE(YEAR($B$1), MONTH($B$1), F$7), _xlpm.filtered, _xlfn._xlws.FILTER(_xlpm.name_col, (_xlpm.date_col = _xlpm.target_date) * (_xlpm.loc_col =$B12), ""), IF(_xlpm.filtered="", "", _xlpm.filtered) )} -> Wah | G12: {=_xlfn.LET( _xlpm.data, 表格3_5[[Date]:[Location]], _xlpm.date_col, INDEX(_xlpm.data, , 1), _xlpm.name_col, INDEX(_xlpm.data, , 2), _xlpm.loc_col, INDEX(_xlpm.data, , 3), _xlpm.target_date, DATE(YEAR($B$1), MONTH($B$1), G$7), _xlpm.filtered, _xlfn._xlws.FILTER(_xlpm.name_col, (_xlpm.date_col = _xlpm.target_date) * (_xlpm.loc_col =$B12), ""), IF(_xlpm.filtered="", "", _xlpm.filtered) )} -> Wah | H12: {=_xlfn.LET( _xlpm.data, 表格3_5[[Date]:[Location]], _xlpm.date_col, INDEX(_xlpm.data, , 1), _xlpm.name_col, INDEX(_xlpm.data, , 2), _xlpm.loc_col, INDEX(_xlpm.data, , 3), _xlpm.target_date, DATE(YEAR($B$1), MONTH($B$1), H$7), _xlpm.filtered, _xlfn._xlws.FILTER(_xlpm.name_col, (_xlpm.date_col = _xlpm.target_date) * (_xlpm.loc_col =$B12), ""), IF(_xlpm.filtered="", "", _xlpm.filtered) )} -> Wah | I12: {=_xlfn.LET( _xlpm.data, 表格3_5[[Date]:[Location]], _xlpm.date_col, INDEX(_xlpm.data, , 1), _xlpm.name_col, INDEX(_xlpm.data, , 2), _xlpm.loc_col, INDEX(_xlpm.data, , 3), _xlpm.target_date, DATE(YEAR($B$1), MONTH($B$1), I$7), _xlpm.filtered, _xlfn._xlws.FILTER(_xlpm.name_col, (_xlpm.date_col = _xlpm.target_date) * (_xlpm.loc_col =$B12), ""), IF(_xlpm.filtered="", "", _xlpm.filtered) )} -> Wah | J12: {=_xlfn.LET( _xlpm.data, 表格3_5[[Date]:[Location]], _xlpm.date_col, INDEX(_xlpm.data, , 1), _xlpm.name_col, INDEX(_xlpm.data, , 2), _xlpm.loc_col, INDEX(_xlpm.data, , 3), _xlpm.target_date, DATE(YEAR($B$1), MONTH($B$1), J$7), _xlpm.filtered, _xlfn._xlws.FILTER(_xlpm.name_col, (_xlpm.date_col = _xlpm.target_date) * (_xlpm.loc_col =$B12), ""), IF(_xlpm.filtered="", "", _xlpm.filtered) )} | ... AG12: {=_xlfn.LET( _xlpm.data, 表格3_5[[Date]:[Location]], _xlpm.date_col, INDEX(_xlpm.data, , 1), _xlpm.name_col, INDEX(_xlpm.data, , 2), _xlpm.loc_col, INDEX(_xlpm.data, , 3), _xlpm.target_date, DATE(YEAR($B$1), MONTH($B$1), AG$7), _xlpm.filtered, _xlfn._xlws.FILTER(_xlpm.name_col, (_xlpm.date_col = _xlpm.target_date) * (_xlpm.loc_col =$B12), ""), IF(_xlpm.filtered="", "", _xlpm.filtered) )} | AH12: =COUNTIF(C12:AG12,"?*") -> 16 | AI12: =AH12*8 -> 128 | AL12: =B12 -> Kowloon Bay Fortress | AM12: =IF(C12=".",C12,IF(VLOOKUP($AL12&C$1+C7&C12, 工作表1!$C:$V,1,) > 0,C12,"ERROR")) -> #N/A | AN12: =IF(D12=".",D12,IF(VLOOKUP($AL12&D$1+D7&D12, 工作表1!$C:$V,1,) > 0,D12,"ERROR")) -> #N/A | AO12: =IF(E12=".",E12,IF(VLOOKUP($AL12&E$1+E7&E12, 工作表1!$C:$V,1,) > 0,E12,"ERROR")) -> #N/A | AP12: =IF(F12=".",F12,IF(VLOOKUP($AL12&F$1+F7&F12, 工作表1!$C:$V,1,) > 0,F12,"ERROR")) -> #N/A | AQ12: =IF(G12=".",G12,IF(VLOOKUP($AL12&G$1+G7&G12, 工作表1!$C:$V,1,) > 0,G12,"ERROR")) -> #N/A | AR12: =IF(H12=".",H12,IF(VLOOKUP($AL12&H$1+H7&H12, 工作表1!$C:$V,1,) > 0,H12,"ERROR")) -> #N/A | AS12: =IF(I12=".",I12,IF(VLOOKUP($AL12&I$1+I7&I12, 工作表1!$C:$V,1,) > 0,I12,"ERROR")) -> #N/A | AT12: =IF(J12=".",J12,IF(VLOOKUP($AL12&J$1+J7&J12, 工作表1!$C:$V,1,) > 0,J12,"ERROR")) -> #N/A | ... BQ12: =IF(AG12=".",AG12,IF(VLOOKUP($AL12&AG$1+AG7&AG12, 工作表1!$C:$V,1,) > 0,AG12,"ERROR")) -> #N/A | BR12: =IF(#REF!=".",#REF!,IF(VLOOKUP($AL12&#REF!+#REF!&#REF!, 工作表1!$C:$V,1,) > 0,#REF!,"ERROR")) -> #REF! | BS12: =IF(#REF!=".",#REF!,IF(VLOOKUP($AL12&#REF!+#REF!&#REF!, 工作表1!$C:$V,1,) > 0,#REF!,"ERROR")) -> #REF!
A13: {=_xlfn.LET( _xlpm.data, C13:AG13, _xlpm.removeList, {" off","."," SL","xxx"}, _xlpm.cleaned, TRIM(_xlfn.REDUCE(_xlpm.data, _xlpm.removeList, _xlfn.LAMBDA(_xlpm.arr,_xlpm.str, SUBSTITUTE(_xlpm.arr, _xlpm.str, "")))), _xlpm.first, _xlfn._xlws.FILTER(_xlpm.cleaned, _xlpm.cleaned <> ""), INDEX(_xlpm.first, 1) )} -> Wu Sir | B13: Kwai Fong Fortress | C13: {=_xlfn.LET( _xlpm.data, 表格3_5[[Date]:[Location]], _xlpm.date_col, INDEX(_xlpm.data, , 1), _xlpm.name_col, INDEX(_xlpm.data, , 2), _xlpm.loc_col, INDEX(_xlpm.data, , 3), _xlpm.target_date, DATE(YEAR($B$1), MONTH($B$1), C$7), _xlpm.filtered, _xlfn._xlws.FILTER(_xlpm.name_col, (_xlpm.date_col = _xlpm.target_date) * (_xlpm.loc_col =$B13), ""), IF(_xlpm.filtered="", "", _xlpm.filtered) )} | D13: {=_xlfn.LET( _xlpm.data, 表格3_5[[Date]:[Location]], _xlpm.date_col, INDEX(_xlpm.data, , 1), _xlpm.name_col, INDEX(_xlpm.data, , 2), _xlpm.loc_col, INDEX(_xlpm.data, , 3), _xlpm.target_date, DATE(YEAR($B$1), MONTH($B$1), D$7), _xlpm.filtered, _xlfn._xlws.FILTER(_xlpm.name_col, (_xlpm.date_col = _xlpm.target_date) * (_xlpm.loc_col =$B13), ""), IF(_xlpm.filtered="", "", _xlpm.filtered) )} | E13: {=_xlfn.LET( _xlpm.data, 表格3_5[[Date]:[Location]], _xlpm.date_col, INDEX(_xlpm.data, , 1), _xlpm.name_col, INDEX(_xlpm.data, , 2), _xlpm.loc_col, INDEX(_xlpm.data, , 3), _xlpm.target_date, DATE(YEAR($B$1), MONTH($B$1), E$7), _xlpm.filtered, _xlfn._xlws.FILTER(_xlpm.name_col, (_xlpm.date_col = _xlpm.target_date) * (_xlpm.loc_col =$B13), ""), IF(_xlpm.filtered="", "", _xlpm.filtered) )} | F13: {=_xlfn.LET( _xlpm.data, 表格3_5[[Date]:[Location]], _xlpm.date_col, INDEX(_xlpm.data, , 1), _xlpm.name_col, INDEX(_xlpm.data, , 2), _xlpm.loc_col, INDEX(_xlpm.data, , 3), _xlpm.target_date, DATE(YEAR($B$1), MONTH($B$1), F$7), _xlpm.filtered, _xlfn._xlws.FILTER(_xlpm.name_col, (_xlpm.date_col = _xlpm.target_date) * (_xlpm.loc_col =$B13), ""), IF(_xlpm.filtered="", "", _xlpm.filtered) )} | G13: {=_xlfn.LET( _xlpm.data, 表格3_5[[Date]:[Location]], _xlpm.date_col, INDEX(_xlpm.data, , 1), _xlpm.name_col, INDEX(_xlpm.data, , 2), _xlpm.loc_col, INDEX(_xlpm.data, , 3), _xlpm.target_date, DATE(YEAR($B$1), MONTH($B$1), G$7), _xlpm.filtered, _xlfn._xlws.FILTER(_xlpm.name_col, (_xlpm.date_col = _xlpm.target_date) * (_xlpm.loc_col =$B13), ""), IF(_xlpm.filtered="", "", _xlpm.filtered) )} | H13: {=_xlfn.LET( _xlpm.data, 表格3_5[[Date]:[Location]], _xlpm.date_col, INDEX(_xlpm.data, , 1), _xlpm.name_col, INDEX(_xlpm.data, , 2), _xlpm.loc_col, INDEX(_xlpm.data, , 3), _xlpm.target_date, DATE(YEAR($B$1), MONTH($B$1), H$7), _xlpm.filtered, _xlfn._xlws.FILTER(_xlpm.name_col, (_xlpm.date_col = _xlpm.target_date) * (_xlpm.loc_col =$B13), ""), IF(_xlpm.filtered="", "", _xlpm.filtered) )} -> Wu Sir | I13: {=_xlfn.LET( _xlpm.data, 表格3_5[[Date]:[Location]], _xlpm.date_col, INDEX(_xlpm.data, , 1), _xlpm.name_col, INDEX(_xlpm.data, , 2), _xlpm.loc_col, INDEX(_xlpm.data, , 3), _xlpm.target_date, DATE(YEAR($B$1), MONTH($B$1), I$7), _xlpm.filtered, _xlfn._xlws.FILTER(_xlpm.name_col, (_xlpm.date_col = _xlpm.target_date) * (_xlpm.loc_col =$B13), ""), IF(_xlpm.filtered="", "", _xlpm.filtered) )} -> Wu Sir | J13: {=_xlfn.LET( _xlpm.data, 表格3_5[[Date]:[Location]], _xlpm.date_col, INDEX(_xlpm.data, , 1), _xlpm.name_col, INDEX(_xlpm.data, , 2), _xlpm.loc_col, INDEX(_xlpm.data, , 3), _xlpm.target_date, DATE(YEAR($B$1), MONTH($B$1), J$7), _xlpm.filtered, _xlfn._xlws.FILTER(_xlpm.name_col, (_xlpm.date_col = _xlpm.target_date) * (_xlpm.loc_col =$B13), ""), IF(_xlpm.filtered="", "", _xlpm.filtered) )} | ... AG13: {=_xlfn.LET( _xlpm.data, 表格3_5[[Date]:[Location]], _xlpm.date_col, INDEX(_xlpm.data, , 1), _xlpm.name_col, INDEX(_xlpm.data, , 2), _xlpm.loc_col, INDEX(_xlpm.data, , 3), _xlpm.target_date, DATE(YEAR($B$1), MONTH($B$1), AG$7), _xlpm.filtered, _xlfn._xlws.FILTER(_xlpm.name_col, (_xlpm.date_col = _xlpm.target_date) * (_xlpm.loc_col =$B13), ""), IF(_xlpm.filtered="", "", _xlpm.filtered) )} | AH13: =COUNTIF(C13:AG13,"?*") -> 6 | AI13: =AH13*8 -> 48 | AL13: =B13 -> Kwai Fong Fortress | AM13: =IF(C13=".",C13,IF(VLOOKUP($AL13&C$1+C8&C13, 工作表1!$C:$V,1,) > 0,C13,"ERROR")) -> #VALUE! | AN13: =IF(D13=".",D13,IF(VLOOKUP($AL13&D$1+D8&D13, 工作表1!$C:$V,1,) > 0,D13,"ERROR")) -> #VALUE! | AO13: =IF(E13=".",E13,IF(VLOOKUP($AL13&E$1+E8&E13, 工作表1!$C:$V,1,) > 0,E13,"ERROR")) -> #VALUE! | AP13: =IF(F13=".",F13,IF(VLOOKUP($AL13&F$1+F8&F13, 工作表1!$C:$V,1,) > 0,F13,"ERROR")) -> #VALUE! | AQ13: =IF(G13=".",G13,IF(VLOOKUP($AL13&G$1+G8&G13, 工作表1!$C:$V,1,) > 0,G13,"ERROR")) -> #VALUE! | AR13: =IF(H13=".",H13,IF(VLOOKUP($AL13&H$1+H8&H13, 工作表1!$C:$V,1,) > 0,H13,"ERROR")) -> #VALUE! | AS13: =IF(I13=".",I13,IF(VLOOKUP($AL13&I$1+I8&I13, 工作表1!$C:$V,1,) > 0,I13,"ERROR")) -> #VALUE! | AT13: =IF(J13=".",J13,IF(VLOOKUP($AL13&J$1+J8&J13, 工作表1!$C:$V,1,) > 0,J13,"ERROR")) -> #VALUE! | ... BQ13: =IF(AG13=".",AG13,IF(VLOOKUP($AL13&AG$1+AG8&AG13, 工作表1!$C:$V,1,) > 0,AG13,"ERROR")) -> #VALUE! | BR13: =IF(#REF!=".",#REF!,IF(VLOOKUP($AL13&#REF!+#REF!&#REF!, 工作表1!$C:$V,1,) > 0,#REF!,"ERROR")) -> #REF! | BS13: =IF(#REF!=".",#REF!,IF(VLOOKUP($AL13&#REF!+#REF!&#REF!, 工作表1!$C:$V,1,) > 0,#REF!,"ERROR")) -> #REF!
A14: {=_xlfn.LET( _xlpm.data, C14:AG14, _xlpm.removeList, {" off","."," SL","xxx"}, _xlpm.cleaned, TRIM(_xlfn.REDUCE(_xlpm.data, _xlpm.removeList, _xlfn.LAMBDA(_xlpm.arr,_xlpm.str, SUBSTITUTE(_xlpm.arr, _xlpm.str, "")))), _xlpm.first, _xlfn._xlws.FILTER(_xlpm.cleaned, _xlpm.cleaned <> ""), INDEX(_xlpm.first, 1) )} -> Margaret | B14: Shatin Fortress | C14: {=_xlfn.LET( _xlpm.data, 表格3_5[[Date]:[Location]], _xlpm.date_col, INDEX(_xlpm.data, , 1), _xlpm.name_col, INDEX(_xlpm.data, , 2), _xlpm.loc_col, INDEX(_xlpm.data, , 3), _xlpm.target_date, DATE(YEAR($B$1), MONTH($B$1), C$7), _xlpm.filtered, _xlfn._xlws.FILTER(_xlpm.name_col, (_xlpm.date_col = _xlpm.target_date) * (_xlpm.loc_col =$B14), ""), IF(_xlpm.filtered="", "", _xlpm.filtered) )} | D14: {=_xlfn.LET( _xlpm.data, 表格3_5[[Date]:[Location]], _xlpm.date_col, INDEX(_xlpm.data, , 1), _xlpm.name_col, INDEX(_xlpm.data, , 2), _xlpm.loc_col, INDEX(_xlpm.data, , 3), _xlpm.target_date, DATE(YEAR($B$1), MONTH($B$1), D$7), _xlpm.filtered, _xlfn._xlws.FILTER(_xlpm.name_col, (_xlpm.date_col = _xlpm.target_date) * (_xlpm.loc_col =$B14), ""), IF(_xlpm.filtered="", "", _xlpm.filtered) )} | E14: {=_xlfn.LET( _xlpm.data, 表格3_5[[Date]:[Location]], _xlpm.date_col, INDEX(_xlpm.data, , 1), _xlpm.name_col, INDEX(_xlpm.data, , 2), _xlpm.loc_col, INDEX(_xlpm.data, , 3), _xlpm.target_date, DATE(YEAR($B$1), MONTH($B$1), E$7), _xlpm.filtered, _xlfn._xlws.FILTER(_xlpm.name_col, (_xlpm.date_col = _xlpm.target_date) * (_xlpm.loc_col =$B14), ""), IF(_xlpm.filtered="", "", _xlpm.filtered) )} | F14: {=_xlfn.LET( _xlpm.data, 表格3_5[[Date]:[Location]], _xlpm.date_col, INDEX(_xlpm.data, , 1), _xlpm.name_col, INDEX(_xlpm.data, , 2), _xlpm.loc_col, INDEX(_xlpm.data, , 3), _xlpm.target_date, DATE(YEAR($B$1), MONTH($B$1), F$7), _xlpm.filtered, _xlfn._xlws.FILTER(_xlpm.name_col, (_xlpm.date_col = _xlpm.target_date) * (_xlpm.loc_col =$B14), ""), IF(_xlpm.filtered="", "", _xlpm.filtered) )} | G14: {=_xlfn.LET( _xlpm.data, 表格3_5[[Date]:[Location]], _xlpm.date_col, INDEX(_xlpm.data, , 1), _xlpm.name_col, INDEX(_xlpm.data, , 2), _xlpm.loc_col, INDEX(_xlpm.data, , 3), _xlpm.target_date, DATE(YEAR($B$1), MONTH($B$1), G$7), _xlpm.filtered, _xlfn._xlws.FILTER(_xlpm.name_col, (_xlpm.date_col = _xlpm.target_date) * (_xlpm.loc_col =$B14), ""), IF(_xlpm.filtered="", "", _xlpm.filtered) )} -> Margaret | H14: {=_xlfn.LET( _xlpm.data, 表格3_5[[Date]:[Location]], _xlpm.date_col, INDEX(_xlpm.data, , 1), _xlpm.name_col, INDEX(_xlpm.data, , 2), _xlpm.loc_col, INDEX(_xlpm.data, , 3), _xlpm.target_date, DATE(YEAR($B$1), MONTH($B$1), H$7), _xlpm.filtered, _xlfn._xlws.FILTER(_xlpm.name_col, (_xlpm.date_col = _xlpm.target_date) * (_xlpm.loc_col =$B14), ""), IF(_xlpm.filtered="", "", _xlpm.filtered) )} -> Margaret | I14: {=_xlfn.LET( _xlpm.data, 表格3_5[[Date]:[Location]], _xlpm.date_col, INDEX(_xlpm.data, , 1), _xlpm.name_col, INDEX(_xlpm.data, , 2), _xlpm.loc_col, INDEX(_xlpm.data, , 3), _xlpm.target_date, DATE(YEAR($B$1), MONTH($B$1), I$7), _xlpm.filtered, _xlfn._xlws.FILTER(_xlpm.name_col, (_xlpm.date_col = _xlpm.target_date) * (_xlpm.loc_col =$B14), ""), IF(_xlpm.filtered="", "", _xlpm.filtered) )} -> Margaret | J14: {=_xlfn.LET( _xlpm.data, 表格3_5[[Date]:[Location]], _xlpm.date_col, INDEX(_xlpm.data, , 1), _xlpm.name_col, INDEX(_xlpm.data, , 2), _xlpm.loc_col, INDEX(_xlpm.data, , 3), _xlpm.target_date, DATE(YEAR($B$1), MONTH($B$1), J$7), _xlpm.filtered, _xlfn._xlws.FILTER(_xlpm.name_col, (_xlpm.date_col = _xlpm.target_date) * (_xlpm.loc_col =$B14), ""), IF(_xlpm.filtered="", "", _xlpm.filtered) )} | ... AG14: {=_xlfn.LET( _xlpm.data, 表格3_5[[Date]:[Location]], _xlpm.date_col, INDEX(_xlpm.data, , 1), _xlpm.name_col, INDEX(_xlpm.data, , 2), _xlpm.loc_col, INDEX(_xlpm.data, , 3), _xlpm.target_date, DATE(YEAR($B$1), MONTH($B$1), AG$7), _xlpm.filtered, _xlfn._xlws.FILTER(_xlpm.name_col, (_xlpm.date_col = _xlpm.target_date) * (_xlpm.loc_col =$B14), ""), IF(_xlpm.filtered="", "", _xlpm.filtered) )} | AH14: =COUNTIF(C14:AG14,"?*") -> 11 | AI14: =AH14*8 -> 88 | AL14: =B14 -> Shatin Fortress | AM14: =IF(C14=".",C14,IF(VLOOKUP($AL14&C$1+C9&C14, 工作表1!$C:$V,1,) > 0,C14,"ERROR")) -> #VALUE! | AN14: =IF(D14=".",D14,IF(VLOOKUP($AL14&D$1+D9&D14, 工作表1!$C:$V,1,) > 0,D14,"ERROR")) -> #VALUE! | AO14: =IF(E14=".",E14,IF(VLOOKUP($AL14&E$1+E9&E14, 工作表1!$C:$V,1,) > 0,E14,"ERROR")) -> #VALUE! | AP14: =IF(F14=".",F14,IF(VLOOKUP($AL14&F$1+F9&F14, 工作表1!$C:$V,1,) > 0,F14,"ERROR")) -> #VALUE! | AQ14: =IF(G14=".",G14,IF(VLOOKUP($AL14&G$1+G9&G14, 工作表1!$C:$V,1,) > 0,G14,"ERROR")) -> #VALUE! | AR14: =IF(H14=".",H14,IF(VLOOKUP($AL14&H$1+H9&H14, 工作表1!$C:$V,1,) > 0,H14,"ERROR")) -> #VALUE! | AS14: =IF(I14=".",I14,IF(VLOOKUP($AL14&I$1+I9&I14, 工作表1!$C:$V,1,) > 0,I14,"ERROR")) -> #VALUE! | AT14: =IF(J14=".",J14,IF(VLOOKUP($AL14&J$1+J9&J14, 工作表1!$C:$V,1,) > 0,J14,"ERROR")) -> #VALUE! | ... BQ14: =IF(AG14=".",AG14,IF(VLOOKUP($AL14&AG$1+AG9&AG14, 工作表1!$C:$V,1,) > 0,AG14,"ERROR")) -> #VALUE! | BR14: =IF(#REF!=".",#REF!,IF(VLOOKUP($AL14&#REF!+#REF!&#REF!, 工作表1!$C:$V,1,) > 0,#REF!,"ERROR")) -> #REF! | BS14: =IF(#REF!=".",#REF!,IF(VLOOKUP($AL14&#REF!+#REF!&#REF!, 工作表1!$C:$V,1,) > 0,#REF!,"ERROR")) -> #REF!
A15: {=_xlfn.LET( _xlpm.data, C15:AG15, _xlpm.removeList, {" off","."," SL","xxx"}, _xlpm.cleaned, TRIM(_xlfn.REDUCE(_xlpm.data, _xlpm.removeList, _xlfn.LAMBDA(_xlpm.arr,_xlpm.str, SUBSTITUTE(_xlpm.arr, _xlpm.str, "")))), _xlpm.first, _xlfn._xlws.FILTER(_xlpm.cleaned, _xlpm.cleaned <> ""), INDEX(_xlpm.first, 1) )} -> Carol | B15: SW Wing On | C15: {=_xlfn.LET( _xlpm.data, 表格3_5[[Date]:[Location]], _xlpm.date_col, INDEX(_xlpm.data, , 1), _xlpm.name_col, INDEX(_xlpm.data, , 2), _xlpm.loc_col, INDEX(_xlpm.data, , 3), _xlpm.target_date, DATE(YEAR($B$1), MONTH($B$1), C$7), _xlpm.filtered, _xlfn._xlws.FILTER(_xlpm.name_col, (_xlpm.date_col = _xlpm.target_date) * (_xlpm.loc_col =$B15), ""), IF(_xlpm.filtered="", "", _xlpm.filtered) )} | D15: {=_xlfn.LET( _xlpm.data, 表格3_5[[Date]:[Location]], _xlpm.date_col, INDEX(_xlpm.data, , 1), _xlpm.name_col, INDEX(_xlpm.data, , 2), _xlpm.loc_col, INDEX(_xlpm.data, , 3), _xlpm.target_date, DATE(YEAR($B$1), MONTH($B$1), D$7), _xlpm.filtered, _xlfn._xlws.FILTER(_xlpm.name_col, (_xlpm.date_col = _xlpm.target_date) * (_xlpm.loc_col =$B15), ""), IF(_xlpm.filtered="", "", _xlpm.filtered) )} | E15: {=_xlfn.LET( _xlpm.data, 表格3_5[[Date]:[Location]], _xlpm.date_col, INDEX(_xlpm.data, , 1), _xlpm.name_col, INDEX(_xlpm.data, , 2), _xlpm.loc_col, INDEX(_xlpm.data, , 3), _xlpm.target_date, DATE(YEAR($B$1), MONTH($B$1), E$7), _xlpm.filtered, _xlfn._xlws.FILTER(_xlpm.name_col, (_xlpm.date_col = _xlpm.target_date) * (_xlpm.loc_col =$B15), ""), IF(_xlpm.filtered="", "", _xlpm.filtered) )} -> Carol | F15: {=_xlfn.LET( _xlpm.data, 表格3_5[[Date]:[Location]], _xlpm.date_col, INDEX(_xlpm.data, , 1), _xlpm.name_col, INDEX(_xlpm.data, , 2), _xlpm.loc_col, INDEX(_xlpm.data, , 3), _xlpm.target_date, DATE(YEAR($B$1), MONTH($B$1), F$7), _xlpm.filtered, _xlfn._xlws.FILTER(_xlpm.name_col, (_xlpm.date_col = _xlpm.target_date) * (_xlpm.loc_col =$B15), ""), IF(_xlpm.filtered="", "", _xlpm.filtered) )} -> Hazel | G15: {=_xlfn.LET( _xlpm.data, 表格3_5[[Date]:[Location]], _xlpm.date_col, INDEX(_xlpm.data, , 1), _xlpm.name_col, INDEX(_xlpm.data, , 2), _xlpm.loc_col, INDEX(_xlpm.data, , 3), _xlpm.target_date, DATE(YEAR($B$1), MONTH($B$1), G$7), _xlpm.filtered, _xlfn._xlws.FILTER(_xlpm.name_col, (_xlpm.date_col = _xlpm.target_date) * (_xlpm.loc_col =$B15), ""), IF(_xlpm.filtered="", "", _xlpm.filtered) )} -> Hazel | H15: {=_xlfn.LET( _xlpm.data, 表格3_5[[Date]:[Location]], _xlpm.date_col, INDEX(_xlpm.data, , 1), _xlpm.name_col, INDEX(_xlpm.data, , 2), _xlpm.loc_col, INDEX(_xlpm.data, , 3), _xlpm.target_date, DATE(YEAR($B$1), MONTH($B$1), H$7), _xlpm.filtered, _xlfn._xlws.FILTER(_xlpm.name_col, (_xlpm.date_col = _xlpm.target_date) * (_xlpm.loc_col =$B15), ""), IF(_xlpm.filtered="", "", _xlpm.filtered) )} -> Hazel | I15: {=_xlfn.LET( _xlpm.data, 表格3_5[[Date]:[Location]], _xlpm.date_col, INDEX(_xlpm.data, , 1), _xlpm.name_col, INDEX(_xlpm.data, , 2), _xlpm.loc_col, INDEX(_xlpm.data, , 3), _xlpm.target_date, DATE(YEAR($B$1), MONTH($B$1), I$7), _xlpm.filtered, _xlfn._xlws.FILTER(_xlpm.name_col, (_xlpm.date_col = _xlpm.target_date) * (_xlpm.loc_col =$B15), ""), IF(_xlpm.filtered="", "", _xlpm.filtered) )} | J15: {=_xlfn.LET( _xlpm.data, 表格3_5[[Date]:[Location]], _xlpm.date_col, INDEX(_xlpm.data, , 1), _xlpm.name_col, INDEX(_xlpm.data, , 2), _xlpm.loc_col, INDEX(_xlpm.data, , 3), _xlpm.target_date, DATE(YEAR($B$1), MONTH($B$1), J$7), _xlpm.filtered, _xlfn._xlws.FILTER(_xlpm.name_col, (_xlpm.date_col = _xlpm.target_date) * (_xlpm.loc_col =$B15), ""), IF(_xlpm.filtered="", "", _xlpm.filtered) )} | ... AG15: {=_xlfn.LET( _xlpm.data, 表格3_5[[Date]:[Location]], _xlpm.date_col, INDEX(_xlpm.data, , 1), _xlpm.name_col, INDEX(_xlpm.data, , 2), _xlpm.loc_col, INDEX(_xlpm.data, , 3), _xlpm.target_date, DATE(YEAR($B$1), MONTH($B$1), AG$7), _xlpm.filtered, _xlfn._xlws.FILTER(_xlpm.name_col, (_xlpm.date_col = _xlpm.target_date) * (_xlpm.loc_col =$B15), ""), IF(_xlpm.filtered="", "", _xlpm.filtered) )} | AH15: =COUNTIF(C15:AG15,"?*") -> 25 | AI15: =AH15*8 -> 200 | AL15: =B15 -> SW Wing On | AM15: =IF(C15=".",C15,IF(VLOOKUP($AL15&C$1+C10&C15, 工作表1!$C:$V,1,) > 0,C15,"ERROR")) -> #VALUE! | AN15: =IF(D15=".",D15,IF(VLOOKUP($AL15&D$1+D10&D15, 工作表1!$C:$V,1,) > 0,D15,"ERROR")) -> #VALUE! | AO15: =IF(E15=".",E15,IF(VLOOKUP($AL15&E$1+E10&E15, 工作表1!$C:$V,1,) > 0,E15,"ERROR")) -> #VALUE! | AP15: =IF(F15=".",F15,IF(VLOOKUP($AL15&F$1+F10&F15, 工作表1!$C:$V,1,) > 0,F15,"ERROR")) -> #VALUE! | AQ15: =IF(G15=".",G15,IF(VLOOKUP($AL15&G$1+G10&G15, 工作表1!$C:$V,1,) > 0,G15,"ERROR")) -> #VALUE! | AR15: =IF(H15=".",H15,IF(VLOOKUP($AL15&H$1+H10&H15, 工作表1!$C:$V,1,) > 0,H15,"ERROR")) -> #VALUE! | AS15: =IF(I15=".",I15,IF(VLOOKUP($AL15&I$1+I10&I15, 工作表1!$C:$V,1,) > 0,I15,"ERROR")) -> #VALUE! | AT15: =IF(J15=".",J15,IF(VLOOKUP($AL15&J$1+J10&J15, 工作表1!$C:$V,1,) > 0,J15,"ERROR")) -> #VALUE! | ... BQ15: =IF(AG15=".",AG15,IF(VLOOKUP($AL15&AG$1+AG10&AG15, 工作表1!$C:$V,1,) > 0,AG15,"ERROR")) -> #VALUE! | BR15: =IF(#REF!=".",#REF!,IF(VLOOKUP($AL15&#REF!+#REF!&#REF!, 工作表1!$C:$V,1,) > 0,#REF!,"ERROR")) -> #REF! | BS15: =IF(#REF!=".",#REF!,IF(VLOOKUP($AL15&#REF!+#REF!&#REF!, 工作表1!$C:$V,1,) > 0,#REF!,"ERROR")) -> #REF!
A16: {=_xlfn.LET( _xlpm.data, C16:AG16, _xlpm.removeList, {" off","."," SL","xxx"}, _xlpm.cleaned, TRIM(_xlfn.REDUCE(_xlpm.data, _xlpm.removeList, _xlfn.LAMBDA(_xlpm.arr,_xlpm.str, SUBSTITUTE(_xlpm.arr, _xlpm.str, "")))), _xlpm.first, _xlfn._xlws.FILTER(_xlpm.cleaned, _xlpm.cleaned <> ""), INDEX(_xlpm.first, 1) )} -> Joe | B16: Tai Po Yata | C16: {=_xlfn.LET( _xlpm.data, 表格3_5[[Date]:[Location]], _xlpm.date_col, INDEX(_xlpm.data, , 1), _xlpm.name_col, INDEX(_xlpm.data, , 2), _xlpm.loc_col, INDEX(_xlpm.data, , 3), _xlpm.target_date, DATE(YEAR($B$1), MONTH($B$1), C$7), _xlpm.filtered, _xlfn._xlws.FILTER(_xlpm.name_col, (_xlpm.date_col = _xlpm.target_date) * (_xlpm.loc_col =$B16), ""), IF(_xlpm.filtered="", "", _xlpm.filtered) )} | D16: {=_xlfn.LET( _xlpm.data, 表格3_5[[Date]:[Location]], _xlpm.date_col, INDEX(_xlpm.data, , 1), _xlpm.name_col, INDEX(_xlpm.data, , 2), _xlpm.loc_col, INDEX(_xlpm.data, , 3), _xlpm.target_date, DATE(YEAR($B$1), MONTH($B$1), D$7), _xlpm.filtered, _xlfn._xlws.FILTER(_xlpm.name_col, (_xlpm.date_col = _xlpm.target_date) * (_xlpm.loc_col =$B16), ""), IF(_xlpm.filtered="", "", _xlpm.filtered) )} | E16: {=_xlfn.LET( _xlpm.data, 表格3_5[[Date]:[Location]], _xlpm.date_col, INDEX(_xlpm.data, , 1), _xlpm.name_col, INDEX(_xlpm.data, , 2), _xlpm.loc_col, INDEX(_xlpm.data, , 3), _xlpm.target_date, DATE(YEAR($B$1), MONTH($B$1), E$7), _xlpm.filtered, _xlfn._xlws.FILTER(_xlpm.name_col, (_xlpm.date_col = _xlpm.target_date) * (_xlpm.loc_col =$B16), ""), IF(_xlpm.filtered="", "", _xlpm.filtered) )} | F16: {=_xlfn.LET( _xlpm.data, 表格3_5[[Date]:[Location]], _xlpm.date_col, INDEX(_xlpm.data, , 1), _xlpm.name_col, INDEX(_xlpm.data, , 2), _xlpm.loc_col, INDEX(_xlpm.data, , 3), _xlpm.target_date, DATE(YEAR($B$1), MONTH($B$1), F$7), _xlpm.filtered, _xlfn._xlws.FILTER(_xlpm.name_col, (_xlpm.date_col = _xlpm.target_date) * (_xlpm.loc_col =$B16), ""), IF(_xlpm.filtered="", "", _xlpm.filtered) )} | G16: {=_xlfn.LET( _xlpm.data, 表格3_5[[Date]:[Location]], _xlpm.date_col, INDEX(_xlpm.data, , 1), _xlpm.name_col, INDEX(_xlpm.data, , 2), _xlpm.loc_col, INDEX(_xlpm.data, , 3), _xlpm.target_date, DATE(YEAR($B$1), MONTH($B$1), G$7), _xlpm.filtered, _xlfn._xlws.FILTER(_xlpm.name_col, (_xlpm.date_col = _xlpm.target_date) * (_xlpm.loc_col =$B16), ""), IF(_xlpm.filtered="", "", _xlpm.filtered) )} -> Joe | H16: {=_xlfn.LET( _xlpm.data, 表格3_5[[Date]:[Location]], _xlpm.date_col, INDEX(_xlpm.data, , 1), _xlpm.name_col, INDEX(_xlpm.data, , 2), _xlpm.loc_col, INDEX(_xlpm.data, , 3), _xlpm.target_date, DATE(YEAR($B$1), MONTH($B$1), H$7), _xlpm.filtered, _xlfn._xlws.FILTER(_xlpm.name_col, (_xlpm.date_col = _xlpm.target_date) * (_xlpm.loc_col =$B16), ""), IF(_xlpm.filtered="", "", _xlpm.filtered) )} -> Joe | I16: {=_xlfn.LET( _xlpm.data, 表格3_5[[Date]:[Location]], _xlpm.date_col, INDEX(_xlpm.data, , 1), _xlpm.name_col, INDEX(_xlpm.data, , 2), _xlpm.loc_col, INDEX(_xlpm.data, , 3), _xlpm.target_date, DATE(YEAR($B$1), MONTH($B$1), I$7), _xlpm.filtered, _xlfn._xlws.FILTER(_xlpm.name_col, (_xlpm.date_col = _xlpm.target_date) * (_xlpm.loc_col =$B16), ""), IF(_xlpm.filtered="", "", _xlpm.filtered) )} -> Joe | J16: {=_xlfn.LET( _xlpm.data, 表格3_5[[Date]:[Location]], _xlpm.date_col, INDEX(_xlpm.data, , 1), _xlpm.name_col, INDEX(_xlpm.data, , 2), _xlpm.loc_col, INDEX(_xlpm.data, , 3), _xlpm.target_date, DATE(YEAR($B$1), MONTH($B$1), J$7), _xlpm.filtered, _xlfn._xlws.FILTER(_xlpm.name_col, (_xlpm.date_col = _xlpm.target_date) * (_xlpm.loc_col =$B16), ""), IF(_xlpm.filtered="", "", _xlpm.filtered) )} | ... AG16: {=_xlfn.LET( _xlpm.data, 表格3_5[[Date]:[Location]], _xlpm.date_col, INDEX(_xlpm.data, , 1), _xlpm.name_col, INDEX(_xlpm.data, , 2), _xlpm.loc_col, INDEX(_xlpm.data, , 3), _xlpm.target_date, DATE(YEAR($B$1), MONTH($B$1), AG$7), _xlpm.filtered, _xlfn._xlws.FILTER(_xlpm.name_col, (_xlpm.date_col = _xlpm.target_date) * (_xlpm.loc_col =$B16), ""), IF(_xlpm.filtered="", "", _xlpm.filtered) )} | AH16: =COUNTIF(C16:AG16,"?*") -> 12 | AI16: =AH16*8 -> 96 | AL16: =B16 -> Tai Po Yata | AM16: =IF(C16=".",C16,IF(VLOOKUP($AL16&C$1+C11&C16, 工作表1!$C:$V,1,) > 0,C16,"ERROR")) -> #VALUE! | AN16: =IF(D16=".",D16,IF(VLOOKUP($AL16&D$1+D11&D16, 工作表1!$C:$V,1,) > 0,D16,"ERROR")) -> #VALUE! | AO16: =IF(E16=".",E16,IF(VLOOKUP($AL16&E$1+E11&E16, 工作表1!$C:$V,1,) > 0,E16,"ERROR")) -> #VALUE! | AP16: =IF(F16=".",F16,IF(VLOOKUP($AL16&F$1+F11&F16, 工作表1!$C:$V,1,) > 0,F16,"ERROR")) -> #VALUE! | AQ16: =IF(G16=".",G16,IF(VLOOKUP($AL16&G$1+G11&G16, 工作表1!$C:$V,1,) > 0,G16,"ERROR")) -> #VALUE! | AR16: =IF(H16=".",H16,IF(VLOOKUP($AL16&H$1+H11&H16, 工作表1!$C:$V,1,) > 0,H16,"ERROR")) -> #VALUE! | AS16: =IF(I16=".",I16,IF(VLOOKUP($AL16&I$1+I11&I16, 工作表1!$C:$V,1,) > 0,I16,"ERROR")) -> #VALUE! | AT16: =IF(J16=".",J16,IF(VLOOKUP($AL16&J$1+J11&J16, 工作表1!$C:$V,1,) > 0,J16,"ERROR")) -> #VALUE! | ... BQ16: =IF(AG16=".",AG16,IF(VLOOKUP($AL16&AG$1+AG11&AG16, 工作表1!$C:$V,1,) > 0,AG16,"ERROR")) -> #VALUE! | BR16: =IF(#REF!=".",#REF!,IF(VLOOKUP($AL16&#REF!+#REF!&#REF!, 工作表1!$C:$V,1,) > 0,#REF!,"ERROR")) -> #REF! | BS16: =IF(#REF!=".",#REF!,IF(VLOOKUP($AL16&#REF!+#REF!&#REF!, 工作表1!$C:$V,1,) > 0,#REF!,"ERROR")) -> #REF!
A17: {=_xlfn.LET( _xlpm.data, C17:AG17, _xlpm.removeList, {" off","."," SL","xxx"}, _xlpm.cleaned, TRIM(_xlfn.REDUCE(_xlpm.data, _xlpm.removeList, _xlfn.LAMBDA(_xlpm.arr,_xlpm.str, SUBSTITUTE(_xlpm.arr, _xlpm.str, "")))), _xlpm.first, _xlfn._xlws.FILTER(_xlpm.cleaned, _xlpm.cleaned <> ""), INDEX(_xlpm.first, 1) )} -> Rebacca | B17: Tai Wan Fortress | C17: {=_xlfn.LET( _xlpm.data, 表格3_5[[Date]:[Location]], _xlpm.date_col, INDEX(_xlpm.data, , 1), _xlpm.name_col, INDEX(_xlpm.data, , 2), _xlpm.loc_col, INDEX(_xlpm.data, , 3), _xlpm.target_date, DATE(YEAR($B$1), MONTH($B$1), C$7), _xlpm.filtered, _xlfn._xlws.FILTER(_xlpm.name_col, (_xlpm.date_col = _xlpm.target_date) * (_xlpm.loc_col =$B17), ""), IF(_xlpm.filtered="", "", _xlpm.filtered) )} | D17: {=_xlfn.LET( _xlpm.data, 表格3_5[[Date]:[Location]], _xlpm.date_col, INDEX(_xlpm.data, , 1), _xlpm.name_col, INDEX(_xlpm.data, , 2), _xlpm.loc_col, INDEX(_xlpm.data, , 3), _xlpm.target_date, DATE(YEAR($B$1), MONTH($B$1), D$7), _xlpm.filtered, _xlfn._xlws.FILTER(_xlpm.name_col, (_xlpm.date_col = _xlpm.target_date) * (_xlpm.loc_col =$B17), ""), IF(_xlpm.filtered="", "", _xlpm.filtered) )} | E17: {=_xlfn.LET( _xlpm.data, 表格3_5[[Date]:[Location]], _xlpm.date_col, INDEX(_xlpm.data, , 1), _xlpm.name_col, INDEX(_xlpm.data, , 2), _xlpm.loc_col, INDEX(_xlpm.data, , 3), _xlpm.target_date, DATE(YEAR($B$1), MONTH($B$1), E$7), _xlpm.filtered, _xlfn._xlws.FILTER(_xlpm.name_col, (_xlpm.date_col = _xlpm.target_date) * (_xlpm.loc_col =$B17), ""), IF(_xlpm.filtered="", "", _xlpm.filtered) )} | F17: {=_xlfn.LET( _xlpm.data, 表格3_5[[Date]:[Location]], _xlpm.date_col, INDEX(_xlpm.data, , 1), _xlpm.name_col, INDEX(_xlpm.data, , 2), _xlpm.loc_col, INDEX(_xlpm.data, , 3), _xlpm.target_date, DATE(YEAR($B$1), MONTH($B$1), F$7), _xlpm.filtered, _xlfn._xlws.FILTER(_xlpm.name_col, (_xlpm.date_col = _xlpm.target_date) * (_xlpm.loc_col =$B17), ""), IF(_xlpm.filtered="", "", _xlpm.filtered) )} | G17: {=_xlfn.LET( _xlpm.data, 表格3_5[[Date]:[Location]], _xlpm.date_col, INDEX(_xlpm.data, , 1), _xlpm.name_col, INDEX(_xlpm.data, , 2), _xlpm.loc_col, INDEX(_xlpm.data, , 3), _xlpm.target_date, DATE(YEAR($B$1), MONTH($B$1), G$7), _xlpm.filtered, _xlfn._xlws.FILTER(_xlpm.name_col, (_xlpm.date_col = _xlpm.target_date) * (_xlpm.loc_col =$B17), ""), IF(_xlpm.filtered="", "", _xlpm.filtered) )} -> Rebacca | H17: {=_xlfn.LET( _xlpm.data, 表格3_5[[Date]:[Location]], _xlpm.date_col, INDEX(_xlpm.data, , 1), _xlpm.name_col, INDEX(_xlpm.data, , 2), _xlpm.loc_col, INDEX(_xlpm.data, , 3), _xlpm.target_date, DATE(YEAR($B$1), MONTH($B$1), H$7), _xlpm.filtered, _xlfn._xlws.FILTER(_xlpm.name_col, (_xlpm.date_col = _xlpm.target_date) * (_xlpm.loc_col =$B17), ""), IF(_xlpm.filtered="", "", _xlpm.filtered) )} -> Rebacca | I17: {=_xlfn.LET( _xlpm.data, 表格3_5[[Date]:[Location]], _xlpm.date_col, INDEX(_xlpm.data, , 1), _xlpm.name_col, INDEX(_xlpm.data, , 2), _xlpm.loc_col, INDEX(_xlpm.data, , 3), _xlpm.target_date, DATE(YEAR($B$1), MONTH($B$1), I$7), _xlpm.filtered, _xlfn._xlws.FILTER(_xlpm.name_col, (_xlpm.date_col = _xlpm.target_date) * (_xlpm.loc_col =$B17), ""), IF(_xlpm.filtered="", "", _xlpm.filtered) )} -> Rebacca | J17: {=_xlfn.LET( _xlpm.data, 表格3_5[[Date]:[Location]], _xlpm.date_col, INDEX(_xlpm.data, , 1), _xlpm.name_col, INDEX(_xlpm.data, , 2), _xlpm.loc_col, INDEX(_xlpm.data, , 3), _xlpm.target_date, DATE(YEAR($B$1), MONTH($B$1), J$7), _xlpm.filtered, _xlfn._xlws.FILTER(_xlpm.name_col, (_xlpm.date_col = _xlpm.target_date) * (_xlpm.loc_col =$B17), ""), IF(_xlpm.filtered="", "", _xlpm.filtered) )} | ... AG17: {=_xlfn.LET( _xlpm.data, 表格3_5[[Date]:[Location]], _xlpm.date_col, INDEX(_xlpm.data, , 1), _xlpm.name_col, INDEX(_xlpm.data, , 2), _xlpm.loc_col, INDEX(_xlpm.data, , 3), _xlpm.target_date, DATE(YEAR($B$1), MONTH($B$1), AG$7), _xlpm.filtered, _xlfn._xlws.FILTER(_xlpm.name_col, (_xlpm.date_col = _xlpm.target_date) * (_xlpm.loc_col =$B17), ""), IF(_xlpm.filtered="", "", _xlpm.filtered) )} | AH17: =COUNTIF(C17:AG17,"?*") -> 12 | AI17: =AH17*8 -> 96 | AL17: =B17 -> Tai Wan Fortress | AM17: =IF(C17=".",C17,IF(VLOOKUP($AL17&C$1+C12&C17, 工作表1!$C:$V,1,) > 0,C17,"ERROR")) -> #VALUE! | AN17: =IF(D17=".",D17,IF(VLOOKUP($AL17&D$1+D12&D17, 工作表1!$C:$V,1,) > 0,D17,"ERROR")) -> #VALUE! | AO17: =IF(E17=".",E17,IF(VLOOKUP($AL17&E$1+E12&E17, 工作表1!$C:$V,1,) > 0,E17,"ERROR")) -> #VALUE! | AP17: =IF(F17=".",F17,IF(VLOOKUP($AL17&F$1+F12&F17, 工作表1!$C:$V,1,) > 0,F17,"ERROR")) -> #VALUE! | AQ17: =IF(G17=".",G17,IF(VLOOKUP($AL17&G$1+G12&G17, 工作表1!$C:$V,1,) > 0,G17,"ERROR")) -> #VALUE! | AR17: =IF(H17=".",H17,IF(VLOOKUP($AL17&H$1+H12&H17, 工作表1!$C:$V,1,) > 0,H17,"ERROR")) -> #VALUE! | AS17: =IF(I17=".",I17,IF(VLOOKUP($AL17&I$1+I12&I17, 工作表1!$C:$V,1,) > 0,I17,"ERROR")) -> #VALUE! | AT17: =IF(J17=".",J17,IF(VLOOKUP($AL17&J$1+J12&J17, 工作表1!$C:$V,1,) > 0,J17,"ERROR")) -> #VALUE! | ... BQ17: =IF(AG17=".",AG17,IF(VLOOKUP($AL17&AG$1+AG12&AG17, 工作表1!$C:$V,1,) > 0,AG17,"ERROR")) -> #VALUE! | BR17: =IF(#REF!=".",#REF!,IF(VLOOKUP($AL17&#REF!+#REF!&#REF!, 工作表1!$C:$V,1,) > 0,#REF!,"ERROR")) -> #REF! | BS17: =IF(#REF!=".",#REF!,IF(VLOOKUP($AL17&#REF!+#REF!&#REF!, 工作表1!$C:$V,1,) > 0,#REF!,"ERROR")) -> #REF!
A18: {=_xlfn.LET( _xlpm.data, C18:AG18, _xlpm.removeList, {" off","."," SL","xxx"}, _xlpm.cleaned, TRIM(_xlfn.REDUCE(_xlpm.data, _xlpm.removeList, _xlfn.LAMBDA(_xlpm.arr,_xlpm.str, SUBSTITUTE(_xlpm.arr, _xlpm.str, "")))), _xlpm.first, _xlfn._xlws.FILTER(_xlpm.cleaned, _xlpm.cleaned <> ""), INDEX(_xlpm.first, 1) )} -> Tammy | B18: Tsing Yi Fortress | C18: {=_xlfn.LET( _xlpm.data, 表格3_5[[Date]:[Location]], _xlpm.date_col, INDEX(_xlpm.data, , 1), _xlpm.name_col, INDEX(_xlpm.data, , 2), _xlpm.loc_col, INDEX(_xlpm.data, , 3), _xlpm.target_date, DATE(YEAR($B$1), MONTH($B$1), C$7), _xlpm.filtered, _xlfn._xlws.FILTER(_xlpm.name_col, (_xlpm.date_col = _xlpm.target_date) * (_xlpm.loc_col =$B18), ""), IF(_xlpm.filtered="", "", _xlpm.filtered) )} | D18: {=_xlfn.LET( _xlpm.data, 表格3_5[[Date]:[Location]], _xlpm.date_col, INDEX(_xlpm.data, , 1), _xlpm.name_col, INDEX(_xlpm.data, , 2), _xlpm.loc_col, INDEX(_xlpm.data, , 3), _xlpm.target_date, DATE(YEAR($B$1), MONTH($B$1), D$7), _xlpm.filtered, _xlfn._xlws.FILTER(_xlpm.name_col, (_xlpm.date_col = _xlpm.target_date) * (_xlpm.loc_col =$B18), ""), IF(_xlpm.filtered="", "", _xlpm.filtered) )} | E18: {=_xlfn.LET( _xlpm.data, 表格3_5[[Date]:[Location]], _xlpm.date_col, INDEX(_xlpm.data, , 1), _xlpm.name_col, INDEX(_xlpm.data, , 2), _xlpm.loc_col, INDEX(_xlpm.data, , 3), _xlpm.target_date, DATE(YEAR($B$1), MONTH($B$1), E$7), _xlpm.filtered, _xlfn._xlws.FILTER(_xlpm.name_col, (_xlpm.date_col = _xlpm.target_date) * (_xlpm.loc_col =$B18), ""), IF(_xlpm.filtered="", "", _xlpm.filtered) )} | F18: {=_xlfn.LET( _xlpm.data, 表格3_5[[Date]:[Location]], _xlpm.date_col, INDEX(_xlpm.data, , 1), _xlpm.name_col, INDEX(_xlpm.data, , 2), _xlpm.loc_col, INDEX(_xlpm.data, , 3), _xlpm.target_date, DATE(YEAR($B$1), MONTH($B$1), F$7), _xlpm.filtered, _xlfn._xlws.FILTER(_xlpm.name_col, (_xlpm.date_col = _xlpm.target_date) * (_xlpm.loc_col =$B18), ""), IF(_xlpm.filtered="", "", _xlpm.filtered) )} | G18: {=_xlfn.LET( _xlpm.data, 表格3_5[[Date]:[Location]], _xlpm.date_col, INDEX(_xlpm.data, , 1), _xlpm.name_col, INDEX(_xlpm.data, , 2), _xlpm.loc_col, INDEX(_xlpm.data, , 3), _xlpm.target_date, DATE(YEAR($B$1), MONTH($B$1), G$7), _xlpm.filtered, _xlfn._xlws.FILTER(_xlpm.name_col, (_xlpm.date_col = _xlpm.target_date) * (_xlpm.loc_col =$B18), ""), IF(_xlpm.filtered="", "", _xlpm.filtered) )} -> Tammy | H18: {=_xlfn.LET( _xlpm.data, 表格3_5[[Date]:[Location]], _xlpm.date_col, INDEX(_xlpm.data, , 1), _xlpm.name_col, INDEX(_xlpm.data, , 2), _xlpm.loc_col, INDEX(_xlpm.data, , 3), _xlpm.target_date, DATE(YEAR($B$1), MONTH($B$1), H$7), _xlpm.filtered, _xlfn._xlws.FILTER(_xlpm.name_col, (_xlpm.date_col = _xlpm.target_date) * (_xlpm.loc_col =$B18), ""), IF(_xlpm.filtered="", "", _xlpm.filtered) )} -> Tammy | I18: {=_xlfn.LET( _xlpm.data, 表格3_5[[Date]:[Location]], _xlpm.date_col, INDEX(_xlpm.data, , 1), _xlpm.name_col, INDEX(_xlpm.data, , 2), _xlpm.loc_col, INDEX(_xlpm.data, , 3), _xlpm.target_date, DATE(YEAR($B$1), MONTH($B$1), I$7), _xlpm.filtered, _xlfn._xlws.FILTER(_xlpm.name_col, (_xlpm.date_col = _xlpm.target_date) * (_xlpm.loc_col =$B18), ""), IF(_xlpm.filtered="", "", _xlpm.filtered) )} -> Tammy | J18: {=_xlfn.LET( _xlpm.data, 表格3_5[[Date]:[Location]], _xlpm.date_col, INDEX(_xlpm.data, , 1), _xlpm.name_col, INDEX(_xlpm.data, , 2), _xlpm.loc_col, INDEX(_xlpm.data, , 3), _xlpm.target_date, DATE(YEAR($B$1), MONTH($B$1), J$7), _xlpm.filtered, _xlfn._xlws.FILTER(_xlpm.name_col, (_xlpm.date_col = _xlpm.target_date) * (_xlpm.loc_col =$B18), ""), IF(_xlpm.filtered="", "", _xlpm.filtered) )} | ... AG18: {=_xlfn.LET( _xlpm.data, 表格3_5[[Date]:[Location]], _xlpm.date_col, INDEX(_xlpm.data, , 1), _xlpm.name_col, INDEX(_xlpm.data, , 2), _xlpm.loc_col, INDEX(_xlpm.data, , 3), _xlpm.target_date, DATE(YEAR($B$1), MONTH($B$1), AG$7), _xlpm.filtered, _xlfn._xlws.FILTER(_xlpm.name_col, (_xlpm.date_col = _xlpm.target_date) * (_xlpm.loc_col =$B18), ""), IF(_xlpm.filtered="", "", _xlpm.filtered) )} | AH18: =COUNTIF(C18:AG18,"?*") -> 9 | AI18: =AH18*8 -> 72 | AL18: =B18 -> Tsing Yi Fortress | AM18: =IF(C18=".",C18,IF(VLOOKUP($AL18&C$1+C13&C18, 工作表1!$C:$V,1,) > 0,C18,"ERROR")) -> #VALUE! | AN18: =IF(D18=".",D18,IF(VLOOKUP($AL18&D$1+D13&D18, 工作表1!$C:$V,1,) > 0,D18,"ERROR")) -> #VALUE! | AO18: =IF(E18=".",E18,IF(VLOOKUP($AL18&E$1+E13&E18, 工作表1!$C:$V,1,) > 0,E18,"ERROR")) -> #VALUE! | AP18: =IF(F18=".",F18,IF(VLOOKUP($AL18&F$1+F13&F18, 工作表1!$C:$V,1,) > 0,F18,"ERROR")) -> #VALUE! | AQ18: =IF(G18=".",G18,IF(VLOOKUP($AL18&G$1+G13&G18, 工作表1!$C:$V,1,) > 0,G18,"ERROR")) -> #VALUE! | AR18: =IF(H18=".",H18,IF(VLOOKUP($AL18&H$1+H13&H18, 工作表1!$C:$V,1,) > 0,H18,"ERROR")) -> #VALUE! | AS18: =IF(I18=".",I18,IF(VLOOKUP($AL18&I$1+I13&I18, 工作表1!$C:$V,1,) > 0,I18,"ERROR")) -> #VALUE! | AT18: =IF(J18=".",J18,IF(VLOOKUP($AL18&J$1+J13&J18, 工作表1!$C:$V,1,) > 0,J18,"ERROR")) -> #VALUE! | ... BQ18: =IF(AG18=".",AG18,IF(VLOOKUP($AL18&AG$1+AG13&AG18, 工作表1!$C:$V,1,) > 0,AG18,"ERROR")) -> #VALUE! | BR18: =IF(#REF!=".",#REF!,IF(VLOOKUP($AL18&#REF!+#REF!&#REF!, 工作表1!$C:$V,1,) > 0,#REF!,"ERROR")) -> #REF! | BS18: =IF(#REF!=".",#REF!,IF(VLOOKUP($AL18&#REF!+#REF!&#REF!, 工作表1!$C:$V,1,) > 0,#REF!,"ERROR")) -> #REF!
A19: {=_xlfn.LET( _xlpm.data, C19:AG19, _xlpm.removeList, {" off","."," SL","xxx"}, _xlpm.cleaned, TRIM(_xlfn.REDUCE(_xlpm.data, _xlpm.removeList, _xlfn.LAMBDA(_xlpm.arr,_xlpm.str, SUBSTITUTE(_xlpm.arr, _xlpm.str, "")))), _xlpm.first, _xlfn._xlws.FILTER(_xlpm.cleaned, _xlpm.cleaned <> ""), INDEX(_xlpm.first, 1) )} -> May M | B19: Tuen Mun Broadway | C19: {=_xlfn.LET( _xlpm.data, 表格3_5[[Date]:[Location]], _xlpm.date_col, INDEX(_xlpm.data, , 1), _xlpm.name_col, INDEX(_xlpm.data, , 2), _xlpm.loc_col, INDEX(_xlpm.data, , 3), _xlpm.target_date, DATE(YEAR($B$1), MONTH($B$1), C$7), _xlpm.filtered, _xlfn._xlws.FILTER(_xlpm.name_col, (_xlpm.date_col = _xlpm.target_date) * (_xlpm.loc_col =$B19), ""), IF(_xlpm.filtered="", "", _xlpm.filtered) )} | D19: {=_xlfn.LET( _xlpm.data, 表格3_5[[Date]:[Location]], _xlpm.date_col, INDEX(_xlpm.data, , 1), _xlpm.name_col, INDEX(_xlpm.data, , 2), _xlpm.loc_col, INDEX(_xlpm.data, , 3), _xlpm.target_date, DATE(YEAR($B$1), MONTH($B$1), D$7), _xlpm.filtered, _xlfn._xlws.FILTER(_xlpm.name_col, (_xlpm.date_col = _xlpm.target_date) * (_xlpm.loc_col =$B19), ""), IF(_xlpm.filtered="", "", _xlpm.filtered) )} | E19: {=_xlfn.LET( _xlpm.data, 表格3_5[[Date]:[Location]], _xlpm.date_col, INDEX(_xlpm.data, , 1), _xlpm.name_col, INDEX(_xlpm.data, , 2), _xlpm.loc_col, INDEX(_xlpm.data, , 3), _xlpm.target_date, DATE(YEAR($B$1), MONTH($B$1), E$7), _xlpm.filtered, _xlfn._xlws.FILTER(_xlpm.name_col, (_xlpm.date_col = _xlpm.target_date) * (_xlpm.loc_col =$B19), ""), IF(_xlpm.filtered="", "", _xlpm.filtered) )} | F19: {=_xlfn.LET( _xlpm.data, 表格3_5[[Date]:[Location]], _xlpm.date_col, INDEX(_xlpm.data, , 1), _xlpm.name_col, INDEX(_xlpm.data, , 2), _xlpm.loc_col, INDEX(_xlpm.data, , 3), _xlpm.target_date, DATE(YEAR($B$1), MONTH($B$1), F$7), _xlpm.filtered, _xlfn._xlws.FILTER(_xlpm.name_col, (_xlpm.date_col = _xlpm.target_date) * (_xlpm.loc_col =$B19), ""), IF(_xlpm.filtered="", "", _xlpm.filtered) )} -> May M | G19: {=_xlfn.LET( _xlpm.data, 表格3_5[[Date]:[Location]], _xlpm.date_col, INDEX(_xlpm.data, , 1), _xlpm.name_col, INDEX(_xlpm.data, , 2), _xlpm.loc_col, INDEX(_xlpm.data, , 3), _xlpm.target_date, DATE(YEAR($B$1), MONTH($B$1), G$7), _xlpm.filtered, _xlfn._xlws.FILTER(_xlpm.name_col, (_xlpm.date_col = _xlpm.target_date) * (_xlpm.loc_col =$B19), ""), IF(_xlpm.filtered="", "", _xlpm.filtered) )} -> May M | H19: {=_xlfn.LET( _xlpm.data, 表格3_5[[Date]:[Location]], _xlpm.date_col, INDEX(_xlpm.data, , 1), _xlpm.name_col, INDEX(_xlpm.data, , 2), _xlpm.loc_col, INDEX(_xlpm.data, , 3), _xlpm.target_date, DATE(YEAR($B$1), MONTH($B$1), H$7), _xlpm.filtered, _xlfn._xlws.FILTER(_xlpm.name_col, (_xlpm.date_col = _xlpm.target_date) * (_xlpm.loc_col =$B19), ""), IF(_xlpm.filtered="", "", _xlpm.filtered) )} -> May M | I19: {=_xlfn.LET( _xlpm.data, 表格3_5[[Date]:[Location]], _xlpm.date_col, INDEX(_xlpm.data, , 1), _xlpm.name_col, INDEX(_xlpm.data, , 2), _xlpm.loc_col, INDEX(_xlpm.data, , 3), _xlpm.target_date, DATE(YEAR($B$1), MONTH($B$1), I$7), _xlpm.filtered, _xlfn._xlws.FILTER(_xlpm.name_col, (_xlpm.date_col = _xlpm.target_date) * (_xlpm.loc_col =$B19), ""), IF(_xlpm.filtered="", "", _xlpm.filtered) )} -> May M | J19: {=_xlfn.LET( _xlpm.data, 表格3_5[[Date]:[Location]], _xlpm.date_col, INDEX(_xlpm.data, , 1), _xlpm.name_col, INDEX(_xlpm.data, , 2), _xlpm.loc_col, INDEX(_xlpm.data, , 3), _xlpm.target_date, DATE(YEAR($B$1), MONTH($B$1), J$7), _xlpm.filtered, _xlfn._xlws.FILTER(_xlpm.name_col, (_xlpm.date_col = _xlpm.target_date) * (_xlpm.loc_col =$B19), ""), IF(_xlpm.filtered="", "", _xlpm.filtered) )} | ... AG19: {=_xlfn.LET( _xlpm.data, 表格3_5[[Date]:[Location]], _xlpm.date_col, INDEX(_xlpm.data, , 1), _xlpm.name_col, INDEX(_xlpm.data, , 2), _xlpm.loc_col, INDEX(_xlpm.data, , 3), _xlpm.target_date, DATE(YEAR($B$1), MONTH($B$1), AG$7), _xlpm.filtered, _xlfn._xlws.FILTER(_xlpm.name_col, (_xlpm.date_col = _xlpm.target_date) * (_xlpm.loc_col =$B19), ""), IF(_xlpm.filtered="", "", _xlpm.filtered) )} | AH19: =COUNTIF(C19:AG19,"?*") -> 16 | AI19: =AH19*8 -> 128 | AL19: =B19 -> Tuen Mun Broadway | AM19: =IF(C19=".",C19,IF(VLOOKUP($AL19&C$1+C14&C19, 工作表1!$C:$V,1,) > 0,C19,"ERROR")) -> #VALUE! | AN19: =IF(D19=".",D19,IF(VLOOKUP($AL19&D$1+D14&D19, 工作表1!$C:$V,1,) > 0,D19,"ERROR")) -> #VALUE! | AO19: =IF(E19=".",E19,IF(VLOOKUP($AL19&E$1+E14&E19, 工作表1!$C:$V,1,) > 0,E19,"ERROR")) -> #VALUE! | AP19: =IF(F19=".",F19,IF(VLOOKUP($AL19&F$1+F14&F19, 工作表1!$C:$V,1,) > 0,F19,"ERROR")) -> #VALUE! | AQ19: =IF(G19=".",G19,IF(VLOOKUP($AL19&G$1+G14&G19, 工作表1!$C:$V,1,) > 0,G19,"ERROR")) -> #VALUE! | AR19: =IF(H19=".",H19,IF(VLOOKUP($AL19&H$1+H14&H19, 工作表1!$C:$V,1,) > 0,H19,"ERROR")) -> #VALUE! | AS19: =IF(I19=".",I19,IF(VLOOKUP($AL19&I$1+I14&I19, 工作表1!$C:$V,1,) > 0,I19,"ERROR")) -> #VALUE! | AT19: =IF(J19=".",J19,IF(VLOOKUP($AL19&J$1+J14&J19, 工作表1!$C:$V,1,) > 0,J19,"ERROR")) -> #VALUE! | ... BQ19: =IF(AG19=".",AG19,IF(VLOOKUP($AL19&AG$1+AG14&AG19, 工作表1!$C:$V,1,) > 0,AG19,"ERROR")) -> #VALUE! | BR19: =IF(#REF!=".",#REF!,IF(VLOOKUP($AL19&#REF!+#REF!&#REF!, 工作表1!$C:$V,1,) > 0,#REF!,"ERROR")) -> #REF! | BS19: =IF(#REF!=".",#REF!,IF(VLOOKUP($AL19&#REF!+#REF!&#REF!, 工作表1!$C:$V,1,) > 0,#REF!,"ERROR")) -> #REF!
A20: {=_xlfn.LET( _xlpm.data, C20:AG20, _xlpm.removeList, {" off","."," SL","xxx"}, _xlpm.cleaned, TRIM(_xlfn.REDUCE(_xlpm.data, _xlpm.removeList, _xlfn.LAMBDA(_xlpm.arr,_xlpm.str, SUBSTITUTE(_xlpm.arr, _xlpm.str, "")))), _xlpm.first, _xlfn._xlws.FILTER(_xlpm.cleaned, _xlpm.cleaned <> ""), INDEX(_xlpm.first, 1) )} -> Fan | B20: TW Aeon | C20: {=_xlfn.LET( _xlpm.data, 表格3_5[[Date]:[Location]], _xlpm.date_col, INDEX(_xlpm.data, , 1), _xlpm.name_col, INDEX(_xlpm.data, , 2), _xlpm.loc_col, INDEX(_xlpm.data, , 3), _xlpm.target_date, DATE(YEAR($B$1), MONTH($B$1), C$7), _xlpm.filtered, _xlfn._xlws.FILTER(_xlpm.name_col, (_xlpm.date_col = _xlpm.target_date) * (_xlpm.loc_col =$B20), ""), IF(_xlpm.filtered="", "", _xlpm.filtered) )} | D20: {=_xlfn.LET( _xlpm.data, 表格3_5[[Date]:[Location]], _xlpm.date_col, INDEX(_xlpm.data, , 1), _xlpm.name_col, INDEX(_xlpm.data, , 2), _xlpm.loc_col, INDEX(_xlpm.data, , 3), _xlpm.target_date, DATE(YEAR($B$1), MONTH($B$1), D$7), _xlpm.filtered, _xlfn._xlws.FILTER(_xlpm.name_col, (_xlpm.date_col = _xlpm.target_date) * (_xlpm.loc_col =$B20), ""), IF(_xlpm.filtered="", "", _xlpm.filtered) )} | E20: {=_xlfn.LET( _xlpm.data, 表格3_5[[Date]:[Location]], _xlpm.date_col, INDEX(_xlpm.data, , 1), _xlpm.name_col, INDEX(_xlpm.data, , 2), _xlpm.loc_col, INDEX(_xlpm.data, , 3), _xlpm.target_date, DATE(YEAR($B$1), MONTH($B$1), E$7), _xlpm.filtered, _xlfn._xlws.FILTER(_xlpm.name_col, (_xlpm.date_col = _xlpm.target_date) * (_xlpm.loc_col =$B20), ""), IF(_xlpm.filtered="", "", _xlpm.filtered) )} | F20: {=_xlfn.LET( _xlpm.data, 表格3_5[[Date]:[Location]], _xlpm.date_col, INDEX(_xlpm.data, , 1), _xlpm.name_col, INDEX(_xlpm.data, , 2), _xlpm.loc_col, INDEX(_xlpm.data, , 3), _xlpm.target_date, DATE(YEAR($B$1), MONTH($B$1), F$7), _xlpm.filtered, _xlfn._xlws.FILTER(_xlpm.name_col, (_xlpm.date_col = _xlpm.target_date) * (_xlpm.loc_col =$B20), ""), IF(_xlpm.filtered="", "", _xlpm.filtered) )} | G20: {=_xlfn.LET( _xlpm.data, 表格3_5[[Date]:[Location]], _xlpm.date_col, INDEX(_xlpm.data, , 1), _xlpm.name_col, INDEX(_xlpm.data, , 2), _xlpm.loc_col, INDEX(_xlpm.data, , 3), _xlpm.target_date, DATE(YEAR($B$1), MONTH($B$1), G$7), _xlpm.filtered, _xlfn._xlws.FILTER(_xlpm.name_col, (_xlpm.date_col = _xlpm.target_date) * (_xlpm.loc_col =$B20), ""), IF(_xlpm.filtered="", "", _xlpm.filtered) )} | H20: {=_xlfn.LET( _xlpm.data, 表格3_5[[Date]:[Location]], _xlpm.date_col, INDEX(_xlpm.data, , 1), _xlpm.name_col, INDEX(_xlpm.data, , 2), _xlpm.loc_col, INDEX(_xlpm.data, , 3), _xlpm.target_date, DATE(YEAR($B$1), MONTH($B$1), H$7), _xlpm.filtered, _xlfn._xlws.FILTER(_xlpm.name_col, (_xlpm.date_col = _xlpm.target_date) * (_xlpm.loc_col =$B20), ""), IF(_xlpm.filtered="", "", _xlpm.filtered) )} -> Fan | I20: {=_xlfn.LET( _xlpm.data, 表格3_5[[Date]:[Location]], _xlpm.date_col, INDEX(_xlpm.data, , 1), _xlpm.name_col, INDEX(_xlpm.data, , 2), _xlpm.loc_col, INDEX(_xlpm.data, , 3), _xlpm.target_date, DATE(YEAR($B$1), MONTH($B$1), I$7), _xlpm.filtered, _xlfn._xlws.FILTER(_xlpm.name_col, (_xlpm.date_col = _xlpm.target_date) * (_xlpm.loc_col =$B20), ""), IF(_xlpm.filtered="", "", _xlpm.filtered) )} -> Fan | J20: {=_xlfn.LET( _xlpm.data, 表格3_5[[Date]:[Location]], _xlpm.date_col, INDEX(_xlpm.data, , 1), _xlpm.name_col, INDEX(_xlpm.data, , 2), _xlpm.loc_col, INDEX(_xlpm.data, , 3), _xlpm.target_date, DATE(YEAR($B$1), MONTH($B$1), J$7), _xlpm.filtered, _xlfn._xlws.FILTER(_xlpm.name_col, (_xlpm.date_col = _xlpm.target_date) * (_xlpm.loc_col =$B20), ""), IF(_xlpm.filtered="", "", _xlpm.filtered) )} | ... AG20: {=_xlfn.LET( _xlpm.data, 表格3_5[[Date]:[Location]], _xlpm.date_col, INDEX(_xlpm.data, , 1), _xlpm.name_col, INDEX(_xlpm.data, , 2), _xlpm.loc_col, INDEX(_xlpm.data, , 3), _xlpm.target_date, DATE(YEAR($B$1), MONTH($B$1), AG$7), _xlpm.filtered, _xlfn._xlws.FILTER(_xlpm.name_col, (_xlpm.date_col = _xlpm.target_date) * (_xlpm.loc_col =$B20), ""), IF(_xlpm.filtered="", "", _xlpm.filtered) )} | AH20: =COUNTIF(C20:AG20,"?*") -> 8 | AI20: =AH20*8 -> 64 | AL20: =B20 -> TW Aeon | AM20: =IF(C20=".",C20,IF(VLOOKUP($AL20&C$1+C15&C20, 工作表1!$C:$V,1,) > 0,C20,"ERROR")) -> #VALUE! | AN20: =IF(D20=".",D20,IF(VLOOKUP($AL20&D$1+D15&D20, 工作表1!$C:$V,1,) > 0,D20,"ERROR")) -> #VALUE! | AO20: =IF(E20=".",E20,IF(VLOOKUP($AL20&E$1+E15&E20, 工作表1!$C:$V,1,) > 0,E20,"ERROR")) -> #VALUE! | AP20: =IF(F20=".",F20,IF(VLOOKUP($AL20&F$1+F15&F20, 工作表1!$C:$V,1,) > 0,F20,"ERROR")) -> #VALUE! | AQ20: =IF(G20=".",G20,IF(VLOOKUP($AL20&G$1+G15&G20, 工作表1!$C:$V,1,) > 0,G20,"ERROR")) -> #VALUE! | AR20: =IF(H20=".",H20,IF(VLOOKUP($AL20&H$1+H15&H20, 工作表1!$C:$V,1,) > 0,H20,"ERROR")) -> #VALUE! | AS20: =IF(I20=".",I20,IF(VLOOKUP($AL20&I$1+I15&I20, 工作表1!$C:$V,1,) > 0,I20,"ERROR")) -> #VALUE! | AT20: =IF(J20=".",J20,IF(VLOOKUP($AL20&J$1+J15&J20, 工作表1!$C:$V,1,) > 0,J20,"ERROR")) -> #VALUE! | ... BQ20: =IF(AG20=".",AG20,IF(VLOOKUP($AL20&AG$1+AG15&AG20, 工作表1!$C:$V,1,) > 0,AG20,"ERROR")) -> #VALUE! | BR20: =IF(#REF!=".",#REF!,IF(VLOOKUP($AL20&#REF!+#REF!&#REF!, 工作表1!$C:$V,1,) > 0,#REF!,"ERROR")) -> #REF! | BS20: =IF(#REF!=".",#REF!,IF(VLOOKUP($AL20&#REF!+#REF!&#REF!, 工作表1!$C:$V,1,) > 0,#REF!,"ERROR")) -> #REF!
A21: {=_xlfn.LET( _xlpm.data, C21:AG21, _xlpm.removeList, {" off","."," SL","xxx"}, _xlpm.cleaned, TRIM(_xlfn.REDUCE(_xlpm.data, _xlpm.removeList, _xlfn.LAMBDA(_xlpm.arr,_xlpm.str, SUBSTITUTE(_xlpm.arr, _xlpm.str, "")))), _xlpm.first, _xlfn._xlws.FILTER(_xlpm.cleaned, _xlpm.cleaned <> ""), INDEX(_xlpm.first, 1) )} -> Mei Kiu | B21: TW YATA | C21: {=_xlfn.LET( _xlpm.data, 表格3_5[[Date]:[Location]], _xlpm.date_col, INDEX(_xlpm.data, , 1), _xlpm.name_col, INDEX(_xlpm.data, , 2), _xlpm.loc_col, INDEX(_xlpm.data, , 3), _xlpm.target_date, DATE(YEAR($B$1), MONTH($B$1), C$7), _xlpm.filtered, _xlfn._xlws.FILTER(_xlpm.name_col, (_xlpm.date_col = _xlpm.target_date) * (_xlpm.loc_col =$B21), ""), IF(_xlpm.filtered="", "", _xlpm.filtered) )} | D21: {=_xlfn.LET( _xlpm.data, 表格3_5[[Date]:[Location]], _xlpm.date_col, INDEX(_xlpm.data, , 1), _xlpm.name_col, INDEX(_xlpm.data, , 2), _xlpm.loc_col, INDEX(_xlpm.data, , 3), _xlpm.target_date, DATE(YEAR($B$1), MONTH($B$1), D$7), _xlpm.filtered, _xlfn._xlws.FILTER(_xlpm.name_col, (_xlpm.date_col = _xlpm.target_date) * (_xlpm.loc_col =$B21), ""), IF(_xlpm.filtered="", "", _xlpm.filtered) )} | E21: {=_xlfn.LET( _xlpm.data, 表格3_5[[Date]:[Location]], _xlpm.date_col, INDEX(_xlpm.data, , 1), _xlpm.name_col, INDEX(_xlpm.data, , 2), _xlpm.loc_col, INDEX(_xlpm.data, , 3), _xlpm.target_date, DATE(YEAR($B$1), MONTH($B$1), E$7), _xlpm.filtered, _xlfn._xlws.FILTER(_xlpm.name_col, (_xlpm.date_col = _xlpm.target_date) * (_xlpm.loc_col =$B21), ""), IF(_xlpm.filtered="", "", _xlpm.filtered) )} | F21: {=_xlfn.LET( _xlpm.data, 表格3_5[[Date]:[Location]], _xlpm.date_col, INDEX(_xlpm.data, , 1), _xlpm.name_col, INDEX(_xlpm.data, , 2), _xlpm.loc_col, INDEX(_xlpm.data, , 3), _xlpm.target_date, DATE(YEAR($B$1), MONTH($B$1), F$7), _xlpm.filtered, _xlfn._xlws.FILTER(_xlpm.name_col, (_xlpm.date_col = _xlpm.target_date) * (_xlpm.loc_col =$B21), ""), IF(_xlpm.filtered="", "", _xlpm.filtered) )} | G21: {=_xlfn.LET( _xlpm.data, 表格3_5[[Date]:[Location]], _xlpm.date_col, INDEX(_xlpm.data, , 1), _xlpm.name_col, INDEX(_xlpm.data, , 2), _xlpm.loc_col, INDEX(_xlpm.data, , 3), _xlpm.target_date, DATE(YEAR($B$1), MONTH($B$1), G$7), _xlpm.filtered, _xlfn._xlws.FILTER(_xlpm.name_col, (_xlpm.date_col = _xlpm.target_date) * (_xlpm.loc_col =$B21), ""), IF(_xlpm.filtered="", "", _xlpm.filtered) )} | H21: {=_xlfn.LET( _xlpm.data, 表格3_5[[Date]:[Location]], _xlpm.date_col, INDEX(_xlpm.data, , 1), _xlpm.name_col, INDEX(_xlpm.data, , 2), _xlpm.loc_col, INDEX(_xlpm.data, , 3), _xlpm.target_date, DATE(YEAR($B$1), MONTH($B$1), H$7), _xlpm.filtered, _xlfn._xlws.FILTER(_xlpm.name_col, (_xlpm.date_col = _xlpm.target_date) * (_xlpm.loc_col =$B21), ""), IF(_xlpm.filtered="", "", _xlpm.filtered) )} -> Mei Kiu | I21: {=_xlfn.LET( _xlpm.data, 表格3_5[[Date]:[Location]], _xlpm.date_col, INDEX(_xlpm.data, , 1), _xlpm.name_col, INDEX(_xlpm.data, , 2), _xlpm.loc_col, INDEX(_xlpm.data, , 3), _xlpm.target_date, DATE(YEAR($B$1), MONTH($B$1), I$7), _xlpm.filtered, _xlfn._xlws.FILTER(_xlpm.name_col, (_xlpm.date_col = _xlpm.target_date) * (_xlpm.loc_col =$B21), ""), IF(_xlpm.filtered="", "", _xlpm.filtered) )} -> Mei Kiu | J21: {=_xlfn.LET( _xlpm.data, 表格3_5[[Date]:[Location]], _xlpm.date_col, INDEX(_xlpm.data, , 1), _xlpm.name_col, INDEX(_xlpm.data, , 2), _xlpm.loc_col, INDEX(_xlpm.data, , 3), _xlpm.target_date, DATE(YEAR($B$1), MONTH($B$1), J$7), _xlpm.filtered, _xlfn._xlws.FILTER(_xlpm.name_col, (_xlpm.date_col = _xlpm.target_date) * (_xlpm.loc_col =$B21), ""), IF(_xlpm.filtered="", "", _xlpm.filtered) )} | ... AG21: {=_xlfn.LET( _xlpm.data, 表格3_5[[Date]:[Location]], _xlpm.date_col, INDEX(_xlpm.data, , 1), _xlpm.name_col, INDEX(_xlpm.data, , 2), _xlpm.loc_col, INDEX(_xlpm.data, , 3), _xlpm.target_date, DATE(YEAR($B$1), MONTH($B$1), AG$7), _xlpm.filtered, _xlfn._xlws.FILTER(_xlpm.name_col, (_xlpm.date_col = _xlpm.target_date) * (_xlpm.loc_col =$B21), ""), IF(_xlpm.filtered="", "", _xlpm.filtered) )} | AH21: =COUNTIF(C21:AG21,"?*") -> 8 | AI21: =AH21*8 -> 64
A22: {=_xlfn.LET( _xlpm.data, C22:AG22, _xlpm.removeList, {" off","."," SL","xxx"}, _xlpm.cleaned, TRIM(_xlfn.REDUCE(_xlpm.data, _xlpm.removeList, _xlfn.LAMBDA(_xlpm.arr,_xlpm.str, SUBSTITUTE(_xlpm.arr, _xlpm.str, "")))), _xlpm.first, _xlfn._xlws.FILTER(_xlpm.cleaned, _xlpm.cleaned <> ""), INDEX(_xlpm.first, 1) )} -> Ling | B22: YL Citistore | C22: {=_xlfn.LET( _xlpm.data, 表格3_5[[Date]:[Location]], _xlpm.date_col, INDEX(_xlpm.data, , 1), _xlpm.name_col, INDEX(_xlpm.data, , 2), _xlpm.loc_col, INDEX(_xlpm.data, , 3), _xlpm.target_date, DATE(YEAR($B$1), MONTH($B$1), C$7), _xlpm.filtered, _xlfn._xlws.FILTER(_xlpm.name_col, (_xlpm.date_col = _xlpm.target_date) * (_xlpm.loc_col =$B22), ""), IF(_xlpm.filtered="", "", _xlpm.filtered) )} | D22: {=_xlfn.LET( _xlpm.data, 表格3_5[[Date]:[Location]], _xlpm.date_col, INDEX(_xlpm.data, , 1), _xlpm.name_col, INDEX(_xlpm.data, , 2), _xlpm.loc_col, INDEX(_xlpm.data, , 3), _xlpm.target_date, DATE(YEAR($B$1), MONTH($B$1), D$7), _xlpm.filtered, _xlfn._xlws.FILTER(_xlpm.name_col, (_xlpm.date_col = _xlpm.target_date) * (_xlpm.loc_col =$B22), ""), IF(_xlpm.filtered="", "", _xlpm.filtered) )} | E22: {=_xlfn.LET( _xlpm.data, 表格3_5[[Date]:[Location]], _xlpm.date_col, INDEX(_xlpm.data, , 1), _xlpm.name_col, INDEX(_xlpm.data, , 2), _xlpm.loc_col, INDEX(_xlpm.data, , 3), _xlpm.target_date, DATE(YEAR($B$1), MONTH($B$1), E$7), _xlpm.filtered, _xlfn._xlws.FILTER(_xlpm.name_col, (_xlpm.date_col = _xlpm.target_date) * (_xlpm.loc_col =$B22), ""), IF(_xlpm.filtered="", "", _xlpm.filtered) )} | F22: {=_xlfn.LET( _xlpm.data, 表格3_5[[Date]:[Location]], _xlpm.date_col, INDEX(_xlpm.data, , 1), _xlpm.name_col, INDEX(_xlpm.data, , 2), _xlpm.loc_col, INDEX(_xlpm.data, , 3), _xlpm.target_date, DATE(YEAR($B$1), MONTH($B$1), F$7), _xlpm.filtered, _xlfn._xlws.FILTER(_xlpm.name_col, (_xlpm.date_col = _xlpm.target_date) * (_xlpm.loc_col =$B22), ""), IF(_xlpm.filtered="", "", _xlpm.filtered) )} -> Ling | G22: {=_xlfn.LET( _xlpm.data, 表格3_5[[Date]:[Location]], _xlpm.date_col, INDEX(_xlpm.data, , 1), _xlpm.name_col, INDEX(_xlpm.data, , 2), _xlpm.loc_col, INDEX(_xlpm.data, , 3), _xlpm.target_date, DATE(YEAR($B$1), MONTH($B$1), G$7), _xlpm.filtered, _xlfn._xlws.FILTER(_xlpm.name_col, (_xlpm.date_col = _xlpm.target_date) * (_xlpm.loc_col =$B22), ""), IF(_xlpm.filtered="", "", _xlpm.filtered) )} -> Ling | H22: {=_xlfn.LET( _xlpm.data, 表格3_5[[Date]:[Location]], _xlpm.date_col, INDEX(_xlpm.data, , 1), _xlpm.name_col, INDEX(_xlpm.data, , 2), _xlpm.loc_col, INDEX(_xlpm.data, , 3), _xlpm.target_date, DATE(YEAR($B$1), MONTH($B$1), H$7), _xlpm.filtered, _xlfn._xlws.FILTER(_xlpm.name_col, (_xlpm.date_col = _xlpm.target_date) * (_xlpm.loc_col =$B22), ""), IF(_xlpm.filtered="", "", _xlpm.filtered) )} -> Ling | I22: {=_xlfn.LET( _xlpm.data, 表格3_5[[Date]:[Location]], _xlpm.date_col, INDEX(_xlpm.data, , 1), _xlpm.name_col, INDEX(_xlpm.data, , 2), _xlpm.loc_col, INDEX(_xlpm.data, , 3), _xlpm.target_date, DATE(YEAR($B$1), MONTH($B$1), I$7), _xlpm.filtered, _xlfn._xlws.FILTER(_xlpm.name_col, (_xlpm.date_col = _xlpm.target_date) * (_xlpm.loc_col =$B22), ""), IF(_xlpm.filtered="", "", _xlpm.filtered) )} -> Ling | J22: {=_xlfn.LET( _xlpm.data, 表格3_5[[Date]:[Location]], _xlpm.date_col, INDEX(_xlpm.data, , 1), _xlpm.name_col, INDEX(_xlpm.data, , 2), _xlpm.loc_col, INDEX(_xlpm.data, , 3), _xlpm.target_date, DATE(YEAR($B$1), MONTH($B$1), J$7), _xlpm.filtered, _xlfn._xlws.FILTER(_xlpm.name_col, (_xlpm.date_col = _xlpm.target_date) * (_xlpm.loc_col =$B22), ""), IF(_xlpm.filtered="", "", _xlpm.filtered) )} | ... AG22: {=_xlfn.LET( _xlpm.data, 表格3_5[[Date]:[Location]], _xlpm.date_col, INDEX(_xlpm.data, , 1), _xlpm.name_col, INDEX(_xlpm.data, , 2), _xlpm.loc_col, INDEX(_xlpm.data, , 3), _xlpm.target_date, DATE(YEAR($B$1), MONTH($B$1), AG$7), _xlpm.filtered, _xlfn._xlws.FILTER(_xlpm.name_col, (_xlpm.date_col = _xlpm.target_date) * (_xlpm.loc_col =$B22), ""), IF(_xlpm.filtered="", "", _xlpm.filtered) )} | AH22: =COUNTIF(C22:AG22,"?*") -> 16 | AI22: =AH22*8 -> 128 | AM22: =IF(OR(C8="."), C8,"ERROR") -> ERROR
A23: {=_xlfn.LET( _xlpm.data, C23:AG23, _xlpm.removeList, {" off","."," SL","xxx"}, _xlpm.cleaned, TRIM(_xlfn.REDUCE(_xlpm.data, _xlpm.removeList, _xlfn.LAMBDA(_xlpm.arr,_xlpm.str, SUBSTITUTE(_xlpm.arr, _xlpm.str, "")))), _xlpm.first, _xlfn._xlws.FILTER(_xlpm.cleaned, _xlpm.cleaned <> ""), INDEX(_xlpm.first, 1) )} -> #VALUE! | C23: {=_xlfn.LET( _xlpm.data, 表格3_5[[Date]:[Location]], _xlpm.date_col, INDEX(_xlpm.data, , 1), _xlpm.name_col, INDEX(_xlpm.data, , 2), _xlpm.loc_col, INDEX(_xlpm.data, , 3), _xlpm.target_date, DATE(YEAR($B$1), MONTH($B$1), C$7), _xlpm.filtered, _xlfn._xlws.FILTER(_xlpm.name_col, (_xlpm.date_col = _xlpm.target_date) * (_xlpm.loc_col =$B23), ""), IF(_xlpm.filtered="", "", _xlpm.filtered) )} | D23: {=_xlfn.LET( _xlpm.data, 表格3_5[[Date]:[Location]], _xlpm.date_col, INDEX(_xlpm.data, , 1), _xlpm.name_col, INDEX(_xlpm.data, , 2), _xlpm.loc_col, INDEX(_xlpm.data, , 3), _xlpm.target_date, DATE(YEAR($B$1), MONTH($B$1), D$7), _xlpm.filtered, _xlfn._xlws.FILTER(_xlpm.name_col, (_xlpm.date_col = _xlpm.target_date) * (_xlpm.loc_col =$B23), ""), IF(_xlpm.filtered="", "", _xlpm.filtered) )} | E23: {=_xlfn.LET( _xlpm.data, 表格3_5[[Date]:[Location]], _xlpm.date_col, INDEX(_xlpm.data, , 1), _xlpm.name_col, INDEX(_xlpm.data, , 2), _xlpm.loc_col, INDEX(_xlpm.data, , 3), _xlpm.target_date, DATE(YEAR($B$1), MONTH($B$1), E$7), _xlpm.filtered, _xlfn._xlws.FILTER(_xlpm.name_col, (_xlpm.date_col = _xlpm.target_date) * (_xlpm.loc_col =$B23), ""), IF(_xlpm.filtered="", "", _xlpm.filtered) )} | F23: {=_xlfn.LET( _xlpm.data, 表格3_5[[Date]:[Location]], _xlpm.date_col, INDEX(_xlpm.data, , 1), _xlpm.name_col, INDEX(_xlpm.data, , 2), _xlpm.loc_col, INDEX(_xlpm.data, , 3), _xlpm.target_date, DATE(YEAR($B$1), MONTH($B$1), F$7), _xlpm.filtered, _xlfn._xlws.FILTER(_xlpm.name_col, (_xlpm.date_col = _xlpm.target_date) * (_xlpm.loc_col =$B23), ""), IF(_xlpm.filtered="", "", _xlpm.filtered) )} | G23: {=_xlfn.LET( _xlpm.data, 表格3_5[[Date]:[Location]], _xlpm.date_col, INDEX(_xlpm.data, , 1), _xlpm.name_col, INDEX(_xlpm.data, , 2), _xlpm.loc_col, INDEX(_xlpm.data, , 3), _xlpm.target_date, DATE(YEAR($B$1), MONTH($B$1), G$7), _xlpm.filtered, _xlfn._xlws.FILTER(_xlpm.name_col, (_xlpm.date_col = _xlpm.target_date) * (_xlpm.loc_col =$B23), ""), IF(_xlpm.filtered="", "", _xlpm.filtered) )} | H23: {=_xlfn.LET( _xlpm.data, 表格3_5[[Date]:[Location]], _xlpm.date_col, INDEX(_xlpm.data, , 1), _xlpm.name_col, INDEX(_xlpm.data, , 2), _xlpm.loc_col, INDEX(_xlpm.data, , 3), _xlpm.target_date, DATE(YEAR($B$1), MONTH($B$1), H$7), _xlpm.filtered, _xlfn._xlws.FILTER(_xlpm.name_col, (_xlpm.date_col = _xlpm.target_date) * (_xlpm.loc_col =$B23), ""), IF(_xlpm.filtered="", "", _xlpm.filtered) )} | I23: {=_xlfn.LET( _xlpm.data, 表格3_5[[Date]:[Location]], _xlpm.date_col, INDEX(_xlpm.data, , 1), _xlpm.name_col, INDEX(_xlpm.data, , 2), _xlpm.loc_col, INDEX(_xlpm.data, , 3), _xlpm.target_date, DATE(YEAR($B$1), MONTH($B$1), I$7), _xlpm.filtered, _xlfn._xlws.FILTER(_xlpm.name_col, (_xlpm.date_col = _xlpm.target_date) * (_xlpm.loc_col =$B23), ""), IF(_xlpm.filtered="", "", _xlpm.filtered) )} | J23: {=_xlfn.LET( _xlpm.data, 表格3_5[[Date]:[Location]], _xlpm.date_col, INDEX(_xlpm.data, , 1), _xlpm.name_col, INDEX(_xlpm.data, , 2), _xlpm.loc_col, INDEX(_xlpm.data, , 3), _xlpm.target_date, DATE(YEAR($B$1), MONTH($B$1), J$7), _xlpm.filtered, _xlfn._xlws.FILTER(_xlpm.name_col, (_xlpm.date_col = _xlpm.target_date) * (_xlpm.loc_col =$B23), ""), IF(_xlpm.filtered="", "", _xlpm.filtered) )} | ... AG23: {=_xlfn.LET( _xlpm.data, 表格3_5[[Date]:[Location]], _xlpm.date_col, INDEX(_xlpm.data, , 1), _xlpm.name_col, INDEX(_xlpm.data, , 2), _xlpm.loc_col, INDEX(_xlpm.data, , 3), _xlpm.target_date, DATE(YEAR($B$1), MONTH($B$1), AG$7), _xlpm.filtered, _xlfn._xlws.FILTER(_xlpm.name_col, (_xlpm.date_col = _xlpm.target_date) * (_xlpm.loc_col =$B23), ""), IF(_xlpm.filtered="", "", _xlpm.filtered) )} | AH23: =COUNTIF(C23:AG23,"?*") -> 0 | AI23: =AH23*8 -> 0
A24: {=_xlfn.LET( _xlpm.data, C24:AG24, _xlpm.removeList, {" off","."," SL","xxx"}, _xlpm.cleaned, TRIM(_xlfn.REDUCE(_xlpm.data, _xlpm.removeList, _xlfn.LAMBDA(_xlpm.arr,_xlpm.str, SUBSTITUTE(_xlpm.arr, _xlpm.str, "")))), _xlpm.first, _xlfn._xlws.FILTER(_xlpm.cleaned, _xlpm.cleaned <> ""), INDEX(_xlpm.first, 1) )} -> #VALUE! | C24: {=_xlfn.LET( _xlpm.data, 表格3_5[[Date]:[Location]], _xlpm.date_col, INDEX(_xlpm.data, , 1), _xlpm.name_col, INDEX(_xlpm.data, , 2), _xlpm.loc_col, INDEX(_xlpm.data, , 3), _xlpm.target_date, DATE(YEAR($B$1), MONTH($B$1), C$7), _xlpm.filtered, _xlfn._xlws.FILTER(_xlpm.name_col, (_xlpm.date_col = _xlpm.target_date) * (_xlpm.loc_col =$B24), ""), IF(_xlpm.filtered="", "", _xlpm.filtered) )} | D24: {=_xlfn.LET( _xlpm.data, 表格3_5[[Date]:[Location]], _xlpm.date_col, INDEX(_xlpm.data, , 1), _xlpm.name_col, INDEX(_xlpm.data, , 2), _xlpm.loc_col, INDEX(_xlpm.data, , 3), _xlpm.target_date, DATE(YEAR($B$1), MONTH($B$1), D$7), _xlpm.filtered, _xlfn._xlws.FILTER(_xlpm.name_col, (_xlpm.date_col = _xlpm.target_date) * (_xlpm.loc_col =$B24), ""), IF(_xlpm.filtered="", "", _xlpm.filtered) )} | E24: {=_xlfn.LET( _xlpm.data, 表格3_5[[Date]:[Location]], _xlpm.date_col, INDEX(_xlpm.data, , 1), _xlpm.name_col, INDEX(_xlpm.data, , 2), _xlpm.loc_col, INDEX(_xlpm.data, , 3), _xlpm.target_date, DATE(YEAR($B$1), MONTH($B$1), E$7), _xlpm.filtered, _xlfn._xlws.FILTER(_xlpm.name_col, (_xlpm.date_col = _xlpm.target_date) * (_xlpm.loc_col =$B24), ""), IF(_xlpm.filtered="", "", _xlpm.filtered) )} | F24: {=_xlfn.LET( _xlpm.data, 表格3_5[[Date]:[Location]], _xlpm.date_col, INDEX(_xlpm.data, , 1), _xlpm.name_col, INDEX(_xlpm.data, , 2), _xlpm.loc_col, INDEX(_xlpm.data, , 3), _xlpm.target_date, DATE(YEAR($B$1), MONTH($B$1), F$7), _xlpm.filtered, _xlfn._xlws.FILTER(_xlpm.name_col, (_xlpm.date_col = _xlpm.target_date) * (_xlpm.loc_col =$B24), ""), IF(_xlpm.filtered="", "", _xlpm.filtered) )} | G24: {=_xlfn.LET( _xlpm.data, 表格3_5[[Date]:[Location]], _xlpm.date_col, INDEX(_xlpm.data, , 1), _xlpm.name_col, INDEX(_xlpm.data, , 2), _xlpm.loc_col, INDEX(_xlpm.data, , 3), _xlpm.target_date, DATE(YEAR($B$1), MONTH($B$1), G$7), _xlpm.filtered, _xlfn._xlws.FILTER(_xlpm.name_col, (_xlpm.date_col = _xlpm.target_date) * (_xlpm.loc_col =$B24), ""), IF(_xlpm.filtered="", "", _xlpm.filtered) )} | H24: {=_xlfn.LET( _xlpm.data, 表格3_5[[Date]:[Location]], _xlpm.date_col, INDEX(_xlpm.data, , 1), _xlpm.name_col, INDEX(_xlpm.data, , 2), _xlpm.loc_col, INDEX(_xlpm.data, , 3), _xlpm.target_date, DATE(YEAR($B$1), MONTH($B$1), H$7), _xlpm.filtered, _xlfn._xlws.FILTER(_xlpm.name_col, (_xlpm.date_col = _xlpm.target_date) * (_xlpm.loc_col =$B24), ""), IF(_xlpm.filtered="", "", _xlpm.filtered) )} | I24: {=_xlfn.LET( _xlpm.data, 表格3_5[[Date]:[Location]], _xlpm.date_col, INDEX(_xlpm.data, , 1), _xlpm.name_col, INDEX(_xlpm.data, , 2), _xlpm.loc_col, INDEX(_xlpm.data, , 3), _xlpm.target_date, DATE(YEAR($B$1), MONTH($B$1), I$7), _xlpm.filtered, _xlfn._xlws.FILTER(_xlpm.name_col, (_xlpm.date_col = _xlpm.target_date) * (_xlpm.loc_col =$B24), ""), IF(_xlpm.filtered="", "", _xlpm.filtered) )} | J24: {=_xlfn.LET( _xlpm.data, 表格3_5[[Date]:[Location]], _xlpm.date_col, INDEX(_xlpm.data, , 1), _xlpm.name_col, INDEX(_xlpm.data, , 2), _xlpm.loc_col, INDEX(_xlpm.data, , 3), _xlpm.target_date, DATE(YEAR($B$1), MONTH($B$1), J$7), _xlpm.filtered, _xlfn._xlws.FILTER(_xlpm.name_col, (_xlpm.date_col = _xlpm.target_date) * (_xlpm.loc_col =$B24), ""), IF(_xlpm.filtered="", "", _xlpm.filtered) )} | ... AG24: {=_xlfn.LET( _xlpm.data, 表格3_5[[Date]:[Location]], _xlpm.date_col, INDEX(_xlpm.data, , 1), _xlpm.name_col, INDEX(_xlpm.data, , 2), _xlpm.loc_col, INDEX(_xlpm.data, , 3), _xlpm.target_date, DATE(YEAR($B$1), MONTH($B$1), AG$7), _xlpm.filtered, _xlfn._xlws.FILTER(_xlpm.name_col, (_xlpm.date_col = _xlpm.target_date) * (_xlpm.loc_col =$B24), ""), IF(_xlpm.filtered="", "", _xlpm.filtered) )} | AH24: =COUNTIF(C24:AG24,"?*") -> 0 | AI24: =AH24*8 -> 0
A25: {=_xlfn.LET( _xlpm.data, C25:AG25, _xlpm.removeList, {" off","."," SL","xxx"}, _xlpm.cleaned, TRIM(_xlfn.REDUCE(_xlpm.data, _xlpm.removeList, _xlfn.LAMBDA(_xlpm.arr,_xlpm.str, SUBSTITUTE(_xlpm.arr, _xlpm.str, "")))), _xlpm.first, _xlfn._xlws.FILTER(_xlpm.cleaned, _xlpm.cleaned <> ""), INDEX(_xlpm.first, 1) )} -> #VALUE! | C25: {=_xlfn.LET( _xlpm.data, 表格3_5[[Date]:[Location]], _xlpm.date_col, INDEX(_xlpm.data, , 1), _xlpm.name_col, INDEX(_xlpm.data, , 2), _xlpm.loc_col, INDEX(_xlpm.data, , 3), _xlpm.target_date, DATE(YEAR($B$1), MONTH($B$1), C$7), _xlpm.filtered, _xlfn._xlws.FILTER(_xlpm.name_col, (_xlpm.date_col = _xlpm.target_date) * (_xlpm.loc_col =$B25), ""), IF(_xlpm.filtered="", "", _xlpm.filtered) )} | D25: {=_xlfn.LET( _xlpm.data, 表格3_5[[Date]:[Location]], _xlpm.date_col, INDEX(_xlpm.data, , 1), _xlpm.name_col, INDEX(_xlpm.data, , 2), _xlpm.loc_col, INDEX(_xlpm.data, , 3), _xlpm.target_date, DATE(YEAR($B$1), MONTH($B$1), D$7), _xlpm.filtered, _xlfn._xlws.FILTER(_xlpm.name_col, (_xlpm.date_col = _xlpm.target_date) * (_xlpm.loc_col =$B25), ""), IF(_xlpm.filtered="", "", _xlpm.filtered) )} | E25: {=_xlfn.LET( _xlpm.data, 表格3_5[[Date]:[Location]], _xlpm.date_col, INDEX(_xlpm.data, , 1), _xlpm.name_col, INDEX(_xlpm.data, , 2), _xlpm.loc_col, INDEX(_xlpm.data, , 3), _xlpm.target_date, DATE(YEAR($B$1), MONTH($B$1), E$7), _xlpm.filtered, _xlfn._xlws.FILTER(_xlpm.name_col, (_xlpm.date_col = _xlpm.target_date) * (_xlpm.loc_col =$B25), ""), IF(_xlpm.filtered="", "", _xlpm.filtered) )} | F25: {=_xlfn.LET( _xlpm.data, 表格3_5[[Date]:[Location]], _xlpm.date_col, INDEX(_xlpm.data, , 1), _xlpm.name_col, INDEX(_xlpm.data, , 2), _xlpm.loc_col, INDEX(_xlpm.data, , 3), _xlpm.target_date, DATE(YEAR($B$1), MONTH($B$1), F$7), _xlpm.filtered, _xlfn._xlws.FILTER(_xlpm.name_col, (_xlpm.date_col = _xlpm.target_date) * (_xlpm.loc_col =$B25), ""), IF(_xlpm.filtered="", "", _xlpm.filtered) )} | G25: {=_xlfn.LET( _xlpm.data, 表格3_5[[Date]:[Location]], _xlpm.date_col, INDEX(_xlpm.data, , 1), _xlpm.name_col, INDEX(_xlpm.data, , 2), _xlpm.loc_col, INDEX(_xlpm.data, , 3), _xlpm.target_date, DATE(YEAR($B$1), MONTH($B$1), G$7), _xlpm.filtered, _xlfn._xlws.FILTER(_xlpm.name_col, (_xlpm.date_col = _xlpm.target_date) * (_xlpm.loc_col =$B25), ""), IF(_xlpm.filtered="", "", _xlpm.filtered) )} | H25: {=_xlfn.LET( _xlpm.data, 表格3_5[[Date]:[Location]], _xlpm.date_col, INDEX(_xlpm.data, , 1), _xlpm.name_col, INDEX(_xlpm.data, , 2), _xlpm.loc_col, INDEX(_xlpm.data, , 3), _xlpm.target_date, DATE(YEAR($B$1), MONTH($B$1), H$7), _xlpm.filtered, _xlfn._xlws.FILTER(_xlpm.name_col, (_xlpm.date_col = _xlpm.target_date) * (_xlpm.loc_col =$B25), ""), IF(_xlpm.filtered="", "", _xlpm.filtered) )} | I25: {=_xlfn.LET( _xlpm.data, 表格3_5[[Date]:[Location]], _xlpm.date_col, INDEX(_xlpm.data, , 1), _xlpm.name_col, INDEX(_xlpm.data, , 2), _xlpm.loc_col, INDEX(_xlpm.data, , 3), _xlpm.target_date, DATE(YEAR($B$1), MONTH($B$1), I$7), _xlpm.filtered, _xlfn._xlws.FILTER(_xlpm.name_col, (_xlpm.date_col = _xlpm.target_date) * (_xlpm.loc_col =$B25), ""), IF(_xlpm.filtered="", "", _xlpm.filtered) )} | J25: {=_xlfn.LET( _xlpm.data, 表格3_5[[Date]:[Location]], _xlpm.date_col, INDEX(_xlpm.data, , 1), _xlpm.name_col, INDEX(_xlpm.data, , 2), _xlpm.loc_col, INDEX(_xlpm.data, , 3), _xlpm.target_date, DATE(YEAR($B$1), MONTH($B$1), J$7), _xlpm.filtered, _xlfn._xlws.FILTER(_xlpm.name_col, (_xlpm.date_col = _xlpm.target_date) * (_xlpm.loc_col =$B25), ""), IF(_xlpm.filtered="", "", _xlpm.filtered) )} | ... AG25: {=_xlfn.LET( _xlpm.data, 表格3_5[[Date]:[Location]], _xlpm.date_col, INDEX(_xlpm.data, , 1), _xlpm.name_col, INDEX(_xlpm.data, , 2), _xlpm.loc_col, INDEX(_xlpm.data, , 3), _xlpm.target_date, DATE(YEAR($B$1), MONTH($B$1), AG$7), _xlpm.filtered, _xlfn._xlws.FILTER(_xlpm.name_col, (_xlpm.date_col = _xlpm.target_date) * (_xlpm.loc_col =$B25), ""), IF(_xlpm.filtered="", "", _xlpm.filtered) )} | AH25: =COUNTIF(C25:AG25,"?*") -> 0 | AI25: =AH25*8 -> 0
A26: {=_xlfn.LET( _xlpm.data, C26:AG26, _xlpm.removeList, {" off","."," SL","xxx"}, _xlpm.cleaned, TRIM(_xlfn.REDUCE(_xlpm.data, _xlpm.removeList, _xlfn.LAMBDA(_xlpm.arr,_xlpm.str, SUBSTITUTE(_xlpm.arr, _xlpm.str, "")))), _xlpm.first, _xlfn._xlws.FILTER(_xlpm.cleaned, _xlpm.cleaned <> ""), INDEX(_xlpm.first, 1) )} -> #VALUE! | C26: {=_xlfn.LET( _xlpm.data, 表格3_5[[Date]:[Location]], _xlpm.date_col, INDEX(_xlpm.data, , 1), _xlpm.name_col, INDEX(_xlpm.data, , 2), _xlpm.loc_col, INDEX(_xlpm.data, , 3), _xlpm.target_date, DATE(YEAR($B$1), MONTH($B$1), C$7), _xlpm.filtered, _xlfn._xlws.FILTER(_xlpm.name_col, (_xlpm.date_col = _xlpm.target_date) * (_xlpm.loc_col =$B26), ""), IF(_xlpm.filtered="", "", _xlpm.filtered) )} | D26: {=_xlfn.LET( _xlpm.data, 表格3_5[[Date]:[Location]], _xlpm.date_col, INDEX(_xlpm.data, , 1), _xlpm.name_col, INDEX(_xlpm.data, , 2), _xlpm.loc_col, INDEX(_xlpm.data, , 3), _xlpm.target_date, DATE(YEAR($B$1), MONTH($B$1), D$7), _xlpm.filtered, _xlfn._xlws.FILTER(_xlpm.name_col, (_xlpm.date_col = _xlpm.target_date) * (_xlpm.loc_col =$B26), ""), IF(_xlpm.filtered="", "", _xlpm.filtered) )} | E26: {=_xlfn.LET( _xlpm.data, 表格3_5[[Date]:[Location]], _xlpm.date_col, INDEX(_xlpm.data, , 1), _xlpm.name_col, INDEX(_xlpm.data, , 2), _xlpm.loc_col, INDEX(_xlpm.data, , 3), _xlpm.target_date, DATE(YEAR($B$1), MONTH($B$1), E$7), _xlpm.filtered, _xlfn._xlws.FILTER(_xlpm.name_col, (_xlpm.date_col = _xlpm.target_date) * (_xlpm.loc_col =$B26), ""), IF(_xlpm.filtered="", "", _xlpm.filtered) )} | F26: {=_xlfn.LET( _xlpm.data, 表格3_5[[Date]:[Location]], _xlpm.date_col, INDEX(_xlpm.data, , 1), _xlpm.name_col, INDEX(_xlpm.data, , 2), _xlpm.loc_col, INDEX(_xlpm.data, , 3), _xlpm.target_date, DATE(YEAR($B$1), MONTH($B$1), F$7), _xlpm.filtered, _xlfn._xlws.FILTER(_xlpm.name_col, (_xlpm.date_col = _xlpm.target_date) * (_xlpm.loc_col =$B26), ""), IF(_xlpm.filtered="", "", _xlpm.filtered) )} | G26: {=_xlfn.LET( _xlpm.data, 表格3_5[[Date]:[Location]], _xlpm.date_col, INDEX(_xlpm.data, , 1), _xlpm.name_col, INDEX(_xlpm.data, , 2), _xlpm.loc_col, INDEX(_xlpm.data, , 3), _xlpm.target_date, DATE(YEAR($B$1), MONTH($B$1), G$7), _xlpm.filtered, _xlfn._xlws.FILTER(_xlpm.name_col, (_xlpm.date_col = _xlpm.target_date) * (_xlpm.loc_col =$B26), ""), IF(_xlpm.filtered="", "", _xlpm.filtered) )} | H26: {=_xlfn.LET( _xlpm.data, 表格3_5[[Date]:[Location]], _xlpm.date_col, INDEX(_xlpm.data, , 1), _xlpm.name_col, INDEX(_xlpm.data, , 2), _xlpm.loc_col, INDEX(_xlpm.data, , 3), _xlpm.target_date, DATE(YEAR($B$1), MONTH($B$1), H$7), _xlpm.filtered, _xlfn._xlws.FILTER(_xlpm.name_col, (_xlpm.date_col = _xlpm.target_date) * (_xlpm.loc_col =$B26), ""), IF(_xlpm.filtered="", "", _xlpm.filtered) )} | I26: {=_xlfn.LET( _xlpm.data, 表格3_5[[Date]:[Location]], _xlpm.date_col, INDEX(_xlpm.data, , 1), _xlpm.name_col, INDEX(_xlpm.data, , 2), _xlpm.loc_col, INDEX(_xlpm.data, , 3), _xlpm.target_date, DATE(YEAR($B$1), MONTH($B$1), I$7), _xlpm.filtered, _xlfn._xlws.FILTER(_xlpm.name_col, (_xlpm.date_col = _xlpm.target_date) * (_xlpm.loc_col =$B26), ""), IF(_xlpm.filtered="", "", _xlpm.filtered) )} | J26: {=_xlfn.LET( _xlpm.data, 表格3_5[[Date]:[Location]], _xlpm.date_col, INDEX(_xlpm.data, , 1), _xlpm.name_col, INDEX(_xlpm.data, , 2), _xlpm.loc_col, INDEX(_xlpm.data, , 3), _xlpm.target_date, DATE(YEAR($B$1), MONTH($B$1), J$7), _xlpm.filtered, _xlfn._xlws.FILTER(_xlpm.name_col, (_xlpm.date_col = _xlpm.target_date) * (_xlpm.loc_col =$B26), ""), IF(_xlpm.filtered="", "", _xlpm.filtered) )} | ... AG26: {=_xlfn.LET( _xlpm.data, 表格3_5[[Date]:[Location]], _xlpm.date_col, INDEX(_xlpm.data, , 1), _xlpm.name_col, INDEX(_xlpm.data, , 2), _xlpm.loc_col, INDEX(_xlpm.data, , 3), _xlpm.target_date, DATE(YEAR($B$1), MONTH($B$1), AG$7), _xlpm.filtered, _xlfn._xlws.FILTER(_xlpm.name_col, (_xlpm.date_col = _xlpm.target_date) * (_xlpm.loc_col =$B26), ""), IF(_xlpm.filtered="", "", _xlpm.filtered) )} | AH26: =COUNTIF(C26:AG26,"?*") -> 0 | AI26: =AH26*8 -> 0
A27: {=_xlfn.LET( _xlpm.data, C27:AG27, _xlpm.removeList, {" off","."," SL","xxx"}, _xlpm.cleaned, TRIM(_xlfn.REDUCE(_xlpm.data, _xlpm.removeList, _xlfn.LAMBDA(_xlpm.arr,_xlpm.str, SUBSTITUTE(_xlpm.arr, _xlpm.str, "")))), _xlpm.first, _xlfn._xlws.FILTER(_xlpm.cleaned, _xlpm.cleaned <> ""), INDEX(_xlpm.first, 1) )} -> #VALUE! | C27: {=_xlfn.LET( _xlpm.data, 表格3_5[[Date]:[Location]], _xlpm.date_col, INDEX(_xlpm.data, , 1), _xlpm.name_col, INDEX(_xlpm.data, , 2), _xlpm.loc_col, INDEX(_xlpm.data, , 3), _xlpm.target_date, DATE(YEAR($B$1), MONTH($B$1), C$7), _xlpm.filtered, _xlfn._xlws.FILTER(_xlpm.name_col, (_xlpm.date_col = _xlpm.target_date) * (_xlpm.loc_col =$B27), ""), IF(_xlpm.filtered="", "", _xlpm.filtered) )} | D27: {=_xlfn.LET( _xlpm.data, 表格3_5[[Date]:[Location]], _xlpm.date_col, INDEX(_xlpm.data, , 1), _xlpm.name_col, INDEX(_xlpm.data, , 2), _xlpm.loc_col, INDEX(_xlpm.data, , 3), _xlpm.target_date, DATE(YEAR($B$1), MONTH($B$1), D$7), _xlpm.filtered, _xlfn._xlws.FILTER(_xlpm.name_col, (_xlpm.date_col = _xlpm.target_date) * (_xlpm.loc_col =$B27), ""), IF(_xlpm.filtered="", "", _xlpm.filtered) )} | E27: {=_xlfn.LET( _xlpm.data, 表格3_5[[Date]:[Location]], _xlpm.date_col, INDEX(_xlpm.data, , 1), _xlpm.name_col, INDEX(_xlpm.data, , 2), _xlpm.loc_col, INDEX(_xlpm.data, , 3), _xlpm.target_date, DATE(YEAR($B$1), MONTH($B$1), E$7), _xlpm.filtered, _xlfn._xlws.FILTER(_xlpm.name_col, (_xlpm.date_col = _xlpm.target_date) * (_xlpm.loc_col =$B27), ""), IF(_xlpm.filtered="", "", _xlpm.filtered) )} | F27: {=_xlfn.LET( _xlpm.data, 表格3_5[[Date]:[Location]], _xlpm.date_col, INDEX(_xlpm.data, , 1), _xlpm.name_col, INDEX(_xlpm.data, , 2), _xlpm.loc_col, INDEX(_xlpm.data, , 3), _xlpm.target_date, DATE(YEAR($B$1), MONTH($B$1), F$7), _xlpm.filtered, _xlfn._xlws.FILTER(_xlpm.name_col, (_xlpm.date_col = _xlpm.target_date) * (_xlpm.loc_col =$B27), ""), IF(_xlpm.filtered="", "", _xlpm.filtered) )} | G27: {=_xlfn.LET( _xlpm.data, 表格3_5[[Date]:[Location]], _xlpm.date_col, INDEX(_xlpm.data, , 1), _xlpm.name_col, INDEX(_xlpm.data, , 2), _xlpm.loc_col, INDEX(_xlpm.data, , 3), _xlpm.target_date, DATE(YEAR($B$1), MONTH($B$1), G$7), _xlpm.filtered, _xlfn._xlws.FILTER(_xlpm.name_col, (_xlpm.date_col = _xlpm.target_date) * (_xlpm.loc_col =$B27), ""), IF(_xlpm.filtered="", "", _xlpm.filtered) )} | H27: {=_xlfn.LET( _xlpm.data, 表格3_5[[Date]:[Location]], _xlpm.date_col, INDEX(_xlpm.data, , 1), _xlpm.name_col, INDEX(_xlpm.data, , 2), _xlpm.loc_col, INDEX(_xlpm.data, , 3), _xlpm.target_date, DATE(YEAR($B$1), MONTH($B$1), H$7), _xlpm.filtered, _xlfn._xlws.FILTER(_xlpm.name_col, (_xlpm.date_col = _xlpm.target_date) * (_xlpm.loc_col =$B27), ""), IF(_xlpm.filtered="", "", _xlpm.filtered) )} | I27: {=_xlfn.LET( _xlpm.data, 表格3_5[[Date]:[Location]], _xlpm.date_col, INDEX(_xlpm.data, , 1), _xlpm.name_col, INDEX(_xlpm.data, , 2), _xlpm.loc_col, INDEX(_xlpm.data, , 3), _xlpm.target_date, DATE(YEAR($B$1), MONTH($B$1), I$7), _xlpm.filtered, _xlfn._xlws.FILTER(_xlpm.name_col, (_xlpm.date_col = _xlpm.target_date) * (_xlpm.loc_col =$B27), ""), IF(_xlpm.filtered="", "", _xlpm.filtered) )} | J27: {=_xlfn.LET( _xlpm.data, 表格3_5[[Date]:[Location]], _xlpm.date_col, INDEX(_xlpm.data, , 1), _xlpm.name_col, INDEX(_xlpm.data, , 2), _xlpm.loc_col, INDEX(_xlpm.data, , 3), _xlpm.target_date, DATE(YEAR($B$1), MONTH($B$1), J$7), _xlpm.filtered, _xlfn._xlws.FILTER(_xlpm.name_col, (_xlpm.date_col = _xlpm.target_date) * (_xlpm.loc_col =$B27), ""), IF(_xlpm.filtered="", "", _xlpm.filtered) )} | ... AG27: {=_xlfn.LET( _xlpm.data, 表格3_5[[Date]:[Location]], _xlpm.date_col, INDEX(_xlpm.data, , 1), _xlpm.name_col, INDEX(_xlpm.data, , 2), _xlpm.loc_col, INDEX(_xlpm.data, , 3), _xlpm.target_date, DATE(YEAR($B$1), MONTH($B$1), AG$7), _xlpm.filtered, _xlfn._xlws.FILTER(_xlpm.name_col, (_xlpm.date_col = _xlpm.target_date) * (_xlpm.loc_col =$B27), ""), IF(_xlpm.filtered="", "", _xlpm.filtered) )} | AH27: =COUNTIF(C27:AG27,"?*") -> 0 | AI27: =AH27*8 -> 0
A28: {=_xlfn.LET( _xlpm.data, C28:AG28, _xlpm.removeList, {" off","."," SL","xxx"}, _xlpm.cleaned, TRIM(_xlfn.REDUCE(_xlpm.data, _xlpm.removeList, _xlfn.LAMBDA(_xlpm.arr,_xlpm.str, SUBSTITUTE(_xlpm.arr, _xlpm.str, "")))), _xlpm.first, _xlfn._xlws.FILTER(_xlpm.cleaned, _xlpm.cleaned <> ""), INDEX(_xlpm.first, 1) )} -> #VALUE! | C28: {=_xlfn.LET( _xlpm.data, 表格3_5[[Date]:[Location]], _xlpm.date_col, INDEX(_xlpm.data, , 1), _xlpm.name_col, INDEX(_xlpm.data, , 2), _xlpm.loc_col, INDEX(_xlpm.data, , 3), _xlpm.target_date, DATE(YEAR($B$1), MONTH($B$1), C$7), _xlpm.filtered, _xlfn._xlws.FILTER(_xlpm.name_col, (_xlpm.date_col = _xlpm.target_date) * (_xlpm.loc_col =$B28), ""), IF(_xlpm.filtered="", "", _xlpm.filtered) )} | D28: {=_xlfn.LET( _xlpm.data, 表格3_5[[Date]:[Location]], _xlpm.date_col, INDEX(_xlpm.data, , 1), _xlpm.name_col, INDEX(_xlpm.data, , 2), _xlpm.loc_col, INDEX(_xlpm.data, , 3), _xlpm.target_date, DATE(YEAR($B$1), MONTH($B$1), D$7), _xlpm.filtered, _xlfn._xlws.FILTER(_xlpm.name_col, (_xlpm.date_col = _xlpm.target_date) * (_xlpm.loc_col =$B28), ""), IF(_xlpm.filtered="", "", _xlpm.filtered) )} | E28: {=_xlfn.LET( _xlpm.data, 表格3_5[[Date]:[Location]], _xlpm.date_col, INDEX(_xlpm.data, , 1), _xlpm.name_col, INDEX(_xlpm.data, , 2), _xlpm.loc_col, INDEX(_xlpm.data, , 3), _xlpm.target_date, DATE(YEAR($B$1), MONTH($B$1), E$7), _xlpm.filtered, _xlfn._xlws.FILTER(_xlpm.name_col, (_xlpm.date_col = _xlpm.target_date) * (_xlpm.loc_col =$B28), ""), IF(_xlpm.filtered="", "", _xlpm.filtered) )} | F28: {=_xlfn.LET( _xlpm.data, 表格3_5[[Date]:[Location]], _xlpm.date_col, INDEX(_xlpm.data, , 1), _xlpm.name_col, INDEX(_xlpm.data, , 2), _xlpm.loc_col, INDEX(_xlpm.data, , 3), _xlpm.target_date, DATE(YEAR($B$1), MONTH($B$1), F$7), _xlpm.filtered, _xlfn._xlws.FILTER(_xlpm.name_col, (_xlpm.date_col = _xlpm.target_date) * (_xlpm.loc_col =$B28), ""), IF(_xlpm.filtered="", "", _xlpm.filtered) )} | G28: {=_xlfn.LET( _xlpm.data, 表格3_5[[Date]:[Location]], _xlpm.date_col, INDEX(_xlpm.data, , 1), _xlpm.name_col, INDEX(_xlpm.data, , 2), _xlpm.loc_col, INDEX(_xlpm.data, , 3), _xlpm.target_date, DATE(YEAR($B$1), MONTH($B$1), G$7), _xlpm.filtered, _xlfn._xlws.FILTER(_xlpm.name_col, (_xlpm.date_col = _xlpm.target_date) * (_xlpm.loc_col =$B28), ""), IF(_xlpm.filtered="", "", _xlpm.filtered) )} | H28: {=_xlfn.LET( _xlpm.data, 表格3_5[[Date]:[Location]], _xlpm.date_col, INDEX(_xlpm.data, , 1), _xlpm.name_col, INDEX(_xlpm.data, , 2), _xlpm.loc_col, INDEX(_xlpm.data, , 3), _xlpm.target_date, DATE(YEAR($B$1), MONTH($B$1), H$7), _xlpm.filtered, _xlfn._xlws.FILTER(_xlpm.name_col, (_xlpm.date_col = _xlpm.target_date) * (_xlpm.loc_col =$B28), ""), IF(_xlpm.filtered="", "", _xlpm.filtered) )} | I28: {=_xlfn.LET( _xlpm.data, 表格3_5[[Date]:[Location]], _xlpm.date_col, INDEX(_xlpm.data, , 1), _xlpm.name_col, INDEX(_xlpm.data, , 2), _xlpm.loc_col, INDEX(_xlpm.data, , 3), _xlpm.target_date, DATE(YEAR($B$1), MONTH($B$1), I$7), _xlpm.filtered, _xlfn._xlws.FILTER(_xlpm.name_col, (_xlpm.date_col = _xlpm.target_date) * (_xlpm.loc_col =$B28), ""), IF(_xlpm.filtered="", "", _xlpm.filtered) )} | J28: {=_xlfn.LET( _xlpm.data, 表格3_5[[Date]:[Location]], _xlpm.date_col, INDEX(_xlpm.data, , 1), _xlpm.name_col, INDEX(_xlpm.data, , 2), _xlpm.loc_col, INDEX(_xlpm.data, , 3), _xlpm.target_date, DATE(YEAR($B$1), MONTH($B$1), J$7), _xlpm.filtered, _xlfn._xlws.FILTER(_xlpm.name_col, (_xlpm.date_col = _xlpm.target_date) * (_xlpm.loc_col =$B28), ""), IF(_xlpm.filtered="", "", _xlpm.filtered) )} | ... AG28: {=_xlfn.LET( _xlpm.data, 表格3_5[[Date]:[Location]], _xlpm.date_col, INDEX(_xlpm.data, , 1), _xlpm.name_col, INDEX(_xlpm.data, , 2), _xlpm.loc_col, INDEX(_xlpm.data, , 3), _xlpm.target_date, DATE(YEAR($B$1), MONTH($B$1), AG$7), _xlpm.filtered, _xlfn._xlws.FILTER(_xlpm.name_col, (_xlpm.date_col = _xlpm.target_date) * (_xlpm.loc_col =$B28), ""), IF(_xlpm.filtered="", "", _xlpm.filtered) )} | AH28: =COUNTIF(C28:AG28,"?*") -> 0 | AI28: =AH28*8 -> 0
A29: {=_xlfn.LET( _xlpm.data, C29:AG29, _xlpm.removeList, {" off","."," SL","xxx"}, _xlpm.cleaned, TRIM(_xlfn.REDUCE(_xlpm.data, _xlpm.removeList, _xlfn.LAMBDA(_xlpm.arr,_xlpm.str, SUBSTITUTE(_xlpm.arr, _xlpm.str, "")))), _xlpm.first, _xlfn._xlws.FILTER(_xlpm.cleaned, _xlpm.cleaned <> ""), INDEX(_xlpm.first, 1) )} -> #VALUE! | C29: {=_xlfn.LET( _xlpm.data, 表格3_5[[Date]:[Location]], _xlpm.date_col, INDEX(_xlpm.data, , 1), _xlpm.name_col, INDEX(_xlpm.data, , 2), _xlpm.loc_col, INDEX(_xlpm.data, , 3), _xlpm.target_date, DATE(YEAR($B$1), MONTH($B$1), C$7), _xlpm.filtered, _xlfn._xlws.FILTER(_xlpm.name_col, (_xlpm.date_col = _xlpm.target_date) * (_xlpm.loc_col =$B29), ""), IF(_xlpm.filtered="", "", _xlpm.filtered) )} | D29: {=_xlfn.LET( _xlpm.data, 表格3_5[[Date]:[Location]], _xlpm.date_col, INDEX(_xlpm.data, , 1), _xlpm.name_col, INDEX(_xlpm.data, , 2), _xlpm.loc_col, INDEX(_xlpm.data, , 3), _xlpm.target_date, DATE(YEAR($B$1), MONTH($B$1), D$7), _xlpm.filtered, _xlfn._xlws.FILTER(_xlpm.name_col, (_xlpm.date_col = _xlpm.target_date) * (_xlpm.loc_col =$B29), ""), IF(_xlpm.filtered="", "", _xlpm.filtered) )} | E29: {=_xlfn.LET( _xlpm.data, 表格3_5[[Date]:[Location]], _xlpm.date_col, INDEX(_xlpm.data, , 1), _xlpm.name_col, INDEX(_xlpm.data, , 2), _xlpm.loc_col, INDEX(_xlpm.data, , 3), _xlpm.target_date, DATE(YEAR($B$1), MONTH($B$1), E$7), _xlpm.filtered, _xlfn._xlws.FILTER(_xlpm.name_col, (_xlpm.date_col = _xlpm.target_date) * (_xlpm.loc_col =$B29), ""), IF(_xlpm.filtered="", "", _xlpm.filtered) )} | F29: {=_xlfn.LET( _xlpm.data, 表格3_5[[Date]:[Location]], _xlpm.date_col, INDEX(_xlpm.data, , 1), _xlpm.name_col, INDEX(_xlpm.data, , 2), _xlpm.loc_col, INDEX(_xlpm.data, , 3), _xlpm.target_date, DATE(YEAR($B$1), MONTH($B$1), F$7), _xlpm.filtered, _xlfn._xlws.FILTER(_xlpm.name_col, (_xlpm.date_col = _xlpm.target_date) * (_xlpm.loc_col =$B29), ""), IF(_xlpm.filtered="", "", _xlpm.filtered) )} | G29: {=_xlfn.LET( _xlpm.data, 表格3_5[[Date]:[Location]], _xlpm.date_col, INDEX(_xlpm.data, , 1), _xlpm.name_col, INDEX(_xlpm.data, , 2), _xlpm.loc_col, INDEX(_xlpm.data, , 3), _xlpm.target_date, DATE(YEAR($B$1), MONTH($B$1), G$7), _xlpm.filtered, _xlfn._xlws.FILTER(_xlpm.name_col, (_xlpm.date_col = _xlpm.target_date) * (_xlpm.loc_col =$B29), ""), IF(_xlpm.filtered="", "", _xlpm.filtered) )} | H29: {=_xlfn.LET( _xlpm.data, 表格3_5[[Date]:[Location]], _xlpm.date_col, INDEX(_xlpm.data, , 1), _xlpm.name_col, INDEX(_xlpm.data, , 2), _xlpm.loc_col, INDEX(_xlpm.data, , 3), _xlpm.target_date, DATE(YEAR($B$1), MONTH($B$1), H$7), _xlpm.filtered, _xlfn._xlws.FILTER(_xlpm.name_col, (_xlpm.date_col = _xlpm.target_date) * (_xlpm.loc_col =$B29), ""), IF(_xlpm.filtered="", "", _xlpm.filtered) )} | I29: {=_xlfn.LET( _xlpm.data, 表格3_5[[Date]:[Location]], _xlpm.date_col, INDEX(_xlpm.data, , 1), _xlpm.name_col, INDEX(_xlpm.data, , 2), _xlpm.loc_col, INDEX(_xlpm.data, , 3), _xlpm.target_date, DATE(YEAR($B$1), MONTH($B$1), I$7), _xlpm.filtered, _xlfn._xlws.FILTER(_xlpm.name_col, (_xlpm.date_col = _xlpm.target_date) * (_xlpm.loc_col =$B29), ""), IF(_xlpm.filtered="", "", _xlpm.filtered) )} | J29: {=_xlfn.LET( _xlpm.data, 表格3_5[[Date]:[Location]], _xlpm.date_col, INDEX(_xlpm.data, , 1), _xlpm.name_col, INDEX(_xlpm.data, , 2), _xlpm.loc_col, INDEX(_xlpm.data, , 3), _xlpm.target_date, DATE(YEAR($B$1), MONTH($B$1), J$7), _xlpm.filtered, _xlfn._xlws.FILTER(_xlpm.name_col, (_xlpm.date_col = _xlpm.target_date) * (_xlpm.loc_col =$B29), ""), IF(_xlpm.filtered="", "", _xlpm.filtered) )} | ... AG29: {=_xlfn.LET( _xlpm.data, 表格3_5[[Date]:[Location]], _xlpm.date_col, INDEX(_xlpm.data, , 1), _xlpm.name_col, INDEX(_xlpm.data, , 2), _xlpm.loc_col, INDEX(_xlpm.data, , 3), _xlpm.target_date, DATE(YEAR($B$1), MONTH($B$1), AG$7), _xlpm.filtered, _xlfn._xlws.FILTER(_xlpm.name_col, (_xlpm.date_col = _xlpm.target_date) * (_xlpm.loc_col =$B29), ""), IF(_xlpm.filtered="", "", _xlpm.filtered) )} | AH29: =COUNTIF(C29:AG29,"?*") -> 0 | AI29: =AH29*8 -> 0
A30: {=_xlfn.LET( _xlpm.data, C30:AG30, _xlpm.removeList, {" off","."," SL","xxx"}, _xlpm.cleaned, TRIM(_xlfn.REDUCE(_xlpm.data, _xlpm.removeList, _xlfn.LAMBDA(_xlpm.arr,_xlpm.str, SUBSTITUTE(_xlpm.arr, _xlpm.str, "")))), _xlpm.first, _xlfn._xlws.FILTER(_xlpm.cleaned, _xlpm.cleaned <> ""), INDEX(_xlpm.first, 1) )} -> #VALUE! | C30: {=_xlfn.LET( _xlpm.data, 表格3_5[[Date]:[Location]], _xlpm.date_col, INDEX(_xlpm.data, , 1), _xlpm.name_col, INDEX(_xlpm.data, , 2), _xlpm.loc_col, INDEX(_xlpm.data, , 3), _xlpm.target_date, DATE(YEAR($B$1), MONTH($B$1), C$7), _xlpm.filtered, _xlfn._xlws.FILTER(_xlpm.name_col, (_xlpm.date_col = _xlpm.target_date) * (_xlpm.loc_col =$B30), ""), IF(_xlpm.filtered="", "", _xlpm.filtered) )} | D30: {=_xlfn.LET( _xlpm.data, 表格3_5[[Date]:[Location]], _xlpm.date_col, INDEX(_xlpm.data, , 1), _xlpm.name_col, INDEX(_xlpm.data, , 2), _xlpm.loc_col, INDEX(_xlpm.data, , 3), _xlpm.target_date, DATE(YEAR($B$1), MONTH($B$1), D$7), _xlpm.filtered, _xlfn._xlws.FILTER(_xlpm.name_col, (_xlpm.date_col = _xlpm.target_date) * (_xlpm.loc_col =$B30), ""), IF(_xlpm.filtered="", "", _xlpm.filtered) )} | E30: {=_xlfn.LET( _xlpm.data, 表格3_5[[Date]:[Location]], _xlpm.date_col, INDEX(_xlpm.data, , 1), _xlpm.name_col, INDEX(_xlpm.data, , 2), _xlpm.loc_col, INDEX(_xlpm.data, , 3), _xlpm.target_date, DATE(YEAR($B$1), MONTH($B$1), E$7), _xlpm.filtered, _xlfn._xlws.FILTER(_xlpm.name_col, (_xlpm.date_col = _xlpm.target_date) * (_xlpm.loc_col =$B30), ""), IF(_xlpm.filtered="", "", _xlpm.filtered) )} | F30: {=_xlfn.LET( _xlpm.data, 表格3_5[[Date]:[Location]], _xlpm.date_col, INDEX(_xlpm.data, , 1), _xlpm.name_col, INDEX(_xlpm.data, , 2), _xlpm.loc_col, INDEX(_xlpm.data, , 3), _xlpm.target_date, DATE(YEAR($B$1), MONTH($B$1), F$7), _xlpm.filtered, _xlfn._xlws.FILTER(_xlpm.name_col, (_xlpm.date_col = _xlpm.target_date) * (_xlpm.loc_col =$B30), ""), IF(_xlpm.filtered="", "", _xlpm.filtered) )} | G30: {=_xlfn.LET( _xlpm.data, 表格3_5[[Date]:[Location]], _xlpm.date_col, INDEX(_xlpm.data, , 1), _xlpm.name_col, INDEX(_xlpm.data, , 2), _xlpm.loc_col, INDEX(_xlpm.data, , 3), _xlpm.target_date, DATE(YEAR($B$1), MONTH($B$1), G$7), _xlpm.filtered, _xlfn._xlws.FILTER(_xlpm.name_col, (_xlpm.date_col = _xlpm.target_date) * (_xlpm.loc_col =$B30), ""), IF(_xlpm.filtered="", "", _xlpm.filtered) )} | H30: {=_xlfn.LET( _xlpm.data, 表格3_5[[Date]:[Location]], _xlpm.date_col, INDEX(_xlpm.data, , 1), _xlpm.name_col, INDEX(_xlpm.data, , 2), _xlpm.loc_col, INDEX(_xlpm.data, , 3), _xlpm.target_date, DATE(YEAR($B$1), MONTH($B$1), H$7), _xlpm.filtered, _xlfn._xlws.FILTER(_xlpm.name_col, (_xlpm.date_col = _xlpm.target_date) * (_xlpm.loc_col =$B30), ""), IF(_xlpm.filtered="", "", _xlpm.filtered) )} | I30: {=_xlfn.LET( _xlpm.data, 表格3_5[[Date]:[Location]], _xlpm.date_col, INDEX(_xlpm.data, , 1), _xlpm.name_col, INDEX(_xlpm.data, , 2), _xlpm.loc_col, INDEX(_xlpm.data, , 3), _xlpm.target_date, DATE(YEAR($B$1), MONTH($B$1), I$7), _xlpm.filtered, _xlfn._xlws.FILTER(_xlpm.name_col, (_xlpm.date_col = _xlpm.target_date) * (_xlpm.loc_col =$B30), ""), IF(_xlpm.filtered="", "", _xlpm.filtered) )} | J30: {=_xlfn.LET( _xlpm.data, 表格3_5[[Date]:[Location]], _xlpm.date_col, INDEX(_xlpm.data, , 1), _xlpm.name_col, INDEX(_xlpm.data, , 2), _xlpm.loc_col, INDEX(_xlpm.data, , 3), _xlpm.target_date, DATE(YEAR($B$1), MONTH($B$1), J$7), _xlpm.filtered, _xlfn._xlws.FILTER(_xlpm.name_col, (_xlpm.date_col = _xlpm.target_date) * (_xlpm.loc_col =$B30), ""), IF(_xlpm.filtered="", "", _xlpm.filtered) )} | ... AG30: {=_xlfn.LET( _xlpm.data, 表格3_5[[Date]:[Location]], _xlpm.date_col, INDEX(_xlpm.data, , 1), _xlpm.name_col, INDEX(_xlpm.data, , 2), _xlpm.loc_col, INDEX(_xlpm.data, , 3), _xlpm.target_date, DATE(YEAR($B$1), MONTH($B$1), AG$7), _xlpm.filtered, _xlfn._xlws.FILTER(_xlpm.name_col, (_xlpm.date_col = _xlpm.target_date) * (_xlpm.loc_col =$B30), ""), IF(_xlpm.filtered="", "", _xlpm.filtered) )} | AH30: =COUNTIF(C30:AG30,"?*") -> 0 | AI30: =AH30*8 -> 0
A31: {=_xlfn.LET( _xlpm.data, C31:AG31, _xlpm.removeList, {" off","."," SL","xxx"}, _xlpm.cleaned, TRIM(_xlfn.REDUCE(_xlpm.data, _xlpm.removeList, _xlfn.LAMBDA(_xlpm.arr,_xlpm.str, SUBSTITUTE(_xlpm.arr, _xlpm.str, "")))), _xlpm.first, _xlfn._xlws.FILTER(_xlpm.cleaned, _xlpm.cleaned <> ""), INDEX(_xlpm.first, 1) )} -> #VALUE! | C31: {=_xlfn.LET( _xlpm.data, 表格3_5[[Date]:[Location]], _xlpm.date_col, INDEX(_xlpm.data, , 1), _xlpm.name_col, INDEX(_xlpm.data, , 2), _xlpm.loc_col, INDEX(_xlpm.data, , 3), _xlpm.target_date, DATE(YEAR($B$1), MONTH($B$1), C$7), _xlpm.filtered, _xlfn._xlws.FILTER(_xlpm.name_col, (_xlpm.date_col = _xlpm.target_date) * (_xlpm.loc_col =$B31), ""), IF(_xlpm.filtered="", "", _xlpm.filtered) )} | D31: {=_xlfn.LET( _xlpm.data, 表格3_5[[Date]:[Location]], _xlpm.date_col, INDEX(_xlpm.data, , 1), _xlpm.name_col, INDEX(_xlpm.data, , 2), _xlpm.loc_col, INDEX(_xlpm.data, , 3), _xlpm.target_date, DATE(YEAR($B$1), MONTH($B$1), D$7), _xlpm.filtered, _xlfn._xlws.FILTER(_xlpm.name_col, (_xlpm.date_col = _xlpm.target_date) * (_xlpm.loc_col =$B31), ""), IF(_xlpm.filtered="", "", _xlpm.filtered) )} | E31: {=_xlfn.LET( _xlpm.data, 表格3_5[[Date]:[Location]], _xlpm.date_col, INDEX(_xlpm.data, , 1), _xlpm.name_col, INDEX(_xlpm.data, , 2), _xlpm.loc_col, INDEX(_xlpm.data, , 3), _xlpm.target_date, DATE(YEAR($B$1), MONTH($B$1), E$7), _xlpm.filtered, _xlfn._xlws.FILTER(_xlpm.name_col, (_xlpm.date_col = _xlpm.target_date) * (_xlpm.loc_col =$B31), ""), IF(_xlpm.filtered="", "", _xlpm.filtered) )} | F31: {=_xlfn.LET( _xlpm.data, 表格3_5[[Date]:[Location]], _xlpm.date_col, INDEX(_xlpm.data, , 1), _xlpm.name_col, INDEX(_xlpm.data, , 2), _xlpm.loc_col, INDEX(_xlpm.data, , 3), _xlpm.target_date, DATE(YEAR($B$1), MONTH($B$1), F$7), _xlpm.filtered, _xlfn._xlws.FILTER(_xlpm.name_col, (_xlpm.date_col = _xlpm.target_date) * (_xlpm.loc_col =$B31), ""), IF(_xlpm.filtered="", "", _xlpm.filtered) )} | G31: {=_xlfn.LET( _xlpm.data, 表格3_5[[Date]:[Location]], _xlpm.date_col, INDEX(_xlpm.data, , 1), _xlpm.name_col, INDEX(_xlpm.data, , 2), _xlpm.loc_col, INDEX(_xlpm.data, , 3), _xlpm.target_date, DATE(YEAR($B$1), MONTH($B$1), G$7), _xlpm.filtered, _xlfn._xlws.FILTER(_xlpm.name_col, (_xlpm.date_col = _xlpm.target_date) * (_xlpm.loc_col =$B31), ""), IF(_xlpm.filtered="", "", _xlpm.filtered) )} | H31: {=_xlfn.LET( _xlpm.data, 表格3_5[[Date]:[Location]], _xlpm.date_col, INDEX(_xlpm.data, , 1), _xlpm.name_col, INDEX(_xlpm.data, , 2), _xlpm.loc_col, INDEX(_xlpm.data, , 3), _xlpm.target_date, DATE(YEAR($B$1), MONTH($B$1), H$7), _xlpm.filtered, _xlfn._xlws.FILTER(_xlpm.name_col, (_xlpm.date_col = _xlpm.target_date) * (_xlpm.loc_col =$B31), ""), IF(_xlpm.filtered="", "", _xlpm.filtered) )} | I31: {=_xlfn.LET( _xlpm.data, 表格3_5[[Date]:[Location]], _xlpm.date_col, INDEX(_xlpm.data, , 1), _xlpm.name_col, INDEX(_xlpm.data, , 2), _xlpm.loc_col, INDEX(_xlpm.data, , 3), _xlpm.target_date, DATE(YEAR($B$1), MONTH($B$1), I$7), _xlpm.filtered, _xlfn._xlws.FILTER(_xlpm.name_col, (_xlpm.date_col = _xlpm.target_date) * (_xlpm.loc_col =$B31), ""), IF(_xlpm.filtered="", "", _xlpm.filtered) )} | J31: {=_xlfn.LET( _xlpm.data, 表格3_5[[Date]:[Location]], _xlpm.date_col, INDEX(_xlpm.data, , 1), _xlpm.name_col, INDEX(_xlpm.data, , 2), _xlpm.loc_col, INDEX(_xlpm.data, , 3), _xlpm.target_date, DATE(YEAR($B$1), MONTH($B$1), J$7), _xlpm.filtered, _xlfn._xlws.FILTER(_xlpm.name_col, (_xlpm.date_col = _xlpm.target_date) * (_xlpm.loc_col =$B31), ""), IF(_xlpm.filtered="", "", _xlpm.filtered) )} | ... AG31: {=_xlfn.LET( _xlpm.data, 表格3_5[[Date]:[Location]], _xlpm.date_col, INDEX(_xlpm.data, , 1), _xlpm.name_col, INDEX(_xlpm.data, , 2), _xlpm.loc_col, INDEX(_xlpm.data, , 3), _xlpm.target_date, DATE(YEAR($B$1), MONTH($B$1), AG$7), _xlpm.filtered, _xlfn._xlws.FILTER(_xlpm.name_col, (_xlpm.date_col = _xlpm.target_date) * (_xlpm.loc_col =$B31), ""), IF(_xlpm.filtered="", "", _xlpm.filtered) )} | AH31: =COUNTIF(C31:AG31,"?*") -> 0 | AI31: =AH31*8 -> 0

Sheet 工作表1
F1: =SUBTOTAL(3,表格3_5[Date]) -> 155 | L1: =SUBTOTAL(9,表格3_5[[ Hours]]) -> 1249.9 | Q1: =SUBTOTAL(9,表格3_5[Hours Worked]) -> 1245.5
A2: No | B2: Test | C2: ID1 | D2: ID2 | E2: ID3 | F2: Date | G2: Nick Name | H2: Location | I2: Name | J2: In-Time | K2: Out-Time | L2: Hours | M2: OT Hours | N2: In-Time2 | O2: Out-Time2 | P2: Normal working hours | Q2: Hours Worked | R2: Hourly Rate | S2: Total Pay | T2: Remark
A3: 1 | B3: =_xlfn.CONCAT(表格3_5[[#This Row],[Name]],表格3_5[[#This Row],[Location]]) -> Lo Chun WahKowloon Bay Fortress | E3: =DAY(表格3_5[[#This Row],[Date]])&"" -> 4 | F3: 46177 | G3: =_xlfn.XLOOKUP(表格3_5[[#This Row],[Name]],Name_list[Full Name],Name_list[Nick Name]) -> Wah | H3: Kowloon Bay Fortress | I3: Lo Chun Wah | J3: 0.5 | K3: 0.83333333 | L3: =(表格3_5[[#This Row],[Out-Time]] - 表格3_5[[#This Row],[In-Time]])*24 -> 8 | M3: =表格3_5[[#This Row],[ Hours]]-表格3_5[[#This Row],[Normal working hours]] -> 0 | N3: 0.5 | O3: 0.83333333 | P3: =(表格3_5[[#This Row],[Out-Time2]] - 表格3_5[[#This Row],[In-Time2]])*24 -> 8 | Q3: 8 | R3: =_xlfn.XLOOKUP(表格3_5[[#This Row],[Name]],Name_list[Full Name],Name_list[Hourr Rate]) -> 60 | S3: =表格3_5[[#This Row],[Hours Worked]]*表格3_5[[#This Row],[Hourly Rate]] -> 480
A4: 2 | B4: =_xlfn.CONCAT(表格3_5[[#This Row],[Name]],表格3_5[[#This Row],[Location]]) -> Lo Chun WahKowloon Bay Fortress | E4: =DAY(表格3_5[[#This Row],[Date]])&"" -> 5 | F4: 46178 | G4: =_xlfn.XLOOKUP(表格3_5[[#This Row],[Name]],Name_list[Full Name],Name_list[Nick Name]) -> Wah | H4: Kowloon Bay Fortress | I4: Lo Chun Wah | J4: 0.5 | K4: 0.83333333 | L4: =(表格3_5[[#This Row],[Out-Time]] - 表格3_5[[#This Row],[In-Time]])*24 -> 8 | M4: =表格3_5[[#This Row],[ Hours]]-表格3_5[[#This Row],[Normal working hours]] -> 0 | N4: 0.5 | O4: 0.83333333 | P4: =(表格3_5[[#This Row],[Out-Time2]] - 表格3_5[[#This Row],[In-Time2]])*24 -> 8 | Q4: 8 | R4: =_xlfn.XLOOKUP(表格3_5[[#This Row],[Name]],Name_list[Full Name],Name_list[Hourr Rate]) -> 60 | S4: =表格3_5[[#This Row],[Hours Worked]]*表格3_5[[#This Row],[Hourly Rate]] -> 480
A5: 3 | B5: =_xlfn.CONCAT(表格3_5[[#This Row],[Name]],表格3_5[[#This Row],[Location]]) -> Lo Chun WahKowloon Bay Fortress | E5: =DAY(表格3_5[[#This Row],[Date]])&"" -> 6 | F5: 46179 | G5: =_xlfn.XLOOKUP(表格3_5[[#This Row],[Name]],Name_list[Full Name],Name_list[Nick Name]) -> Wah | H5: Kowloon Bay Fortress | I5: Lo Chun Wah | J5: 0.5 | K5: 0.83333333 | L5: =(表格3_5[[#This Row],[Out-Time]] - 表格3_5[[#This Row],[In-Time]])*24 -> 8 | M5: =表格3_5[[#This Row],[ Hours]]-表格3_5[[#This Row],[Normal working hours]] -> 0 | N5: 0.5 | O5: 0.83333333 | P5: =(表格3_5[[#This Row],[Out-Time2]] - 表格3_5[[#This Row],[In-Time2]])*24 -> 8 | Q5: 8 | R5: =_xlfn.XLOOKUP(表格3_5[[#This Row],[Name]],Name_list[Full Name],Name_list[Hourr Rate]) -> 60 | S5: =表格3_5[[#This Row],[Hours Worked]]*表格3_5[[#This Row],[Hourly Rate]] -> 480
A6: 4 | B6: =_xlfn.CONCAT(表格3_5[[#This Row],[Name]],表格3_5[[#This Row],[Location]]) -> Lo Chun WahKowloon Bay Fortress | E6: =DAY(表格3_5[[#This Row],[Date]])&"" -> 7 | F6: 46180 | G6: =_xlfn.XLOOKUP(表格3_5[[#This Row],[Name]],Name_list[Full Name],Name_list[Nick Name]) -> Wah | H6: Kowloon Bay Fortress | I6: Lo Chun Wah | J6: 0.5 | K6: 0.83333333 | L6: =(表格3_5[[#This Row],[Out-Time]] - 表格3_5[[#This Row],[In-Time]])*24 -> 8 | M6: =表格3_5[[#This Row],[ Hours]]-表格3_5[[#This Row],[Normal working hours]] -> 0 | N6: 0.5 | O6: 0.83333333 | P6: =(表格3_5[[#This Row],[Out-Time2]] - 表格3_5[[#This Row],[In-Time2]])*24 -> 8 | Q6: 8 | R6: =_xlfn.XLOOKUP(表格3_5[[#This Row],[Name]],Name_list[Full Name],Name_list[Hourr Rate]) -> 60 | S6: =表格3_5[[#This Row],[Hours Worked]]*表格3_5[[#This Row],[Hourly Rate]] -> 480
A7: 5 | B7: =_xlfn.CONCAT(表格3_5[[#This Row],[Name]],表格3_5[[#This Row],[Location]]) -> Lo Chun WahKowloon Bay Fortress | E7: =DAY(表格3_5[[#This Row],[Date]])&"" -> 11 | F7: 46184 | G7: =_xlfn.XLOOKUP(表格3_5[[#This Row],[Name]],Name_list[Full Name],Name_list[Nick Name]) -> Wah | H7: Kowloon Bay Fortress | I7: Lo Chun Wah | J7: 0.5 | K7: 0.83333333 | L7: =(表格3_5[[#This Row],[Out-Time]] - 表格3_5[[#This Row],[In-Time]])*24 -> 8 | M7: =表格3_5[[#This Row],[ Hours]]-表格3_5[[#This Row],[Normal working hours]] -> 0 | N7: 0.5 | O7: 0.83333333 | P7: =(表格3_5[[#This Row],[Out-Time2]] - 表格3_5[[#This Row],[In-Time2]])*24 -> 8 | Q7: 8 | R7: =_xlfn.XLOOKUP(表格3_5[[#This Row],[Name]],Name_list[Full Name],Name_list[Hourr Rate]) -> 60 | S7: =表格3_5[[#This Row],[Hours Worked]]*表格3_5[[#This Row],[Hourly Rate]] -> 480
A8: 6 | B8: =_xlfn.CONCAT(表格3_5[[#This Row],[Name]],表格3_5[[#This Row],[Location]]) -> Lo Chun WahKowloon Bay Fortress | E8: =DAY(表格3_5[[#This Row],[Date]])&"" -> 12 | F8: 46185 | G8: =_xlfn.XLOOKUP(表格3_5[[#This Row],[Name]],Name_list[Full Name],Name_list[Nick Name]) -> Wah | H8: Kowloon Bay Fortress | I8: Lo Chun Wah | J8: 0.5 | K8: 0.83333333 | L8: =(表格3_5[[#This Row],[Out-Time]] - 表格3_5[[#This Row],[In-Time]])*24 -> 8 | M8: =表格3_5[[#This Row],[ Hours]]-表格3_5[[#This Row],[Normal working hours]] -> 0 | N8: 0.5 | O8: 0.83333333 | P8: =(表格3_5[[#This Row],[Out-Time2]] - 表格3_5[[#This Row],[In-Time2]])*24 -> 8 | Q8: 8 | R8: =_xlfn.XLOOKUP(表格3_5[[#This Row],[Name]],Name_list[Full Name],Name_list[Hourr Rate]) -> 60 | S8: =表格3_5[[#This Row],[Hours Worked]]*表格3_5[[#This Row],[Hourly Rate]] -> 480
A9: 7 | B9: =_xlfn.CONCAT(表格3_5[[#This Row],[Name]],表格3_5[[#This Row],[Location]]) -> Lo Chun WahKowloon Bay Fortress | E9: =DAY(表格3_5[[#This Row],[Date]])&"" -> 13 | F9: 46186 | G9: =_xlfn.XLOOKUP(表格3_5[[#This Row],[Name]],Name_list[Full Name],Name_list[Nick Name]) -> Wah | H9: Kowloon Bay Fortress | I9: Lo Chun Wah | J9: 0.5 | K9: 0.83333333 | L9: =(表格3_5[[#This Row],[Out-Time]] - 表格3_5[[#This Row],[In-Time]])*24 -> 8 | M9: =表格3_5[[#This Row],[ Hours]]-表格3_5[[#This Row],[Normal working hours]] -> 0 | N9: 0.5 | O9: 0.83333333 | P9: =(表格3_5[[#This Row],[Out-Time2]] - 表格3_5[[#This Row],[In-Time2]])*24 -> 8 | Q9: 8 | R9: =_xlfn.XLOOKUP(表格3_5[[#This Row],[Name]],Name_list[Full Name],Name_list[Hourr Rate]) -> 60 | S9: =表格3_5[[#This Row],[Hours Worked]]*表格3_5[[#This Row],[Hourly Rate]] -> 480
A10: 8 | B10: =_xlfn.CONCAT(表格3_5[[#This Row],[Name]],表格3_5[[#This Row],[Location]]) -> Lo Chun WahKowloon Bay Fortress | E10: =DAY(表格3_5[[#This Row],[Date]])&"" -> 14 | F10: 46187 | G10: =_xlfn.XLOOKUP(表格3_5[[#This Row],[Name]],Name_list[Full Name],Name_list[Nick Name]) -> Wah | H10: Kowloon Bay Fortress | I10: Lo Chun Wah | J10: 0.5 | K10: 0.83333333 | L10: =(表格3_5[[#This Row],[Out-Time]] - 表格3_5[[#This Row],[In-Time]])*24 -> 8 | M10: =表格3_5[[#This Row],[ Hours]]-表格3_5[[#This Row],[Normal working hours]] -> 0 | N10: 0.5 | O10: 0.83333333 | P10: =(表格3_5[[#This Row],[Out-Time2]] - 表格3_5[[#This Row],[In-Time2]])*24 -> 8 | Q10: 8 | R10: =_xlfn.XLOOKUP(表格3_5[[#This Row],[Name]],Name_list[Full Name],Name_list[Hourr Rate]) -> 60 | S10: =表格3_5[[#This Row],[Hours Worked]]*表格3_5[[#This Row],[Hourly Rate]] -> 480
A11: 9 | B11: =_xlfn.CONCAT(表格3_5[[#This Row],[Name]],表格3_5[[#This Row],[Location]]) -> Lo Chun WahKowloon Bay Fortress | E11: =DAY(表格3_5[[#This Row],[Date]])&"" -> 18 | F11: 46191 | G11: =_xlfn.XLOOKUP(表格3_5[[#This Row],[Name]],Name_list[Full Name],Name_list[Nick Name]) -> Wah | H11: Kowloon Bay Fortress | I11: Lo Chun Wah | J11: 0.5 | K11: 0.83333333 | L11: =(表格3_5[[#This Row],[Out-Time]] - 表格3_5[[#This Row],[In-Time]])*24 -> 8 | M11: =表格3_5[[#This Row],[ Hours]]-表格3_5[[#This Row],[Normal working hours]] -> 0 | N11: 0.5 | O11: 0.83333333 | P11: =(表格3_5[[#This Row],[Out-Time2]] - 表格3_5[[#This Row],[In-Time2]])*24 -> 8 | Q11: 8 | R11: =_xlfn.XLOOKUP(表格3_5[[#This Row],[Name]],Name_list[Full Name],Name_list[Hourr Rate]) -> 60 | S11: =表格3_5[[#This Row],[Hours Worked]]*表格3_5[[#This Row],[Hourly Rate]] -> 480
A12: 10 | B12: =_xlfn.CONCAT(表格3_5[[#This Row],[Name]],表格3_5[[#This Row],[Location]]) -> Lo Chun WahKowloon Bay Fortress | E12: =DAY(表格3_5[[#This Row],[Date]])&"" -> 19 | F12: 46192 | G12: =_xlfn.XLOOKUP(表格3_5[[#This Row],[Name]],Name_list[Full Name],Name_list[Nick Name]) -> Wah | H12: Kowloon Bay Fortress | I12: Lo Chun Wah | J12: 0.5 | K12: 0.83333333 | L12: =(表格3_5[[#This Row],[Out-Time]] - 表格3_5[[#This Row],[In-Time]])*24 -> 8 | M12: =表格3_5[[#This Row],[ Hours]]-表格3_5[[#This Row],[Normal working hours]] -> 0 | N12: 0.5 | O12: 0.83333333 | P12: =(表格3_5[[#This Row],[Out-Time2]] - 表格3_5[[#This Row],[In-Time2]])*24 -> 8 | Q12: 8 | R12: =_xlfn.XLOOKUP(表格3_5[[#This Row],[Name]],Name_list[Full Name],Name_list[Hourr Rate]) -> 60 | S12: =表格3_5[[#This Row],[Hours Worked]]*表格3_5[[#This Row],[Hourly Rate]] -> 480
A13: 11 | B13: =_xlfn.CONCAT(表格3_5[[#This Row],[Name]],表格3_5[[#This Row],[Location]]) -> Lo Chun WahKowloon Bay Fortress | E13: =DAY(表格3_5[[#This Row],[Date]])&"" -> 20 | F13: 46193 | G13: =_xlfn.XLOOKUP(表格3_5[[#This Row],[Name]],Name_list[Full Name],Name_list[Nick Name]) -> Wah | H13: Kowloon Bay Fortress | I13: Lo Chun Wah | J13: 0.5 | K13: 0.83333333 | L13: =(表格3_5[[#This Row],[Out-Time]] - 表格3_5[[#This Row],[In-Time]])*24 -> 8 | M13: =表格3_5[[#This Row],[ Hours]]-表格3_5[[#This Row],[Normal working hours]] -> 0 | N13: 0.5 | O13: 0.83333333 | P13: =(表格3_5[[#This Row],[Out-Time2]] - 表格3_5[[#This Row],[In-Time2]])*24 -> 8 | Q13: 8 | R13: =_xlfn.XLOOKUP(表格3_5[[#This Row],[Name]],Name_list[Full Name],Name_list[Hourr Rate]) -> 60 | S13: =表格3_5[[#This Row],[Hours Worked]]*表格3_5[[#This Row],[Hourly Rate]] -> 480
A14: 12 | B14: =_xlfn.CONCAT(表格3_5[[#This Row],[Name]],表格3_5[[#This Row],[Location]]) -> Lo Chun WahKowloon Bay Fortress | E14: =DAY(表格3_5[[#This Row],[Date]])&"" -> 21 | F14: 46194 | G14: =_xlfn.XLOOKUP(表格3_5[[#This Row],[Name]],Name_list[Full Name],Name_list[Nick Name]) -> Wah | H14: Kowloon Bay Fortress | I14: Lo Chun Wah | J14: 0.5 | K14: 0.83333333 | L14: =(表格3_5[[#This Row],[Out-Time]] - 表格3_5[[#This Row],[In-Time]])*24 -> 8 | M14: =表格3_5[[#This Row],[ Hours]]-表格3_5[[#This Row],[Normal working hours]] -> 0 | N14: 0.5 | O14: 0.83333333 | P14: =(表格3_5[[#This Row],[Out-Time2]] - 表格3_5[[#This Row],[In-Time2]])*24 -> 8 | Q14: 8 | R14: =_xlfn.XLOOKUP(表格3_5[[#This Row],[Name]],Name_list[Full Name],Name_list[Hourr Rate]) -> 60 | S14: =表格3_5[[#This Row],[Hours Worked]]*表格3_5[[#This Row],[Hourly Rate]] -> 480
... A157: 155 | B157: =_xlfn.CONCAT(表格3_5[[#This Row],[Name]],表格3_5[[#This Row],[Location]]) -> Tang Chiu FanTW Aeon | E157: =DAY(表格3_5[[#This Row],[Date]])&"" -> 28 | F157: 46201 | G157: =_xlfn.XLOOKUP(表格3_5[[#This Row],[Name]],Name_list[Full Name],Name_list[Nick Name]) -> Fan | H157: TW Aeon | I157: Tang Chiu Fan | J157: 0.5 | K157: 0.83333333 | L157: =(表格3_5[[#This Row],[Out-Time]] - 表格3_5[[#This Row],[In-Time]])*24 -> 8 | M157: =表格3_5[[#This Row],[ Hours]]-表格3_5[[#This Row],[Normal working hours]] -> 0 | N157: 0.5 | O157: 0.83333333 | P157: =(表格3_5[[#This Row],[Out-Time2]] - 表格3_5[[#This Row],[In-Time2]])*24 -> 8 | Q157: 8 | R157: =_xlfn.XLOOKUP(表格3_5[[#This Row],[Name]],Name_list[Full Name],Name_list[Hourr Rate]) -> 60 | S157: =表格3_5[[#This Row],[Hours Worked]]*表格3_5[[#This Row],[Hourly Rate]] -> 480
A158: 156 | B158: =_xlfn.CONCAT(表格3_5[[#This Row],[Name]],表格3_5[[#This Row],[Location]]) | E158: =DAY(表格3_5[[#This Row],[Date]])&"" -> 0 | G158: =_xlfn.XLOOKUP(表格3_5[[#This Row],[Name]],Name_list[Full Name],Name_list[Nick Name]) -> 0 | L158: =(表格3_5[[#This Row],[Out-Time]] - 表格3_5[[#This Row],[In-Time]])*24 -> 0 | M158: =表格3_5[[#This Row],[ Hours]]-表格3_5[[#This Row],[Normal working hours]] -> 0 | P158: =(表格3_5[[#This Row],[Out-Time2]] - 表格3_5[[#This Row],[In-Time2]])*24 -> 0 | R158: =_xlfn.XLOOKUP(表格3_5[[#This Row],[Name]],Name_list[Full Name],Name_list[Hourr Rate]) -> 0 | S158: =表格3_5[[#This Row],[Hours Worked]]*表格3_5[[#This Row],[Hourly Rate]] -> 0
A159: 157 | B159: =_xlfn.CONCAT(表格3_5[[#This Row],[Name]],表格3_5[[#This Row],[Location]]) | E159: =DAY(表格3_5[[#This Row],[Date]])&"" -> 0 | G159: =_xlfn.XLOOKUP(表格3_5[[#This Row],[Name]],Name_list[Full Name],Name_list[Nick Name]) -> 0 | L159: =(表格3_5[[#This Row],[Out-Time]] - 表格3_5[[#This Row],[In-Time]])*24 -> 0 | M159: =表格3_5[[#This Row],[ Hours]]-表格3_5[[#This Row],[Normal working hours]] -> 0 | P159: =(表格3_5[[#This Row],[Out-Time2]] - 表格3_5[[#This Row],[In-Time2]])*24 -> 0 | R159: =_xlfn.XLOOKUP(表格3_5[[#This Row],[Name]],Name_list[Full Name],Name_list[Hourr Rate]) -> 0 | S159: =表格3_5[[#This Row],[Hours Worked]]*表格3_5[[#This Row],[Hourly Rate]] -> 0
A160: 158 | B160: =_xlfn.CONCAT(表格3_5[[#This Row],[Name]],表格3_5[[#This Row],[Location]]) | E160: =DAY(表格3_5[[#This Row],[Date]])&"" -> 0 | G160: =_xlfn.XLOOKUP(表格3_5[[#This Row],[Name]],Name_list[Full Name],Name_list[Nick Name]) -> 0 | L160: =(表格3_5[[#This Row],[Out-Time]] - 表格3_5[[#This Row],[In-Time]])*24 -> 0 | M160: =表格3_5[[#This Row],[ Hours]]-表格3_5[[#This Row],[Normal working hours]] -> 0 | P160: =(表格3_5[[#This Row],[Out-Time2]] - 表格3_5[[#This Row],[In-Time2]])*24 -> 0 | R160: =_xlfn.XLOOKUP(表格3_5[[#This Row],[Name]],Name_list[Full Name],Name_list[Hourr Rate]) -> 0 | S160: =表格3_5[[#This Row],[Hours Worked]]*表格3_5[[#This Row],[Hourly Rate]] -> 0
A161: 159 | B161: =_xlfn.CONCAT(表格3_5[[#This Row],[Name]],表格3_5[[#This Row],[Location]]) | E161: =DAY(表格3_5[[#This Row],[Date]])&"" -> 0 | G161: =_xlfn.XLOOKUP(表格3_5[[#This Row],[Name]],Name_list[Full Name],Name_list[Nick Name]) -> 0 | L161: =(表格3_5[[#This Row],[Out-Time]] - 表格3_5[[#This Row],[In-Time]])*24 -> 0 | M161: =表格3_5[[#This Row],[ Hours]]-表格3_5[[#This Row],[Normal working hours]] -> 0 | P161: =(表格3_5[[#This Row],[Out-Time2]] - 表格3_5[[#This Row],[In-Time2]])*24 -> 0 | R161: =_xlfn.XLOOKUP(表格3_5[[#This Row],[Name]],Name_list[Full Name],Name_list[Hourr Rate]) -> 0 | S161: =表格3_5[[#This Row],[Hours Worked]]*表格3_5[[#This Row],[Hourly Rate]] -> 0
A162: 160 | B162: =_xlfn.CONCAT(表格3_5[[#This Row],[Name]],表格3_5[[#This Row],[Location]]) | E162: =DAY(表格3_5[[#This Row],[Date]])&"" -> 0 | G162: =_xlfn.XLOOKUP(表格3_5[[#This Row],[Name]],Name_list[Full Name],Name_list[Nick Name]) -> 0 | L162: =(表格3_5[[#This Row],[Out-Time]] - 表格3_5[[#This Row],[In-Time]])*24 -> 0 | M162: =表格3_5[[#This Row],[ Hours]]-表格3_5[[#This Row],[Normal working hours]] -> 0 | P162: =(表格3_5[[#This Row],[Out-Time2]] - 表格3_5[[#This Row],[In-Time2]])*24 -> 0 | R162: =_xlfn.XLOOKUP(表格3_5[[#This Row],[Name]],Name_list[Full Name],Name_list[Hourr Rate]) -> 0 | S162: =表格3_5[[#This Row],[Hours Worked]]*表格3_5[[#This Row],[Hourly Rate]] -> 0
A163: 161 | B163: =_xlfn.CONCAT(表格3_5[[#This Row],[Name]],表格3_5[[#This Row],[Location]]) | E163: =DAY(表格3_5[[#This Row],[Date]])&"" -> 0 | G163: =_xlfn.XLOOKUP(表格3_5[[#This Row],[Name]],Name_list[Full Name],Name_list[Nick Name]) -> 0 | L163: =(表格3_5[[#This Row],[Out-Time]] - 表格3_5[[#This Row],[In-Time]])*24 -> 0 | M163: =表格3_5[[#This Row],[ Hours]]-表格3_5[[#This Row],[Normal working hours]] -> 0 | P163: =(表格3_5[[#This Row],[Out-Time2]] - 表格3_5[[#This Row],[In-Time2]])*24 -> 0 | R163: =_xlfn.XLOOKUP(表格3_5[[#This Row],[Name]],Name_list[Full Name],Name_list[Hourr Rate]) -> 0 | S163: =表格3_5[[#This Row],[Hours Worked]]*表格3_5[[#This Row],[Hourly Rate]] -> 0
A164: 162 | B164: =_xlfn.CONCAT(表格3_5[[#This Row],[Name]],表格3_5[[#This Row],[Location]]) | E164: =DAY(表格3_5[[#This Row],[Date]])&"" -> 0 | G164: =_xlfn.XLOOKUP(表格3_5[[#This Row],[Name]],Name_list[Full Name],Name_list[Nick Name]) -> 0 | L164: =(表格3_5[[#This Row],[Out-Time]] - 表格3_5[[#This Row],[In-Time]])*24 -> 0 | M164: =表格3_5[[#This Row],[ Hours]]-表格3_5[[#This Row],[Normal working hours]] -> 0 | P164: =(表格3_5[[#This Row],[Out-Time2]] - 表格3_5[[#This Row],[In-Time2]])*24 -> 0 | R164: =_xlfn.XLOOKUP(表格3_5[[#This Row],[Name]],Name_list[Full Name],Name_list[Hourr Rate]) -> 0 | S164: =表格3_5[[#This Row],[Hours Worked]]*表格3_5[[#This Row],[Hourly Rate]] -> 0
A165: 163 | B165: =_xlfn.CONCAT(表格3_5[[#This Row],[Name]],表格3_5[[#This Row],[Location]]) | E165: =DAY(表格3_5[[#This Row],[Date]])&"" -> 0 | G165: =_xlfn.XLOOKUP(表格3_5[[#This Row],[Name]],Name_list[Full Name],Name_list[Nick Name]) -> 0 | L165: =(表格3_5[[#This Row],[Out-Time]] - 表格3_5[[#This Row],[In-Time]])*24 -> 0 | M165: =表格3_5[[#This Row],[ Hours]]-表格3_5[[#This Row],[Normal working hours]] -> 0 | P165: =(表格3_5[[#This Row],[Out-Time2]] - 表格3_5[[#This Row],[In-Time2]])*24 -> 0 | R165: =_xlfn.XLOOKUP(表格3_5[[#This Row],[Name]],Name_list[Full Name],Name_list[Hourr Rate]) -> 0 | S165: =表格3_5[[#This Row],[Hours Worked]]*表格3_5[[#This Row],[Hourly Rate]] -> 0
A166: 164 | B166: =_xlfn.CONCAT(表格3_5[[#This Row],[Name]],表格3_5[[#This Row],[Location]]) | E166: =DAY(表格3_5[[#This Row],[Date]])&"" -> 0 | G166: =_xlfn.XLOOKUP(表格3_5[[#This Row],[Name]],Name_list[Full Name],Name_list[Nick Name]) -> 0 | L166: =(表格3_5[[#This Row],[Out-Time]] - 表格3_5[[#This Row],[In-Time]])*24 -> 0 | M166: =表格3_5[[#This Row],[ Hours]]-表格3_5[[#This Row],[Normal working hours]] -> 0 | P166: =(表格3_5[[#This Row],[Out-Time2]] - 表格3_5[[#This Row],[In-Time2]])*24 -> 0 | R166: =_xlfn.XLOOKUP(表格3_5[[#This Row],[Name]],Name_list[Full Name],Name_list[Hourr Rate]) -> 0 | S166: =表格3_5[[#This Row],[Hours Worked]]*表格3_5[[#This Row],[Hourly Rate]] -> 0
A167: 165 | B167: =_xlfn.CONCAT(表格3_5[[#This Row],[Name]],表格3_5[[#This Row],[Location]]) | E167: =DAY(表格3_5[[#This Row],[Date]])&"" -> 0 | G167: =_xlfn.XLOOKUP(表格3_5[[#This Row],[Name]],Name_list[Full Name],Name_list[Nick Name]) -> 0 | L167: =(表格3_5[[#This Row],[Out-Time]] - 表格3_5[[#This Row],[In-Time]])*24 -> 0 | M167: =表格3_5[[#This Row],[ Hours]]-表格3_5[[#This Row],[Normal working hours]] -> 0 | P167: =(表格3_5[[#This Row],[Out-Time2]] - 表格3_5[[#This Row],[In-Time2]])*24 -> 0 | R167: =_xlfn.XLOOKUP(表格3_5[[#This Row],[Name]],Name_list[Full Name],Name_list[Hourr Rate]) -> 0 | S167: =表格3_5[[#This Row],[Hours Worked]]*表格3_5[[#This Row],[Hourly Rate]] -> 0
A168: 166 | B168: =_xlfn.CONCAT(表格3_5[[#This Row],[Name]],表格3_5[[#This Row],[Location]]) | E168: =DAY(表格3_5[[#This Row],[Date]])&"" -> 0 | G168: =_xlfn.XLOOKUP(表格3_5[[#This Row],[Name]],Name_list[Full Name],Name_list[Nick Name]) -> 0 | L168: =(表格3_5[[#This Row],[Out-Time]] - 表格3_5[[#This Row],[In-Time]])*24 -> 0 | M168: =表格3_5[[#This Row],[ Hours]]-表格3_5[[#This Row],[Normal working hours]] -> 0 | P168: =(表格3_5[[#This Row],[Out-Time2]] - 表格3_5[[#This Row],[In-Time2]])*24 -> 0 | R168: =_xlfn.XLOOKUP(表格3_5[[#This Row],[Name]],Name_list[Full Name],Name_list[Hourr Rate]) -> 0 | S168: =表格3_5[[#This Row],[Hours Worked]]*表格3_5[[#This Row],[Hourly Rate]] -> 0
A169: 167 | B169: =_xlfn.CONCAT(表格3_5[[#This Row],[Name]],表格3_5[[#This Row],[Location]]) | E169: =DAY(表格3_5[[#This Row],[Date]])&"" -> 0 | G169: =_xlfn.XLOOKUP(表格3_5[[#This Row],[Name]],Name_list[Full Name],Name_list[Nick Name]) -> 0 | L169: =(表格3_5[[#This Row],[Out-Time]] - 表格3_5[[#This Row],[In-Time]])*24 -> 0 | M169: =表格3_5[[#This Row],[ Hours]]-表格3_5[[#This Row],[Normal working hours]] -> 0 | P169: =(表格3_5[[#This Row],[Out-Time2]] - 表格3_5[[#This Row],[In-Time2]])*24 -> 0 | R169: =_xlfn.XLOOKUP(表格3_5[[#This Row],[Name]],Name_list[Full Name],Name_list[Hourr Rate]) -> 0 | S169: =表格3_5[[#This Row],[Hours Worked]]*表格3_5[[#This Row],[Hourly Rate]] -> 0
... A184: 182 | B184: =_xlfn.CONCAT(表格3_5[[#This Row],[Name]],表格3_5[[#This Row],[Location]]) | E184: =DAY(表格3_5[[#This Row],[Date]])&"" -> 0 | G184: =_xlfn.XLOOKUP(表格3_5[[#This Row],[Name]],Name_list[Full Name],Name_list[Nick Name]) -> 0 | L184: =(表格3_5[[#This Row],[Out-Time]] - 表格3_5[[#This Row],[In-Time]])*24 -> 0 | M184: =表格3_5[[#This Row],[ Hours]]-表格3_5[[#This Row],[Normal working hours]] -> 0 | P184: =(表格3_5[[#This Row],[Out-Time2]] - 表格3_5[[#This Row],[In-Time2]])*24 -> 0 | R184: =_xlfn.XLOOKUP(表格3_5[[#This Row],[Name]],Name_list[Full Name],Name_list[Hourr Rate]) -> 0 | S184: =表格3_5[[#This Row],[Hours Worked]]*表格3_5[[#This Row],[Hourly Rate]] -> 0

Sheet Total
A2: =_xlfn.CONCAT($A$5," ",$A$6," Century Field Promoter Salary Summary") -> 2026 Jun Century Field Promoter Salary Summary | N2: 請勿隨意加/刪行及列會影響糧單公式錯亂 | V2: Invoice No.
U3: Total | V3: Income
G4: 如之前做法, 如當日有編更; 按正常收工時間就可以 如果5號不用返工只TRAINING; 就會計錢 TOTAL 3 小時 @60 = $180; 而要返工的; ;由468 開始有假期錢後, 上公司TRAINING 不會再有額外錢 | H4: Jovi 話正常收工係當8小時，如果有人按平時收工時間收工導致OT 就照計左OT 先，adjust 先再搞 | U4: Total | V4: Pay | W4: =V6 -> 106758.04
A5: 2026 | V5: GP | W5: =W3-W4 -> -106758.04
A6: Jun | H6: =SUM(H8:H16) -> 109 | I6: =SUM(I8:I29) -> 1245.5 | J6: =SUM(J8:J29) -> 1010 | K6: =SUM(K8:K29) -> 73897.5 | L6: =SUM(L8:L29) -> 1052601 | M6: =SUM(M8:M29) -> 752 | N6: =SUM(N8:N29) -> 31578.03 | Q6: =SUM(Q8:Q29) -> 1440 | R6: =SUM(R8:R29) -> 0 | S6: =SUM(S8:S29) -> 30 | T6: =SUM(T8:T29) -> 0 | U6: =SUM(U8:U29) -> -614.928 | V6: =SUM(V8:V29) -> 106758.04 | W6: =SUM(W8:W29) -> 106759 | X6: =SUM(X8:X16) -> 0
A7: 3 | B7: 欄1 | C7: Shop | D7: Name | E7: Full Name | F7: CQ No. | G7: Period | H7: Days | I7: Reg.Hrs | J7: $ | K7: 酬 金 | L7: Sales Amt | M7: Qty | N7: Basic Comm | O7: PH&DA Sales Amt | P7: PH &DA Commission | Q7: Attendance | R7: Allowance | S7: Expenses | T7: Adjustmant | U7: MPF | V7: Total | W7: Input | X7: GP | Y7: Remark
A8: 1 | B8: 1 | C8: SW Wing On | D8: =_xlfn.XLOOKUP(E8,表格3_5[Name],表格3_5[Nick Name]) -> Hazel | E8: Tan Xing Fang | F8: 21186 | G8: {=_xlfn.TEXTJOIN(",",1,_xlfn._xlws.FILTER(表格3_5[ID3],(表格3_5[Location]=C8)*(表格3_5[Name]=E8),""))&"/"&$A$6} -> 4,5,6,9,10,11,12,13,14,15,16,17,20,21,22,23,24,26,27,28,29/Jun | H8: {=IF(OR(Total!E8="", C8=""), 0, COUNTA(_xlfn._xlws.FILTER(工作表1!$F$3:$F$681, (工作表1!$I$3:$I$681=Total!E8) * (工作表1!$H$3:$H$681=C8) * (工作表1!$F$3:$F$681<>"") )) )} -> 21 | I8: =SUMIFS(工作表1!$Q$3:$Q$681,工作表1!$I$3:$I$681,Total!E8,工作表1!$H$3:$H$681,C8) -> 168 | J8: =_xlfn.XLOOKUP(_xlfn.CONCAT($E8,$C8),表格3_5[Test],表格3_5[Hourly Rate]) -> 60 | K8: =J8*I8 -> 10080 | L8: =SUMIFS(sales[Total Price],sales[Promoter],表格3[[#This Row],[Name]],sales[concat],表格3[[#This Row],[Shop]]) -> 122506.2 | M8: =SUMIFS(sales[quantity],sales[Promoter],表格3[[#This Row],[Name]],sales[concat],表格3[[#This Row],[Shop]]) -> 105 | N8: =_xlfn.XLOOKUP(E8,Name_list[Full Name],Name_list[rate])*表格3[[#This Row],[Sales Amt]] -> 3675.186 | P8: =_xlfn.XLOOKUP(E8,Name_list[Full Name],Name_list[ph da comm])*表格3[[#This Row],[PH&DA Sales Amt]] -> 0 | Q8: 480 | R8: =_xlfn.XLOOKUP(E8,Name_list[Full Name],Name_list[Allowance])*H8 -> 0 | V8: =SUM(K8:U8)-表格3[[#This Row],[Sales Amt]]-表格3[[#This Row],[Qty]]-表格3[[#This Row],[PH&DA Sales Amt]] -> 14235.186 | W8: =ROUND(V8,0) -> 14235 | Y8: 4月6
A9: 2 | B9: 2 | C9: SW Wing On | D9: =_xlfn.XLOOKUP(E9,表格3_5[Name],表格3_5[Nick Name]) -> Carol | E9: Yuen Maria Wing Yan | F9: Autopay | G9: {=_xlfn.TEXTJOIN(",",1,_xlfn._xlws.FILTER(表格3_5[ID3],(表格3_5[Location]=C9)*(表格3_5[Name]=E9),""))&"/"&$A$6} -> 3,18,19,25/Jun | H9: {=IF(OR(Total!E9="", C9=""), 0, COUNTA(_xlfn._xlws.FILTER(工作表1!$F$3:$F$681, (工作表1!$I$3:$I$681=Total!E9) * (工作表1!$H$3:$H$681=C9) * (工作表1!$F$3:$F$681<>"") )) )} -> 4 | I9: =SUMIFS(工作表1!$Q$3:$Q$681,工作表1!$I$3:$I$681,Total!E9,工作表1!$H$3:$H$681,C9) -> 32 | J9: =_xlfn.XLOOKUP(_xlfn.CONCAT($E9,$C9),表格3_5[Test],表格3_5[Hourly Rate]) -> 60 | K9: =J9*I9 -> 1920 | L9: =SUMIFS(sales[Total Price],sales[Promoter],表格3[[#This Row],[Name]],sales[concat],表格3[[#This Row],[Shop]]) -> 20214.6 | M9: =SUMIFS(sales[quantity],sales[Promoter],表格3[[#This Row],[Name]],sales[concat],表格3[[#This Row],[Shop]]) -> 20 | N9: =_xlfn.XLOOKUP(E9,Name_list[Full Name],Name_list[rate])*表格3[[#This Row],[Sales Amt]] -> 606.438 | P9: =_xlfn.XLOOKUP(E9,Name_list[Full Name],Name_list[ph da comm])*表格3[[#This Row],[PH&DA Sales Amt]] -> 0 | R9: =_xlfn.XLOOKUP(E9,Name_list[Full Name],Name_list[Allowance])*H9 -> 0 | V9: =SUM(K9:U9)-表格3[[#This Row],[Sales Amt]]-表格3[[#This Row],[Qty]]-表格3[[#This Row],[PH&DA Sales Amt]] -> 2526.438 | W9: =ROUND(V9,0) -> 2526
A10: 3 | B10: 3 | C10: Kowloon Bay Fortress | D10: =_xlfn.XLOOKUP(E10,表格3_5[Name],表格3_5[Nick Name]) -> Wah | E10: Lo Chun Wah | F10: Autopay | G10: {=_xlfn.TEXTJOIN(",",1,_xlfn._xlws.FILTER(表格3_5[ID3],(表格3_5[Location]=C10)*(表格3_5[Name]=E10),""))&"/"&$A$6} -> 4,5,6,7,11,12,13,14,18,19,20,21,25,26,27,28/Jun | H10: {=IF(OR(Total!E10="", C10=""), 0, COUNTA(_xlfn._xlws.FILTER(工作表1!$F$3:$F$681, (工作表1!$I$3:$I$681=Total!E10) * (工作表1!$H$3:$H$681=C10) * (工作表1!$F$3:$F$681<>"") )) )} -> 16 | I10: =SUMIFS(工作表1!$Q$3:$Q$681,工作表1!$I$3:$I$681,Total!E10,工作表1!$H$3:$H$681,C10) -> 128 | J10: =_xlfn.XLOOKUP(_xlfn.CONCAT($E10,$C10),表格3_5[Test],表格3_5[Hourly Rate]) -> 60 | K10: =J10*I10 -> 7680 | L10: =SUMIFS(sales[Total Price],sales[Promoter],表格3[[#This Row],[Name]],sales[concat],表格3[[#This Row],[Shop]]) -> 137952 | M10: =SUMIFS(sales[quantity],sales[Promoter],表格3[[#This Row],[Name]],sales[concat],表格3[[#This Row],[Shop]]) -> 103 | N10: =_xlfn.XLOOKUP(E10,Name_list[Full Name],Name_list[rate])*表格3[[#This Row],[Sales Amt]] -> 4138.56 | P10: =_xlfn.XLOOKUP(E10,Name_list[Full Name],Name_list[ph da comm])*表格3[[#This Row],[PH&DA Sales Amt]] -> 0 | Q10: 480 | R10: =_xlfn.XLOOKUP(E10,Name_list[Full Name],Name_list[Allowance])*H10 -> 0 | U10: =-_xlfn.XLOOKUP(E10,Name_list[Full Name],Name_list[MPF])*(表格3[[#This Row],[酬 金]]+表格3[[#This Row],[Basic Comm]]+表格3[[#This Row],[Allowance]]+表格3[[#This Row],[Expenses]]+表格3[[#This Row],[Adjustmant]]+表格3[[#This Row],[Attendance]]) -> -614.928 | V10: =SUM(K10:U10)-表格3[[#This Row],[Sales Amt]]-表格3[[#This Row],[Qty]]-表格3[[#This Row],[PH&DA Sales Amt]] -> 11683.632 | W10: =ROUND(V10,0) -> 11684 | Y10: 1月18
A11: 4 | B11: 4 | C11: YL Citistore | D11: =_xlfn.XLOOKUP(E11,表格3_5[Name],表格3_5[Nick Name]) -> Ling | E11: Lok Yin Ling | F11: 21187 | G11: {=_xlfn.TEXTJOIN(",",1,_xlfn._xlws.FILTER(表格3_5[ID3],(表格3_5[Location]=C11)*(表格3_5[Name]=E11),""))&"/"&$A$6} -> 4,5,6,7,11,12,13,14,18,19,20,21,25,26,27,28/Jun | H11: {=IF(OR(Total!E11="", C11=""), 0, COUNTA(_xlfn._xlws.FILTER(工作表1!$F$3:$F$681, (工作表1!$I$3:$I$681=Total!E11) * (工作表1!$H$3:$H$681=C11) * (工作表1!$F$3:$F$681<>"") )) )} -> 16 | I11: =SUMIFS(工作表1!$Q$3:$Q$681,工作表1!$I$3:$I$681,Total!E11,工作表1!$H$3:$H$681,C11) -> 128 | J11: =_xlfn.XLOOKUP(_xlfn.CONCAT($E11,$C11),表格3_5[Test],表格3_5[Hourly Rate]) -> 60 | K11: =J11*I11 -> 7680 | L11: 46940.4 | M11: =SUMIFS(sales[quantity],sales[Promoter],表格3[[#This Row],[Name]],sales[concat],表格3[[#This Row],[Shop]]) -> 0 | N11: =_xlfn.XLOOKUP(E11,Name_list[Full Name],Name_list[rate])*表格3[[#This Row],[Sales Amt]] -> 1408.212 | O11: 21372 | P11: =_xlfn.XLOOKUP(E11,Name_list[Full Name],Name_list[ph da comm])*表格3[[#This Row],[PH&DA Sales Amt]] -> 427.44 | Q11: =60*8 -> 480 | R11: =_xlfn.XLOOKUP(E11,Name_list[Full Name],Name_list[Allowance])*H11 -> 0 | V11: =SUM(K11:U11)-表格3[[#This Row],[Sales Amt]]-表格3[[#This Row],[Qty]]-表格3[[#This Row],[PH&DA Sales Amt]] -> 9995.652 | W11: =ROUND(V11,0) -> 9996 | Y11: 1月18
A12: 5 | B12: 5 | C12: Kwai Fong Fortress | D12: =_xlfn.XLOOKUP(E12,表格3_5[Name],表格3_5[Nick Name]) -> Wu Sir | E12: Woo Kin Ming | F12: Autopay | G12: {=_xlfn.TEXTJOIN(",",1,_xlfn._xlws.FILTER(表格3_5[ID3],(表格3_5[Location]=C12)*(表格3_5[Name]=E12),""))&"/"&$A$6} -> 6,7,20,21,27,28/Jun | H12: {=IF(OR(Total!E12="", C12=""), 0, COUNTA(_xlfn._xlws.FILTER(工作表1!$F$3:$F$681, (工作表1!$I$3:$I$681=Total!E12) * (工作表1!$H$3:$H$681=C12) * (工作表1!$F$3:$F$681<>"") )) )} -> 6 | I12: =SUMIFS(工作表1!$Q$3:$Q$681,工作表1!$I$3:$I$681,Total!E12,工作表1!$H$3:$H$681,C12) -> 48 | J12: =_xlfn.XLOOKUP(_xlfn.CONCAT($E12,$C12),表格3_5[Test],表格3_5[Hourly Rate]) -> 65 | K12: =J12*I12 -> 3120 | L12: =SUMIFS(sales[Total Price],sales[Promoter],表格3[[#This Row],[Name]],sales[concat],表格3[[#This Row],[Shop]]) -> 84434 | M12: =SUMIFS(sales[quantity],sales[Promoter],表格3[[#This Row],[Name]],sales[concat],表格3[[#This Row],[Shop]]) -> 46 | N12: =_xlfn.XLOOKUP(E12,Name_list[Full Name],Name_list[rate])*表格3[[#This Row],[Sales Amt]] -> 2533.02 | P12: =_xlfn.XLOOKUP(E12,Name_list[Full Name],Name_list[ph da comm])*表格3[[#This Row],[PH&DA Sales Amt]] -> 0 | R12: =_xlfn.XLOOKUP(E12,Name_list[Full Name],Name_list[Allowance])*H12 -> 0 | V12: =SUM(K12:U12)-表格3[[#This Row],[Sales Amt]]-表格3[[#This Row],[Qty]]-表格3[[#This Row],[PH&DA Sales Amt]] -> 5653.02 | W12: =ROUND(V12,0) -> 5653
A13: 6 | B13: 6 | C13: Tai Wan Fortress | D13: =_xlfn.XLOOKUP(E13,表格3_5[Name],表格3_5[Nick Name]) -> Rebacca | E13: Choi Pui Ha | F13: Autopay | G13: {=_xlfn.TEXTJOIN(",",1,_xlfn._xlws.FILTER(表格3_5[ID3],(表格3_5[Location]=C13)*(表格3_5[Name]=E13),""))&"/"&$A$6} -> 5,6,7,12,13,14,19,20,21,26,27,28/Jun | H13: {=IF(OR(Total!E13="", C13=""), 0, COUNTA(_xlfn._xlws.FILTER(工作表1!$F$3:$F$681, (工作表1!$I$3:$I$681=Total!E13) * (工作表1!$H$3:$H$681=C13) * (工作表1!$F$3:$F$681<>"") )) )} -> 12 | I13: =SUMIFS(工作表1!$Q$3:$Q$681,工作表1!$I$3:$I$681,Total!E13,工作表1!$H$3:$H$681,C13) -> 96 | J13: =_xlfn.XLOOKUP(_xlfn.CONCAT($E13,$C13),表格3_5[Test],表格3_5[Hourly Rate]) -> 60 | K13: =J13*I13 -> 5760 | L13: =SUMIFS(sales[Total Price],sales[Promoter],表格3[[#This Row],[Name]],sales[concat],表格3[[#This Row],[Shop]]) -> 76395 | M13: =SUMIFS(sales[quantity],sales[Promoter],表格3[[#This Row],[Name]],sales[concat],表格3[[#This Row],[Shop]]) -> 53 | N13: =_xlfn.XLOOKUP(E13,Name_list[Full Name],Name_list[rate])*表格3[[#This Row],[Sales Amt]] -> 2291.85 | P13: =_xlfn.XLOOKUP(E13,Name_list[Full Name],Name_list[ph da comm])*表格3[[#This Row],[PH&DA Sales Amt]] -> 0 | R13: =_xlfn.XLOOKUP(E13,Name_list[Full Name],Name_list[Allowance])*H13 -> 0 | V13: =SUM(K13:U13)-表格3[[#This Row],[Sales Amt]]-表格3[[#This Row],[Qty]]-表格3[[#This Row],[PH&DA Sales Amt]] -> 8051.85 | W13: =ROUND(V13,0) -> 8052
A14: 7 | B14: 7 | C14: Tuen Mun Broadway | D14: =_xlfn.XLOOKUP(E14,表格3_5[Name],表格3_5[Nick Name]) -> May M | E14: Mok Yun Mei Marine | F14: 21188 | G14: {=_xlfn.TEXTJOIN(",",1,_xlfn._xlws.FILTER(表格3_5[ID3],(表格3_5[Location]=C14)*(表格3_5[Name]=E14),""))&"/"&$A$6} -> 4,5,6,7,11,12,13,14,18,19,20,21,25,26,27,28/Jun | H14: {=IF(OR(Total!E14="", C14=""), 0, COUNTA(_xlfn._xlws.FILTER(工作表1!$F$3:$F$681, (工作表1!$I$3:$I$681=Total!E14) * (工作表1!$H$3:$H$681=C14) * (工作表1!$F$3:$F$681<>"") )) )} -> 16 | I14: =SUMIFS(工作表1!$Q$3:$Q$681,工作表1!$I$3:$I$681,Total!E14,工作表1!$H$3:$H$681,C14) -> 128 | J14: =_xlfn.XLOOKUP(_xlfn.CONCAT($E14,$C14),表格3_5[Test],表格3_5[Hourly Rate]) -> 56.25 | K14: =J14*I14 -> 7200 | L14: =SUMIFS(sales[Total Price],sales[Promoter],表格3[[#This Row],[Name]],sales[concat],表格3[[#This Row],[Shop]]) -> 218918 | M14: =SUMIFS(sales[quantity],sales[Promoter],表格3[[#This Row],[Name]],sales[concat],表格3[[#This Row],[Shop]]) -> 125 | N14: =_xlfn.XLOOKUP(E14,Name_list[Full Name],Name_list[rate])*表格3[[#This Row],[Sales Amt]] -> 6567.54 | P14: =_xlfn.XLOOKUP(E14,Name_list[Full Name],Name_list[ph da comm])*表格3[[#This Row],[PH&DA Sales Amt]] -> 0 | R14: =_xlfn.XLOOKUP(E14,Name_list[Full Name],Name_list[Allowance])*H14 -> 0 | V14: =SUM(K14:U14)-表格3[[#This Row],[Sales Amt]]-表格3[[#This Row],[Qty]]-表格3[[#This Row],[PH&DA Sales Amt]] -> 13767.54 | W14: =ROUND(V14,0) -> 13768
A15: 8 | B15: 8 | C15: Shatin Fortress | D15: =_xlfn.XLOOKUP(E15,表格3_5[Name],表格3_5[Nick Name]) -> Margaret | E15: Siu Wai Ling | F15: 21189 | G15: {=_xlfn.TEXTJOIN(",",1,_xlfn._xlws.FILTER(表格3_5[ID3],(表格3_5[Location]=C15)*(表格3_5[Name]=E15),""))&"/"&$A$6} -> 5,6,7,12,13,14,19,20,21,25,29/Jun | H15: {=IF(OR(Total!E15="", C15=""), 0, COUNTA(_xlfn._xlws.FILTER(工作表1!$F$3:$F$681, (工作表1!$I$3:$I$681=Total!E15) * (工作表1!$H$3:$H$681=C15) * (工作表1!$F$3:$F$681<>"") )) )} -> 11 | I15: =SUMIFS(工作表1!$Q$3:$Q$681,工作表1!$I$3:$I$681,Total!E15,工作表1!$H$3:$H$681,C15) -> 88 | J15: =_xlfn.XLOOKUP(_xlfn.CONCAT($E15,$C15),表格3_5[Test],表格3_5[Hourly Rate]) -> 56.25 | K15: =J15*I15 -> 4950 | L15: =SUMIFS(sales[Total Price],sales[Promoter],表格3[[#This Row],[Name]],sales[concat],表格3[[#This Row],[Shop]]) -> 159644 | M15: =SUMIFS(sales[quantity],sales[Promoter],表格3[[#This Row],[Name]],sales[concat],表格3[[#This Row],[Shop]]) -> 106 | N15: =_xlfn.XLOOKUP(E15,Name_list[Full Name],Name_list[rate])*表格3[[#This Row],[Sales Amt]] -> 4789.32 | P15: =_xlfn.XLOOKUP(E15,Name_list[Full Name],Name_list[ph da comm])*表格3[[#This Row],[PH&DA Sales Amt]] -> 0 | R15: =_xlfn.XLOOKUP(E15,Name_list[Full Name],Name_list[Allowance])*H15 -> 0 | V15: =SUM(K15:U15)-表格3[[#This Row],[Sales Amt]]-表格3[[#This Row],[Qty]]-表格3[[#This Row],[PH&DA Sales Amt]] -> 9739.32 | W15: =ROUND(V15,0) -> 9739
A16: 9 | B16: 9 | C16: Central Fortress | D16: =_xlfn.XLOOKUP(E16,表格3_5[Name],表格3_5[Nick Name]) -> Margaret | E16: Siu Wai Ling | F16: 21190 | G16: {=_xlfn.TEXTJOIN(",",1,_xlfn._xlws.FILTER(表格3_5[ID3],(表格3_5[Location]=C16)*(表格3_5[Name]=E16),""))&"/"&$A$6} -> 1,2,8,9,15,22,23/Jun | H16: {=IF(OR(Total!E16="", C16=""), 0, COUNTA(_xlfn._xlws.FILTER(工作表1!$F$3:$F$681, (工作表1!$I$3:$I$681=Total!E16) * (工作表1!$H$3:$H$681=C16) * (工作表1!$F$3:$F$681<>"") )) )} -> 7 | I16: =SUMIFS(工作表1!$Q$3:$Q$681,工作表1!$I$3:$I$681,Total!E16,工作表1!$H$3:$H$681,C16) -> 56 | J16: =_xlfn.XLOOKUP(_xlfn.CONCAT($E16,$C16),表格3_5[Test],表格3_5[Hourly Rate]) -> 56.25 | K16: =J16*I16 -> 3150 | L16: =SUMIFS(sales[Total Price],sales[Promoter],表格3[[#This Row],[Name]],sales[concat],表格3[[#This Row],[Shop]]) -> 55390 | M16: =SUMIFS(sales[quantity],sales[Promoter],表格3[[#This Row],[Name]],sales[concat],表格3[[#This Row],[Shop]]) -> 56 | N16: =_xlfn.XLOOKUP(E16,Name_list[Full Name],Name_list[rate])*表格3[[#This Row],[Sales Amt]] -> 1661.7 | P16: =_xlfn.XLOOKUP(E16,Name_list[Full Name],Name_list[ph da comm])*表格3[[#This Row],[PH&DA Sales Amt]] -> 0 | R16: =_xlfn.XLOOKUP(E16,Name_list[Full Name],Name_list[Allowance])*H16 -> 0 | V16: =SUM(K16:U16)-表格3[[#This Row],[Sales Amt]]-表格3[[#This Row],[Qty]]-表格3[[#This Row],[PH&DA Sales Amt]] -> 4811.7 | W16: =ROUND(V16,0) -> 4812
A17: 10 | B17: 10 | C17: In - Home Expo 2 | D17: =_xlfn.XLOOKUP(E17,表格3_5[Name],表格3_5[Nick Name]) -> Margaret | E17: Siu Wai Ling | F17: 21191 | G17: {=_xlfn.TEXTJOIN(",",1,_xlfn._xlws.FILTER(表格3_5[ID3],(表格3_5[Location]=C17)*(表格3_5[Name]=E17),""))&"/"&$A$6} -> 27,28/Jun | H17: {=IF(OR(Total!E17="", C17=""), 0, COUNTA(_xlfn._xlws.FILTER(工作表1!$F$3:$F$681, (工作表1!$I$3:$I$681=Total!E17) * (工作表1!$H$3:$H$681=C17) * (工作表1!$F$3:$F$681<>"") )) )} -> 2 | I17: =SUMIFS(工作表1!$Q$3:$Q$681,工作表1!$I$3:$I$681,Total!E17,工作表1!$H$3:$H$681,C17) -> 14 | J17: =_xlfn.XLOOKUP(_xlfn.CONCAT($E17,$C17),表格3_5[Test],表格3_5[Hourly Rate]) -> 56.25 | K17: =J17*I17 -> 787.5 | L17: =SUMIFS(sales[Total Price],sales[Promoter],表格3[[#This Row],[Name]],sales[concat],表格3[[#This Row],[Shop]]) -> 0 | M17: =SUMIFS(sales[quantity],sales[Promoter],表格3[[#This Row],[Name]],sales[concat],表格3[[#This Row],[Shop]]) -> 0 | N17: =_xlfn.XLOOKUP(E17,Name_list[Full Name],Name_list[rate])*表格3[[#This Row],[Sales Amt]] -> 0 | P17: =_xlfn.XLOOKUP(E17,Name_list[Full Name],Name_list[ph da comm])*表格3[[#This Row],[PH&DA Sales Amt]] -> 0 | R17: =_xlfn.XLOOKUP(E17,Name_list[Full Name],Name_list[Allowance])*H17 -> 0 | V17: =SUM(K17:U17)-表格3[[#This Row],[Sales Amt]]-表格3[[#This Row],[Qty]]-表格3[[#This Row],[PH&DA Sales Amt]] -> 787.5 | W17: =ROUND(V17,0) -> 788
A18: 11 | B18: 11 | C18: In - Home Expo | D18: =_xlfn.XLOOKUP(E18,表格3_5[Name],表格3_5[Nick Name]) -> Jenny P | E18: Pang Kam Chun | F18: 21192 | G18: {=_xlfn.TEXTJOIN(",",1,_xlfn._xlws.FILTER(表格3_5[ID3],(表格3_5[Location]=C18)*(表格3_5[Name]=E18),""))&"/"&$A$6} -> 25,26,27,28/Jun | H18: {=IF(OR(Total!E18="", C18=""), 0, COUNTA(_xlfn._xlws.FILTER(工作表1!$F$3:$F$681, (工作表1!$I$3:$I$681=Total!E18) * (工作表1!$H$3:$H$681=C18) * (工作表1!$F$3:$F$681<>"") )) )} -> 4 | I18: =SUMIFS(工作表1!$Q$3:$Q$681,工作表1!$I$3:$I$681,Total!E18,工作表1!$H$3:$H$681,C18) -> 34.5 | J18: =_xlfn.XLOOKUP(_xlfn.CONCAT($E18,$C18),表格3_5[Test],表格3_5[Hourly Rate]) -> 60 | K18: =J18*I18 -> 2070 | L18: =SUMIFS(sales[Total Price],sales[Promoter],表格3[[#This Row],[Name]],sales[concat],表格3[[#This Row],[Shop]]) -> 0 | M18: =SUMIFS(sales[quantity],sales[Promoter],表格3[[#This Row],[Name]],sales[concat],表格3[[#This Row],[Shop]]) -> 0 | N18: =_xlfn.XLOOKUP(E18,Name_list[Full Name],Name_list[rate])*表格3[[#This Row],[Sales Amt]] -> 0 | P18: =_xlfn.XLOOKUP(E18,Name_list[Full Name],Name_list[ph da comm])*表格3[[#This Row],[PH&DA Sales Amt]] -> 0 | R18: =_xlfn.XLOOKUP(E18,Name_list[Full Name],Name_list[Allowance])*H18 -> 0 | V18: =SUM(K18:U18)-表格3[[#This Row],[Sales Amt]]-表格3[[#This Row],[Qty]]-表格3[[#This Row],[PH&DA Sales Amt]] -> 2070 | W18: =ROUND(V18,0) -> 2070
A19: 12 | B19: 12 | C19: Tai Po Yata | D19: =_xlfn.XLOOKUP(E19,表格3_5[Name],表格3_5[Nick Name]) -> Joe | E19: Wong Sui Ping | F19: 21181 | G19: {=_xlfn.TEXTJOIN(",",1,_xlfn._xlws.FILTER(表格3_5[ID3],(表格3_5[Location]=C19)*(表格3_5[Name]=E19),""))&"/"&$A$6} -> 5,6,7,12,13,14,19,20,21,26,27,28/Jun | H19: {=IF(OR(Total!E19="", C19=""), 0, COUNTA(_xlfn._xlws.FILTER(工作表1!$F$3:$F$681, (工作表1!$I$3:$I$681=Total!E19) * (工作表1!$H$3:$H$681=C19) * (工作表1!$F$3:$F$681<>"") )) )} -> 12 | I19: =SUMIFS(工作表1!$Q$3:$Q$681,工作表1!$I$3:$I$681,Total!E19,工作表1!$H$3:$H$681,C19) -> 97 | J19: =_xlfn.XLOOKUP(_xlfn.CONCAT($E19,$C19),表格3_5[Test],表格3_5[Hourly Rate]) -> 60 | K19: =J19*I19 -> 5820 | L19: =SUMIFS(sales[Total Price],sales[Promoter],表格3[[#This Row],[Name]],sales[concat],表格3[[#This Row],[Shop]]) -> 91042.8 | M19: =SUMIFS(sales[quantity],sales[Promoter],表格3[[#This Row],[Name]],sales[concat],表格3[[#This Row],[Shop]]) -> 95 | N19: =_xlfn.XLOOKUP(E19,Name_list[Full Name],Name_list[rate])*表格3[[#This Row],[Sales Amt]] -> 2731.284 | P19: =_xlfn.XLOOKUP(E19,Name_list[Full Name],Name_list[ph da comm])*表格3[[#This Row],[PH&DA Sales Amt]] -> 0 | R19: =_xlfn.XLOOKUP(E19,Name_list[Full Name],Name_list[Allowance])*H19 -> 0 | V19: =SUM(K19:U19)-表格3[[#This Row],[Sales Amt]]-表格3[[#This Row],[Qty]]-表格3[[#This Row],[PH&DA Sales Amt]] -> 8551.284 | W19: =ROUND(V19,0) -> 8551
A20: 13 | B20: 13 | C20: TW Aeon | D20: =_xlfn.XLOOKUP(E20,表格3_5[Name],表格3_5[Nick Name]) -> Fan | E20: Tang Chiu Fan | F20: 21193 | G20: {=_xlfn.TEXTJOIN(",",1,_xlfn._xlws.FILTER(表格3_5[ID3],(表格3_5[Location]=C20)*(表格3_5[Name]=E20),""))&"/"&$A$6} -> 6,7,13,14,27,28/Jun | H20: {=IF(OR(Total!E20="", C20=""), 0, COUNTA(_xlfn._xlws.FILTER(工作表1!$F$3:$F$681, (工作表1!$I$3:$I$681=Total!E20) * (工作表1!$H$3:$H$681=C20) * (工作表1!$F$3:$F$681<>"") )) )} -> 6 | I20: =SUMIFS(工作表1!$Q$3:$Q$681,工作表1!$I$3:$I$681,Total!E20,工作表1!$H$3:$H$681,C20) -> 48 | J20: =_xlfn.XLOOKUP(_xlfn.CONCAT($E20,$C20),表格3_5[Test],表格3_5[Hourly Rate]) -> 60 | K20: =J20*I20 -> 2880 | L20: =SUMIFS(sales[Total Price],sales[Promoter],表格3[[#This Row],[Name]],sales[concat],表格3[[#This Row],[Shop]]) -> 3578 | M20: =SUMIFS(sales[quantity],sales[Promoter],表格3[[#This Row],[Name]],sales[concat],表格3[[#This Row],[Shop]]) -> 7 | N20: =_xlfn.XLOOKUP(E20,Name_list[Full Name],Name_list[rate])*表格3[[#This Row],[Sales Amt]] -> 107.34 | P20: =_xlfn.XLOOKUP(E20,Name_list[Full Name],Name_list[ph da comm])*表格3[[#This Row],[PH&DA Sales Amt]] -> 0 | R20: =_xlfn.XLOOKUP(E20,Name_list[Full Name],Name_list[Allowance])*H20 -> 0 | V20: =SUM(K20:U20)-表格3[[#This Row],[Sales Amt]]-表格3[[#This Row],[Qty]]-表格3[[#This Row],[PH&DA Sales Amt]] -> 2987.34 | W20: =ROUND(V20,0) -> 2987
A21: 14 | B21: 14 | C21: TW YATA | D21: =_xlfn.XLOOKUP(E21,表格3_5[Name],表格3_5[Nick Name]) -> Mei Kiu | E21: Leung Mei Kiu | F21: Autopay | G21: {=_xlfn.TEXTJOIN(",",1,_xlfn._xlws.FILTER(表格3_5[ID3],(表格3_5[Location]=C21)*(表格3_5[Name]=E21),""))&"/"&$A$6} -> 6,7,13,14,20,21,27,28/Jun | H21: {=IF(OR(Total!E21="", C21=""), 0, COUNTA(_xlfn._xlws.FILTER(工作表1!$F$3:$F$681, (工作表1!$I$3:$I$681=Total!E21) * (工作表1!$H$3:$H$681=C21) * (工作表1!$F$3:$F$681<>"") )) )} -> 8 | I21: =SUMIFS(工作表1!$Q$3:$Q$681,工作表1!$I$3:$I$681,Total!E21,工作表1!$H$3:$H$681,C21) -> 64 | J21: =_xlfn.XLOOKUP(_xlfn.CONCAT($E21,$C21),表格3_5[Test],表格3_5[Hourly Rate]) -> 60 | K21: =J21*I21 -> 3840 | L21: =SUMIFS(sales[Total Price],sales[Promoter],表格3[[#This Row],[Name]],sales[concat],表格3[[#This Row],[Shop]]) -> 0 | M21: =SUMIFS(sales[quantity],sales[Promoter],表格3[[#This Row],[Name]],sales[concat],表格3[[#This Row],[Shop]]) -> 0 | N21: =_xlfn.XLOOKUP(E21,Name_list[Full Name],Name_list[rate])*表格3[[#This Row],[Sales Amt]] -> 0 | P21: =_xlfn.XLOOKUP(E21,Name_list[Full Name],Name_list[ph da comm])*表格3[[#This Row],[PH&DA Sales Amt]] -> 0 | R21: =_xlfn.XLOOKUP(E21,Name_list[Full Name],Name_list[Allowance])*H21 -> 0 | V21: =SUM(K21:U21)-表格3[[#This Row],[Sales Amt]]-表格3[[#This Row],[Qty]]-表格3[[#This Row],[PH&DA Sales Amt]] -> 3840 | W21: =ROUND(V21,0) -> 3840
A22: 15 | B22: 15 | C22: Tsing Yi Fortress | D22: =_xlfn.XLOOKUP(E22,表格3_5[Name],表格3_5[Nick Name]) -> Tammy | E22: Chan Tung Pan | F22: Autopay | G22: {=_xlfn.TEXTJOIN(",",1,_xlfn._xlws.FILTER(表格3_5[ID3],(表格3_5[Location]=C22)*(表格3_5[Name]=E22),""))&"/"&$A$6} -> 5,6,7,12,13,14,19,20,21/Jun | H22: {=IF(OR(Total!E22="", C22=""), 0, COUNTA(_xlfn._xlws.FILTER(工作表1!$F$3:$F$681, (工作表1!$I$3:$I$681=Total!E22) * (工作表1!$H$3:$H$681=C22) * (工作表1!$F$3:$F$681<>"") )) )} -> 9 | I22: =SUMIFS(工作表1!$Q$3:$Q$681,工作表1!$I$3:$I$681,Total!E22,工作表1!$H$3:$H$681,C22) -> 76 | J22: =_xlfn.XLOOKUP(_xlfn.CONCAT($E22,$C22),表格3_5[Test],表格3_5[Hourly Rate]) -> 60 | K22: =J22*I22 -> 4560 | L22: =SUMIFS(sales[Total Price],sales[Promoter],表格3[[#This Row],[Name]],sales[concat],表格3[[#This Row],[Shop]]) -> 30604 | M22: =SUMIFS(sales[quantity],sales[Promoter],表格3[[#This Row],[Name]],sales[concat],表格3[[#This Row],[Shop]]) -> 27 | N22: =_xlfn.XLOOKUP(E22,Name_list[Full Name],Name_list[rate])*表格3[[#This Row],[Sales Amt]] -> 918.12 | P22: =_xlfn.XLOOKUP(E22,Name_list[Full Name],Name_list[ph da comm])*表格3[[#This Row],[PH&DA Sales Amt]] -> 0 | R22: =_xlfn.XLOOKUP(E22,Name_list[Full Name],Name_list[Allowance])*H22 -> 0 | V22: =SUM(K22:U22)-表格3[[#This Row],[Sales Amt]]-表格3[[#This Row],[Qty]]-表格3[[#This Row],[PH&DA Sales Amt]] -> 5478.12 | W22: =ROUND(V22,0) -> 5478
A23: 16 | B23: 16 | C23: Festival Walk Fortress | D23: =_xlfn.XLOOKUP(E23,表格3_5[Name],表格3_5[Nick Name]) -> Shirley | E23: Sit Kwok Fong | F23: Autopay | G23: {=_xlfn.TEXTJOIN(",",1,_xlfn._xlws.FILTER(表格3_5[ID3],(表格3_5[Location]=C23)*(表格3_5[Name]=E23),""))&"/"&$A$6} -> 5,6,7/Jun | H23: {=IF(OR(Total!E23="", C23=""), 0, COUNTA(_xlfn._xlws.FILTER(工作表1!$F$3:$F$681, (工作表1!$I$3:$I$681=Total!E23) * (工作表1!$H$3:$H$681=C23) * (工作表1!$F$3:$F$681<>"") )) )} -> 3 | I23: =SUMIFS(工作表1!$Q$3:$Q$681,工作表1!$I$3:$I$681,Total!E23,工作表1!$H$3:$H$681,C23) -> 24 | J23: =_xlfn.XLOOKUP(_xlfn.CONCAT($E23,$C23),表格3_5[Test],表格3_5[Hourly Rate]) -> 60 | K23: =J23*I23 -> 1440 | L23: =SUMIFS(sales[Total Price],sales[Promoter],表格3[[#This Row],[Name]],sales[concat],表格3[[#This Row],[Shop]]) -> 2890 | M23: =SUMIFS(sales[quantity],sales[Promoter],表格3[[#This Row],[Name]],sales[concat],表格3[[#This Row],[Shop]]) -> 5 | N23: =_xlfn.XLOOKUP(E23,Name_list[Full Name],Name_list[rate])*表格3[[#This Row],[Sales Amt]] -> 86.7 | P23: =_xlfn.XLOOKUP(E23,Name_list[Full Name],Name_list[ph da comm])*表格3[[#This Row],[PH&DA Sales Amt]] -> 0 | R23: =_xlfn.XLOOKUP(E23,Name_list[Full Name],Name_list[Allowance])*H23 -> 0 | V23: =SUM(K23:U23)-表格3[[#This Row],[Sales Amt]]-表格3[[#This Row],[Qty]]-表格3[[#This Row],[PH&DA Sales Amt]] -> 1526.7 | W23: =ROUND(V23,0) -> 1527
A24: 17 | B24: 17 | C24: TW Aeon | D24: =_xlfn.XLOOKUP(E24,表格3_5[Name],表格3_5[Nick Name]) -> Apple | E24: Sin Wai Chun | F24: Autopay | G24: {=_xlfn.TEXTJOIN(",",1,_xlfn._xlws.FILTER(表格3_5[ID3],(表格3_5[Location]=C24)*(表格3_5[Name]=E24),""))&"/"&$A$6} -> 20,21/Jun | H24: {=IF(OR(Total!E24="", C24=""), 0, COUNTA(_xlfn._xlws.FILTER(工作表1!$F$3:$F$681, (工作表1!$I$3:$I$681=Total!E24) * (工作表1!$H$3:$H$681=C24) * (工作表1!$F$3:$F$681<>"") )) )} -> 2 | I24: =SUMIFS(工作表1!$Q$3:$Q$681,工作表1!$I$3:$I$681,Total!E24,工作表1!$H$3:$H$681,C24) -> 16 | J24: =_xlfn.XLOOKUP(_xlfn.CONCAT($E24,$C24),表格3_5[Test],表格3_5[Hourly Rate]) -> 60 | K24: =J24*I24 -> 960 | L24: =SUMIFS(sales[Total Price],sales[Promoter],表格3[[#This Row],[Name]],sales[concat],表格3[[#This Row],[Shop]]) -> 2092 | M24: =SUMIFS(sales[quantity],sales[Promoter],表格3[[#This Row],[Name]],sales[concat],表格3[[#This Row],[Shop]]) -> 4 | N24: =_xlfn.XLOOKUP(E24,Name_list[Full Name],Name_list[rate])*表格3[[#This Row],[Sales Amt]] -> 62.76 | P24: =_xlfn.XLOOKUP(E24,Name_list[Full Name],Name_list[ph da comm])*表格3[[#This Row],[PH&DA Sales Amt]] -> 0 | R24: =_xlfn.XLOOKUP(E24,Name_list[Full Name],Name_list[Allowance])*H24 -> 0 | S24: 30 | V24: =SUM(K24:U24)-表格3[[#This Row],[Sales Amt]]-表格3[[#This Row],[Qty]]-表格3[[#This Row],[PH&DA Sales Amt]] -> 1052.76 | W24: =ROUND(V24,0) -> 1053
A25: 18 | B25: 18 | D25: =_xlfn.XLOOKUP(E25,表格3_5[Name],表格3_5[Nick Name]) -> 0 | G25: {=_xlfn.TEXTJOIN(",",1,_xlfn._xlws.FILTER(表格3_5[ID3],(表格3_5[Location]=C25)*(表格3_5[Name]=E25),""))&"/"&$A$6} -> 0,0,0,0,0,0,0,0,0,0,0,0,0,0,0,0,0,0,0,0,0,0,0,0,0,0,0/Jun | H25: {=IF(OR(Total!E25="", C25=""), 0, COUNTA(_xlfn._xlws.FILTER(工作表1!$F$3:$F$681, (工作表1!$I$3:$I$681=Total!E25) * (工作表1!$H$3:$H$681=C25) * (工作表1!$F$3:$F$681<>"") )) )} -> 0 | I25: =SUMIFS(工作表1!$Q$3:$Q$681,工作表1!$I$3:$I$681,Total!E25,工作表1!$H$3:$H$681,C25) -> 0 | J25: =_xlfn.XLOOKUP(_xlfn.CONCAT($E25,$C25),表格3_5[Test],表格3_5[Hourly Rate]) -> 0 | K25: =J25*I25 -> 0 | L25: =SUMIFS(sales[Total Price],sales[Promoter],表格3[[#This Row],[Name]],sales[concat],表格3[[#This Row],[Shop]]) -> 0 | M25: =SUMIFS(sales[quantity],sales[Promoter],表格3[[#This Row],[Name]],sales[concat],表格3[[#This Row],[Shop]]) -> 0 | N25: =_xlfn.XLOOKUP(E25,Name_list[Full Name],Name_list[rate])*表格3[[#This Row],[Sales Amt]] -> 0 | P25: =_xlfn.XLOOKUP(E25,Name_list[Full Name],Name_list[ph da comm])*表格3[[#This Row],[PH&DA Sales Amt]] -> 0 | R25: =_xlfn.XLOOKUP(E25,Name_list[Full Name],Name_list[Allowance])*H25 -> 0 | V25: =SUM(K25:U25)-表格3[[#This Row],[Sales Amt]]-表格3[[#This Row],[Qty]]-表格3[[#This Row],[PH&DA Sales Amt]] -> 0 | W25: =ROUND(V25,0) -> 0
A26: 19 | B26: 19 | D26: =_xlfn.XLOOKUP(E26,表格3_5[Name],表格3_5[Nick Name]) -> 0 | G26: {=_xlfn.TEXTJOIN(",",1,_xlfn._xlws.FILTER(表格3_5[ID3],(表格3_5[Location]=C26)*(表格3_5[Name]=E26),""))&"/"&$A$6} -> 0,0,0,0,0,0,0,0,0,0,0,0,0,0,0,0,0,0,0,0,0,0,0,0,0,0,0/Jun | H26: {=IF(OR(Total!E26="", C26=""), 0, COUNTA(_xlfn._xlws.FILTER(工作表1!$F$3:$F$681, (工作表1!$I$3:$I$681=Total!E26) * (工作表1!$H$3:$H$681=C26) * (工作表1!$F$3:$F$681<>"") )) )} -> 0 | I26: =SUMIFS(工作表1!$Q$3:$Q$681,工作表1!$I$3:$I$681,Total!E26,工作表1!$H$3:$H$681,C26) -> 0 | J26: =_xlfn.XLOOKUP(_xlfn.CONCAT($E26,$C26),表格3_5[Test],表格3_5[Hourly Rate]) -> 0 | K26: =J26*I26 -> 0 | L26: =SUMIFS(sales[Total Price],sales[Promoter],表格3[[#This Row],[Name]],sales[concat],表格3[[#This Row],[Shop]]) -> 0 | M26: =SUMIFS(sales[quantity],sales[Promoter],表格3[[#This Row],[Name]],sales[concat],表格3[[#This Row],[Shop]]) -> 0 | N26: =_xlfn.XLOOKUP(E26,Name_list[Full Name],Name_list[rate])*表格3[[#This Row],[Sales Amt]] -> 0 | P26: =_xlfn.XLOOKUP(E26,Name_list[Full Name],Name_list[ph da comm])*表格3[[#This Row],[PH&DA Sales Amt]] -> 0 | R26: =_xlfn.XLOOKUP(E26,Name_list[Full Name],Name_list[Allowance])*H26 -> 0 | V26: =SUM(K26:U26)-表格3[[#This Row],[Sales Amt]]-表格3[[#This Row],[Qty]]-表格3[[#This Row],[PH&DA Sales Amt]] -> 0 | W26: =ROUND(V26,0) -> 0
A27: 20 | B27: 20 | D27: =_xlfn.XLOOKUP(E27,表格3_5[Name],表格3_5[Nick Name]) -> 0 | G27: {=_xlfn.TEXTJOIN(",",1,_xlfn._xlws.FILTER(表格3_5[ID3],(表格3_5[Location]=C27)*(表格3_5[Name]=E27),""))&"/"&$A$6} -> 0,0,0,0,0,0,0,0,0,0,0,0,0,0,0,0,0,0,0,0,0,0,0,0,0,0,0/Jun | H27: {=IF(OR(Total!E27="", C27=""), 0, COUNTA(_xlfn._xlws.FILTER(工作表1!$F$3:$F$681, (工作表1!$I$3:$I$681=Total!E27) * (工作表1!$H$3:$H$681=C27) * (工作表1!$F$3:$F$681<>"") )) )} -> 0 | I27: =SUMIFS(工作表1!$Q$3:$Q$681,工作表1!$I$3:$I$681,Total!E27,工作表1!$H$3:$H$681,C27) -> 0 | J27: =_xlfn.XLOOKUP(_xlfn.CONCAT($E27,$C27),表格3_5[Test],表格3_5[Hourly Rate]) -> 0 | K27: =J27*I27 -> 0 | L27: =SUMIFS(sales[Total Price],sales[Promoter],表格3[[#This Row],[Name]],sales[concat],表格3[[#This Row],[Shop]]) -> 0 | M27: =SUMIFS(sales[quantity],sales[Promoter],表格3[[#This Row],[Name]],sales[concat],表格3[[#This Row],[Shop]]) -> 0 | N27: =_xlfn.XLOOKUP(E27,Name_list[Full Name],Name_list[rate])*表格3[[#This Row],[Sales Amt]] -> 0 | P27: =_xlfn.XLOOKUP(E27,Name_list[Full Name],Name_list[ph da comm])*表格3[[#This Row],[PH&DA Sales Amt]] -> 0 | R27: =_xlfn.XLOOKUP(E27,Name_list[Full Name],Name_list[Allowance])*H27 -> 0 | V27: =SUM(K27:U27)-表格3[[#This Row],[Sales Amt]]-表格3[[#This Row],[Qty]]-表格3[[#This Row],[PH&DA Sales Amt]] -> 0 | W27: =ROUND(V27,0) -> 0
A28: 21 | B28: 21 | D28: =_xlfn.XLOOKUP(E28,表格3_5[Name],表格3_5[Nick Name]) -> 0 | G28: {=_xlfn.TEXTJOIN(",",1,_xlfn._xlws.FILTER(表格3_5[ID3],(表格3_5[Location]=C28)*(表格3_5[Name]=E28),""))&"/"&$A$6} -> 0,0,0,0,0,0,0,0,0,0,0,0,0,0,0,0,0,0,0,0,0,0,0,0,0,0,0/Jun | H28: {=IF(OR(Total!E28="", C28=""), 0, COUNTA(_xlfn._xlws.FILTER(工作表1!$F$3:$F$681, (工作表1!$I$3:$I$681=Total!E28) * (工作表1!$H$3:$H$681=C28) * (工作表1!$F$3:$F$681<>"") )) )} -> 0 | I28: =SUMIFS(工作表1!$Q$3:$Q$681,工作表1!$I$3:$I$681,Total!E28,工作表1!$H$3:$H$681,C28) -> 0 | J28: =_xlfn.XLOOKUP(_xlfn.CONCAT($E28,$C28),表格3_5[Test],表格3_5[Hourly Rate]) -> 0 | K28: =J28*I28 -> 0 | L28: =SUMIFS(sales[Total Price],sales[Promoter],表格3[[#This Row],[Name]],sales[concat],表格3[[#This Row],[Shop]]) -> 0 | M28: =SUMIFS(sales[quantity],sales[Promoter],表格3[[#This Row],[Name]],sales[concat],表格3[[#This Row],[Shop]]) -> 0 | N28: =_xlfn.XLOOKUP(E28,Name_list[Full Name],Name_list[rate])*表格3[[#This Row],[Sales Amt]] -> 0 | P28: =_xlfn.XLOOKUP(E28,Name_list[Full Name],Name_list[ph da comm])*表格3[[#This Row],[PH&DA Sales Amt]] -> 0 | R28: =_xlfn.XLOOKUP(E28,Name_list[Full Name],Name_list[Allowance])*H28 -> 0 | V28: =SUM(K28:U28)-表格3[[#This Row],[Sales Amt]]-表格3[[#This Row],[Qty]]-表格3[[#This Row],[PH&DA Sales Amt]] -> 0 | W28: =ROUND(V28,0) -> 0

Sheet 店鋪
A1: SW Wing On | B1: Hazel | C1: Tan Xing Fang
A2: SW Wing On A | B2: Apple | C2: Sin Wai Chun
A3: SW Wing On A | B3: Wu Sir | C3: Woo Kin Ming
A4: Kowloon Bay Fortress | B4: Wah | C4: Lo Chun Wah
A5: Kwai Fong Fortress | B5: Wu Sir | C5: Woo Kin Ming
A6: Kwai Fong Fortress | B6: Henry | C6: Siu Tsz Kin
A7: Tuen Mun Suning | B7: Rebecca | C7: Choi Pui Ha
A8: Tuen Mun Broadway | B8: May M | C8: Mok Yun Mei Marine
A9: Shain Fortress | B9: Ling S | C9: Siu Wai Ling
A10: Cental Fortress | B10: Ling S | C10: Siu Wai Ling
A11: YL Citistore | B11: Ling | C11: Lok Yin Ling
A12: Tai Po Yata | B12: Joe | C12: Wong Sui Ping
... A17: TW Yata | B17: Carol | C17: Yuen Maria Wing Yan

Sheet Name List
K1: 以下自動不用理….
A2: No | B2: Full Name | C2: Nick Name | D2: Hourr Rate | E2: Allowance | F2: rate | G2: ph da comm | H2: MPF | I2: Remark | K2: 當月location | N2: Nick Name | O2: Name | P2: Location | Q2: 計數 - Date
A3: 1 | B3: Chan Yun Hing | C3: Irene | D3: 60 | F3: 0.03 | K3: {=_xlfn._xlws.SORT(_xlfn._xlws.FILTER(_xlfn.UNIQUE(表格3_5[Location]), _xlfn.UNIQUE(表格3_5[Location])<>0),,1)} -> Central Fortress | N3: #N/A | O3: (空白) | P3: (空白)
A4: 2 | B4: Lo Chun Wah | C4: Wah | D4: 60 | F4: 0.03 | H4: 0.05 | I4: 1月18號開始計假期 | K4: Festival Walk Fortress | N4: Yu | O4: Chan Fung Yu | P4: Kwai Fong Fortress | Q4: 4
A5: 3 | B5: Lok Yin Ling | C5: Ling | D5: 60 | F5: 0.03 | G5: 0.02 | I5: 1月18號開始計假期 | K5: In - Home Expo | N5: Wah | O5: Lo Chun Wah | P5: Kowloon Bay Fortress | Q5: 21
A6: 4 | B6: Woo Kin Ming | C6: Wu Sir | D6: 65 | F6: 0.03 | K6: In - Home Expo 2 | N6: Pinky | O6: Chueng Yin Ping | P6: Tai Po Yata | Q6: 2
A7: 5 | B7: Wong Sui Ping | C7: Joe | D7: 60 | F7: 0.03 | K7: Kowloon Bay Fortress | N7: Mei Kiu | O7: Leung Mei Kiu | P7: Tuen Wan Aeon | Q7: 6
A8: 6 | B8: Wong Ka Mei | C8: Candy | D8: 60 | F8: 0.03 | K8: Kwai Fong Fortress | N8: Mei Kiu | O8: Leung Mei Kiu | P8: Tuen Wan Yata | Q8: 6
A9: 7 | B9: Yuen Maria Wing Yan | C9: Carol | D9: 60 | F9: 0.03 | K9: Shatin Fortress | N9: Ling | O9: Lok Yin Ling | P9: Yuen Long Citistore | Q9: 13
A10: 8 | B10: Sin Wai Chun | C10: Apple | D10: 60 | F10: 0.03 | H10: Roadshow | I10: Roadshow | K10: SW Wing On | N10: Joe | O10: Wong Sui Ping | P10: Tai Po Yata | Q10: 14
A11: 9 | B11: Leung Mei Kiu | C11: Mei Kiu | D11: 60 | F11: 0.03 | K11: Tai Po Yata | N11: Irene | O11: Chan Yun Hing | P11: SW Wing On | Q11: 23
A12: 10 | B12: Cheung Yin Ping | C12: Pinky | D12: 60 | F12: 0.03 | K12: Tai Wan Fortress | N12: Carol | O12: Yuen Maria Wing Yan | P12: Suning TKO Roadshow | Q12: 4
A13: 11 | B13: Yuen Maria Wing Yan 2 | C13: Carol | D13: 60 | F13: 0.015 | H13: Roadshow | I13: Roadshow | K13: Tsing Yi Fortress | N13: Wu Sir | O13: Woo Kin Ming | P13: CWB Sogo | Q13: 4
A14: 12 | B14: Chan Fung Yu | C14: Yu | D14: 60 | F14: 0.03 | K14: Tuen Mun Broadway | N14: Wu Sir | O14: Woo Kin Ming | P14: Kwai Fong Fortress | Q14: 7
A15: 13 | B15: Wong Ka Mei 2 | C15: Candy | D15: 65 | F15: 0.015 | H15: Roadshow | I15: Roadshow | K15: TW Aeon | N15: 總計 | Q15: 104
A16: 14 | B16: Yim Wan Chau | C16: Chau | D16: 60 | F16: 0.03 | K16: TW YATA
A17: 15 | B17: Ho Lai Sim | C17: Mandy | D17: 60 | F17: 0.03 | K17: YL Citistore
A18: 16 | B18: Chan Fung Yu 2 | C18: Yu | D18: 60 | F18: 0.015 | H18: Roadshow | I18: Roadshow
A19: 17 | B19: Lam Tsz Man | C19: Joey | D19: 60 | F19: 0.03
A20: 18 | B20: Tan Xing Fang | C20: Hazel | D20: 60 | F20: 0.03 | I20: 4月6號開始，7月6號後有假期
A21: 19 | B21: Chu Pik Fung | C21: Connie | D21: 60 | F21: 0.03
A22: 20 | B22: Chan Chi Tim | C22: Eddy | D22: 60 | F22: 0.03
A23: 21 | B23: Ng Tsui Ching | C23: Ching | D23: 60 | F23: 0.03
A24: 22 | B24: Mok Yun Mei Marine | C24: May M | D24: =450/8 -> 56.25 | F24: 0.03 | I24: 3日年假
A25: 23 | B25: Siu Wai Ling | C25: Margaret | D25: =450/8 -> 56.25 | F25: 0.03 | I25: 2日年假
A26: 24 | B26: Choi Pui Ha | C26: Rebacca | D26: 60 | F26: 0.03
A27: 25 | B27: Siu Tsz Kin | C27: Henry | D27: 60 | F27: 0.03
A28: 26 | B28: Yau Shuk Kuen | C28: Kuen | D28: 60 | F28: 0.03
A29: 27 | B29: Chan Tung Pan | C29: Tammy | D29: 60 | F29: 0.03
A30: 28 | B30: Sit Kwok Fong | C30: Shirley | D30: 60 | F30: 0.03
A31: 29 | B31: Pang Kam Chun | C31: Jenny P | D31: 60 | F31: 0.03
A32: 30 | B32: Tang Chiu Fan | C32: Fan | D32: 60 | F32: 0.03
A33: 31
A34: 32

Sheet editable-sales-form
J1: =SUBTOTAL(9,sales[quantity]) -> 889 | L1: =SUBTOTAL(9,sales[Total Price]) -> 1101833.4 | P1: =SUM(P3:P996) -> 0
A2: No. | B2: Shop | C2: Location | D2: Promoter | E2: month | F2: date | G2: Model | H2: Product Line | I2: Input | J2: quantity | K2: price | L2: Total Price | M2: Commission 3% | N2: Commission 2.5% | O2: Commission 1.5% | P2: ADD8906 5% | Q2: Page | R2: concat | S2: Remark
A3: 1 | B3: Kowloon Bay | C3: Fortress | D3: =OFFSET(Roster!$B$7, MATCH(B3&" "&C3&"*",Roster!$B$8:$B$20,0),DAY(sales[[#This Row],[date]]),1, 1) -> Wah | E3: =MONTH(sales[[#This Row],[date]]) -> 6 | F3: 46177 | G3: =VLOOKUP("*"&sales[[#This Row],[Input]]&"*",'Ref-List'!$A:$C,1,0) -> 6901+541 | H3: =VLOOKUP("*"&G3&"*",'Ref-List'!$A:$C,3,0) -> RO純淨飲水機 + 濾芯 | I3: 6901 | J3: 1 | K3: 1898 | L3: =sales[[#This Row],[quantity]]*sales[[#This Row],[price]] -> 1898 | M3: =sales[[#This Row],[Total Price]]*3% -> 56.94 | N3: =sales[[#This Row],[Total Price]]*2.5% -> 47.45 | O3: =sales[[#This Row],[Total Price]]*1.5% -> 28.47 | R3: =_xlfn.CONCAT(sales[[#This Row],[Shop]]," ",sales[[#This Row],[Location]]) -> Kowloon Bay Fortress
A4: 2 | B4: Kowloon Bay | C4: Fortress | D4: =OFFSET(Roster!$B$7, MATCH(B4&" "&C4&"*",Roster!$B$8:$B$20,0),DAY(sales[[#This Row],[date]]),1, 1) -> Wah | E4: =MONTH(sales[[#This Row],[date]]) -> 6 | F4: 46177 | G4: =VLOOKUP("*"&sales[[#This Row],[Input]]&"*",'Ref-List'!$A:$C,1,0) -> 3773+3922 | H4: =VLOOKUP("*"&G4&"*",'Ref-List'!$A:$C,3,0) -> 水龍頭過濾器 + 濾心 | I4: 3773+3922 | J4: 1 | K4: 1338 | L4: =sales[[#This Row],[quantity]]*sales[[#This Row],[price]] -> 1338 | M4: =sales[[#This Row],[Total Price]]*3% -> 40.14 | N4: =sales[[#This Row],[Total Price]]*2.5% -> 33.45 | O4: =sales[[#This Row],[Total Price]]*1.5% -> 20.07 | R4: =_xlfn.CONCAT(sales[[#This Row],[Shop]]," ",sales[[#This Row],[Location]]) -> Kowloon Bay Fortress
A5: 3 | B5: Kowloon Bay | C5: Fortress | D5: =OFFSET(Roster!$B$7, MATCH(B5&" "&C5&"*",Roster!$B$8:$B$20,0),DAY(sales[[#This Row],[date]]),1, 1) -> Wah | E5: =MONTH(sales[[#This Row],[date]]) -> 6 | F5: 46177 | G5: =VLOOKUP("*"&sales[[#This Row],[Input]]&"*",'Ref-List'!$A:$C,1,0) -> 3733+3922 | H5: =VLOOKUP("*"&G5&"*",'Ref-List'!$A:$C,3,0) -> 超濾龍頭式淨水器組合 | I5: 3922 | J5: 1 | K5: 598 | L5: =sales[[#This Row],[quantity]]*sales[[#This Row],[price]] -> 598 | M5: =sales[[#This Row],[Total Price]]*3% -> 17.94 | N5: =sales[[#This Row],[Total Price]]*2.5% -> 14.95 | O5: =sales[[#This Row],[Total Price]]*1.5% -> 8.97 | R5: =_xlfn.CONCAT(sales[[#This Row],[Shop]]," ",sales[[#This Row],[Location]]) -> Kowloon Bay Fortress
A6: 4 | B6: Kowloon Bay | C6: Fortress | D6: =OFFSET(Roster!$B$7, MATCH(B6&" "&C6&"*",Roster!$B$8:$B$20,0),DAY(sales[[#This Row],[date]]),1, 1) -> Wah | E6: =MONTH(sales[[#This Row],[date]]) -> 6 | F6: 46178 | G6: =VLOOKUP("*"&sales[[#This Row],[Input]]&"*",'Ref-List'!$A:$C,1,0) -> #N/A | H6: =VLOOKUP("*"&G6&"*",'Ref-List'!$A:$C,3,0) -> #N/A | I6: 6912 | J6: 1 | K6: 2998 | L6: =sales[[#This Row],[quantity]]*sales[[#This Row],[price]] -> 2998 | M6: =sales[[#This Row],[Total Price]]*3% -> 89.94 | N6: =sales[[#This Row],[Total Price]]*2.5% -> 74.95 | O6: =sales[[#This Row],[Total Price]]*1.5% -> 44.97 | R6: =_xlfn.CONCAT(sales[[#This Row],[Shop]]," ",sales[[#This Row],[Location]]) -> Kowloon Bay Fortress
A7: 5 | B7: Kowloon Bay | C7: Fortress | D7: =OFFSET(Roster!$B$7, MATCH(B7&" "&C7&"*",Roster!$B$8:$B$20,0),DAY(sales[[#This Row],[date]]),1, 1) -> Wah | E7: =MONTH(sales[[#This Row],[date]]) -> 6 | F7: 46178 | G7: =VLOOKUP("*"&sales[[#This Row],[Input]]&"*",'Ref-List'!$A:$C,1,0) -> 6901+541 | H7: =VLOOKUP("*"&G7&"*",'Ref-List'!$A:$C,3,0) -> RO純淨飲水機 + 濾芯 | I7: 6901 | J7: 1 | K7: 1898 | L7: =sales[[#This Row],[quantity]]*sales[[#This Row],[price]] -> 1898 | M7: =sales[[#This Row],[Total Price]]*3% -> 56.94 | N7: =sales[[#This Row],[Total Price]]*2.5% -> 47.45 | O7: =sales[[#This Row],[Total Price]]*1.5% -> 28.47 | R7: =_xlfn.CONCAT(sales[[#This Row],[Shop]]," ",sales[[#This Row],[Location]]) -> Kowloon Bay Fortress
A8: 6 | B8: Kowloon Bay | C8: Fortress | D8: =OFFSET(Roster!$B$7, MATCH(B8&" "&C8&"*",Roster!$B$8:$B$20,0),DAY(sales[[#This Row],[date]]),1, 1) -> Wah | E8: =MONTH(sales[[#This Row],[date]]) -> 6 | F8: 46178 | G8: =VLOOKUP("*"&sales[[#This Row],[Input]]&"*",'Ref-List'!$A:$C,1,0) -> 3733+3922 | H8: =VLOOKUP("*"&G8&"*",'Ref-List'!$A:$C,3,0) -> 超濾龍頭式淨水器組合 | I8: 3922 | J8: 1 | K8: 598 | L8: =sales[[#This Row],[quantity]]*sales[[#This Row],[price]] -> 598 | M8: =sales[[#This Row],[Total Price]]*3% -> 17.94 | N8: =sales[[#This Row],[Total Price]]*2.5% -> 14.95 | O8: =sales[[#This Row],[Total Price]]*1.5% -> 8.97 | R8: =_xlfn.CONCAT(sales[[#This Row],[Shop]]," ",sales[[#This Row],[Location]]) -> Kowloon Bay Fortress
A9: 7 | B9: Kowloon Bay | C9: Fortress | D9: =OFFSET(Roster!$B$7, MATCH(B9&" "&C9&"*",Roster!$B$8:$B$20,0),DAY(sales[[#This Row],[date]]),1, 1) -> Wah | E9: =MONTH(sales[[#This Row],[date]]) -> 6 | F9: 46179 | G9: =VLOOKUP("*"&sales[[#This Row],[Input]]&"*",'Ref-List'!$A:$C,1,0) -> #N/A | H9: =VLOOKUP("*"&G9&"*",'Ref-List'!$A:$C,3,0) -> #N/A | I9: 2754 | J9: 1 | K9: 368 | L9: =sales[[#This Row],[quantity]]*sales[[#This Row],[price]] -> 368 | M9: =sales[[#This Row],[Total Price]]*3% -> 11.04 | N9: =sales[[#This Row],[Total Price]]*2.5% -> 9.2 | O9: =sales[[#This Row],[Total Price]]*1.5% -> 5.52 | R9: =_xlfn.CONCAT(sales[[#This Row],[Shop]]," ",sales[[#This Row],[Location]]) -> Kowloon Bay Fortress
A10: 8 | B10: Kowloon Bay | C10: Fortress | D10: =OFFSET(Roster!$B$7, MATCH(B10&" "&C10&"*",Roster!$B$8:$B$20,0),DAY(sales[[#This Row],[date]]),1, 1) -> Wah | E10: =MONTH(sales[[#This Row],[date]]) -> 6 | F10: 46179 | G10: =VLOOKUP("*"&sales[[#This Row],[Input]]&"*",'Ref-List'!$A:$C,1,0) -> 6901+541 | H10: =VLOOKUP("*"&G10&"*",'Ref-List'!$A:$C,3,0) -> RO純淨飲水機 + 濾芯 | I10: 6901 | J10: 1 | K10: 1899 | L10: =sales[[#This Row],[quantity]]*sales[[#This Row],[price]] -> 1899 | M10: =sales[[#This Row],[Total Price]]*3% -> 56.97 | N10: =sales[[#This Row],[Total Price]]*2.5% -> 47.475 | O10: =sales[[#This Row],[Total Price]]*1.5% -> 28.485 | R10: =_xlfn.CONCAT(sales[[#This Row],[Shop]]," ",sales[[#This Row],[Location]]) -> Kowloon Bay Fortress
A11: 9 | B11: Kowloon Bay | C11: Fortress | D11: =OFFSET(Roster!$B$7, MATCH(B11&" "&C11&"*",Roster!$B$8:$B$20,0),DAY(sales[[#This Row],[date]]),1, 1) -> Wah | E11: =MONTH(sales[[#This Row],[date]]) -> 6 | F11: 46179 | G11: =VLOOKUP("*"&sales[[#This Row],[Input]]&"*",'Ref-List'!$A:$C,1,0) -> #N/A | H11: =VLOOKUP("*"&G11&"*",'Ref-List'!$A:$C,3,0) -> #N/A | I11: 6912 | J11: 1 | K11: 2998 | L11: =sales[[#This Row],[quantity]]*sales[[#This Row],[price]] -> 2998 | M11: =sales[[#This Row],[Total Price]]*3% -> 89.94 | N11: =sales[[#This Row],[Total Price]]*2.5% -> 74.95 | O11: =sales[[#This Row],[Total Price]]*1.5% -> 44.97 | R11: =_xlfn.CONCAT(sales[[#This Row],[Shop]]," ",sales[[#This Row],[Location]]) -> Kowloon Bay Fortress
A12: 10 | B12: Kowloon Bay | C12: Fortress | D12: =OFFSET(Roster!$B$7, MATCH(B12&" "&C12&"*",Roster!$B$8:$B$20,0),DAY(sales[[#This Row],[date]]),1, 1) -> Wah | E12: =MONTH(sales[[#This Row],[date]]) -> 6 | F12: 46179 | G12: =VLOOKUP("*"&sales[[#This Row],[Input]]&"*",'Ref-List'!$A:$C,1,0) -> 6910+550 | H12: =VLOOKUP("*"&G12&"*",'Ref-List'!$A:$C,3,0) -> 冷熱飲水機 + 濾心 | I12: 550 | J12: 1 | K12: 598 | L12: =sales[[#This Row],[quantity]]*sales[[#This Row],[price]] -> 598 | M12: =sales[[#This Row],[Total Price]]*3% -> 17.94 | N12: =sales[[#This Row],[Total Price]]*2.5% -> 14.95 | O12: =sales[[#This Row],[Total Price]]*1.5% -> 8.97 | R12: =_xlfn.CONCAT(sales[[#This Row],[Shop]]," ",sales[[#This Row],[Location]]) -> Kowloon Bay Fortress
A13: 11 | B13: Kowloon Bay | C13: Fortress | D13: =OFFSET(Roster!$B$7, MATCH(B13&" "&C13&"*",Roster!$B$8:$B$20,0),DAY(sales[[#This Row],[date]]),1, 1) -> Wah | E13: =MONTH(sales[[#This Row],[date]]) -> 6 | F13: 46179 | G13: =VLOOKUP("*"&sales[[#This Row],[Input]]&"*",'Ref-List'!$A:$C,1,0) -> 6910+550 | H13: =VLOOKUP("*"&G13&"*",'Ref-List'!$A:$C,3,0) -> 冷熱飲水機 + 濾心 | I13: 550 | J13: 1 | K13: 598 | L13: =sales[[#This Row],[quantity]]*sales[[#This Row],[price]] -> 598 | M13: =sales[[#This Row],[Total Price]]*3% -> 17.94 | N13: =sales[[#This Row],[Total Price]]*2.5% -> 14.95 | O13: =sales[[#This Row],[Total Price]]*1.5% -> 8.97 | R13: =_xlfn.CONCAT(sales[[#This Row],[Shop]]," ",sales[[#This Row],[Location]]) -> Kowloon Bay Fortress
A14: 12 | B14: Kowloon Bay | C14: Fortress | D14: =OFFSET(Roster!$B$7, MATCH(B14&" "&C14&"*",Roster!$B$8:$B$20,0),DAY(sales[[#This Row],[date]]),1, 1) -> Wah | E14: =MONTH(sales[[#This Row],[date]]) -> 6 | F14: 46179 | G14: =VLOOKUP("*"&sales[[#This Row],[Input]]&"*",'Ref-List'!$A:$C,1,0) -> 3780/97 | H14: =VLOOKUP("*"&G14&"*",'Ref-List'!$A:$C,3,0) -> 座檯濾水器 | I14: 3780 | J14: 1 | K14: 1188 | L14: =sales[[#This Row],[quantity]]*sales[[#This Row],[price]] -> 1188 | M14: =sales[[#This Row],[Total Price]]*3% -> 35.64 | N14: =sales[[#This Row],[Total Price]]*2.5% -> 29.7 | O14: =sales[[#This Row],[Total Price]]*1.5% -> 17.82 | R14: =_xlfn.CONCAT(sales[[#This Row],[Shop]]," ",sales[[#This Row],[Location]]) -> Kowloon Bay Fortress
A15: 13 | B15: Kowloon Bay | C15: Fortress | D15: =OFFSET(Roster!$B$7, MATCH(B15&" "&C15&"*",Roster!$B$8:$B$20,0),DAY(sales[[#This Row],[date]]),1, 1) -> Wah | E15: =MONTH(sales[[#This Row],[date]]) -> 6 | F15: 46180 | G15: =VLOOKUP("*"&sales[[#This Row],[Input]]&"*",'Ref-List'!$A:$C,1,0) -> 2769/97 | H15: =VLOOKUP("*"&G15&"*",'Ref-List'!$A:$C,3,0) -> 電熱水樽 | I15: 2769 | J15: 1 | K15: 298 | L15: =sales[[#This Row],[quantity]]*sales[[#This Row],[price]] -> 298 | M15: =sales[[#This Row],[Total Price]]*3% -> 8.94 | N15: =sales[[#This Row],[Total Price]]*2.5% -> 7.45 | O15: =sales[[#This Row],[Total Price]]*1.5% -> 4.47 | R15: =_xlfn.CONCAT(sales[[#This Row],[Shop]]," ",sales[[#This Row],[Location]]) -> Kowloon Bay Fortress
A16: 14 | B16: Kowloon Bay | C16: Fortress | D16: =OFFSET(Roster!$B$7, MATCH(B16&" "&C16&"*",Roster!$B$8:$B$20,0),DAY(sales[[#This Row],[date]]),1, 1) -> Wah | E16: =MONTH(sales[[#This Row],[date]]) -> 6 | F16: 46180 | G16: =VLOOKUP("*"&sales[[#This Row],[Input]]&"*",'Ref-List'!$A:$C,1,0) -> 4030/90 | H16: =VLOOKUP("*"&G16&"*",'Ref-List'!$A:$C,3,0) -> 櫥下型濾水器 | I16: 4030 | J16: 1 | K16: 2645 | L16: =sales[[#This Row],[quantity]]*sales[[#This Row],[price]] -> 2645 | M16: =sales[[#This Row],[Total Price]]*3% -> 79.35 | N16: =sales[[#This Row],[Total Price]]*2.5% -> 66.125 | O16: =sales[[#This Row],[Total Price]]*1.5% -> 39.675 | R16: =_xlfn.CONCAT(sales[[#This Row],[Shop]]," ",sales[[#This Row],[Location]]) -> Kowloon Bay Fortress
... A27: 25 | B27: Kowloon Bay | C27: Fortress | D27: =OFFSET(Roster!$B$7, MATCH(B27&" "&C27&"*",Roster!$B$8:$B$20,0),DAY(sales[[#This Row],[date]]),1, 1) -> Wah | E27: =MONTH(sales[[#This Row],[date]]) -> 6 | F27: 46184 | G27: =VLOOKUP("*"&sales[[#This Row],[Input]]&"*",'Ref-List'!$A:$C,1,0) -> #N/A | H27: =VLOOKUP("*"&G27&"*",'Ref-List'!$A:$C,3,0) -> #N/A | I27: 583 | J27: 1 | K27: 848 | L27: =sales[[#This Row],[quantity]]*sales[[#This Row],[price]] -> 848 | M27: =sales[[#This Row],[Total Price]]*3% -> 25.44 | N27: =sales[[#This Row],[Total Price]]*2.5% -> 21.2 | O27: =sales[[#This Row],[Total Price]]*1.5% -> 12.72 | R27: =_xlfn.CONCAT(sales[[#This Row],[Shop]]," ",sales[[#This Row],[Location]]) -> Kowloon Bay Fortress
A28: 26 | B28: Kowloon Bay | C28: Fortress | D28: =OFFSET(Roster!$B$7, MATCH(B28&" "&C28&"*",Roster!$B$8:$B$20,0),DAY(sales[[#This Row],[date]]),1, 1) -> Wah | E28: =MONTH(sales[[#This Row],[date]]) -> 6 | F28: 46184 | G28: =VLOOKUP("*"&sales[[#This Row],[Input]]&"*",'Ref-List'!$A:$C,1,0) -> #N/A | H28: =VLOOKUP("*"&G28&"*",'Ref-List'!$A:$C,3,0) -> #N/A | I28: 541+547 | J28: 1 | K28: 796 | L28: =sales[[#This Row],[quantity]]*sales[[#This Row],[price]] -> 796 | M28: =sales[[#This Row],[Total Price]]*3% -> 23.88 | N28: =sales[[#This Row],[Total Price]]*2.5% -> 19.9 | O28: =sales[[#This Row],[Total Price]]*1.5% -> 11.94 | R28: =_xlfn.CONCAT(sales[[#This Row],[Shop]]," ",sales[[#This Row],[Location]]) -> Kowloon Bay Fortress
A29: 27 | B29: Kowloon Bay | C29: Fortress | D29: =OFFSET(Roster!$B$7, MATCH(B29&" "&C29&"*",Roster!$B$8:$B$20,0),DAY(sales[[#This Row],[date]]),1, 1) -> Wah | E29: =MONTH(sales[[#This Row],[date]]) -> 6 | F29: 46184 | G29: =VLOOKUP("*"&sales[[#This Row],[Input]]&"*",'Ref-List'!$A:$C,1,0) -> 6911+553 | H29: =VLOOKUP("*"&G29&"*",'Ref-List'!$A:$C,3,0) -> 冷熱飲水機 + 濾心 | I29: 553 | J29: 1 | K29: 598 | L29: =sales[[#This Row],[quantity]]*sales[[#This Row],[price]] -> 598 | M29: =sales[[#This Row],[Total Price]]*3% -> 17.94 | N29: =sales[[#This Row],[Total Price]]*2.5% -> 14.95 | O29: =sales[[#This Row],[Total Price]]*1.5% -> 8.97 | R29: =_xlfn.CONCAT(sales[[#This Row],[Shop]]," ",sales[[#This Row],[Location]]) -> Kowloon Bay Fortress
A30: 28 | B30: Kowloon Bay | C30: Fortress | D30: =OFFSET(Roster!$B$7, MATCH(B30&" "&C30&"*",Roster!$B$8:$B$20,0),DAY(sales[[#This Row],[date]]),1, 1) -> Wah | E30: =MONTH(sales[[#This Row],[date]]) -> 6 | F30: 46184 | G30: =VLOOKUP("*"&sales[[#This Row],[Input]]&"*",'Ref-List'!$A:$C,1,0) -> 2769/97 | H30: =VLOOKUP("*"&G30&"*",'Ref-List'!$A:$C,3,0) -> 電熱水樽 | I30: 2769 | J30: 1 | K30: 298 | L30: =sales[[#This Row],[quantity]]*sales[[#This Row],[price]] -> 298 | M30: =sales[[#This Row],[Total Price]]*3% -> 8.94 | N30: =sales[[#This Row],[Total Price]]*2.5% -> 7.45 | O30: =sales[[#This Row],[Total Price]]*1.5% -> 4.47 | R30: =_xlfn.CONCAT(sales[[#This Row],[Shop]]," ",sales[[#This Row],[Location]]) -> Kowloon Bay Fortress
A31: 29 | B31: Kowloon Bay | C31: Fortress | D31: =OFFSET(Roster!$B$7, MATCH(B31&" "&C31&"*",Roster!$B$8:$B$20,0),DAY(sales[[#This Row],[date]]),1, 1) -> Wah | E31: =MONTH(sales[[#This Row],[date]]) -> 6 | F31: 46185 | G31: =VLOOKUP("*"&sales[[#This Row],[Input]]&"*",'Ref-List'!$A:$C,1,0) -> 6901+541 | H31: =VLOOKUP("*"&G31&"*",'Ref-List'!$A:$C,3,0) -> RO純淨飲水機 + 濾芯 | I31: 6901 | J31: 1 | K31: 1899 | L31: =sales[[#This Row],[quantity]]*sales[[#This Row],[price]] -> 1899 | M31: =sales[[#This Row],[Total Price]]*3% -> 56.97 | N31: =sales[[#This Row],[Total Price]]*2.5% -> 47.475 | O31: =sales[[#This Row],[Total Price]]*1.5% -> 28.485 | R31: =_xlfn.CONCAT(sales[[#This Row],[Shop]]," ",sales[[#This Row],[Location]]) -> Kowloon Bay Fortress
A32: 30 | B32: Kowloon Bay | C32: Fortress | D32: =OFFSET(Roster!$B$7, MATCH(B32&" "&C32&"*",Roster!$B$8:$B$20,0),DAY(sales[[#This Row],[date]]),1, 1) -> Wah | E32: =MONTH(sales[[#This Row],[date]]) -> 6 | F32: 46185 | G32: =VLOOKUP("*"&sales[[#This Row],[Input]]&"*",'Ref-List'!$A:$C,1,0) -> #N/A | H32: =VLOOKUP("*"&G32&"*",'Ref-List'!$A:$C,3,0) -> #N/A | I32: 6912 | J32: 1 | K32: 2998 | L32: =sales[[#This Row],[quantity]]*sales[[#This Row],[price]] -> 2998 | M32: =sales[[#This Row],[Total Price]]*3% -> 89.94 | N32: =sales[[#This Row],[Total Price]]*2.5% -> 74.95 | O32: =sales[[#This Row],[Total Price]]*1.5% -> 44.97 | R32: =_xlfn.CONCAT(sales[[#This Row],[Shop]]," ",sales[[#This Row],[Location]]) -> Kowloon Bay Fortress
A33: 31 | B33: Kowloon Bay | C33: Fortress | D33: =OFFSET(Roster!$B$7, MATCH(B33&" "&C33&"*",Roster!$B$8:$B$20,0),DAY(sales[[#This Row],[date]]),1, 1) -> Wah | E33: =MONTH(sales[[#This Row],[date]]) -> 6 | F33: 46185 | G33: =VLOOKUP("*"&sales[[#This Row],[Input]]&"*",'Ref-List'!$A:$C,1,0) -> 3733+3922 | H33: =VLOOKUP("*"&G33&"*",'Ref-List'!$A:$C,3,0) -> 超濾龍頭式淨水器組合 | I33: 3922 | J33: 1 | K33: 598 | L33: =sales[[#This Row],[quantity]]*sales[[#This Row],[price]] -> 598 | M33: =sales[[#This Row],[Total Price]]*3% -> 17.94 | N33: =sales[[#This Row],[Total Price]]*2.5% -> 14.95 | O33: =sales[[#This Row],[Total Price]]*1.5% -> 8.97 | R33: =_xlfn.CONCAT(sales[[#This Row],[Shop]]," ",sales[[#This Row],[Location]]) -> Kowloon Bay Fortress
A34: 32 | B34: Kowloon Bay | C34: Fortress | D34: =OFFSET(Roster!$B$7, MATCH(B34&" "&C34&"*",Roster!$B$8:$B$20,0),DAY(sales[[#This Row],[date]]),1, 1) -> Wah | E34: =MONTH(sales[[#This Row],[date]]) -> 6 | F34: 46186 | G34: =VLOOKUP("*"&sales[[#This Row],[Input]]&"*",'Ref-List'!$A:$C,1,0) -> 3733+3922 | H34: =VLOOKUP("*"&G34&"*",'Ref-List'!$A:$C,3,0) -> 超濾龍頭式淨水器組合 | I34: 3922 | J34: 1 | K34: 598 | L34: =sales[[#This Row],[quantity]]*sales[[#This Row],[price]] -> 598 | M34: =sales[[#This Row],[Total Price]]*3% -> 17.94 | N34: =sales[[#This Row],[Total Price]]*2.5% -> 14.95 | O34: =sales[[#This Row],[Total Price]]*1.5% -> 8.97 | R34: =_xlfn.CONCAT(sales[[#This Row],[Shop]]," ",sales[[#This Row],[Location]]) -> Kowloon Bay Fortress
A35: 33 | B35: Kowloon Bay | C35: Fortress | D35: =OFFSET(Roster!$B$7, MATCH(B35&" "&C35&"*",Roster!$B$8:$B$20,0),DAY(sales[[#This Row],[date]]),1, 1) -> Wah | E35: =MONTH(sales[[#This Row],[date]]) -> 6 | F35: 46186 | G35: =VLOOKUP("*"&sales[[#This Row],[Input]]&"*",'Ref-List'!$A:$C,1,0) -> 6901+541 | H35: =VLOOKUP("*"&G35&"*",'Ref-List'!$A:$C,3,0) -> RO純淨飲水機 + 濾芯 | I35: 6901 | J35: 1 | K35: 1899 | L35: =sales[[#This Row],[quantity]]*sales[[#This Row],[price]] -> 1899 | M35: =sales[[#This Row],[Total Price]]*3% -> 56.97 | N35: =sales[[#This Row],[Total Price]]*2.5% -> 47.475 | O35: =sales[[#This Row],[Total Price]]*1.5% -> 28.485 | R35: =_xlfn.CONCAT(sales[[#This Row],[Shop]]," ",sales[[#This Row],[Location]]) -> Kowloon Bay Fortress
A36: 34 | B36: Kowloon Bay | C36: Fortress | D36: =OFFSET(Roster!$B$7, MATCH(B36&" "&C36&"*",Roster!$B$8:$B$20,0),DAY(sales[[#This Row],[date]]),1, 1) -> Wah | E36: =MONTH(sales[[#This Row],[date]]) -> 6 | F36: 46186 | G36: =VLOOKUP("*"&sales[[#This Row],[Input]]&"*",'Ref-List'!$A:$C,1,0) -> 2769/97 | H36: =VLOOKUP("*"&G36&"*",'Ref-List'!$A:$C,3,0) -> 電熱水樽 | I36: 2769 | J36: 1 | K36: 328 | L36: =sales[[#This Row],[quantity]]*sales[[#This Row],[price]] -> 328 | M36: =sales[[#This Row],[Total Price]]*3% -> 9.84 | N36: =sales[[#This Row],[Total Price]]*2.5% -> 8.2 | O36: =sales[[#This Row],[Total Price]]*1.5% -> 4.92 | R36: =_xlfn.CONCAT(sales[[#This Row],[Shop]]," ",sales[[#This Row],[Location]]) -> Kowloon Bay Fortress
A37: 35 | B37: Kowloon Bay | C37: Fortress | D37: =OFFSET(Roster!$B$7, MATCH(B37&" "&C37&"*",Roster!$B$8:$B$20,0),DAY(sales[[#This Row],[date]]),1, 1) -> Wah | E37: =MONTH(sales[[#This Row],[date]]) -> 6 | F37: 46186 | G37: =VLOOKUP("*"&sales[[#This Row],[Input]]&"*",'Ref-List'!$A:$C,1,0) -> 3733+3922 | H37: =VLOOKUP("*"&G37&"*",'Ref-List'!$A:$C,3,0) -> 超濾龍頭式淨水器組合 | I37: 3922 | J37: 1 | K37: 598 | L37: =sales[[#This Row],[quantity]]*sales[[#This Row],[price]] -> 598 | M37: =sales[[#This Row],[Total Price]]*3% -> 17.94 | N37: =sales[[#This Row],[Total Price]]*2.5% -> 14.95 | O37: =sales[[#This Row],[Total Price]]*1.5% -> 8.97 | R37: =_xlfn.CONCAT(sales[[#This Row],[Shop]]," ",sales[[#This Row],[Location]]) -> Kowloon Bay Fortress
A38: 36 | B38: Kowloon Bay | C38: Fortress | D38: =OFFSET(Roster!$B$7, MATCH(B38&" "&C38&"*",Roster!$B$8:$B$20,0),DAY(sales[[#This Row],[date]]),1, 1) -> Wah | E38: =MONTH(sales[[#This Row],[date]]) -> 6 | F38: 46186 | G38: =VLOOKUP("*"&sales[[#This Row],[Input]]&"*",'Ref-List'!$A:$C,1,0) -> 6901+541 | H38: =VLOOKUP("*"&G38&"*",'Ref-List'!$A:$C,3,0) -> RO純淨飲水機 + 濾芯 | I38: 541 | J38: 1 | K38: 628 | L38: =sales[[#This Row],[quantity]]*sales[[#This Row],[price]] -> 628 | M38: =sales[[#This Row],[Total Price]]*3% -> 18.84 | N38: =sales[[#This Row],[Total Price]]*2.5% -> 15.7 | O38: =sales[[#This Row],[Total Price]]*1.5% -> 9.42 | R38: =_xlfn.CONCAT(sales[[#This Row],[Shop]]," ",sales[[#This Row],[Location]]) -> Kowloon Bay Fortress
A39: 37 | B39: Kowloon Bay | C39: Fortress | D39: =OFFSET(Roster!$B$7, MATCH(B39&" "&C39&"*",Roster!$B$8:$B$20,0),DAY(sales[[#This Row],[date]]),1, 1) -> Wah | E39: =MONTH(sales[[#This Row],[date]]) -> 6 | F39: 46186 | G39: =VLOOKUP("*"&sales[[#This Row],[Input]]&"*",'Ref-List'!$A:$C,1,0) -> 6901+541 | H39: =VLOOKUP("*"&G39&"*",'Ref-List'!$A:$C,3,0) -> RO純淨飲水機 + 濾芯 | I39: 6901 | J39: 1 | K39: 1899 | L39: =sales[[#This Row],[quantity]]*sales[[#This Row],[price]] -> 1899 | M39: =sales[[#This Row],[Total Price]]*3% -> 56.97 | N39: =sales[[#This Row],[Total Price]]*2.5% -> 47.475 | O39: =sales[[#This Row],[Total Price]]*1.5% -> 28.485 | R39: =_xlfn.CONCAT(sales[[#This Row],[Shop]]," ",sales[[#This Row],[Location]]) -> Kowloon Bay Fortress
A40: 38 | B40: Kowloon Bay | C40: Fortress | D40: =OFFSET(Roster!$B$7, MATCH(B40&" "&C40&"*",Roster!$B$8:$B$20,0),DAY(sales[[#This Row],[date]]),1, 1) -> Wah | E40: =MONTH(sales[[#This Row],[date]]) -> 6 | F40: 46186 | G40: =VLOOKUP("*"&sales[[#This Row],[Input]]&"*",'Ref-List'!$A:$C,1,0) -> 6901+541 | H40: =VLOOKUP("*"&G40&"*",'Ref-List'!$A:$C,3,0) -> RO純淨飲水機 + 濾芯 | I40: 6901 | J40: 1 | K40: 1899 | L40: =sales[[#This Row],[quantity]]*sales[[#This Row],[price]] -> 1899 | M40: =sales[[#This Row],[Total Price]]*3% -> 56.97 | N40: =sales[[#This Row],[Total Price]]*2.5% -> 47.475 | O40: =sales[[#This Row],[Total Price]]*1.5% -> 28.485 | R40: =_xlfn.CONCAT(sales[[#This Row],[Shop]]," ",sales[[#This Row],[Location]]) -> Kowloon Bay Fortress
... A51: 49 | B51: Kowloon Bay | C51: Fortress | D51: =OFFSET(Roster!$B$7, MATCH(B51&" "&C51&"*",Roster!$B$8:$B$20,0),DAY(sales[[#This Row],[date]]),1, 1) -> Wah | E51: =MONTH(sales[[#This Row],[date]]) -> 6 | F51: 46187 | G51: =VLOOKUP("*"&sales[[#This Row],[Input]]&"*",'Ref-List'!$A:$C,1,0) -> #N/A | H51: =VLOOKUP("*"&G51&"*",'Ref-List'!$A:$C,3,0) -> #N/A | I51: 6912 | J51: 1 | K51: 2998 | L51: =sales[[#This Row],[quantity]]*sales[[#This Row],[price]] -> 2998 | M51: =sales[[#This Row],[Total Price]]*3% -> 89.94 | N51: =sales[[#This Row],[Total Price]]*2.5% -> 74.95 | O51: =sales[[#This Row],[Total Price]]*1.5% -> 44.97 | R51: =_xlfn.CONCAT(sales[[#This Row],[Shop]]," ",sales[[#This Row],[Location]]) -> Kowloon Bay Fortress
A52: 50 | B52: Kowloon Bay | C52: Fortress | D52: =OFFSET(Roster!$B$7, MATCH(B52&" "&C52&"*",Roster!$B$8:$B$20,0),DAY(sales[[#This Row],[date]]),1, 1) -> Wah | E52: =MONTH(sales[[#This Row],[date]]) -> 6 | F52: 46187 | G52: =VLOOKUP("*"&sales[[#This Row],[Input]]&"*",'Ref-List'!$A:$C,1,0) -> #N/A | H52: =VLOOKUP("*"&G52&"*",'Ref-List'!$A:$C,3,0) -> #N/A | I52: 3773+39922 | J52: 1 | K52: 868 | L52: =sales[[#This Row],[quantity]]*sales[[#This Row],[price]] -> 868 | M52: =sales[[#This Row],[Total Price]]*3% -> 26.04 | N52: =sales[[#This Row],[Total Price]]*2.5% -> 21.7 | O52: =sales[[#This Row],[Total Price]]*1.5% -> 13.02 | R52: =_xlfn.CONCAT(sales[[#This Row],[Shop]]," ",sales[[#This Row],[Location]]) -> Kowloon Bay Fortress
