Workbook
Name Slicer_Full_Name1: #N/A
Name Slicer_Name.: #N/A

Sheet 1-10
A2: i Wall@
A3: SharpSing Limited
A4: Room 1609, 16/F., Golden Era Plaza, No. 39 Sai Yee Street, Mongkok, KLN. Tel:35868635 Fax:31889330
B6: 2025' Toshiba Promoter Salary Summary
B8: Name/姓名 | C8: =Total!$D$48 -> Chan So Mui | D8: {=INDEX(Total!$C$8:$C$992,MATCH($C8&$G8,Total!$D$8:$D$992&Total!$E$8:$E$992,0))} -> Mui Chan_2 | F8: CQ NO. | G8: =Total!$E$48 -> Autopay
B10: Job Detail | E10: Content
B11: Job Categories/工作類別 | E11: Promoter
B12: Location/工作地點 | E12: {=INDEX(Total!$F$8:$F$891,MATCH($C8&$G8,Total!$D$8:$D$891&Total!$E$8:$E$891,0))} -> Diamond Hill_2 Broadway
B13: Period/工作日子 | E13: {=INDEX(Total!$G$8:$G$891,MATCH($C8&$G8,Total!$D$8:$D$891&Total!$E$8:$E$891,0))} -> Mar/21-22
B14: Reg.Day/工作日數 | E14: {=INDEX(Total!$H$8:$H$891,MATCH($C8&$G8,Total!$D$8:$D$891&Total!$E$8:$E$891,0))} -> 2
B15: Reg.Hour/工作時數 | E15: {=INDEX(Total!$I$8:$I$891,MATCH($C8&$G8,Total!$D$8:$D$891&Total!$E$8:$E$891,0))} -> 16
B16: HK$/時薪 | E16: {=INDEX(Total!$J$8:$J$891,MATCH($C8&$G8,Total!$D$8:$D$891&Total!$E$8:$E$891,0))} -> 60
B17: Sales Record/銷售紀錄 | E17: {=INDEX(Total!$L$8:$L$891,MATCH($C8&$G8,Total!$D$8:$D$891&Total!$E$8:$E$891,0))} -> 17304
C19: Salary Detail | F19: Sub. Total
C20: Basic/酬金 | G20: {=INDEX(Total!$K$8:$K$891,MATCH($C8&$G8,Total!$D$8:$D$891&Total!$E$8:$E$891,0))} -> 960
C21: =表格1[[#Headers],[三門雪櫃特佣 GR-RM469WE-PGA(B3)]] -> 三門雪櫃特佣 GR-RM469WE-PGA(B3) | G21: {=INDEX(Total!$AH$8:$AH$891,MATCH($C8&$G8,Total!$D$8:$D$891&Total!$E$8:$E$891,0))} -> 1336
C22: Commission/佣金 | G22: {=INDEX(Total!$N$8:$N$891,MATCH($C8&$G8,Total!$D$8:$D$891&Total!$E$8:$E$891,0))} -> 346.08
C23: Allowance/津貼 | G23: {=INDEX(Total!$P$8:$P$891,MATCH($C8&$G8,Total!$D$8:$D$891&Total!$E$8:$E$891,0))} -> 0
C24: =表格1[[#Headers],[嵌入式微波氣炸蒸焗爐特佣 EB-T500APW]] -> 嵌入式微波氣炸蒸焗爐特佣 EB-T500APW | G24: {=INDEX(Total!$S$8:$S$891,MATCH($C8&$G8,Total!$D$8:$D$891&Total!$E$8:$E$891,0))} -> 0
C25: =表格1[[#Headers],[蒸氣烤焗水波爐特佣 ER-VD7000HK(XK)]] -> 蒸氣烤焗水波爐特佣 ER-VD7000HK(XK) | G25: {=INDEX(Total!$T$8:$T$891,MATCH($C8&$G8,Total!$D$8:$D$891&Total!$E$8:$E$891,0))} -> 0
C26: =表格1[[#Headers],[日本飯煲 RC-DS10K/18K]] -> 日本飯煲 RC-DS10K/18K | G26: {=INDEX(Total!$Q$8:$Q$891,MATCH($C8&$G8,Total!$D$8:$D$891&Total!$E$8:$E$891,0))} -> 0
C27: =表格1[[#Headers],[TWDT21BU95 ]] -> TWDT21BU95 | G27: {=INDEX(Total!$U$8:$U$891,MATCH($C8&$G8,Total!$D$8:$D$891&Total!$E$8:$E$891,0))} -> 0
C28: =表格1[[#Headers],[日式洗衣機二特佣 AW-Q801APH(WW)]] -> 日式洗衣機二特佣 AW-Q801APH(WW) | G28: {=INDEX(Total!$Z$8:$Z$1002,MATCH($C8&$G8,Total!$D$8:$D$1002&Total!$E$8:$E$1002,0))} -> 0
C29: Expenses/支出 | G29: {=INDEX(Total!$W$8:$W$891,MATCH($C8&$G8,Total!$D$8:$D$891&Total!$E$8:$E$891,0))} -> 0
E30: Total | F30: =SUM($G20:$G29) -> 2642.08 | J30: {=INDEX(Total!$AJ$8:$AJ$1002,MATCH($C8&$G8,Total!$D$8:$D$1002&Total!$E$8:$E$1002,0))} -> 1306.08
B32: **如屬自僱人仕必須自行購買勞工保險及強積金；
B33: 註 1：如所支付之金額有錯誤，請在兩天內提出；
B34: 註 2：請自行核對清楚支票上的姓名及金額；
E35: Promoter 確認簽名 :
F37: I.D. Card No. :
A40: i Wall@
A41: SharpSing Limited
A42: Room 1609, 16/F., Golden Era Plaza, No. 39 Sai Yee Street, Mongkok, KLN. Tel:35868635 Fax:31889330
B44: 2025' Toshiba Promoter Salary Summary
B46: Name/姓名 | C46: =Total!$D$9 -> Wong Wai Chu | D46: {=INDEX(Total!$C$8:$C$1002,MATCH($C46&$G46,Total!$D$8:$D$1002&Total!$E$8:$E$1002,0))} -> Ivy Wong_1 | F46: CQ NO. | G46: =Total!$E$9 -> Autopay
B48: Job Detail | E48: Content
B49: Job Categories/工作類別 | E49: Promoter
B50: Location/工作地點 | E50: {=INDEX(Total!$F$8:$F$1002,MATCH($C46&$G46,Total!$D$8:$D$1002&Total!$E$8:$E$1002,0))} -> Vcity_1 Fortress
B51: Period/工作日子 | E51: {=INDEX(Total!$G$8:$G$1002,MATCH($C46&$G46,Total!$D$8:$D$1002&Total!$E$8:$E$1002,0))} -> Mar/1,14-15,21-22,25,28
B52: Reg.Day/工作日數 | E52: {=INDEX(Total!$H$8:$H$1002,MATCH($C46&$G46,Total!$D$8:$D$1002&Total!$E$8:$E$1002,0))} -> 7
B53: Reg.Hour/工作時數 | E53: {=INDEX(Total!$I$8:$I$1002,MATCH($C46&$G46,Total!$D$8:$D$1002&Total!$E$8:$E$1002,0))} -> 56
B54: HK$/時薪 | E54: {=INDEX(Total!$J$8:$J$1002,MATCH($C46&$G46,Total!$D$8:$D$1002&Total!$E$8:$E$1002,0))} -> 60
B55: Sales Record/銷售紀錄 | E55: {=INDEX(Total!$L$8:$L$1002,MATCH($C46&$G46,Total!$D$8:$D$1002&Total!$E$8:$E$1002,0))} -> 242326
C57: Salary Detail | F57: Sub. Total
C58: Basic/酬金 | G58: {=INDEX(Total!$K$8:$K$1002,MATCH($C46&$G46,Total!$D$8:$D$1002&Total!$E$8:$E$1002,0))} -> 3360
C59: =表格1[[#Headers],[三門雪櫃特佣 GR-RM469WE-PGA(B3)]] -> 三門雪櫃特佣 GR-RM469WE-PGA(B3) | G59: {=INDEX(Total!$AH$8:$AH$1002,MATCH($C46&$G46,Total!$D$8:$D$1002&Total!$E$8:$E$1002,0))} -> 8607
C60: Commission/佣金 | G60: {=INDEX(Total!$N$8:$N$1002,MATCH($C46&$G46,Total!$D$8:$D$1002&Total!$E$8:$E$1002,0))} -> 4846.52
C61: Allowance/津貼 | G61: {=INDEX(Total!$P$8:$P$1002,MATCH($C46&$G46,Total!$D$8:$D$1002&Total!$E$8:$E$1002,0))} -> 0
C62: =表格1[[#Headers],[嵌入式微波氣炸蒸焗爐特佣 EB-T500APW]] -> 嵌入式微波氣炸蒸焗爐特佣 EB-T500APW | G62: {=INDEX(Total!$S$8:$S$1002,MATCH($C46&$G46,Total!$D$8:$D$1002&Total!$E$8:$E$1002,0))} -> 0
C63: =表格1[[#Headers],[蒸氣烤焗水波爐特佣 ER-VD7000HK(XK)]] -> 蒸氣烤焗水波爐特佣 ER-VD7000HK(XK) | G63: {=INDEX(Total!$T$8:$T$1002,MATCH($C46&$G46,Total!$D$8:$D$1002&Total!$E$8:$E$1002,0))} -> 0
C64: =表格1[[#Headers],[日本飯煲 RC-DS10K/18K]] -> 日本飯煲 RC-DS10K/18K | G64: {=INDEX(Total!$Q$8:$Q$1002,MATCH($C46&$G46,Total!$D$8:$D$1002&Total!$E$8:$E$1002,0))} -> 0
C65: =表格1[[#Headers],[TWDT21BU95 ]] -> TWDT21BU95 | G65: {=INDEX(Total!$U$8:$U$1002,MATCH($C46&$G46,Total!$D$8:$D$1002&Total!$E$8:$E$1002,0))} -> 0
C66: =表格1[[#Headers],[日式洗衣機二特佣 AW-Q801APH(WW)]] -> 日式洗衣機二特佣 AW-Q801APH(WW) | G66: {=INDEX(Total!$Z$8:$Z$1002,MATCH($C46&$G46,Total!$D$8:$D$1002&Total!$E$8:$E$1002,0))} -> 0
C67: Expenses/支出 | G67: {=INDEX(Total!$W$8:$W$1002,MATCH($C46&$G46,Total!$D$8:$D$1002&Total!$E$8:$E$1002,0))} -> 0
E68: Total | F68: =SUM($G58:$G67) -> 16813.52 | J68: {=INDEX(Total!$AJ$8:$AJ$1002,MATCH($C46&$G46,Total!$D$8:$D$1002&Total!$E$8:$E$1002,0))} -> 8606.52
B70: **如屬自僱人仕必須自行購買勞工保險及強積金；
B71: 註 1：如所支付之金額有錯誤，請在兩天內提出；
B72: 註 2：請自行核對清楚支票上的姓名及金額；
E73: Promoter 確認簽名 :
F75: I.D. Card No. :
A78: i Wall@
A79: SharpSing Limited
A80: Room 1609, 16/F., Golden Era Plaza, No. 39 Sai Yee Street, Mongkok, KLN. Tel:35868635 Fax:31889330
B82: 2025' Toshiba Promoter Salary Summary
B84: Name/姓名 | C84: =Total!$D$10 -> Li Wenjie | D84: {=INDEX(Total!$C$8:$C$1002,MATCH($C84&$G84,Total!$D$8:$D$1002&Total!$E$8:$E$1002,0))} -> Kit_3 | F84: CQ NO. | G84: =Total!$E$10 -> Autopay
B86: Job Detail | E86: Content
B87: Job Categories/工作類別 | E87: Promoter
B88: Location/工作地點 | E88: {=INDEX(Total!$F$8:$F$1002,MATCH($C84&$G84,Total!$D$8:$D$1002&Total!$E$8:$E$1002,0))} -> Vcity_2 Fortress
B89: Period/工作日子 | E89: {=INDEX(Total!$G$8:$G$1002,MATCH($C84&$G84,Total!$D$8:$D$1002&Total!$E$8:$E$1002,0))} -> Mar/7-8
B90: Reg.Day/工作日數 | E90: {=INDEX(Total!$H$8:$H$1002,MATCH($C84&$G84,Total!$D$8:$D$1002&Total!$E$8:$E$1002,0))} -> 2
B91: Reg.Hour/工作時數 | E91: {=INDEX(Total!$I$8:$I$1002,MATCH($C84&$G84,Total!$D$8:$D$1002&Total!$E$8:$E$1002,0))} -> 16
B92: HK$/時薪 | E92: {=INDEX(Total!$J$8:$J$1002,MATCH($C84&$G84,Total!$D$8:$D$1002&Total!$E$8:$E$1002,0))} -> 60
B93: Sales Record/銷售紀錄 | E93: {=INDEX(Total!$L$8:$L$1002,MATCH($C84&$G84,Total!$D$8:$D$1002&Total!$E$8:$E$1002,0))} -> 7911 | L93: 🙏🏻自取票同事可於今天起至9號上午到取‼️
L94: 🌟公司於2月10日至18日放假🧧請各位留意🙏🏻
C95: Salary Detail | F95: Sub. Total
C96: Basic/酬金 | G96: {=INDEX(Total!$K$8:$K$1002,MATCH($C84&$G84,Total!$D$8:$D$1002&Total!$E$8:$E$1002,0))} -> 960
C97: =表格1[[#Headers],[三門雪櫃特佣 GR-RM469WE-PGA(B3)]] -> 三門雪櫃特佣 GR-RM469WE-PGA(B3) | G97: {=INDEX(Total!$AH$8:$AH$1002,MATCH($C84&$G84,Total!$D$8:$D$1002&Total!$E$8:$E$1002,0))} -> 1118
C98: Commission/佣金 | G98: {=INDEX(Total!$N$8:$N$1002,MATCH($C84&$G84,Total!$D$8:$D$1002&Total!$E$8:$E$1002,0))} -> 158.22
C99: Allowance/津貼 | G99: {=INDEX(Total!$P$8:$P$1002,MATCH($C84&$G84,Total!$D$8:$D$1002&Total!$E$8:$E$1002,0))} -> 0
C100: =表格1[[#Headers],[嵌入式微波氣炸蒸焗爐特佣 EB-T500APW]] -> 嵌入式微波氣炸蒸焗爐特佣 EB-T500APW | G100: {=INDEX(Total!$S$8:$S$1002,MATCH($C84&$G84,Total!$D$8:$D$1002&Total!$E$8:$E$1002,0))} -> 0
C101: =表格1[[#Headers],[蒸氣烤焗水波爐特佣 ER-VD7000HK(XK)]] -> 蒸氣烤焗水波爐特佣 ER-VD7000HK(XK) | G101: {=INDEX(Total!$T$8:$T$1002,MATCH($C84&$G84,Total!$D$8:$D$1002&Total!$E$8:$E$1002,0))} -> 0
C102: =表格1[[#Headers],[日本飯煲 RC-DS10K/18K]] -> 日本飯煲 RC-DS10K/18K | G102: {=INDEX(Total!$Q$8:$Q$1002,MATCH($C84&$G84,Total!$D$8:$D$1002&Total!$E$8:$E$1002,0))} -> 0
C103: =表格1[[#Headers],[TWDT21BU95 ]] -> TWDT21BU95 | G103: {=INDEX(Total!$U$8:$U$1002,MATCH($C84&$G84,Total!$D$8:$D$1002&Total!$E$8:$E$1002,0))} -> 0
C104: =表格1[[#Headers],[日式洗衣機二特佣 AW-Q801APH(WW)]] -> 日式洗衣機二特佣 AW-Q801APH(WW) | G104: {=INDEX(Total!$Z$8:$Z$1002,MATCH($C84&$G84,Total!$D$8:$D$1002&Total!$E$8:$E$1002,0))} -> 0
C105: Expenses/支出 | G105: {=INDEX(Total!$W$8:$W$1002,MATCH($C84&$G84,Total!$D$8:$D$1002&Total!$E$8:$E$1002,0))} -> 0
E106: Total | F106: =SUM($G96:$G105) -> 2236.22 | J106: {=INDEX(Total!$AJ$8:$AJ$1002,MATCH($C84&$G84,Total!$D$8:$D$1002&Total!$E$8:$E$1002,0))} -> 1118.22
B108: **如屬自僱人仕必須自行購買勞工保險及強積金；
B109: 註 1：如所支付之金額有錯誤，請在兩天內提出；
B110: 註 2：請自行核對清楚支票上的姓名及金額；
E111: Promoter 確認簽名 :
F113: I.D. Card No. :
A116: i Wall@
A117: SharpSing Limited
A118: Room 1609, 16/F., Golden Era Plaza, No. 39 Sai Yee Street, Mongkok, KLN. Tel:35868635 Fax:31889330
B120: 2025' Toshiba Promoter Salary Summary
B122: Name/姓名 | C122: =Total!$D$11 -> Leung Ching | D122: {=INDEX(Total!$C$8:$C$1002,MATCH($C122&$G122,Total!$D$8:$D$1002&Total!$E$8:$E$1002,0))} -> Vicky L | F122: CQ NO. | G122: =Total!$E$11 -> 20851
B124: Job Detail | E124: Content
B125: Job Categories/工作類別 | E125: Promoter
B126: Location/工作地點 | E126: {=INDEX(Total!$F$8:$F$1002,MATCH($C122&$G122,Total!$D$8:$D$1002&Total!$E$8:$E$1002,0))} -> Diamond Hill Fortress
B127: Period/工作日子 | E127: {=INDEX(Total!$G$8:$G$1002,MATCH($C122&$G122,Total!$D$8:$D$1002&Total!$E$8:$E$1002,0))} -> Mar/1-2,4,6-8,13-19,21-31
...

Sheet 1-10 (2)
A2: i Wall@
A3: SharpSing Limited
A4: Room 1609, 16/F., Golden Era Plaza, No. 39 Sai Yee Street, Mongkok, KLN. Tel:35868635 Fax:31889330
B6: 2023' Toshiba Promoter Salary Summary
B8: Name/姓名 | C8: =Total!$D$20 -> Ho Lai Sim | D8: {=INDEX(Total!$C$8:$C$992,MATCH($C8&$G8,Total!$D$8:$D$992&Total!$E$8:$E$992,0))} -> Mandy | F8: CQ NO. | G8: =Total!$E$20 -> Autopay
B10: Job Detail | E10: Content
B11: Job Categories/工作類別 | E11: Promoter
B12: Location/工作地點 | E12: {=INDEX(Total!$F$8:$F$891,MATCH($C8&$G8,Total!$D$8:$D$891&Total!$E$8:$E$891,0))} -> TW_3 Citistore
B13: Period/工作日子 | E13: {=INDEX(Total!$G$8:$G$891,MATCH($C8&$G8,Total!$D$8:$D$891&Total!$E$8:$E$891,0))} -> Mar/12
B14: Reg.Day/工作日數 | E14: {=INDEX(Total!$H$8:$H$891,MATCH($C8&$G8,Total!$D$8:$D$891&Total!$E$8:$E$891,0))} -> 1
B15: Reg.Hour/工作時數 | E15: {=INDEX(Total!$I$8:$I$891,MATCH($C8&$G8,Total!$D$8:$D$891&Total!$E$8:$E$891,0))} -> 9
B16: HK$/時薪 | E16: {=INDEX(Total!$J$8:$J$891,MATCH($C8&$G8,Total!$D$8:$D$891&Total!$E$8:$E$891,0))} -> 60
B17: Sales Record/銷售紀錄 | E17: {=INDEX(Total!$L$8:$L$891,MATCH($C8&$G8,Total!$D$8:$D$891&Total!$E$8:$E$891,0))} -> 4664
C19: Salary Detail | F19: Sub. Total
C20: Basic/酬金 | G20: {=INDEX(Total!$K$8:$K$891,MATCH($C8&$G8,Total!$D$8:$D$891&Total!$E$8:$E$891,0))} -> 540
C21: Attendance/出勤 | G21: {=INDEX(Total!$AH$8:$AH$891,MATCH($C8&$G8,Total!$D$8:$D$891&Total!$E$8:$E$891,0))} -> 633
C22: Commission/佣金 | G22: {=INDEX(Total!$N$8:$N$891,MATCH($C8&$G8,Total!$D$8:$D$891&Total!$E$8:$E$891,0))} -> 93.28
C23: Allowance/津貼 | G23: {=INDEX(Total!$P$8:$P$891,MATCH($C8&$G8,Total!$D$8:$D$891&Total!$E$8:$E$891,0))} -> 0
C24: Award/獎金 | G24: {=INDEX(Total!$S$8:$S$891,MATCH($C8&$G8,Total!$D$8:$D$891&Total!$E$8:$E$891,0))} -> 0
C25: Expenses/支出 | G25: {=INDEX(Total!$T$8:$T$891,MATCH($C8&$G8,Total!$D$8:$D$891&Total!$E$8:$E$891,0))} -> 0
C26: Other/其他 | G26: {=INDEX(Total!$W$8:$W$891,MATCH($C8&$G8,Total!$D$8:$D$891&Total!$E$8:$E$891,0))} -> 0
C27: Adjustment/調整 | G27: {=INDEX(Total!$U$8:$U$891,MATCH($C8&$G8,Total!$D$8:$D$891&Total!$E$8:$E$891,0))} -> 0
C28: MPF/強積金** | G28: {=-INDEX(Total!$Z$8:$Z$891,MATCH($C8&$G8,Total!$D$8:$D$891&Total!$E$8:$E$891,0))} -> 0
E29: Total | F29: =SUM($G20:$G28) -> 1266.28 | J29: {=INDEX(Total!$AJ$8:$AJ$1002,MATCH($C8&$G8,Total!$D$8:$D$1002&Total!$E$8:$E$1002,0))} -> 633.28
B31: **如屬自僱人仕必須自行購買勞工保險及強積金；
B32: 註 1：如所支付之金額有錯誤，請在兩天內提出；
B33: 註 2：請自行核對清楚支票上的姓名及金額；
E34: Promoter 確認簽名 :
F36: I.D. Card No. :
A39: i Wall@
A40: SharpSing Limited
A41: Room 1609, 16/F., Golden Era Plaza, No. 39 Sai Yee Street, Mongkok, KLN. Tel:35868635 Fax:31889330
B43: 2023' Toshiba Promoter Salary Summary
B45: Name/姓名 | C45: =Total!$D$21 -> Chiu Fung Shan | D45: {=INDEX(Total!$C$8:$C$1002,MATCH($C45&$G45,Total!$D$8:$D$1002&Total!$E$8:$E$1002,0))} -> Shan_2 | F45: CQ NO. | G45: =Total!$E$21 -> 20856
B47: Job Detail | E47: Content
B48: Job Categories/工作類別 | E48: Promoter
B49: Location/工作地點 | E49: {=INDEX(Total!$F$8:$F$1002,MATCH($C45&$G45,Total!$D$8:$D$1002&Total!$E$8:$E$1002,0))} -> TW RS_1 Citistore
B50: Period/工作日子 | E50: {=INDEX(Total!$G$8:$G$1002,MATCH($C45&$G45,Total!$D$8:$D$1002&Total!$E$8:$E$1002,0))} -> Mar/25-31
B51: Reg.Day/工作日數 | E51: {=INDEX(Total!$H$8:$H$1002,MATCH($C45&$G45,Total!$D$8:$D$1002&Total!$E$8:$E$1002,0))} -> 7
B52: Reg.Hour/工作時數 | E52: {=INDEX(Total!$I$8:$I$1002,MATCH($C45&$G45,Total!$D$8:$D$1002&Total!$E$8:$E$1002,0))} -> 56
B53: HK$/時薪 | E53: {=INDEX(Total!$J$8:$J$1002,MATCH($C45&$G45,Total!$D$8:$D$1002&Total!$E$8:$E$1002,0))} -> 60
B54: Sales Record/銷售紀錄 | E54: {=INDEX(Total!$L$8:$L$1002,MATCH($C45&$G45,Total!$D$8:$D$1002&Total!$E$8:$E$1002,0))} -> 151474.6
C56: Salary Detail | F56: Sub. Total
C57: Basic/酬金 | G57: {=INDEX(Total!$K$8:$K$1002,MATCH($C45&$G45,Total!$D$8:$D$1002&Total!$E$8:$E$1002,0))} -> 3360
C58: Attendance/出勤 | G58: {=INDEX(Total!$AH$8:$AH$1002,MATCH($C45&$G45,Total!$D$8:$D$1002&Total!$E$8:$E$1002,0))} -> 6389
C59: Commission/佣金 | G59: {=INDEX(Total!$N$8:$N$1002,MATCH($C45&$G45,Total!$D$8:$D$1002&Total!$E$8:$E$1002,0))} -> 3029.492
C60: Allowance/津貼 | G60: {=INDEX(Total!$P$8:$P$1002,MATCH($C45&$G45,Total!$D$8:$D$1002&Total!$E$8:$E$1002,0))} -> 0
C61: Award/獎金 | G61: {=INDEX(Total!$S$8:$S$1002,MATCH($C45&$G45,Total!$D$8:$D$1002&Total!$E$8:$E$1002,0))} -> 0
C62: Expenses/支出 | G62: {=INDEX(Total!$T$8:$T$1002,MATCH($C45&$G45,Total!$D$8:$D$1002&Total!$E$8:$E$1002,0))} -> 0
C63: Other/其他 | G63: {=INDEX(Total!$W$8:$W$1002,MATCH($C45&$G45,Total!$D$8:$D$1002&Total!$E$8:$E$1002,0))} -> 0
C64: Adjustment/調整 | G64: {=INDEX(Total!$U$8:$U$1002,MATCH($C45&$G45,Total!$D$8:$D$1002&Total!$E$8:$E$1002,0))} -> 0
C65: MPF/強積金** | G65: {=-INDEX(Total!$Z$8:$Z$1002,MATCH($C45&$G45,Total!$D$8:$D$1002&Total!$E$8:$E$1002,0))} -> 0
E66: Total | F66: =SUM($G57:$G65) -> 12778.492 | J66: {=INDEX(Total!$AJ$8:$AJ$1002,MATCH($C45&$G45,Total!$D$8:$D$1002&Total!$E$8:$E$1002,0))} -> 6389.492
B68: **如屬自僱人仕必須自行購買勞工保險及強積金；
B69: 註 1：如所支付之金額有錯誤，請在兩天內提出；
B70: 註 2：請自行核對清楚支票上的姓名及金額；
A76: i Wall@
A77: SharpSing Limited
A78: Room 1609, 16/F., Golden Era Plaza, No. 39 Sai Yee Street, Mongkok, KLN. Tel:35868635 Fax:31889330
B80: 2023' Toshiba Promoter Salary Summary
B82: Name/姓名 | C82: =Total!$D$22 -> Wong Lai Ying | D82: {=INDEX(Total!$C$8:$C$1002,MATCH($C82&$G82,Total!$D$8:$D$1002&Total!$E$8:$E$1002,0))} -> Wendy Wong_1 | F82: CQ NO. | G82: =Total!$E$22 -> Autopay
B84: Job Detail | E84: Content
B85: Job Categories/工作類別 | E85: Promoter
B86: Location/工作地點 | E86: {=INDEX(Total!$F$8:$F$1002,MATCH($C82&$G82,Total!$D$8:$D$1002&Total!$E$8:$E$1002,0))} -> TW_2 Citistore
B87: Period/工作日子 | E87: {=INDEX(Total!$G$8:$G$1002,MATCH($C82&$G82,Total!$D$8:$D$1002&Total!$E$8:$E$1002,0))} -> Mar/3-4,11,13,18-19,24
B88: Reg.Day/工作日數 | E88: {=INDEX(Total!$H$8:$H$1002,MATCH($C82&$G82,Total!$D$8:$D$1002&Total!$E$8:$E$1002,0))} -> 7
B89: Reg.Hour/工作時數 | E89: {=INDEX(Total!$I$8:$I$1002,MATCH($C82&$G82,Total!$D$8:$D$1002&Total!$E$8:$E$1002,0))} -> 63
B90: HK$/時薪 | E90: {=INDEX(Total!$J$8:$J$1002,MATCH($C82&$G82,Total!$D$8:$D$1002&Total!$E$8:$E$1002,0))} -> 60
B91: Sales Record/銷售紀錄 | E91: {=INDEX(Total!$L$8:$L$1002,MATCH($C82&$G82,Total!$D$8:$D$1002&Total!$E$8:$E$1002,0))} -> 28203
C93: Salary Detail | F93: Sub. Total
C94: Basic/酬金 | G94: {=INDEX(Total!$K$8:$K$1002,MATCH($C82&$G82,Total!$D$8:$D$1002&Total!$E$8:$E$1002,0))} -> 3780
C95: Attendance/出勤 | G95: {=INDEX(Total!$AH$8:$AH$1002,MATCH($C82&$G82,Total!$D$8:$D$1002&Total!$E$8:$E$1002,0))} -> 4344
C96: Commission/佣金 | G96: {=INDEX(Total!$N$8:$N$1002,MATCH($C82&$G82,Total!$D$8:$D$1002&Total!$E$8:$E$1002,0))} -> 564.06
C97: Allowance/津貼 | G97: {=INDEX(Total!$P$8:$P$1002,MATCH($C82&$G82,Total!$D$8:$D$1002&Total!$E$8:$E$1002,0))} -> 0
C98: Award/獎金 | G98: {=INDEX(Total!$S$8:$S$1002,MATCH($C82&$G82,Total!$D$8:$D$1002&Total!$E$8:$E$1002,0))} -> 0
C99: Expenses/支出 | G99: {=INDEX(Total!$T$8:$T$1002,MATCH($C82&$G82,Total!$D$8:$D$1002&Total!$E$8:$E$1002,0))} -> 0
C100: Other/其他 | G100: {=INDEX(Total!$W$8:$W$1002,MATCH($C82&$G82,Total!$D$8:$D$1002&Total!$E$8:$E$1002,0))} -> 0
C101: Adjustment/調整 | G101: {=INDEX(Total!$U$8:$U$1002,MATCH($C82&$G82,Total!$D$8:$D$1002&Total!$E$8:$E$1002,0))} -> 0
C102: MPF/強積金** | G102: {=-INDEX(Total!$Z$8:$Z$1002,MATCH($C82&$G82,Total!$D$8:$D$1002&Total!$E$8:$E$1002,0))} -> 0
E103: Total | F103: =SUM($G94:$G102) -> 8688.06 | J103: {=INDEX(Total!$AJ$8:$AJ$1002,MATCH($C82&$G82,Total!$D$8:$D$1002&Total!$E$8:$E$1002,0))} -> 4344.06
B105: **如屬自僱人仕必須自行購買勞工保險及強積金；
B106: 註 1：如所支付之金額有錯誤，請在兩天內提出；
B107: 註 2：請自行核對清楚支票上的姓名及金額；
E108: Promoter 確認簽名 :
F110: I.D. Card No. :
A113: i Wall@
A114: SharpSing Limited
A115: Room 1609, 16/F., Golden Era Plaza, No. 39 Sai Yee Street, Mongkok, KLN. Tel:35868635 Fax:31889330
B117: 2023' Toshiba Promoter Salary Summary
B119: Name/姓名 | C119: =Total!$D$23 -> Chan Mei Sim | D119: {=INDEX(Total!$C$8:$C$1002,MATCH($C119&$G119,Total!$D$8:$D$1002&Total!$E$8:$E$1002,0))} -> Kiko | F119: CQ NO. | G119: =Total!$E$23 -> Autopay
B121: Job Detail | E121: Content
B122: Job Categories/工作類別 | E122: Promoter
B123: Location/工作地點 | E123: {=INDEX(Total!$F$8:$F$1002,MATCH($C119&$G119,Total!$D$8:$D$1002&Total!$E$8:$E$1002,0))} -> Tai Koo Fortress
B124: Period/工作日子 | E124: {=INDEX(Total!$G$8:$G$1002,MATCH($C119&$G119,Total!$D$8:$D$1002&Total!$E$8:$E$1002,0))} -> Mar/1-3,7-11,14-18,21-25,28-31
B125: Reg.Day/工作日數 | E125: {=INDEX(Total!$H$8:$H$1002,MATCH($C119&$G119,Total!$D$8:$D$1002&Total!$E$8:$E$1002,0))} -> 22
B126: Reg.Hour/工作時數 | E126: {=INDEX(Total!$I$8:$I$1002,MATCH($C119&$G119,Total!$D$8:$D$1002&Total!$E$8:$E$1002,0))} -> 176
B127: HK$/時薪 | E127: {=INDEX(Total!$J$8:$J$1002,MATCH($C119&$G119,Total!$D$8:$D$1002&Total!$E$8:$E$1002,0))} -> 60
B128: Sales Record/銷售紀錄 | E128: {=INDEX(Total!$L$8:$L$1002,MATCH($C119&$G119,Total!$D$8:$D$1002&Total!$E$8:$E$1002,0))} -> 487590
C130: Salary Detail | F130: Sub. Total
C131: Basic/酬金 | G131: {=INDEX(Total!$K$8:$K$1002,MATCH($C119&$G119,Total!$D$8:$D$1002&Total!$E$8:$E$1002,0))} -> 10560
...

Sheet Total
F1: Toshiba AC | G1: SSPT20220440 - Toshiba AC | AU1: Invoice No. | AV1: MPF | AW1: Total
AG2: Invoice No. | AU2: =AH2 -> 0 | AV2: 0 | AW2: =AH6 -> 525200
AG3: Income | AH3: 576057
AG4: Pay | AH4: =AH6 -> 525200
N5: 36453.96 | P5: MCA Oven | R5: LAD | S5: SDA JP RCK | T5: REF RM612 | V5: Comfee RAC | W5: LAD BN90 | AG5: GP | AH5: =AH3-AH4 -> 50857
A6: 2026 | B6: March | C6: Toshiba | H6: =SUM(H8:H133) -> 652 | I6: =SUM(I8:I133) -> 5330.5 | J6: =SUM(J8:J133) -> 3810 | K6: =SUM(K8:K133) -> 312060 | L6: =SUM(L8:L133) -> 9587202.9 | M6: =SUM(M8:M133) -> 0 | N6: =SUM(N8:N133) -> 183924.79 | O6: =SUM(O8:O133) -> 10820.54 | ... AH6: =SUM(AH8:AH133) -> 525200
A7: No. | B7: 欄1 | C7: Name. | D7: Full Name. | E7: CQ No. | F7: Shop | G7: Period | H7: Days | I7: Reg.Hrs | J7: $ | K7: Basic | L7: Sales | M7: QTY | N7: Commission (1% OR 2%) | O7: Allowance | P7: 日本飯煲 RC-DS10K/18K | Q7: 酵活炊電飯煲特佣 RC-18AMXH(W) | R7: 嵌入式微波氣炸蒸焗爐特佣 EB-T500APW | S7: 蒸氣烤焗水波爐特佣 ER-VD7000HK(XK) | T7: TWDT21BU95 | U7: 日式洗衣機一特佣 AW-Q800APH(WW) | V7: 日式洗衣機二特佣 AW-Q801APH(WW) | W7: 三門雪櫃特佣 GR-RM469WE-PGA(B3) | X7: 雙門雪櫃一特佣 GR-RB449WE-PMA(57) | Y7: 雙門雪櫃一特佣 GR-RB410WE-PMA(06) | Z7: 十字門雪櫃 GR-RF698WI | AA7: 水機 TWP-W2265THK(W) | AB7: 抽濕機特佣 | AC7: (Fortress ONLY)TW-T25BZU115MWH(MG) | AD7: 開門紅(三月) | AE7: 開門紅(第一季) | AF7: Expenses/支出 | AG7: Total | AH7: Input | AI7: 欄2 | AJ7: Double check | AK7: Double check2 | AL7: 欄5
A8: 1 | B8: =IF(表格1[[#This Row],[Full Name.]]=工作表1!F2,"OK") -> OK | C8: May C | D8: Cheng Muk Kiu | E8: 20850 | F8: Kornhill Aeon | G8: Mar/1-3,5-8,10-13,15-17,20-23,26-29 | H8: 22 | I8: 176 | J8: 55 | K8: =表格1[[#This Row],[Reg.Hrs]]*表格1[[#This Row],[$]] -> 9680 | L8: 455239.6 | N8: =IFERROR((IF(表格1[[#This Row],[Name.]]=工作表1!$E2,工作表1!$K2," ")*表格1[[#This Row],[Sales]])," ") -> 9104.792 | O8: =IFERROR((IF(表格1[[#This Row],[Full Name.]]=工作表1!F2,工作表1!J2," ")*表格1[[#This Row],[Days]])," ") -> 660 | P8: 0 | Q8: 300 | R8: 0 | S8: 0 | T8: 0 | U8: 0 | V8: 0 | W8: 0 | X8: 0 | Y8: 0 | Z8: 0 | AA8: 0 | AB8: 0 | AC8: 0 | AD8: 0 | AE8: 0 | AG8: =SUM(表格1[[#This Row],[Commission (1% OR 2%)]:[Expenses/支出]])+表格1[[#This Row],[Basic]] -> 19744.792 | AH8: =ROUND(AG8,0) -> 19745 | AJ8: 19744.792 | AK8: =表格1[[#This Row],[Input]]-表格1[[#This Row],[Double check]] -> 0.208
A9: 2 | B9: =IF(表格1[[#This Row],[Full Name.]]=工作表1!F3,"OK") -> OK | C9: Ivy Wong_1 | D9: Wong Wai Chu | E9: Autopay | F9: Vcity_1 Fortress | G9: Mar/1,14-15,21-22,25,28 | H9: 7 | I9: 56 | J9: 60 | K9: =表格1[[#This Row],[Reg.Hrs]]*表格1[[#This Row],[$]] -> 3360 | L9: 242326 | N9: =IFERROR((IF(表格1[[#This Row],[Name.]]=工作表1!$E3,工作表1!$K3," ")*表格1[[#This Row],[Sales]])," ") -> 4846.52 | O9: =IFERROR((IF(表格1[[#This Row],[Full Name.]]=工作表1!F3,工作表1!J3," ")*表格1[[#This Row],[Days]])," ") -> 0 | P9: 0 | Q9: 0 | R9: 0 | S9: 0 | T9: 0 | U9: 0 | V9: 0 | W9: 0 | X9: 0 | Y9: 200 | Z9: 0 | AA9: 200 | AB9: 0 | AC9: 0 | AD9: 0 | AE9: 0 | AG9: =SUM(表格1[[#This Row],[Commission (1% OR 2%)]:[Expenses/支出]])+表格1[[#This Row],[Basic]] -> 8606.52 | AH9: =ROUND(AG9,0) -> 8607 | AJ9: 8606.52 | AK9: =表格1[[#This Row],[Input]]-表格1[[#This Row],[Double check]] -> 0.48
A10: 3 | B10: =IF(表格1[[#This Row],[Full Name.]]=工作表1!F4,"OK") -> OK | C10: Kit_3 | D10: Li Wenjie | E10: Autopay | F10: Vcity_2 Fortress | G10: Mar/7-8 | H10: 2 | I10: 16 | J10: 60 | K10: =表格1[[#This Row],[Reg.Hrs]]*表格1[[#This Row],[$]] -> 960 | L10: 7911 | N10: =IFERROR((IF(表格1[[#This Row],[Name.]]=工作表1!$E4,工作表1!$K4," ")*表格1[[#This Row],[Sales]])," ") -> 158.22 | O10: =IFERROR((IF(表格1[[#This Row],[Full Name.]]=工作表1!F4,工作表1!J4," ")*表格1[[#This Row],[Days]])," ") -> 0 | AG10: =SUM(表格1[[#This Row],[Commission (1% OR 2%)]:[Expenses/支出]])+表格1[[#This Row],[Basic]] -> 1118.22 | AH10: =ROUND(AG10,0) -> 1118 | AJ10: 1118.22 | AK10: =表格1[[#This Row],[Input]]-表格1[[#This Row],[Double check]] -> -0.22
A11: 4 | B11: =IF(表格1[[#This Row],[Full Name.]]=工作表1!F5,"OK") -> OK | C11: Vicky L | D11: Leung Ching | E11: 20851 | F11: Diamond Hill Fortress | G11: Mar/1-2,4,6-8,13-19,21-31 | H11: 24 | I11: 192 | J11: 60 | K11: =表格1[[#This Row],[Reg.Hrs]]*表格1[[#This Row],[$]] -> 11520 | L11: 503165 | N11: =IFERROR((IF(表格1[[#This Row],[Name.]]=工作表1!$E5,工作表1!$K5," ")*表格1[[#This Row],[Sales]])," ") -> 10063.3 | O11: =IFERROR((IF(表格1[[#This Row],[Full Name.]]=工作表1!F5,工作表1!J5," ")*表格1[[#This Row],[Days]])," ") -> 0 | P11: 0 | Q11: 0 | R11: 0 | S11: 0 | T11: 880 | U11: 0 | V11: 0 | W11: 0 | X11: 0 | Y11: 0 | Z11: 0 | AA11: 0 | AB11: 0 | AC11: 0 | AD11: 500 | AE11: 1000 | AG11: =SUM(表格1[[#This Row],[Commission (1% OR 2%)]:[Expenses/支出]])+表格1[[#This Row],[Basic]] -> 23963.3 | AH11: =ROUND(AG11,0) -> 23963 | AJ11: 23963.3 | AK11: =表格1[[#This Row],[Input]]-表格1[[#This Row],[Double check]] -> -0.3
A12: 5 | B12: =IF(表格1[[#This Row],[Full Name.]]=工作表1!F6,"OK") -> OK | C12: Michelle | D12: Lo Muk Chun | E12: Autopay | F12: Good Hope Fortress | G12: Mar/1,5-8,11-15,17-22,25-29,31 | H12: 22 | I12: 176 | J12: 60 | K12: =表格1[[#This Row],[Reg.Hrs]]*表格1[[#This Row],[$]] -> 10560 | L12: 442858 | N12: =IFERROR((IF(表格1[[#This Row],[Name.]]=工作表1!$E6,工作表1!$K6," ")*表格1[[#This Row],[Sales]])," ") -> 8857.16 | O12: =IFERROR((IF(表格1[[#This Row],[Full Name.]]=工作表1!F6,工作表1!J6," ")*表格1[[#This Row],[Days]])," ") -> 0 | P12: 0 | Q12: 0 | R12: 0 | S12: 0 | T12: 480 | U12: 0 | V12: 0 | W12: 0 | X12: 500 | Y12: 0 | Z12: 0 | AA12: 0 | AB12: 0 | AC12: 0 | AD12: 0 | AE12: 0 | AG12: =SUM(表格1[[#This Row],[Commission (1% OR 2%)]:[Expenses/支出]])+表格1[[#This Row],[Basic]] -> 20397.16 | AH12: =ROUND(AG12,0) -> 20397 | AJ12: 20397.16 | AK12: =表格1[[#This Row],[Input]]-表格1[[#This Row],[Double check]] -> -0.16
A13: 6 | B13: =IF(表格1[[#This Row],[Full Name.]]=工作表1!F7,"OK") -> OK | C13: Jessica | D13: Chiu Kan | E13: 20852 | F13: Whampoa Aeon | G13: Mar/1-3,6-9,12-15,19-24,27-28,31 | H13: 20 | I13: 160 | J13: 55 | K13: =表格1[[#This Row],[Reg.Hrs]]*表格1[[#This Row],[$]] -> 8800 | L13: 419085.2 | N13: =IFERROR((IF(表格1[[#This Row],[Name.]]=工作表1!$E7,工作表1!$K7," ")*表格1[[#This Row],[Sales]])," ") -> 8381.704 | O13: =IFERROR((IF(表格1[[#This Row],[Full Name.]]=工作表1!F7,工作表1!J7," ")*表格1[[#This Row],[Days]])," ") -> 1600 | P13: 0 | Q13: 0 | R13: 0 | S13: 0 | T13: 0 | U13: 0 | V13: 0 | W13: 0 | X13: 0 | Y13: 0 | Z13: 0 | AA13: 200 | AB13: 0 | AC13: 0 | AD13: 0 | AE13: 0 | AG13: =SUM(表格1[[#This Row],[Commission (1% OR 2%)]:[Expenses/支出]])+表格1[[#This Row],[Basic]] -> 18981.704 | AH13: =ROUND(AG13,0) -> 18982 | AJ13: 18981.704 | AK13: =表格1[[#This Row],[Input]]-表格1[[#This Row],[Double check]] -> 0.296
A14: 7 | B14: =IF(表格1[[#This Row],[Full Name.]]=工作表1!F8,"OK") -> OK | C14: Kitty Yeung | D14: Yeung Lai Shan | E14: 20853 | F14: TKW Suning | G14: Mar/1-4,7-11,14-17,21-25,28-31 | H14: 22 | I14: 176 | J14: 60 | K14: =表格1[[#This Row],[Reg.Hrs]]*表格1[[#This Row],[$]] -> 10560 | L14: 234404 | N14: =IFERROR((IF(表格1[[#This Row],[Name.]]=工作表1!$E8,工作表1!$K8," ")*表格1[[#This Row],[Sales]])," ") -> 4688.08 | O14: =IFERROR((IF(表格1[[#This Row],[Full Name.]]=工作表1!F8,工作表1!J8," ")*表格1[[#This Row],[Days]])," ") -> 0 | P14: 0 | Q14: 0 | R14: 0 | S14: 0 | T14: 0 | U14: 0 | V14: 250 | W14: 0 | X14: 0 | Y14: 0 | Z14: 0 | AA14: 0 | AB14: 0 | AC14: 0 | AD14: 500 | AE14: 0 | AG14: =SUM(表格1[[#This Row],[Commission (1% OR 2%)]:[Expenses/支出]])+表格1[[#This Row],[Basic]] -> 15998.08 | AH14: =ROUND(AG14,0) -> 15998 | AJ14: 15998.08 | AK14: =表格1[[#This Row],[Input]]-表格1[[#This Row],[Double check]] -> -0.08
A15: 8 | B15: =IF(表格1[[#This Row],[Full Name.]]=工作表1!F9,"OK") -> OK | C15: Amy Or_1 | D15: Or Sim Kiu | E15: 20854 | F15: Tai koo Broadway | G15: Mar/1,7,28-29 | H15: 4 | I15: 32 | J15: 55 | K15: =表格1[[#This Row],[Reg.Hrs]]*表格1[[#This Row],[$]] -> 1760 | L15: 82154 | N15: =IFERROR((IF(表格1[[#This Row],[Name.]]=工作表1!$E9,工作表1!$K9," ")*表格1[[#This Row],[Sales]])," ") -> 1643.08 | O15: =IFERROR((IF(表格1[[#This Row],[Full Name.]]=工作表1!F9,工作表1!J9," ")*表格1[[#This Row],[Days]])," ")+180+60 -> 360 | P15: 0 | Q15: 0 | R15: 0 | S15: 0 | T15: 0 | U15: 0 | V15: 0 | W15: 0 | X15: 0 | Y15: 0 | Z15: 0 | AA15: 0 | AB15: 0 | AC15: 0 | AD15: 0 | AE15: 0 | AG15: =SUM(表格1[[#This Row],[Commission (1% OR 2%)]:[Expenses/支出]])+表格1[[#This Row],[Basic]] -> 3763.08 | AH15: =ROUND(AG15,0) -> 3763 | AJ15: 3523.08 | AK15: =表格1[[#This Row],[Input]]-表格1[[#This Row],[Double check]] -> 239.92
A16: 9 | B16: =IF(表格1[[#This Row],[Full Name.]]=工作表1!F10,"OK") -> OK | C16: Fong_1 | D16: Ng Nga Fong | E16: Autopay | F16: Diamond Hill_1 Broadway | G16: Mar/1,7-8,14-15,28-29 | H16: 7 | I16: 56 | J16: 60 | K16: =表格1[[#This Row],[Reg.Hrs]]*表格1[[#This Row],[$]] -> 3360 | L16: 67587 | N16: =IFERROR((IF(表格1[[#This Row],[Name.]]=工作表1!$E10,工作表1!$K10," ")*表格1[[#This Row],[Sales]])," ") -> 1351.74 | O16: =IFERROR((IF(表格1[[#This Row],[Full Name.]]=工作表1!F10,工作表1!J10," ")*表格1[[#This Row],[Days]])," ") -> 0 | AG16: =SUM(表格1[[#This Row],[Commission (1% OR 2%)]:[Expenses/支出]])+表格1[[#This Row],[Basic]] -> 4711.74 | AH16: =ROUND(AG16,0) -> 4712 | AJ16: 4711.74 | AK16: =表格1[[#This Row],[Input]]-表格1[[#This Row],[Double check]] -> 0.26
A17: 10 | B17: =IF(表格1[[#This Row],[Full Name.]]=工作表1!F11,"OK") -> OK | C17: Mui Chan_2 | D17: Chan So Mui | E17: Autopay | F17: Diamond Hill_2 Broadway | G17: Mar/21-22 | H17: 2 | I17: 16 | J17: 60 | K17: =表格1[[#This Row],[Reg.Hrs]]*表格1[[#This Row],[$]] -> 960 | L17: 17304 | N17: =IFERROR((IF(表格1[[#This Row],[Name.]]=工作表1!$E11,工作表1!$K11," ")*表格1[[#This Row],[Sales]])," ") -> 346.08 | O17: =IFERROR((IF(表格1[[#This Row],[Full Name.]]=工作表1!F11,工作表1!J11," ")*表格1[[#This Row],[Days]])," ") -> 0 | AF17: 30 | AG17: =SUM(表格1[[#This Row],[Commission (1% OR 2%)]:[Expenses/支出]])+表格1[[#This Row],[Basic]] -> 1336.08 | AH17: =ROUND(AG17,0) -> 1336 | AJ17: 1306.08 | AK17: =表格1[[#This Row],[Input]]-表格1[[#This Row],[Double check]] -> 29.92
A18: 11 | B18: =IF(表格1[[#This Row],[Full Name.]]=工作表1!F12,"OK") -> OK | C18: Shan_1 | D18: Chiu Fung Shan | E18: 20855 | F18: TW_1 Citistore | G18: Mar/1-2,5-10,14-17,20-23 | H18: 16 | I18: 144 | J18: 60 | K18: =表格1[[#This Row],[Reg.Hrs]]*表格1[[#This Row],[$]] -> 8640 | L18: 134544 | N18: =IFERROR((IF(表格1[[#This Row],[Name.]]=工作表1!$E12,工作表1!$K12," ")*表格1[[#This Row],[Sales]])," ") -> 2690.88 | O18: =IFERROR((IF(表格1[[#This Row],[Full Name.]]=工作表1!F12,工作表1!J12," ")*表格1[[#This Row],[Days]])," ") -> 0 | P18: 0 | Q18: 0 | R18: 0 | S18: 0 | T18: 0 | U18: 0 | V18: 0 | W18: 0 | X18: 0 | Y18: 0 | Z18: 0 | AA18: 0 | AB18: 0 | AC18: 0 | AD18: 0 | AE18: 0 | AG18: =SUM(表格1[[#This Row],[Commission (1% OR 2%)]:[Expenses/支出]])+表格1[[#This Row],[Basic]] -> 11330.88 | AH18: =ROUND(AG18,0) -> 11331 | AJ18: 11330.88 | AK18: =表格1[[#This Row],[Input]]-表格1[[#This Row],[Double check]] -> 0.12
A19: 12 | B19: =IF(表格1[[#This Row],[Full Name.]]=工作表1!F13,"OK") -> OK | C19: Wendy Wong_1 | D19: Wong Lai Ying | E19: Autopay | F19: TW_2 Citistore | G19: Mar/3-4,11,13,18-19,24 | H19: 7 | I19: 63 | J19: 60 | K19: =表格1[[#This Row],[Reg.Hrs]]*表格1[[#This Row],[$]] -> 3780 | L19: 28203 | N19: =IFERROR((IF(表格1[[#This Row],[Name.]]=工作表1!$E13,工作表1!$K13," ")*表格1[[#This Row],[Sales]])," ") -> 564.06 | O19: =IFERROR((IF(表格1[[#This Row],[Full Name.]]=工作表1!F13,工作表1!J13," ")*表格1[[#This Row],[Days]])," ") -> 0 | AG19: =SUM(表格1[[#This Row],[Commission (1% OR 2%)]:[Expenses/支出]])+表格1[[#This Row],[Basic]] -> 4344.06 | AH19: =ROUND(AG19,0) -> 4344 | AJ19: 4344.06 | AK19: =表格1[[#This Row],[Input]]-表格1[[#This Row],[Double check]] -> -0.06
A20: 13 | B20: =IF(表格1[[#This Row],[Full Name.]]=工作表1!F14,"OK") -> OK | C20: Mandy | D20: Ho Lai Sim | E20: Autopay | F20: TW_3 Citistore | G20: Mar/12 | H20: 1 | I20: 9 | J20: 60 | K20: =表格1[[#This Row],[Reg.Hrs]]*表格1[[#This Row],[$]] -> 540 | L20: 4664 | N20: =IFERROR((IF(表格1[[#This Row],[Name.]]=工作表1!$E14,工作表1!$K14," ")*表格1[[#This Row],[Sales]])," ") -> 93.28 | O20: =IFERROR((IF(表格1[[#This Row],[Full Name.]]=工作表1!F14,工作表1!J14," ")*表格1[[#This Row],[Days]])," ") -> 0 | AG20: =SUM(表格1[[#This Row],[Commission (1% OR 2%)]:[Expenses/支出]])+表格1[[#This Row],[Basic]] -> 633.28 | AH20: =ROUND(AG20,0) -> 633 | AJ20: 633.28 | AK20: =表格1[[#This Row],[Input]]-表格1[[#This Row],[Double check]] -> -0.28
A21: 14 | B21: =IF(表格1[[#This Row],[Full Name.]]=工作表1!F15,"OK") -> OK | C21: Shan_2 | D21: Chiu Fung Shan | E21: 20856 | F21: TW RS_1 Citistore | G21: Mar/25-31 | H21: 7 | I21: 56 | J21: 60 | K21: =表格1[[#This Row],[Reg.Hrs]]*表格1[[#This Row],[$]] -> 3360 | L21: 151474.6 | N21: =IFERROR((IF(表格1[[#This Row],[Name.]]=工作表1!$E15,工作表1!$K15," ")*表格1[[#This Row],[Sales]])," ") -> 3029.492 | O21: =IFERROR((IF(表格1[[#This Row],[Full Name.]]=工作表1!F15,工作表1!J15," ")*表格1[[#This Row],[Days]])," ") -> 0 | AG21: =SUM(表格1[[#This Row],[Commission (1% OR 2%)]:[Expenses/支出]])+表格1[[#This Row],[Basic]] -> 6389.492 | AH21: =ROUND(AG21,0) -> 6389 | AJ21: 6389.492 | AK21: =表格1[[#This Row],[Input]]-表格1[[#This Row],[Double check]] -> -0.492
A22: 15 | B22: =IF(表格1[[#This Row],[Full Name.]]=工作表1!F16,"OK") -> OK | C22: Wendy Wong_2 | D22: Wong Lai Ying | E22: Autopay | F22: TW RS_2 Citistore | G22: Mar/27-29 | H22: 3 | I22: 24 | J22: 60 | K22: =表格1[[#This Row],[Reg.Hrs]]*表格1[[#This Row],[$]] -> 1440 | L22: 79845 | N22: =IFERROR((IF(表格1[[#This Row],[Name.]]=工作表1!$E16,工作表1!$K16," ")*表格1[[#This Row],[Sales]])," ") -> 798.45 | O22: =IFERROR((IF(表格1[[#This Row],[Full Name.]]=工作表1!F16,工作表1!J16," ")*表格1[[#This Row],[Days]])," ") -> 0 | AG22: =SUM(表格1[[#This Row],[Commission (1% OR 2%)]:[Expenses/支出]])+表格1[[#This Row],[Basic]] -> 2238.45 | AH22: =ROUND(AG22,0) -> 2238 | AJ22: 2238.45 | AK22: =表格1[[#This Row],[Input]]-表格1[[#This Row],[Double check]] -> -0.45
A23: 16 | B23: =IF(表格1[[#This Row],[Full Name.]]=工作表1!F17,"OK") -> OK | C23: Kiko | D23: Chan Mei Sim | E23: Autopay | F23: Tai Koo Fortress | G23: Mar/1-3,7-11,14-18,21-25,28-31 | H23: 22 | I23: 176 | J23: 60 | K23: =表格1[[#This Row],[Reg.Hrs]]*表格1[[#This Row],[$]] -> 10560 | L23: 487590 | N23: =IFERROR((IF(表格1[[#This Row],[Name.]]=工作表1!$E17,工作表1!$K17," ")*表格1[[#This Row],[Sales]])," ") -> 9751.8 | O23: =IFERROR((IF(表格1[[#This Row],[Full Name.]]=工作表1!F17,工作表1!J17," ")*表格1[[#This Row],[Days]])," ") -> 0 | P23: 0 | Q23: 0 | R23: 0 | S23: 0 | T23: 320 | U23: 0 | V23: 0 | W23: 0 | X23: 0 | Y23: 0 | Z23: 0 | AA23: 0 | AB23: 0 | AC23: 0 | AD23: 500 | AE23: 1000 | AG23: =SUM(表格1[[#This Row],[Commission (1% OR 2%)]:[Expenses/支出]])+表格1[[#This Row],[Basic]] -> 22131.8 | AH23: =ROUND(AG23,0) -> 22132 | AJ23: 22131.8 | AK23: =表格1[[#This Row],[Input]]-表格1[[#This Row],[Double check]] -> 0.2
A24: 17 | B24: =IF(表格1[[#This Row],[Full Name.]]=工作表1!F18,"OK") -> OK | C24: Jaco | D24: Ka Kui,Jaco | E24: 20857 | F24: Tung Chun Fortress | G24: Mar/2-5,7-11,14-17,20-25,29-31 | H24: 22 | I24: 170 | J24: 60 | K24: =表格1[[#This Row],[Reg.Hrs]]*表格1[[#This Row],[$]] -> 10200 | L24: 372105 | N24: =IFERROR((IF(表格1[[#This Row],[Name.]]=工作表1!$E18,工作表1!$K18," ")*表格1[[#This Row],[Sales]])," ") -> 7442.1 | O24: =IFERROR((IF(表格1[[#This Row],[Full Name.]]=工作表1!F18,工作表1!J18," ")*表格1[[#This Row],[Days]])," ") -> 0 | P24: 0 | Q24: 0 | R24: 0 | S24: 0 | T24: 160 | U24: 0 | V24: 0 | W24: 0 | X24: 300 | Y24: 0 | Z24: 0 | AA24: 0 | AB24: 0 | AC24: 0 | AD24: 0 | AE24: 0 | AG24: =SUM(表格1[[#This Row],[Commission (1% OR 2%)]:[Expenses/支出]])+表格1[[#This Row],[Basic]] -> 18102.1 | AH24: =ROUND(AG24,0) -> 18102 | AJ24: 18102.1 | AK24: =表格1[[#This Row],[Input]]-表格1[[#This Row],[Double check]] -> -0.1
A25: 18 | B25: =IF(表格1[[#This Row],[Full Name.]]=工作表1!F19,"OK") -> OK | C25: Daisy | D25: Yeung Kwai Lin | E25: Autopay | F25: TM Suning | G25: Mar/1-4,7-10,14-18,20-25,28-31 | H25: 23 | I25: 184 | J25: 60 | K25: =表格1[[#This Row],[Reg.Hrs]]*表格1[[#This Row],[$]] -> 11040 | L25: 335290 | N25: =IFERROR((IF(表格1[[#This Row],[Name.]]=工作表1!$E19,工作表1!$K19," ")*表格1[[#This Row],[Sales]])," ") -> 6705.8 | O25: =IFERROR((IF(表格1[[#This Row],[Full Name.]]=工作表1!F19,工作表1!J19," ")*表格1[[#This Row],[Days]])," ") -> 0 | P25: 0 | Q25: 200 | R25: 0 | S25: 0 | T25: 0 | U25: 0 | V25: 0 | W25: 0 | X25: 0 | Y25: 0 | Z25: 0 | AA25: 200 | AB25: 0 | AC25: 0 | AD25: 0 | AE25: 0 | AG25: =SUM(表格1[[#This Row],[Commission (1% OR 2%)]:[Expenses/支出]])+表格1[[#This Row],[Basic]] -> 18145.8 | AH25: =ROUND(AG25,0) -> 18146 | AJ25: 18145.8 | AK25: =表格1[[#This Row],[Input]]-表格1[[#This Row],[Double check]] -> 0.2
A26: 19 | B26: =IF(表格1[[#This Row],[Full Name.]]=工作表1!F20,"OK") -> OK | C26: Pam | D26: Tam Wing Lam | E26: Autopay | F26: Mos_1 Citistore | G26: Mar/1,3-5,7-10,12-16,18,24-26,28-31 | H26: 21 | I26: 168 | J26: 55 | K26: =表格1[[#This Row],[Reg.Hrs]]*表格1[[#This Row],[$]] -> 9240 | L26: 119202.6 | N26: =IFERROR((IF(表格1[[#This Row],[Name.]]=工作表1!$E20,工作表1!$K20," ")*表格1[[#This Row],[Sales]])," ") -> 2384.052 | O26: =IFERROR((IF(表格1[[#This Row],[Full Name.]]=工作表1!F20,工作表1!J20," ")*表格1[[#This Row],[Days]])," ") -> 0 | P26: 0 | Q26: 0 | R26: 0 | S26: 0 | T26: 0 | U26: 0 | V26: 0 | W26: 0 | X26: 0 | Y26: 0 | Z26: 0 | AA26: 0 | AB26: 0 | AC26: 0 | AD26: 0 | AE26: 0 | AG26: =SUM(表格1[[#This Row],[Commission (1% OR 2%)]:[Expenses/支出]])+表格1[[#This Row],[Basic]] -> 11624.052 | AH26: =ROUND(AG26,0) -> 11624 | AJ26: 11624.052 | AK26: =表格1[[#This Row],[Input]]-表格1[[#This Row],[Double check]] -> -0.052
A27: 20 | B27: =IF(表格1[[#This Row],[Full Name.]]=工作表1!F21,"OK") -> OK | C27: Tony_4 | D27: Wong Tak Chung | E27: Autopay | F27: Mos_2 Citistore | G27: Mar/21-22 | H27: 2 | I27: 16 | J27: 60 | K27: =表格1[[#This Row],[Reg.Hrs]]*表格1[[#This Row],[$]] -> 960 | L27: 17628 | N27: =IFERROR((IF(表格1[[#This Row],[Name.]]=工作表1!$E21,工作表1!$K21," ")*表格1[[#This Row],[Sales]])," ") -> 352.56 | O27: =IFERROR((IF(表格1[[#This Row],[Full Name.]]=工作表1!F21,工作表1!J21," ")*表格1[[#This Row],[Days]])," ") -> 0 | AG27: =SUM(表格1[[#This Row],[Commission (1% OR 2%)]:[Expenses/支出]])+表格1[[#This Row],[Basic]] -> 1312.56 | AH27: =ROUND(AG27,0) -> 1313 | AJ27: 1312.56 | AK27: =表格1[[#This Row],[Input]]-表格1[[#This Row],[Double check]] -> 0.44
A28: 21 | B28: =IF(表格1[[#This Row],[Full Name.]]=工作表1!F22,"OK") -> OK | C28: Lily Hon | D28: Hon Lily | E28: 20858 | F28: TM_1 Aeon | G28: Mar/1-2,4,6,8-9,11,13,22-25,27-29,31 | H28: 16 | I28: 128 | J28: 55 | K28: =表格1[[#This Row],[Reg.Hrs]]*表格1[[#This Row],[$]] -> 7040 | L28: 228635.5 | N28: =IFERROR((IF(表格1[[#This Row],[Name.]]=工作表1!$E22,工作表1!$K22," ")*表格1[[#This Row],[Sales]])," ") -> 4572.71 | O28: =IFERROR((IF(表格1[[#This Row],[Full Name.]]=工作表1!F22,工作表1!J22," ")*表格1[[#This Row],[Days]])," ") -> 480 | P28: 0 | Q28: 0 | R28: 0 | S28: 0 | T28: 0 | U28: 0 | V28: 0 | W28: 0 | X28: 0 | Y28: 0 | Z28: 0 | AA28: 0 | AB28: 0 | AC28: 0 | AD28: 0 | AE28: 0 | AG28: =SUM(表格1[[#This Row],[Commission (1% OR 2%)]:[Expenses/支出]])+表格1[[#This Row],[Basic]] -> 12092.71 | AH28: =ROUND(AG28,0) -> 12093 | AJ28: 12092.71 | AK28: =表格1[[#This Row],[Input]]-表格1[[#This Row],[Double check]] -> 0.29
A29: 22 | B29: =IF(表格1[[#This Row],[Full Name.]]=工作表1!F23,"OK") -> OK | C29: Ho_3 | D29: Kwan Tit Ho | E29: 20859 | F29: TM_2 Aeon | G29: Mar/17-18,26,30 | H29: 4 | I29: 32 | J29: 55 | K29: =表格1[[#This Row],[Reg.Hrs]]*表格1[[#This Row],[$]] -> 1760 | L29: 31095 | N29: =IFERROR((IF(表格1[[#This Row],[Name.]]=工作表1!$E23,工作表1!$K23," ")*表格1[[#This Row],[Sales]])," ") -> 621.9 | O29: =IFERROR((IF(表格1[[#This Row],[Full Name.]]=工作表1!F23,工作表1!J23," ")*表格1[[#This Row],[Days]])," ") -> 0 | AG29: =SUM(表格1[[#This Row],[Commission (1% OR 2%)]:[Expenses/支出]])+表格1[[#This Row],[Basic]] -> 2381.9 | AH29: =ROUND(AG29,0) -> 2382 | AJ29: 2381.9 | AK29: =表格1[[#This Row],[Input]]-表格1[[#This Row],[Double check]] -> 0.1
A30: 23 | B30: =IF(表格1[[#This Row],[Full Name.]]=工作表1!F24,"OK") -> OK | C30: Kandy | D30: Sin Hoi Yam | E30: 20860 | F30: TW Fortress | G30: Mar/1,7-8,21-22,28-29 | H30: 7 | I30: 56 | J30: 55 | K30: =表格1[[#This Row],[Reg.Hrs]]*表格1[[#This Row],[$]] -> 3080 | L30: 165639 | N30: =IFERROR((IF(表格1[[#This Row],[Name.]]=工作表1!$E24,工作表1!$K24," ")*表格1[[#This Row],[Sales]])," ") -> 3312.78 | O30: =IFERROR((IF(表格1[[#This Row],[Full Name.]]=工作表1!F24,工作表1!J24," ")*表格1[[#This Row],[Days]])," ") -> 0 | P30: 0 | Q30: 0 | R30: 0 | S30: 0 | T30: 0 | U30: 0 | V30: 0 | W30: 0 | X30: 0 | Y30: 0 | Z30: 0 | AA30: 0 | AB30: 0 | AC30: 0 | AD30: 0 | AE30: 0 | AG30: =SUM(表格1[[#This Row],[Commission (1% OR 2%)]:[Expenses/支出]])+表格1[[#This Row],[Basic]] -> 6392.78 | AH30: =ROUND(AG30,0) -> 6393 | AJ30: 6392.78 | AK30: =表格1[[#This Row],[Input]]-表格1[[#This Row],[Double check]] -> 0.22
A31: 24 | B31: =IF(表格1[[#This Row],[Full Name.]]=工作表1!F25,"OK") -> OK | C31: Hung | D31: Hui Man Hung | E31: 20861 | F31: TW Suning | G31: Mar/1-4,6-12,14-18,20-25 | H31: 22 | I31: 176 | J31: 60 | K31: =表格1[[#This Row],[Reg.Hrs]]*表格1[[#This Row],[$]] -> 10560 | L31: 0 | N31: =IFERROR((IF(表格1[[#This Row],[Name.]]=工作表1!$E25,工作表1!$K25," ")*表格1[[#This Row],[Sales]])," ") -> 0 | O31: =IFERROR((IF(表格1[[#This Row],[Full Name.]]=工作表1!F25,工作表1!J25," ")*表格1[[#This Row],[Days]])," ") -> 0 | P31: 0 | Q31: 0 | R31: 0 | S31: 0 | T31: 0 | U31: 0 | V31: 0 | W31: 0 | X31: 0 | Y31: 0 | Z31: 0 | AA31: 0 | AB31: 0 | AC31: 0 | AD31: 0 | AE31: 0 | AG31: =SUM(表格1[[#This Row],[Commission (1% OR 2%)]:[Expenses/支出]])+表格1[[#This Row],[Basic]] -> 10560 | AH31: =ROUND(AG31,0) -> 10560 | AJ31: 10560 | AK31: =表格1[[#This Row],[Input]]-表格1[[#This Row],[Double check]] -> 0
A32: 25 | B32: =IF(表格1[[#This Row],[Full Name.]]=工作表1!F26,"OK") -> OK | C32: Leo | D32: Lam King Chung | E32: Autopay | F32: Yoho Suning | G32: Mar/2-3,5,7-10,12-17,19-24,26,29-31 | H32: 23 | I32: 184 | J32: 55 | K32: =表格1[[#This Row],[Reg.Hrs]]*表格1[[#This Row],[$]] -> 10120 | L32: 294578 | N32: =IFERROR((IF(表格1[[#This Row],[Name.]]=工作表1!$E26,工作表1!$K26," ")*表格1[[#This Row],[Sales]])," ") -> 5891.56 | O32: =IFERROR((IF(表格1[[#This Row],[Full Name.]]=工作表1!F26,工作表1!J26," ")*表格1[[#This Row],[Days]])," ") -> 0 | P32: 0 | Q32: 0 | R32: 0 | S32: 0 | T32: 0 | U32: 0 | V32: 0 | W32: 0 | X32: 300 | Y32: 0 | Z32: 0 | AA32: 0 | AB32: 0 | AC32: 0 | AD32: 500 | AE32: 1000 | AG32: =SUM(表格1[[#This Row],[Commission (1% OR 2%)]:[Expenses/支出]])+表格1[[#This Row],[Basic]] -> 17811.56 | AH32: =ROUND(AG32,0) -> 17812 | AJ32: 17811.56 | AK32: =表格1[[#This Row],[Input]]-表格1[[#This Row],[Double check]] -> 0.44
A33: 26 | B33: =IF(表格1[[#This Row],[Full Name.]]=工作表1!F27,"OK") -> OK | C33: Yee | D33: Cheung Yu Wing Yee | E33: 20862 | F33: YL Citistore | G33: Mar/1,5-9,12-16,19-22,26-30 | H33: 20 | I33: 160 | J33: 60 | K33: =表格1[[#This Row],[Reg.Hrs]]*表格1[[#This Row],[$]] -> 9600 | L33: 125760 | N33: =IFERROR((IF(表格1[[#This Row],[Name.]]=工作表1!$E27,工作表1!$K27," ")*表格1[[#This Row],[Sales]])," ") -> 2515.2 | O33: =IFERROR((IF(表格1[[#This Row],[Full Name.]]=工作表1!F27,工作表1!J27," ")*表格1[[#This Row],[Days]])," ") -> 0 | P33: 0 | Q33: 0 | R33: 0 | S33: 0 | T33: 0 | U33: 0 | V33: 0 | W33: 0 | X33: 0 | Y33: 0 | Z33: 0 | AA33: 0 | AB33: 0 | AC33: 0 | AD33: 0 | AE33: 0 | AG33: =SUM(表格1[[#This Row],[Commission (1% OR 2%)]:[Expenses/支出]])+表格1[[#This Row],[Basic]] -> 12115.2 | AH33: =ROUND(AG33,0) -> 12115 | AJ33: 12115.2 | AK33: =表格1[[#This Row],[Input]]-表格1[[#This Row],[Double check]] -> -0.2
A34: 27 | B34: =IF(表格1[[#This Row],[Full Name.]]=工作表1!F28,"OK") -> OK | C34: Ling Ho | D34: Ho Wai Ling | E34: Autopay | F34: TM Citistore | G34: Mar/1,3-4,6-9,11-12,14-17,20-24,26-31 | H34: 24 | I34: 192 | J34: 60 | K34: =表格1[[#This Row],[Reg.Hrs]]*表格1[[#This Row],[$]] -> 11520 | L34: 153807.4 | N34: =IFERROR((IF(表格1[[#This Row],[Name.]]=工作表1!$E28,工作表1!$K28," ")*表格1[[#This Row],[Sales]])," ") -> 3076.148 | O34: =IFERROR((IF(表格1[[#This Row],[Full Name.]]=工作表1!F28,工作表1!J28," ")*表格1[[#This Row],[Days]])," ") -> 0 | P34: 0 | Q34: 0 | R34: 0 | S34: 0 | T34: 0 | U34: 0 | V34: 0 | W34: 0 | X34: 0 | Y34: 0 | Z34: 0 | AA34: 0 | AB34: 0 | AC34: 0 | AD34: 0 | AE34: 0 | AG34: =SUM(表格1[[#This Row],[Commission (1% OR 2%)]:[Expenses/支出]])+表格1[[#This Row],[Basic]] -> 14596.148 | AH34: =ROUND(AG34,0) -> 14596 | AJ34: 14596.148 | AK34: =表格1[[#This Row],[Input]]-表格1[[#This Row],[Double check]] -> -0.148
A35: 28 | B35: =IF(表格1[[#This Row],[Full Name.]]=工作表1!F29,"OK") -> OK | C35: Happy | D35: Chun Yin Ling | E35: 20863 | F35: APM Broadway | G35: Mar/1,3-5,7-9,11-12,15-16,19-22,25-31 | H35: 22 | I35: 176 | J35: 60 | K35: =表格1[[#This Row],[Reg.Hrs]]*表格1[[#This Row],[$]] -> 10560 | L35: 470313 | N35: =IFERROR((IF(表格1[[#This Row],[Name.]]=工作表1!$E29,工作表1!$K29," ")*表格1[[#This Row],[Sales]])," ") -> 9406.26 | O35: =IFERROR((IF(表格1[[#This Row],[Full Name.]]=工作表1!F29,工作表1!J29," ")*表格1[[#This Row],[Days]])," ") -> 0 | P35: 0 | Q35: 0 | R35: 0 | S35: 0 | T35: 160 | U35: 0 | V35: 400 | W35: 0 | X35: 0 | Y35: 200 | Z35: 0 | AA35: 0 | AB35: 2450 | AC35: 0 | AD35: 500 | AE35: 1000 | AG35: =SUM(表格1[[#This Row],[Commission (1% OR 2%)]:[Expenses/支出]])+表格1[[#This Row],[Basic]] -> 24676.26 | AH35: =ROUND(AG35,0) -> 24676 | AJ35: 24676.26 | AK35: =表格1[[#This Row],[Input]]-表格1[[#This Row],[Double check]] -> -0.26
A36: 29 | B36: =IF(表格1[[#This Row],[Full Name.]]=工作表1!F30,"OK") -> OK | C36: Tiffany | D36: Man Wai Han | E36: Autopay | F36: APM Fortress | G36: Mar/1,5-6,8-9,11-12,14,16,19-22,24-26,29,31 | H36: 18 | I36: 144 | J36: 60 | K36: =表格1[[#This Row],[Reg.Hrs]]*表格1[[#This Row],[$]] -> 8640 | L36: 376482 | N36: =IFERROR((IF(表格1[[#This Row],[Name.]]=工作表1!$E30,工作表1!$K30," ")*表格1[[#This Row],[Sales]])," ") -> 7529.64 | O36: 6653.48 | P36: 0 | Q36: 0 | R36: 0 | S36: 0 | T36: 160 | U36: 0 | V36: 0 | W36: 0 | X36: 0 | Y36: 0 | Z36: 0 | AA36: 0 | AB36: 0 | AC36: 0 | AD36: 0 | AE36: 0 | AG36: =SUM(表格1[[#This Row],[Commission (1% OR 2%)]:[Expenses/支出]])+表格1[[#This Row],[Basic]] -> 22983.12 | AH36: =ROUND(AG36,0) -> 22983 | AJ36: 16329.64 | AK36: =表格1[[#This Row],[Input]]-表格1[[#This Row],[Double check]] -> 6653.36
A37: 30 | B37: =IF(表格1[[#This Row],[Full Name.]]=工作表1!F31,"OK") -> OK | C37: Coco | D37: Yuen Lai Ying | E37: 20864 | F37: TKO Suning | G37: Mar/1,3-5,7-8,11-12,14-15,17-19,24-26,28-31 | H37: 20 | I37: 160 | J37: 60 | K37: =表格1[[#This Row],[Reg.Hrs]]*表格1[[#This Row],[$]] -> 9600 | L37: 229262 | N37: =IFERROR((IF(表格1[[#This Row],[Name.]]=工作表1!$E31,工作表1!$K31," ")*表格1[[#This Row],[Sales]])," ") -> 4585.24 | O37: =IFERROR((IF(表格1[[#This Row],[Full Name.]]=工作表1!F31,工作表1!J31," ")*表格1[[#This Row],[Days]])," ") -> 0 | P37: 0 | Q37: 0 | R37: 0 | S37: 0 | T37: 0 | U37: 0 | V37: 0 | W37: 0 | X37: 0 | Y37: 0 | Z37: 0 | AA37: 0 | AB37: 0 | AC37: 0 | AD37: 0 | AE37: 0 | AG37: =SUM(表格1[[#This Row],[Commission (1% OR 2%)]:[Expenses/支出]])+表格1[[#This Row],[Basic]] -> 14185.24 | AH37: =ROUND(AG37,0) -> 14185 | AJ37: 14185.24 | AK37: =表格1[[#This Row],[Input]]-表格1[[#This Row],[Double check]] -> -0.24
A38: 31 | B38: =IF(表格1[[#This Row],[Full Name.]]=工作表1!F32,"OK") -> OK | C38: Raymond | D38: Kwok Chun Wah | E38: 20865 | F38: Times Fortress | G38: Mar/1-5,7,9-12,15-18,21-26,28-31 | H38: 24 | I38: 192 | J38: 60 | K38: =表格1[[#This Row],[Reg.Hrs]]*表格1[[#This Row],[$]] -> 11520 | L38: 360494 | N38: =IFERROR((IF(表格1[[#This Row],[Name.]]=工作表1!$E32,工作表1!$K32," ")*表格1[[#This Row],[Sales]])," ") -> 7209.88 | O38: =IFERROR((IF(表格1[[#This Row],[Full Name.]]=工作表1!F32,工作表1!J32," ")*表格1[[#This Row],[Days]])," ") -> 0 | P38: 0 | Q38: 0 | R38: 0 | S38: 0 | T38: 0 | U38: 0 | V38: 0 | W38: 0 | X38: 0 | Y38: 0 | Z38: 0 | AA38: 0 | AB38: 0 | AC38: 0 | AD38: 0 | AE38: 0 | AG38: =SUM(表格1[[#This Row],[Commission (1% OR 2%)]:[Expenses/支出]])+表格1[[#This Row],[Basic]] -> 18729.88 | AH38: =ROUND(AG38,0) -> 18730 | AJ38: 18729.88 | AK38: =表格1[[#This Row],[Input]]-表格1[[#This Row],[Double check]] -> 0.12
A39: 32 | B39: =IF(表格1[[#This Row],[Full Name.]]=工作表1!F33,"OK") -> OK | C39: Maggie Yip | D39: Yip Mei King | E39: 20866 | F39: Shatin_1 Yata | G39: Mar/1-2,5-10,14-17,20-24,27-31 | H39: 22 | I39: 176 | J39: 60 | K39: =表格1[[#This Row],[Reg.Hrs]]*表格1[[#This Row],[$]] -> 10560 | L39: 123292 | N39: =IFERROR((IF(表格1[[#This Row],[Name.]]=工作表1!$E33,工作表1!$K33," ")*表格1[[#This Row],[Sales]])," ") -> 2465.84 | O39: =IFERROR((IF(表格1[[#This Row],[Full Name.]]=工作表1!F33,工作表1!J33," ")*表格1[[#This Row],[Days]])," ") -> 0 | P39: 0 | Q39: 0 | R39: 0 | S39: 0 | T39: 0 | U39: 0 | V39: 0 | W39: 0 | X39: 0 | Y39: 0 | Z39: 0 | AA39: 0 | AB39: 0 | AC39: 0 | AD39: 0 | AE39: 0 | AG39: =SUM(表格1[[#This Row],[Commission (1% OR 2%)]:[Expenses/支出]])+表格1[[#This Row],[Basic]] -> 13025.84 | AH39: =ROUND(AG39,0) -> 13026 | AJ39: 13025.84 | AK39: =表格1[[#This Row],[Input]]-表格1[[#This Row],[Double check]] -> 0.16
A40: 33 | B40: =IF(表格1[[#This Row],[Full Name.]]=工作表1!F34,"OK") -> OK | C40: Emma | D40: Ng Yuk Ying | E40: Autopay | F40: Shatin_2 Yata | G40: Mar/3-4,18-19 | H40: 4 | I40: 32 | J40: 60 | K40: =表格1[[#This Row],[Reg.Hrs]]*表格1[[#This Row],[$]] -> 1920 | L40: 15785 | N40: =IFERROR((IF(表格1[[#This Row],[Name.]]=工作表1!$E34,工作表1!$K34," ")*表格1[[#This Row],[Sales]])," ") -> 315.7 | O40: =IFERROR((IF(表格1[[#This Row],[Full Name.]]=工作表1!F34,工作表1!J34," ")*表格1[[#This Row],[Days]])," ") -> 0 | AF40: 45 | AG40: =SUM(表格1[[#This Row],[Commission (1% OR 2%)]:[Expenses/支出]])+表格1[[#This Row],[Basic]] -> 2280.7 | AH40: =ROUND(AG40,0) -> 2281 | AJ40: 2235.7 | AK40: =表格1[[#This Row],[Input]]-表格1[[#This Row],[Double check]] -> 45.3
A41: 34 | B41: =IF(表格1[[#This Row],[Full Name.]]=工作表1!F35,"OK") -> OK | C41: Tony_1 | D41: Wong Tak Chung | E41: Autopay | F41: Shatin_3 Yata | G41: Mar/25-26 | H41: 2 | I41: 16 | J41: 60 | K41: =表格1[[#This Row],[Reg.Hrs]]*表格1[[#This Row],[$]] -> 960 | L41: 5686 | N41: =IFERROR((IF(表格1[[#This Row],[Name.]]=工作表1!$E35,工作表1!$K35," ")*表格1[[#This Row],[Sales]])," ") -> 113.72 | O41: =IFERROR((IF(表格1[[#This Row],[Full Name.]]=工作表1!F35,工作表1!J35," ")*表格1[[#This Row],[Days]])," ") -> 0 | AG41: =SUM(表格1[[#This Row],[Commission (1% OR 2%)]:[Expenses/支出]])+表格1[[#This Row],[Basic]] -> 1073.72 | AH41: =ROUND(AG41,0) -> 1074 | AJ41: 1073.72 | AK41: =表格1[[#This Row],[Input]]-表格1[[#This Row],[Double check]] -> 0.28
A42: 35 | B42: =IF(表格1[[#This Row],[Full Name.]]=工作表1!F36,"OK") -> OK | C42: Kit_1 | D42: Li Wenjie | E42: Autopay | F42: Shatin_4 Yata | G42: Mar/11-13 | H42: 3 | I42: 24 | J42: 60 | K42: =表格1[[#This Row],[Reg.Hrs]]*表格1[[#This Row],[$]] -> 1440 | L42: 20004 | N42: =IFERROR((IF(表格1[[#This Row],[Name.]]=工作表1!$E36,工作表1!$K36," ")*表格1[[#This Row],[Sales]])," ") -> 400.08 | O42: =IFERROR((IF(表格1[[#This Row],[Full Name.]]=工作表1!F36,工作表1!J36," ")*表格1[[#This Row],[Days]])," ") -> 0 | AG42: =SUM(表格1[[#This Row],[Commission (1% OR 2%)]:[Expenses/支出]])+表格1[[#This Row],[Basic]] -> 1840.08 | AH42: =ROUND(AG42,0) -> 1840 | AJ42: 1840.08 | AK42: =表格1[[#This Row],[Input]]-表格1[[#This Row],[Double check]] -> -0.08
A43: 36 | B43: =IF(表格1[[#This Row],[Full Name.]]=工作表1!F37,"OK") -> OK | C43: Gloria | D43: Yeung Chor Mui | E43: 20867 | F43: TP_1 Yata | G43: Mar/1,4-8,11-15,18-22,25-29 | H43: 21 | I43: 168 | J43: 60 | K43: =表格1[[#This Row],[Reg.Hrs]]*表格1[[#This Row],[$]] -> 10080 | L43: 175117 | N43: =IFERROR((IF(表格1[[#This Row],[Name.]]=工作表1!$E37,工作表1!$K37," ")*表格1[[#This Row],[Sales]])," ") -> 3502.34 | O43: =IFERROR((IF(表格1[[#This Row],[Full Name.]]=工作表1!F37,工作表1!J37," ")*表格1[[#This Row],[Days]])," ") -> 0 | P43: 250 | Q43: 0 | R43: 0 | S43: 0 | T43: 0 | U43: 0 | V43: 0 | W43: 0 | X43: 0 | Y43: 0 | Z43: 0 | AA43: 0 | AB43: 0 | AC43: 0 | AD43: 0 | AE43: 0 | AG43: =SUM(表格1[[#This Row],[Commission (1% OR 2%)]:[Expenses/支出]])+表格1[[#This Row],[Basic]] -> 13832.34 | AH43: =ROUND(AG43,0) -> 13832 | AJ43: 13832.34 | AK43: =表格1[[#This Row],[Input]]-表格1[[#This Row],[Double check]] -> -0.34
A44: 37 | B44: =IF(表格1[[#This Row],[Full Name.]]=工作表1!F38,"OK") -> OK | C44: Tony_2 | D44: Wong Tak Chung | E44: Autopay | F44: TP_2 Yata | G44: Mar/9-10,23-24,30-31 | H44: 6 | I44: 48 | J44: 60 | K44: =表格1[[#This Row],[Reg.Hrs]]*表格1[[#This Row],[$]] -> 2880 | L44: 32952 | N44: =IFERROR((IF(表格1[[#This Row],[Name.]]=工作表1!$E38,工作表1!$K38," ")*表格1[[#This Row],[Sales]])," ") -> 659.04 | O44: =IFERROR((IF(表格1[[#This Row],[Full Name.]]=工作表1!F38,工作表1!J38," ")*表格1[[#This Row],[Days]])," ") -> 0 | AG44: =SUM(表格1[[#This Row],[Commission (1% OR 2%)]:[Expenses/支出]])+表格1[[#This Row],[Basic]] -> 3539.04 | AH44: =ROUND(AG44,0) -> 3539 | AJ44: 3539.04 | AK44: =表格1[[#This Row],[Input]]-表格1[[#This Row],[Double check]] -> -0.04
A45: 38 | B45: =IF(表格1[[#This Row],[Full Name.]]=工作表1!F39,"OK") -> OK | C45: Kit_2 | D45: Li Wenjie | E45: Autopay | F45: TP_3 Yata | G45: Mar/2-3,16-17 | H45: 4 | I45: 32 | J45: 60 | K45: =表格1[[#This Row],[Reg.Hrs]]*表格1[[#This Row],[$]] -> 1920 | L45: 8550 | N45: =IFERROR((IF(表格1[[#This Row],[Name.]]=工作表1!$E39,工作表1!$K39," ")*表格1[[#This Row],[Sales]])," ") -> 171 | O45: =IFERROR((IF(表格1[[#This Row],[Full Name.]]=工作表1!F39,工作表1!J39," ")*表格1[[#This Row],[Days]])," ") -> 0 | AG45: =SUM(表格1[[#This Row],[Commission (1% OR 2%)]:[Expenses/支出]])+表格1[[#This Row],[Basic]] -> 2091 | AH45: =ROUND(AG45,0) -> 2091 | AJ45: 2091 | AK45: =表格1[[#This Row],[Input]]-表格1[[#This Row],[Double check]] -> 0
A46: 39 | B46: =IF(表格1[[#This Row],[Full Name.]]=工作表1!F40,"OK") -> OK | C46: Anita_1 | D46: Chan Siu Kuen | E46: Autopay | F46: Kai Tak_1 Sogo | G46: Mar/21-22,31 | H46: 3 | I46: 24 | J46: 60 | K46: =表格1[[#This Row],[Reg.Hrs]]*表格1[[#This Row],[$]] -> 1440 | L46: 5694 | N46: =IFERROR((IF(表格1[[#This Row],[Name.]]=工作表1!$E40,工作表1!$K40," ")*表格1[[#This Row],[Sales]])," ") -> 113.88 | O46: =IFERROR((IF(表格1[[#This Row],[Full Name.]]=工作表1!F40,工作表1!J40," ")*表格1[[#This Row],[Days]])," ") -> 0 | AG46: =SUM(表格1[[#This Row],[Commission (1% OR 2%)]:[Expenses/支出]])+表格1[[#This Row],[Basic]] -> 1553.88 | AH46: =ROUND(AG46,0) -> 1554 | AJ46: 1553.88 | AK46: =表格1[[#This Row],[Input]]-表格1[[#This Row],[Double check]] -> 0.12
A47: 40 | B47: =IF(表格1[[#This Row],[Full Name.]]=工作表1!F41,"OK") -> OK | C47: Hazel | D47: Tan Xingfang | E47: 20868 | F47: Kai Tak_2 Sogo | G47: Mar/1-4,7-8 | H47: 6 | I47: 48 | J47: 65 | K47: =表格1[[#This Row],[Reg.Hrs]]*表格1[[#This Row],[$]] -> 3120 | L47: 49436 | N47: =362.32+313.2 -> 675.52 | O47: =IFERROR((IF(表格1[[#This Row],[Full Name.]]=工作表1!F41,工作表1!J41," ")*表格1[[#This Row],[Days]])," ") -> 0 | AG47: =SUM(表格1[[#This Row],[Commission (1% OR 2%)]:[Expenses/支出]])+表格1[[#This Row],[Basic]] -> 3795.52 | AH47: =ROUND(AG47,0) -> 3796 | AJ47: 3795.52 | AK47: =表格1[[#This Row],[Input]]-表格1[[#This Row],[Double check]] -> 0.48
A48: 41 | B48: =IF(表格1[[#This Row],[Full Name.]]=工作表1!F42,"OK") -> OK | C48: Mui Chan_1 | D48: Chan So Mui | E48: Autopay | F48: Kai Tak_3 Sogo | G48: Mar/5,9-19,24-26 | H48: 15 | I48: 120 | J48: 60 | K48: =表格1[[#This Row],[Reg.Hrs]]*表格1[[#This Row],[$]] -> 7200 | L48: 187023 | N48: =2454.76+642.85 -> 3097.61 | O48: 887.06 | P48: 0 | Q48: 300 | R48: 400 | S48: 0 | T48: 0 | U48: 0 | V48: 0 | W48: 0 | X48: 0 | Y48: 0 | Z48: 0 | AA48: 0 | AB48: 0 | AC48: 0 | AD48: 0 | AE48: 0 | AG48: =SUM(表格1[[#This Row],[Commission (1% OR 2%)]:[Expenses/支出]])+表格1[[#This Row],[Basic]] -> 11884.67 | AH48: =ROUND(AG48,0) -> 11885 | AJ48: 10997.61 | AK48: =表格1[[#This Row],[Input]]-表格1[[#This Row],[Double check]] -> 887.39
A49: 42 | B49: =IF(表格1[[#This Row],[Full Name.]]=工作表1!F43,"OK") -> OK | C49: Fong_2 | D49: Ng Nga Fong | E49: Autopay | F49: Kai Tak_4 Sogo | G49: Mar/6 | H49: 1 | I49: 8 | J49: 60 | K49: =表格1[[#This Row],[Reg.Hrs]]*表格1[[#This Row],[$]] -> 480 | L49: 3718 | N49: =IFERROR((IF(表格1[[#This Row],[Name.]]=工作表1!$E43,工作表1!$K43," ")*表格1[[#This Row],[Sales]])," ") -> 74.36 | O49: =IFERROR((IF(表格1[[#This Row],[Full Name.]]=工作表1!F43,工作表1!J43," ")*表格1[[#This Row],[Days]])," ") -> 0 | AG49: =SUM(表格1[[#This Row],[Commission (1% OR 2%)]:[Expenses/支出]])+表格1[[#This Row],[Basic]] -> 554.36 | AH49: =ROUND(AG49,0) -> 554 | AJ49: 554.36 | AK49: =表格1[[#This Row],[Input]]-表格1[[#This Row],[Double check]] -> -0.36
A50: 43 | B50: =IF(表格1[[#This Row],[Full Name.]]=工作表1!F44,"OK") -> OK | C50: Shirley | D50: Sit Kwok Fong | E50: 20869 | F50: Kai Tak_5 Sogo | G50: Mar/28-29 | H50: 2 | I50: 16 | J50: 60 | K50: =表格1[[#This Row],[Reg.Hrs]]*表格1[[#This Row],[$]] -> 960 | L50: 10016 | N50: =IFERROR((IF(表格1[[#This Row],[Name.]]=工作表1!$E44,工作表1!$K44," ")*表格1[[#This Row],[Sales]])," ") -> 200.32 | O50: =IFERROR((IF(表格1[[#This Row],[Full Name.]]=工作表1!F44,工作表1!J44," ")*表格1[[#This Row],[Days]])," ") -> 0 | AG50: =SUM(表格1[[#This Row],[Commission (1% OR 2%)]:[Expenses/支出]])+表格1[[#This Row],[Basic]] -> 1160.32 | AH50: =ROUND(AG50,0) -> 1160 | AJ50: 1160.32 | AK50: =表格1[[#This Row],[Input]]-表格1[[#This Row],[Double check]] -> -0.32
A51: 44 | B51: =IF(表格1[[#This Row],[Full Name.]]=工作表1!F45,"OK") -> OK | C51: Wendy Wong_3 | D51: Wong Lai Ying | E51: Autopay | F51: Kai Tak RS_1 Sogo | G51: Mar/1,7-8 | H51: 3 | I51: 24 | J51: 60 | K51: =表格1[[#This Row],[Reg.Hrs]]*表格1[[#This Row],[$]] -> 1440 | L51: 31320 | N51: =IFERROR((IF(表格1[[#This Row],[Name.]]=工作表1!$E45,工作表1!$K45," ")*表格1[[#This Row],[Sales]])," ") -> 313.2 | O51: =IFERROR((IF(表格1[[#This Row],[Full Name.]]=工作表1!F45,工作表1!J45," ")*表格1[[#This Row],[Days]])," ") -> 0 | AG51: =SUM(表格1[[#This Row],[Commission (1% OR 2%)]:[Expenses/支出]])+表格1[[#This Row],[Basic]] -> 1753.2 | AH51: =ROUND(AG51,0) -> 1753 | AJ51: 1753.2 | AK51: =表格1[[#This Row],[Input]]-表格1[[#This Row],[Double check]] -> -0.2
A52: 45 | B52: =IF(表格1[[#This Row],[Full Name.]]=工作表1!F46,"OK") -> OK | C52: Anita_2 | D52: Chan Siu Kuen | E52: Autopay | F52: Kai Tak RS_2 Sogo | G52: Mar/14-15 | H52: 2 | I52: 16 | J52: 60 | K52: =表格1[[#This Row],[Reg.Hrs]]*表格1[[#This Row],[$]] -> 960 | L52: 64285 | N52: =IFERROR((IF(表格1[[#This Row],[Name.]]=工作表1!$E46,工作表1!$K46," ")*表格1[[#This Row],[Sales]])," ") -> 642.85 | O52: =IFERROR((IF(表格1[[#This Row],[Full Name.]]=工作表1!F46,工作表1!J46," ")*表格1[[#This Row],[Days]])," ") -> 0 | AG52: =SUM(表格1[[#This Row],[Commission (1% OR 2%)]:[Expenses/支出]])+表格1[[#This Row],[Basic]] -> 1602.85 | AH52: =ROUND(AG52,0) -> 1603 | AJ52: 1602.85 | AK52: =表格1[[#This Row],[Input]]-表格1[[#This Row],[Double check]] -> 0.15
A53: 46 | B53: =IF(表格1[[#This Row],[Full Name.]]=工作表1!F47,"OK") -> OK | C53: Connie | D53: Chan Siu Mui | E53: 20870 | F53: Mongkok_1 BBE | G53: Mar/26-29 | H53: 4 | I53: 32 | J53: 60 | K53: =表格1[[#This Row],[Reg.Hrs]]*表格1[[#This Row],[$]] -> 1920 | L53: 0 | N53: =IFERROR((IF(表格1[[#This Row],[Name.]]=工作表1!$E47,工作表1!$K47," ")*表格1[[#This Row],[Sales]])," ") -> 0 | O53: =IFERROR((IF(表格1[[#This Row],[Full Name.]]=工作表1!F47,工作表1!J47," ")*表格1[[#This Row],[Days]])," ") -> 0 | AG53: =SUM(表格1[[#This Row],[Commission (1% OR 2%)]:[Expenses/支出]])+表格1[[#This Row],[Basic]] -> 1920 | AH53: =ROUND(AG53,0) -> 1920 | AJ53: 1920 | AK53: =表格1[[#This Row],[Input]]-表格1[[#This Row],[Double check]] -> 0
A54: 47 | B54: =IF(表格1[[#This Row],[Full Name.]]=工作表1!F48,"OK") -> OK | C54: Amy Or_2 | D54: Or Sim Kiu | E54: 20871 | F54: Mongkok_2 BBE | G54: Mar/14-15,19-22 | H54: 6 | I54: 48 | J54: 55 | K54: =表格1[[#This Row],[Reg.Hrs]]*表格1[[#This Row],[$]] -> 2640 | L54: 95604 | N54: =IFERROR((IF(表格1[[#This Row],[Name.]]=工作表1!$E48,工作表1!$K48," ")*表格1[[#This Row],[Sales]])," ") -> 1912.08 | O54: =IFERROR((IF(表格1[[#This Row],[Full Name.]]=工作表1!F48,工作表1!J48," ")*表格1[[#This Row],[Days]])," ") -> 180 | AG54: =SUM(表格1[[#This Row],[Commission (1% OR 2%)]:[Expenses/支出]])+表格1[[#This Row],[Basic]] -> 4732.08 | AH54: =ROUND(AG54,0) -> 4732 | AJ54: 4732.08 | AK54: =表格1[[#This Row],[Input]]-表格1[[#This Row],[Double check]] -> -0.08
A55: 48 | B55: =IF(表格1[[#This Row],[Full Name.]]=工作表1!F49,"OK") -> OK | C55: SK | D55: Ip Sau King | E55: Autopay | F55: Tai Koo_1 Apita | G55: Mar/1,7-8,14,21-24,28-29 | H55: 10 | I55: 80 | J55: 60 | K55: =表格1[[#This Row],[Reg.Hrs]]*表格1[[#This Row],[$]] -> 4800 | L55: 47199 | N55: =IFERROR((IF(表格1[[#This Row],[Name.]]=工作表1!$E49,工作表1!$K49," ")*表格1[[#This Row],[Sales]])," ") -> 943.98 | O55: =IFERROR((IF(表格1[[#This Row],[Full Name.]]=工作表1!F49,工作表1!J49," ")*表格1[[#This Row],[Days]])," ") -> 0 | AG55: =SUM(表格1[[#This Row],[Commission (1% OR 2%)]:[Expenses/支出]])+表格1[[#This Row],[Basic]] -> 5743.98 | AH55: =ROUND(AG55,0) -> 5744 | AJ55: 5743.98 | AK55: =表格1[[#This Row],[Input]]-表格1[[#This Row],[Double check]] -> 0.02
A56: 49 | B56: =IF(表格1[[#This Row],[Full Name.]]=工作表1!F50,"OK") -> OK | C56: Tony_3 | D56: Wong Tak Chung | E56: Autopay | F56: Tai Koo_2 Apita | G56: Mar/15 | H56: 1 | I56: 8 | J56: 60 | K56: =表格1[[#This Row],[Reg.Hrs]]*表格1[[#This Row],[$]] -> 480 | L56: 6265 | N56: =IFERROR((IF(表格1[[#This Row],[Name.]]=工作表1!$E50,工作表1!$K50," ")*表格1[[#This Row],[Sales]])," ") -> 125.3 | O56: =IFERROR((IF(表格1[[#This Row],[Full Name.]]=工作表1!F50,工作表1!J50," ")*表格1[[#This Row],[Days]])," ") -> 0 | AG56: =SUM(表格1[[#This Row],[Commission (1% OR 2%)]:[Expenses/支出]])+表格1[[#This Row],[Basic]] -> 605.3 | AH56: =ROUND(AG56,0) -> 605 | AJ56: 605.3 | AK56: =表格1[[#This Row],[Input]]-表格1[[#This Row],[Double check]] -> -0.3
A57: 50 | B57: =IF(表格1[[#This Row],[Full Name.]]=工作表1!F51,"OK") -> OK | C57: Terence_1 | D57: Tsang Tak Kin | E57: 20872 | F57: Tai Koo_3 Apita | G57: Mar/19-20,25 | H57: 3 | I57: 24 | J57: 60 | K57: =表格1[[#This Row],[Reg.Hrs]]*表格1[[#This Row],[$]] -> 1440 | L57: 11043 | N57: =IFERROR((IF(表格1[[#This Row],[Name.]]=工作表1!$E51,工作表1!$K51," ")*表格1[[#This Row],[Sales]])," ") -> 220.86 | O57: =IFERROR((IF(表格1[[#This Row],[Full Name.]]=工作表1!F51,工作表1!J51," ")*表格1[[#This Row],[Days]])," ") -> 0 | AG57: =SUM(表格1[[#This Row],[Commission (1% OR 2%)]:[Expenses/支出]])+表格1[[#This Row],[Basic]] -> 1660.86 | AH57: =ROUND(AG57,0) -> 1661 | AJ57: 1660.86 | AK57: =表格1[[#This Row],[Input]]-表格1[[#This Row],[Double check]] -> 0.14
A58: 51 | B58: =IF(表格1[[#This Row],[Full Name.]]=工作表1!F52,"OK") -> OK | C58: PoWan | D58: Ng Po Wan | E58: 20873 | F58: Kln Bay Demo Broadway | G58: Mar/1-9 | H58: 9 | I58: 72 | J58: 80 | K58: =表格1[[#This Row],[Reg.Hrs]]*表格1[[#This Row],[$]] -> 5760 | L58: 172594 | N58: =IFERROR((IF(表格1[[#This Row],[Name.]]=工作表1!$E52,工作表1!$K52," ")*表格1[[#This Row],[Sales]])," ") -> 3451.88 | O58: =IFERROR((IF(表格1[[#This Row],[Full Name.]]=工作表1!F52,工作表1!J52," ")*表格1[[#This Row],[Days]])," ") -> 0 | AF58: 1510 | AG58: =SUM(表格1[[#This Row],[Commission (1% OR 2%)]:[Expenses/支出]])+表格1[[#This Row],[Basic]] -> 10721.88 | AH58: =ROUND(AG58,0) -> 10722 | AJ58: 9211.88 | AK58: =表格1[[#This Row],[Input]]-表格1[[#This Row],[Double check]] -> 1510.12
A59: 52 | B59: =IF(表格1[[#This Row],[Full Name.]]=工作表1!F53,"OK") -> OK | C59: Maggie Ho_2 | D59: Ho Lai Kuen | E59: 20874 | F59: CWB Sogo | G59: Mar/16-17,20-21,23-24,26-27 | H59: 8 | I59: 64 | J59: 65 | K59: =表格1[[#This Row],[Reg.Hrs]]*表格1[[#This Row],[$]] -> 4160 | L59: 71785 | N59: =IFERROR((IF(表格1[[#This Row],[Name.]]=工作表1!$E53,工作表1!$K53," ")*表格1[[#This Row],[Sales]])," ") -> 1435.7 | O59: =IFERROR((IF(表格1[[#This Row],[Full Name.]]=工作表1!F53,工作表1!J53," ")*表格1[[#This Row],[Days]])," ") -> 0 | AG59: =SUM(表格1[[#This Row],[Commission (1% OR 2%)]:[Expenses/支出]])+表格1[[#This Row],[Basic]] -> 5595.7 | AH59: =ROUND(AG59,0) -> 5596 | AJ59: 5595.7 | AK59: =表格1[[#This Row],[Input]]-表格1[[#This Row],[Double check]] -> 0.3
A60: 53 | B60: =IF(表格1[[#This Row],[Full Name.]]=工作表1!F54,"OK") -> OK | C60: Ivy Wong_2 | D60: Wong Wai Chu | E60: Autopay | F60: TSW RS Tung Yuen | G60: Mar/6-9 | H60: 4 | I60: 35.5 | J60: 60 | K60: =表格1[[#This Row],[Reg.Hrs]]*表格1[[#This Row],[$]] -> 2130 | L60: 83810 | N60: =IFERROR((IF(表格1[[#This Row],[Name.]]=工作表1!$E54,工作表1!$K54," ")*表格1[[#This Row],[Sales]])," ") -> 1676.2 | O60: =IFERROR((IF(表格1[[#This Row],[Full Name.]]=工作表1!F54,工作表1!J54," ")*表格1[[#This Row],[Days]])," ") -> 0 | AG60: =SUM(表格1[[#This Row],[Commission (1% OR 2%)]:[Expenses/支出]])+表格1[[#This Row],[Basic]] -> 3806.2 | AH60: =ROUND(AG60,0) -> 3806 | AJ60: 3806.2 | AK60: =表格1[[#This Row],[Input]]-表格1[[#This Row],[Double check]] -> -0.2
A61: 54 | B61: =IF(表格1[[#This Row],[Full Name.]]=工作表1!F55,"OK") -> OK | C61: Ho_2 | D61: Kwan Tit Ho | E61: 20875 | F61: TC RS Tung Yuen | G61: Mar/20-23 | H61: 4 | I61: 32 | J61: 60 | K61: =表格1[[#This Row],[Reg.Hrs]]*表格1[[#This Row],[$]] -> 1920 | L61: 75226 | N61: =IFERROR((IF(表格1[[#This Row],[Name.]]=工作表1!$E55,工作表1!$K55," ")*表格1[[#This Row],[Sales]])," ") -> 1504.52 | O61: =IFERROR((IF(表格1[[#This Row],[Full Name.]]=工作表1!F55,工作表1!J55," ")*表格1[[#This Row],[Days]])," ") -> 0 | AG61: =SUM(表格1[[#This Row],[Commission (1% OR 2%)]:[Expenses/支出]])+表格1[[#This Row],[Basic]] -> 3424.52 | AH61: =ROUND(AG61,0) -> 3425 | AJ61: 3424.52 | AK61: =表格1[[#This Row],[Input]]-表格1[[#This Row],[Double check]] -> 0.48
A62: 55 | B62: =IF(表格1[[#This Row],[Full Name.]]=工作表1!F56,"OK") -> OK | C62: Terence_2 | D62: Tsang Tak Kin | E62: 20876 | F62: TM RS Fortress | G62: Mar/27-30 | H62: 4 | I62: 40 | J62: 60 | K62: =表格1[[#This Row],[Reg.Hrs]]*表格1[[#This Row],[$]] -> 2400 | L62: 542192 | N62: =IFERROR((IF(表格1[[#This Row],[Name.]]=工作表1!$E56,工作表1!$K56," ")*表格1[[#This Row],[Sales]])," ") -> 5421.92 | O62: =IFERROR((IF(表格1[[#This Row],[Full Name.]]=工作表1!F56,工作表1!J56," ")*表格1[[#This Row],[Days]])," ") -> 0 | AG62: =SUM(表格1[[#This Row],[Commission (1% OR 2%)]:[Expenses/支出]])+表格1[[#This Row],[Basic]] -> 7821.92 | AH62: =ROUND(AG62,0) -> 7822 | AJ62: 7821.92 | AK62: =表格1[[#This Row],[Input]]-表格1[[#This Row],[Double check]] -> 0.08
A63: 56 | B63: =IF(表格1[[#This Row],[Full Name.]]=工作表1!F57,"OK") -> OK | C63: Ho_1 | D63: Kwan Tit Ho | E63: 20877 | F63: Tsuen Wan Aeon | G63: Mar/1-3,5-12,14-15 | H63: 13 | I63: 104 | J63: 60 | K63: =表格1[[#This Row],[Reg.Hrs]]*表格1[[#This Row],[$]] -> 6240 | L63: 111304 | N63: =IFERROR((IF(表格1[[#This Row],[Name.]]=工作表1!$E57,工作表1!$K57," ")*表格1[[#This Row],[Sales]])," ") -> 2226.08 | O63: =IFERROR((IF(表格1[[#This Row],[Full Name.]]=工作表1!F57,工作表1!J57," ")*表格1[[#This Row],[Days]])," ") -> 0 | AG63: =SUM(表格1[[#This Row],[Commission (1% OR 2%)]:[Expenses/支出]])+表格1[[#This Row],[Basic]] -> 8466.08 | AH63: =ROUND(AG63,0) -> 8466 | AJ63: 8466.08 | AK63: =表格1[[#This Row],[Input]]-表格1[[#This Row],[Double check]] -> -0.08
A64: 57 | B64: =IF(表格1[[#This Row],[Full Name.]]=工作表1!F58,"OK") -> OK | C64: Winnie | D64: Lee Yee Wan | E64: 20878 | F64: Panda Aeon | G64: Mar/1,7-8,14-15 | H64: 5 | I64: 40 | J64: 60 | K64: =表格1[[#This Row],[Reg.Hrs]]*表格1[[#This Row],[$]] -> 2400 | L64: 66360 | N64: =IFERROR((IF(表格1[[#This Row],[Name.]]=工作表1!$E58,工作表1!$K58," ")*表格1[[#This Row],[Sales]])," ") -> 1327.2 | O64: =IFERROR((IF(表格1[[#This Row],[Full Name.]]=工作表1!F58,工作表1!J58," ")*表格1[[#This Row],[Days]])," ") -> 0 | AG64: =SUM(表格1[[#This Row],[Commission (1% OR 2%)]:[Expenses/支出]])+表格1[[#This Row],[Basic]] -> 3727.2 | AH64: =ROUND(AG64,0) -> 3727 | AJ64: 3727.2 | AK64: =表格1[[#This Row],[Input]]-表格1[[#This Row],[Double check]] -> -0.2
A65: 58 | B65: =IF(表格1[[#This Row],[Full Name.]]=工作表1!F59,"OK") -> OK | C65: Wendy Lau | D65: Lau Kwan Wai | E65: 20879 | F65: LCK Aeon | G65: Mar/1,7-8,14-15 | H65: 5 | I65: 40 | J65: 60 | K65: =表格1[[#This Row],[Reg.Hrs]]*表格1[[#This Row],[$]] -> 2400 | L65: 79014 | N65: =IFERROR((IF(表格1[[#This Row],[Name.]]=工作表1!$E59,工作表1!$K59," ")*表格1[[#This Row],[Sales]])," ") -> 1580.28 | O65: =IFERROR((IF(表格1[[#This Row],[Full Name.]]=工作表1!F59,工作表1!J59," ")*表格1[[#This Row],[Days]])," ") -> 0 | AG65: =SUM(表格1[[#This Row],[Commission (1% OR 2%)]:[Expenses/支出]])+表格1[[#This Row],[Basic]] -> 3980.28 | AH65: =ROUND(AG65,0) -> 3980 | AJ65: 3980.28 | AK65: =表格1[[#This Row],[Input]]-表格1[[#This Row],[Double check]] -> -0.28
A66: 59 | B66: =IF(表格1[[#This Row],[Full Name.]]=工作表1!F60,"OK") -> OK | C66: Me | D66: Ngai Kong Ying | E66: Autopay | F66: Megabox Aeon | G66: Mar/1-4,6-10,12-15 | H66: 13 | I66: 104 | J66: 60 | K66: =表格1[[#This Row],[Reg.Hrs]]*表格1[[#This Row],[$]] -> 6240 | L66: 287112 | N66: =IFERROR((IF(表格1[[#This Row],[Name.]]=工作表1!$E60,工作表1!$K60," ")*表格1[[#This Row],[Sales]])," ") -> 5742.24 | O66: =IFERROR((IF(表格1[[#This Row],[Full Name.]]=工作表1!F60,工作表1!J60," ")*表格1[[#This Row],[Days]])," ") -> 0 | AG66: =SUM(表格1[[#This Row],[Commission (1% OR 2%)]:[Expenses/支出]])+表格1[[#This Row],[Basic]] -> 11982.24 | AH66: =ROUND(AG66,0) -> 11982 | AJ66: 11982.24 | AK66: =表格1[[#This Row],[Input]]-表格1[[#This Row],[Double check]] -> -0.24
A67: 60 | B67: =IF(表格1[[#This Row],[Full Name.]]=工作表1!F61,"OK") -> OK | C67: Pinky | D67: Cheung Yin Ping | E67: Autopay | F67: Yau Tong Aeon | G67: Mar/1,7-8,14-15 | H67: 5 | I67: 40 | J67: 60 | K67: =表格1[[#This Row],[Reg.Hrs]]*表格1[[#This Row],[$]] -> 2400 | L67: 10588 | N67: =IFERROR((IF(表格1[[#This Row],[Name.]]=工作表1!$E61,工作表1!$K61," ")*表格1[[#This Row],[Sales]])," ") -> 211.76 | O67: =IFERROR((IF(表格1[[#This Row],[Full Name.]]=工作表1!F61,工作表1!J61," ")*表格1[[#This Row],[Days]])," ") -> 0 | AG67: =SUM(表格1[[#This Row],[Commission (1% OR 2%)]:[Expenses/支出]])+表格1[[#This Row],[Basic]] -> 2611.76 | AH67: =ROUND(AG67,0) -> 2612 | AJ67: 2611.76 | AK67: =表格1[[#This Row],[Input]]-表格1[[#This Row],[Double check]] -> 0.24
A68: 61 | B68: =IF(表格1[[#This Row],[Full Name.]]=工作表1!F62,"OK") -> OK | C68: Maggie Ho_1 | D68: Ho Lai Kuen | E68: 20880 | F68: TKO Aeon | G68: Mar/1,7-8,14-15 | H68: 5 | I68: 40 | J68: 65 | K68: =表格1[[#This Row],[Reg.Hrs]]*表格1[[#This Row],[$]] -> 2600 | L68: 88772 | N68: =IFERROR((IF(表格1[[#This Row],[Name.]]=工作表1!$E62,工作表1!$K62," ")*表格1[[#This Row],[Sales]])," ") -> 1775.44 | O68: =IFERROR((IF(表格1[[#This Row],[Full Name.]]=工作表1!F62,工作表1!J62," ")*表格1[[#This Row],[Days]])," ") -> 0 | AG68: =SUM(表格1[[#This Row],[Commission (1% OR 2%)]:[Expenses/支出]])+表格1[[#This Row],[Basic]] -> 4375.44 | AH68: =ROUND(AG68,0) -> 4375 | AJ68: 4375.44 | AK68: =表格1[[#This Row],[Input]]-表格1[[#This Row],[Double check]] -> -0.44
A69: 62 | B69: =IF(表格1[[#This Row],[Full Name.]]=工作表1!F63,"OK") -> OK | C69: Eddy | D69: Chan Chi Tim | E69: 20881 | F69: Training_1 | G69: Mar/24 | H69: 1 | I69: 7 | J69: 50 | K69: =表格1[[#This Row],[Reg.Hrs]]*表格1[[#This Row],[$]] -> 350 | N69: =IFERROR((IF(表格1[[#This Row],[Name.]]=工作表1!$E63,工作表1!$K63," ")*表格1[[#This Row],[Sales]])," ") -> 0 | O69: =IFERROR((IF(表格1[[#This Row],[Full Name.]]=工作表1!F63,工作表1!J63," ")*表格1[[#This Row],[Days]])," ") -> 0 | AG69: =SUM(表格1[[#This Row],[Commission (1% OR 2%)]:[Expenses/支出]])+表格1[[#This Row],[Basic]] -> 350 | AH69: =ROUND(AG69,0) -> 350 | AJ69: 350 | AK69: =表格1[[#This Row],[Input]]-表格1[[#This Row],[Double check]] -> 0
A70: 63 | B70: =IF(表格1[[#This Row],[Full Name.]]=工作表1!F64,"OK") -> OK | C70: Jenny | D70: Pang Kam Chun | E70: Autopay | F70: Training_2 | G70: Mar/24 | H70: 1 | I70: 7 | J70: 50 | K70: =表格1[[#This Row],[Reg.Hrs]]*表格1[[#This Row],[$]] -> 350 | N70: =IFERROR((IF(表格1[[#This Row],[Name.]]=工作表1!$E64,工作表1!$K64," ")*表格1[[#This Row],[Sales]])," ") -> 0 | O70: =IFERROR((IF(表格1[[#This Row],[Full Name.]]=工作表1!F64,工作表1!J64," ")*表格1[[#This Row],[Days]])," ") -> 0 | AG70: =SUM(表格1[[#This Row],[Commission (1% OR 2%)]:[Expenses/支出]])+表格1[[#This Row],[Basic]] -> 350 | AH70: =ROUND(AG70,0) -> 350 | AJ70: 350 | AK70: =表格1[[#This Row],[Input]]-表格1[[#This Row],[Double check]] -> 0
A71: 64 | B71: =IF(表格1[[#This Row],[Full Name.]]=工作表1!F65,"OK") -> OK | C71: WanWah | D71: Chan Wan Wah | E71: 20882 | F71: Training_3 | G71: Mar/24 | H71: 1 | I71: 7 | J71: 50 | K71: =表格1[[#This Row],[Reg.Hrs]]*表格1[[#This Row],[$]] -> 350 | N71: =IFERROR((IF(表格1[[#This Row],[Name.]]=工作表1!$E65,工作表1!$K65," ")*表格1[[#This Row],[Sales]])," ") -> 0 | O71: =IFERROR((IF(表格1[[#This Row],[Full Name.]]=工作表1!F65,工作表1!J65," ")*表格1[[#This Row],[Days]])," ") -> 0 | AG71: =SUM(表格1[[#This Row],[Commission (1% OR 2%)]:[Expenses/支出]])+表格1[[#This Row],[Basic]] -> 350 | AH71: =ROUND(AG71,0) -> 350 | AJ71: 350 | AK71: =表格1[[#This Row],[Input]]-表格1[[#This Row],[Double check]] -> 0
A72: 24 | B72: =IF(表格1[[#This Row],[Full Name.]]=工作表1!F66,"OK") -> FALSE | C72: Hung | D72: Hui Man Hung | E72: 20889 | K72: =表格1[[#This Row],[Reg.Hrs]]*表格1[[#This Row],[$]] -> 0 | L72: 364140 | N72: =表格1[[#This Row],[Sales]]*2% -> 7282.8 | O72: =IFERROR((IF(表格1[[#This Row],[Full Name.]]=工作表1!F66,工作表1!J66," ")*表格1[[#This Row],[Days]])," ") | AG72: =SUM(表格1[[#This Row],[Commission (1% OR 2%)]:[Expenses/支出]])+表格1[[#This Row],[Basic]] -> 7282.8 | AH72: =ROUND(AG72,0) -> 7283 | AJ72: 0 | AK72: =表格1[[#This Row],[Input]]-表格1[[#This Row],[Double check]] -> 7283
A73: 46 | B73: =IF(表格1[[#This Row],[Full Name.]]=工作表1!F67,"OK") -> FALSE | C73: Connie | D73: Chan Siu Mui | E73: 20890 | K73: =表格1[[#This Row],[Reg.Hrs]]*表格1[[#This Row],[$]] -> 0 | L73: 102671 | N73: =表格1[[#This Row],[Sales]]*2% -> 2053.42 | O73: =IFERROR((IF(表格1[[#This Row],[Full Name.]]=工作表1!F67,工作表1!J67," ")*表格1[[#This Row],[Days]])," ") | AG73: =SUM(表格1[[#This Row],[Commission (1% OR 2%)]:[Expenses/支出]])+表格1[[#This Row],[Basic]] -> 2053.42 | AH73: =ROUND(AG73,0) -> 2053 | AJ73: 0 | AK73: =表格1[[#This Row],[Input]]-表格1[[#This Row],[Double check]] -> 2053
A74: 24 | B74: =IF(表格1[[#This Row],[Full Name.]]=工作表1!F68,"OK") -> FALSE | C74: Hung | D74: Hui Man Hung | E74: 20891 | K74: =表格1[[#This Row],[Reg.Hrs]]*表格1[[#This Row],[$]] -> 0 | N74: =IFERROR((IF(表格1[[#This Row],[Name.]]=工作表1!$E68,工作表1!$K68," ")*表格1[[#This Row],[Sales]])," ") | O74: =IFERROR((IF(表格1[[#This Row],[Full Name.]]=工作表1!F68,工作表1!J68," ")*表格1[[#This Row],[Days]])," ") | P74: 0 | Q74: 0 | R74: 0 | S74: 0 | T74: 0 | U74: 0 | V74: 0 | W74: 0 | X74: 0 | Y74: 0 | Z74: 0 | AA74: 0 | AB74: 0 | AC74: 0 | AD74: 500 | AE74: 1000 | AG74: =SUM(表格1[[#This Row],[Commission (1% OR 2%)]:[Expenses/支出]])+表格1[[#This Row],[Basic]] -> 1500 | AH74: =ROUND(AG74,0) -> 1500 | AJ74: 0 | AK74: =表格1[[#This Row],[Input]]-表格1[[#This Row],[Double check]] -> 1500
B75: =IF(表格1[[#This Row],[Full Name.]]=工作表1!F69,"OK") -> FALSE | C75: Kandy | D75: Sin Hoi Yam | E75: 20907 | F75: TW Fortress | G75: Mar/1,7-8,21-22,28-29 | I75: 56 | J75: 5 | K75: =表格1[[#This Row],[Reg.Hrs]]*表格1[[#This Row],[$]] -> 280 | N75: =IFERROR((IF(表格1[[#This Row],[Name.]]=工作表1!$E69,工作表1!$K69," ")*表格1[[#This Row],[Sales]])," ") | O75: =IFERROR((IF(表格1[[#This Row],[Full Name.]]=工作表1!F69,工作表1!J69," ")*表格1[[#This Row],[Days]])," ") | AG75: =SUM(表格1[[#This Row],[Commission (1% OR 2%)]:[Expenses/支出]])+表格1[[#This Row],[Basic]] -> 280 | AH75: =ROUND(AG75,0) -> 280 | AJ75: 0 | AK75: =表格1[[#This Row],[Input]]-表格1[[#This Row],[Double check]] -> 280
B76: =IF(表格1[[#This Row],[Full Name.]]=工作表1!F70,"OK") -> FALSE | C76: Ho_3 | D76: Kwan Tit Ho | E76: 20962 | F76: 補差價 | I76: 32 | J76: 5 | K76: =表格1[[#This Row],[Reg.Hrs]]*表格1[[#This Row],[$]] -> 160 | N76: =IFERROR((IF(表格1[[#This Row],[Name.]]=工作表1!$E70,工作表1!$K70," ")*表格1[[#This Row],[Sales]])," ") | O76: =IFERROR((IF(表格1[[#This Row],[Full Name.]]=工作表1!F70,工作表1!J70," ")*表格1[[#This Row],[Days]])," ") | AG76: =SUM(表格1[[#This Row],[Commission (1% OR 2%)]:[Expenses/支出]])+表格1[[#This Row],[Basic]] -> 160 | AH76: =ROUND(AG76,0) -> 160 | AJ76: 0 | AK76: =表格1[[#This Row],[Input]]-表格1[[#This Row],[Double check]] -> 160
B77: =IF(表格1[[#This Row],[Full Name.]]=工作表1!F71,"OK") -> FALSE | C77: Hazel | D77: Tan Xingfang | E77: 21015 | G77: 補佣 | K77: =表格1[[#This Row],[Reg.Hrs]]*表格1[[#This Row],[$]] -> 0 | N77: 313.2 | O77: =IFERROR((IF(表格1[[#This Row],[Full Name.]]=工作表1!F71,工作表1!J71," ")*表格1[[#This Row],[Days]])," ") | AG77: =SUM(表格1[[#This Row],[Commission (1% OR 2%)]:[Expenses/支出]])+表格1[[#This Row],[Basic]] -> 313.2 | AH77: =ROUND(AG77,0) -> 313 | AJ77: 0 | AK77: =表格1[[#This Row],[Input]]-表格1[[#This Row],[Double check]] -> 313
B78: =IF(表格1[[#This Row],[Full Name.]]=工作表1!F72,"OK") -> OK | K78: =表格1[[#This Row],[Reg.Hrs]]*表格1[[#This Row],[$]] -> 0 | N78: =IFERROR((IF(表格1[[#This Row],[Name.]]=工作表1!$E68,工作表1!$K68," ")*表格1[[#This Row],[Sales]])," ") -> 0 | O78: =IFERROR((IF(表格1[[#This Row],[Full Name.]]=工作表1!F72,工作表1!J72," ")*表格1[[#This Row],[Days]])," ") -> 0 | AG78: =SUM(表格1[[#This Row],[Commission (1% OR 2%)]:[Expenses/支出]])+表格1[[#This Row],[Basic]] -> 0 | AH78: =ROUND(AG78,0) -> 0 | AJ78: 0 | AK78: =表格1[[#This Row],[Input]]-表格1[[#This Row],[Double check]] -> 0
B79: =IF(表格1[[#This Row],[Full Name.]]=工作表1!F73,"OK") -> OK | K79: =表格1[[#This Row],[Reg.Hrs]]*表格1[[#This Row],[$]] -> 0 | N79: =IFERROR((IF(表格1[[#This Row],[Name.]]=工作表1!$E69,工作表1!$K69," ")*表格1[[#This Row],[Sales]])," ") -> 0 | O79: =IFERROR((IF(表格1[[#This Row],[Full Name.]]=工作表1!F73,工作表1!J73," ")*表格1[[#This Row],[Days]])," ") -> 0 | AG79: =SUM(表格1[[#This Row],[Commission (1% OR 2%)]:[Expenses/支出]])+表格1[[#This Row],[Basic]] -> 0 | AH79: =ROUND(AG79,0) -> 0 | AJ79: 0 | AK79: =表格1[[#This Row],[Input]]-表格1[[#This Row],[Double check]] -> 0
B80: =IF(表格1[[#This Row],[Full Name.]]=工作表1!F74,"OK") -> OK | K80: =表格1[[#This Row],[Reg.Hrs]]*表格1[[#This Row],[$]] -> 0 | N80: =IFERROR((IF(表格1[[#This Row],[Name.]]=工作表1!$E70,工作表1!$K70," ")*表格1[[#This Row],[Sales]])," ") -> 0 | O80: =IFERROR((IF(表格1[[#This Row],[Full Name.]]=工作表1!F74,工作表1!J74," ")*表格1[[#This Row],[Days]])," ") -> 0 | AG80: =SUM(表格1[[#This Row],[Commission (1% OR 2%)]:[Expenses/支出]])+表格1[[#This Row],[Basic]] -> 0 | AH80: =ROUND(AG80,0) -> 0 | AK80: =表格1[[#This Row],[Input]]-表格1[[#This Row],[Double check]] -> 0
B81: =IF(表格1[[#This Row],[Full Name.]]=工作表1!F75,"OK") -> OK | K81: =表格1[[#This Row],[Reg.Hrs]]*表格1[[#This Row],[$]] -> 0 | N81: =IFERROR((IF(表格1[[#This Row],[Name.]]=工作表1!$E71,工作表1!$K71," ")*表格1[[#This Row],[Sales]])," ") -> 0 | O81: =IFERROR((IF(表格1[[#This Row],[Full Name.]]=工作表1!F75,工作表1!J75," ")*表格1[[#This Row],[Days]])," ") -> 0 | AG81: =SUM(表格1[[#This Row],[Commission (1% OR 2%)]:[Expenses/支出]])+表格1[[#This Row],[Basic]] -> 0 | AH81: =ROUND(AG81,0) -> 0 | AK81: =表格1[[#This Row],[Input]]-表格1[[#This Row],[Double check]] -> 0
B82: =IF(表格1[[#This Row],[Full Name.]]=工作表1!F76,"OK") -> OK | K82: =表格1[[#This Row],[Reg.Hrs]]*表格1[[#This Row],[$]] -> 0 | N82: =IFERROR((IF(表格1[[#This Row],[Name.]]=工作表1!$E72,工作表1!$K72," ")*表格1[[#This Row],[Sales]])," ") -> 0 | O82: =IFERROR((IF(表格1[[#This Row],[Full Name.]]=工作表1!F72,工作表1!J72," ")*表格1[[#This Row],[Days]])," ") -> 0 | AG82: =SUM(表格1[[#This Row],[Commission (1% OR 2%)]:[Expenses/支出]])+表格1[[#This Row],[Basic]] -> 0 | AH82: =ROUND(AG82,0) -> 0 | AK82: =表格1[[#This Row],[Input]]-表格1[[#This Row],[Double check]] -> 0
B83: =IF(表格1[[#This Row],[Full Name.]]=工作表1!F77,"OK") -> OK | K83: =表格1[[#This Row],[Reg.Hrs]]*表格1[[#This Row],[$]] -> 0 | N83: =IFERROR((IF(表格1[[#This Row],[Name.]]=工作表1!$E73,工作表1!$K73," ")*表格1[[#This Row],[Sales]])," ") -> 0 | O83: =IFERROR((IF(表格1[[#This Row],[Full Name.]]=工作表1!F74,工作表1!J74," ")*表格1[[#This Row],[Days]])," ") -> 0 | AG83: =SUM(表格1[[#This Row],[Commission (1% OR 2%)]:[Expenses/支出]])+表格1[[#This Row],[Basic]] -> 0 | AH83: =ROUND(AG83,0) -> 0 | AK83: =表格1[[#This Row],[Input]]-表格1[[#This Row],[Double check]] -> 0
B84: =IF(表格1[[#This Row],[Full Name.]]=工作表1!F78,"OK") -> OK | K84: =表格1[[#This Row],[Reg.Hrs]]*表格1[[#This Row],[$]] -> 0 | N84: =IFERROR((IF(表格1[[#This Row],[Name.]]=工作表1!$E74,工作表1!$K74," ")*表格1[[#This Row],[Sales]])," ") -> 0 | O84: =IFERROR((IF(表格1[[#This Row],[Full Name.]]=工作表1!F75,工作表1!J75," ")*表格1[[#This Row],[Days]])," ") -> 0 | AG84: =SUM(表格1[[#This Row],[Commission (1% OR 2%)]:[Expenses/支出]])+表格1[[#This Row],[Basic]] -> 0 | AH84: =ROUND(AG84,0) -> 0 | AK84: =表格1[[#This Row],[Input]]-表格1[[#This Row],[Double check]] -> 0
B85: =IF(表格1[[#This Row],[Full Name.]]=工作表1!F79,"OK") -> OK | K85: =表格1[[#This Row],[Reg.Hrs]]*表格1[[#This Row],[$]] -> 0 | N85: =IFERROR((IF(表格1[[#This Row],[Name.]]=工作表1!$E75,工作表1!$K75," ")*表格1[[#This Row],[Sales]])," ") -> 0 | O85: =IFERROR((IF(表格1[[#This Row],[Full Name.]]=工作表1!F76,工作表1!J76," ")*表格1[[#This Row],[Days]])," ") -> 0 | AG85: =SUM(表格1[[#This Row],[Commission (1% OR 2%)]:[Expenses/支出]])+表格1[[#This Row],[Basic]] -> 0 | AH85: =ROUND(AG85,0) -> 0 | AK85: =表格1[[#This Row],[Input]]-表格1[[#This Row],[Double check]] -> 0
B86: =IF(表格1[[#This Row],[Full Name.]]=工作表1!F80,"OK") -> OK | K86: =表格1[[#This Row],[Reg.Hrs]]*表格1[[#This Row],[$]] -> 0 | N86: =IFERROR((IF(表格1[[#This Row],[Name.]]=工作表1!$E76,工作表1!$K76," ")*表格1[[#This Row],[Sales]])," ") -> 0 | O86: =IFERROR((IF(表格1[[#This Row],[Full Name.]]=工作表1!F77,工作表1!J77," ")*表格1[[#This Row],[Days]])," ") -> 0 | AG86: =SUM(表格1[[#This Row],[Commission (1% OR 2%)]:[Expenses/支出]])+表格1[[#This Row],[Basic]] -> 0 | AH86: =ROUND(AG86,0) -> 0 | AK86: =表格1[[#This Row],[Input]]-表格1[[#This Row],[Double check]] -> 0
B87: =IF(表格1[[#This Row],[Full Name.]]=工作表1!F81,"OK") -> OK | K87: =表格1[[#This Row],[Reg.Hrs]]*表格1[[#This Row],[$]] -> 0 | N87: =IFERROR((IF(表格1[[#This Row],[Name.]]=工作表1!$E77,工作表1!$K77," ")*表格1[[#This Row],[Sales]])," ") -> 0 | O87: =IFERROR((IF(表格1[[#This Row],[Full Name.]]=工作表1!F78,工作表1!J78," ")*表格1[[#This Row],[Days]])," ") -> 0 | AG87: =SUM(表格1[[#This Row],[Commission (1% OR 2%)]:[Expenses/支出]])+表格1[[#This Row],[Basic]] -> 0 | AH87: =ROUND(AG87,0) -> 0 | AK87: =表格1[[#This Row],[Input]]-表格1[[#This Row],[Double check]] -> 0
B88: =IF(表格1[[#This Row],[Full Name.]]=工作表1!F82,"OK") -> OK | K88: =表格1[[#This Row],[Reg.Hrs]]*表格1[[#This Row],[$]] -> 0 | N88: =IFERROR((IF(表格1[[#This Row],[Name.]]=工作表1!$E78,工作表1!$K78," ")*表格1[[#This Row],[Sales]])," ") -> 0 | O88: =IFERROR((IF(表格1[[#This Row],[Full Name.]]=工作表1!F79,工作表1!J79," ")*表格1[[#This Row],[Days]])," ") -> 0 | AG88: =SUM(表格1[[#This Row],[Commission (1% OR 2%)]:[Expenses/支出]])+表格1[[#This Row],[Basic]] -> 0 | AH88: =ROUND(AG88,0) -> 0 | AK88: =表格1[[#This Row],[Input]]-表格1[[#This Row],[Double check]] -> 0
B89: =IF(表格1[[#This Row],[Full Name.]]=工作表1!F83,"OK") -> OK | K89: =表格1[[#This Row],[Reg.Hrs]]*表格1[[#This Row],[$]] -> 0 | N89: =IFERROR((IF(表格1[[#This Row],[Name.]]=工作表1!$E79,工作表1!$K79," ")*表格1[[#This Row],[Sales]])," ") -> 0 | O89: =IFERROR((IF(表格1[[#This Row],[Full Name.]]=工作表1!F80,工作表1!J80," ")*表格1[[#This Row],[Days]])," ") | AG89: =SUM(表格1[[#This Row],[Commission (1% OR 2%)]:[Expenses/支出]])+表格1[[#This Row],[Basic]] -> 0 | AH89: =ROUND(AG89,0) -> 0 | AK89: =表格1[[#This Row],[Input]]-表格1[[#This Row],[Double check]] -> 0

Sheet 工作表1
A1: Name | B1: Full Name | E1: Name1 | F1: Full Name1 | G1: Shop | H1: No | I1: $$$ | J1: Allowance | K1: % | L1: "Total" No. | M1: 欄2 | N1: 欄3
A2: Amy Or | B2: Or Sim Kiu | E2: May C | F2: Cheng Muk Kiu | G2: Kornhill Aeon | H2: 1 | I2: 55 | J2: 30 | K2: 0.02 | L2: {=_xlfn._xlws.FILTER(表格1[No.],(表格1[Name.]=表格4[[#This Row],[Name1]])+(表格1[Name.]&"_1"=表格4[[#This Row],[Name1]])+(表格1[Name.]&"_2"=表格4[[#This Row],[Name1]])+(表格1[Name.]&"_3"=表格4[[#This Row],[Name1]])+(表格1[Name.]&"_4"=表格4[[#This Row],[Name1]])+(表格1[Name.]&"_5"=表格4[[#This Row],[Name1]]))} -> 1 | M2: =IF(表格4[[#This Row],["Total" No.]]=表格4[[#This Row],[No]],表格4[[#This Row],[No]],"F") -> 1 | N2: =COUNTIF(表格1[No.],表格4[[#This Row],["Total" No.]]) -> 1
A3: Anita | B3: Chan Siu Kuen | E3: Ivy Wong_1 | F3: Wong Wai Chu | G3: Vcity_1 Fortress | H3: 2 | I3: 60 | J3: 0 | K3: 0.02 | L3: {=_xlfn._xlws.FILTER(表格1[No.],(表格1[Name.]=表格4[[#This Row],[Name1]])+(表格1[Name.]&"_1"=表格4[[#This Row],[Name1]])+(表格1[Name.]&"_2"=表格4[[#This Row],[Name1]])+(表格1[Name.]&"_3"=表格4[[#This Row],[Name1]])+(表格1[Name.]&"_4"=表格4[[#This Row],[Name1]])+(表格1[Name.]&"_5"=表格4[[#This Row],[Name1]]))} -> 2 | M3: =IF(表格4[[#This Row],["Total" No.]]=表格4[[#This Row],[No]],表格4[[#This Row],[No]],"F") -> 2 | N3: =COUNTIF(表格1[No.],表格4[[#This Row],["Total" No.]]) -> 1
A4: Cindy | B4: Ng Mei Han | E4: Kit_3 | F4: Li Wenjie | G4: Vcity_2 Fortress | H4: 3 | I4: 60 | K4: 0.02 | L4: {=_xlfn._xlws.FILTER(表格1[No.],(表格1[Name.]=表格4[[#This Row],[Name1]])+(表格1[Name.]&"_1"=表格4[[#This Row],[Name1]])+(表格1[Name.]&"_2"=表格4[[#This Row],[Name1]])+(表格1[Name.]&"_3"=表格4[[#This Row],[Name1]])+(表格1[Name.]&"_4"=表格4[[#This Row],[Name1]])+(表格1[Name.]&"_5"=表格4[[#This Row],[Name1]]))} -> 3 | M4: =IF(表格4[[#This Row],["Total" No.]]=表格4[[#This Row],[No]],表格4[[#This Row],[No]],"F") -> 3 | N4: =COUNTIF(表格1[No.],表格4[[#This Row],["Total" No.]]) -> 1
A5: Coco | B5: Yuen Lai Ying | E5: Vicky L | F5: Leung Ching | G5: Diamond Hill Fortress | H5: 4 | I5: 60 | J5: 0 | K5: 0.02 | L5: {=_xlfn._xlws.FILTER(表格1[No.],(表格1[Name.]=表格4[[#This Row],[Name1]])+(表格1[Name.]&"_1"=表格4[[#This Row],[Name1]])+(表格1[Name.]&"_2"=表格4[[#This Row],[Name1]])+(表格1[Name.]&"_3"=表格4[[#This Row],[Name1]])+(表格1[Name.]&"_4"=表格4[[#This Row],[Name1]])+(表格1[Name.]&"_5"=表格4[[#This Row],[Name1]]))} -> 4 | M5: =IF(表格4[[#This Row],["Total" No.]]=表格4[[#This Row],[No]],表格4[[#This Row],[No]],"F") -> 4 | N5: =COUNTIF(表格1[No.],表格4[[#This Row],["Total" No.]]) -> 1
A6: Connie | B6: Chan Siu Mui | E6: Michelle | F6: Lo Muk Chun | G6: Good Hope Fortress | H6: 5 | I6: 60 | J6: 0 | K6: 0.02 | L6: {=_xlfn._xlws.FILTER(表格1[No.],(表格1[Name.]=表格4[[#This Row],[Name1]])+(表格1[Name.]&"_1"=表格4[[#This Row],[Name1]])+(表格1[Name.]&"_2"=表格4[[#This Row],[Name1]])+(表格1[Name.]&"_3"=表格4[[#This Row],[Name1]])+(表格1[Name.]&"_4"=表格4[[#This Row],[Name1]])+(表格1[Name.]&"_5"=表格4[[#This Row],[Name1]]))} -> 5 | M6: =IF(表格4[[#This Row],["Total" No.]]=表格4[[#This Row],[No]],表格4[[#This Row],[No]],"F") -> 5 | N6: =COUNTIF(表格1[No.],表格4[[#This Row],["Total" No.]]) -> 1
A7: Daisy | B7: Yeung Kwai Lin | E7: Jessica | F7: Chiu Kan | G7: Whampoa Aeon | H7: 6 | I7: 55 | J7: 80 | K7: 0.02 | L7: {=_xlfn._xlws.FILTER(表格1[No.],(表格1[Name.]=表格4[[#This Row],[Name1]])+(表格1[Name.]&"_1"=表格4[[#This Row],[Name1]])+(表格1[Name.]&"_2"=表格4[[#This Row],[Name1]])+(表格1[Name.]&"_3"=表格4[[#This Row],[Name1]])+(表格1[Name.]&"_4"=表格4[[#This Row],[Name1]])+(表格1[Name.]&"_5"=表格4[[#This Row],[Name1]]))} -> 6 | M7: =IF(表格4[[#This Row],["Total" No.]]=表格4[[#This Row],[No]],表格4[[#This Row],[No]],"F") -> 6 | N7: =COUNTIF(表格1[No.],表格4[[#This Row],["Total" No.]]) -> 1
A8: Donnie | B8: Chau Chi Wah | E8: Kitty Yeung | F8: Yeung Lai Shan | G8: TKW Suning | H8: 7 | I8: 60 | J8: 0 | K8: 0.02 | L8: {=_xlfn._xlws.FILTER(表格1[No.],(表格1[Name.]=表格4[[#This Row],[Name1]])+(表格1[Name.]&"_1"=表格4[[#This Row],[Name1]])+(表格1[Name.]&"_2"=表格4[[#This Row],[Name1]])+(表格1[Name.]&"_3"=表格4[[#This Row],[Name1]])+(表格1[Name.]&"_4"=表格4[[#This Row],[Name1]])+(表格1[Name.]&"_5"=表格4[[#This Row],[Name1]]))} -> 7 | M8: =IF(表格4[[#This Row],["Total" No.]]=表格4[[#This Row],[No]],表格4[[#This Row],[No]],"F") -> 7 | N8: =COUNTIF(表格1[No.],表格4[[#This Row],["Total" No.]]) -> 1
A9: Emma | B9: Ng Yuk Ying | E9: Amy Or_1 | F9: Or Sim Kiu | G9: Tai koo Broadway | H9: 8 | I9: 55 | J9: 30 | K9: 0.02 | L9: {=_xlfn._xlws.FILTER(表格1[No.],(表格1[Name.]=表格4[[#This Row],[Name1]])+(表格1[Name.]&"_1"=表格4[[#This Row],[Name1]])+(表格1[Name.]&"_2"=表格4[[#This Row],[Name1]])+(表格1[Name.]&"_3"=表格4[[#This Row],[Name1]])+(表格1[Name.]&"_4"=表格4[[#This Row],[Name1]])+(表格1[Name.]&"_5"=表格4[[#This Row],[Name1]]))} -> 8 | M9: =IF(表格4[[#This Row],["Total" No.]]=表格4[[#This Row],[No]],表格4[[#This Row],[No]],"F") -> 8 | N9: =COUNTIF(表格1[No.],表格4[[#This Row],["Total" No.]]) -> 1
A10: Fong | B10: Ng Nga Fong | E10: Fong_1 | F10: Ng Nga Fong | G10: Diamond Hill_1 Broadway | H10: 9 | I10: 60 | J10: 0 | K10: 0.02 | L10: {=_xlfn._xlws.FILTER(表格1[No.],(表格1[Name.]=表格4[[#This Row],[Name1]])+(表格1[Name.]&"_1"=表格4[[#This Row],[Name1]])+(表格1[Name.]&"_2"=表格4[[#This Row],[Name1]])+(表格1[Name.]&"_3"=表格4[[#This Row],[Name1]])+(表格1[Name.]&"_4"=表格4[[#This Row],[Name1]])+(表格1[Name.]&"_5"=表格4[[#This Row],[Name1]]))} -> 9 | M10: =IF(表格4[[#This Row],["Total" No.]]=表格4[[#This Row],[No]],表格4[[#This Row],[No]],"F") -> 9 | N10: =COUNTIF(表格1[No.],表格4[[#This Row],["Total" No.]]) -> 1
A11: Gloria | B11: Yeung Chor Mui | E11: Mui Chan_2 | F11: Chan So Mui | G11: Diamond Hill_2 Broadway | H11: 10 | I11: 60 | J11: 0 | K11: 0.02 | L11: {=_xlfn._xlws.FILTER(表格1[No.],(表格1[Name.]=表格4[[#This Row],[Name1]])+(表格1[Name.]&"_1"=表格4[[#This Row],[Name1]])+(表格1[Name.]&"_2"=表格4[[#This Row],[Name1]])+(表格1[Name.]&"_3"=表格4[[#This Row],[Name1]])+(表格1[Name.]&"_4"=表格4[[#This Row],[Name1]])+(表格1[Name.]&"_5"=表格4[[#This Row],[Name1]]))} -> 10 | M11: =IF(表格4[[#This Row],["Total" No.]]=表格4[[#This Row],[No]],表格4[[#This Row],[No]],"F") -> 10 | N11: =COUNTIF(表格1[No.],表格4[[#This Row],["Total" No.]]) -> 1
A12: Grace | B12: Mok Choi Lin | E12: Shan_1 | F12: Chiu Fung Shan | G12: TW_1 Citistore | H12: 11 | I12: 60 | J12: 0 | K12: 0.02 | L12: {=_xlfn._xlws.FILTER(表格1[No.],(表格1[Name.]=表格4[[#This Row],[Name1]])+(表格1[Name.]&"_1"=表格4[[#This Row],[Name1]])+(表格1[Name.]&"_2"=表格4[[#This Row],[Name1]])+(表格1[Name.]&"_3"=表格4[[#This Row],[Name1]])+(表格1[Name.]&"_4"=表格4[[#This Row],[Name1]])+(表格1[Name.]&"_5"=表格4[[#This Row],[Name1]]))} -> 11 | M12: =IF(表格4[[#This Row],["Total" No.]]=表格4[[#This Row],[No]],表格4[[#This Row],[No]],"F") -> 11 | N12: =COUNTIF(表格1[No.],表格4[[#This Row],["Total" No.]]) -> 1
A13: Happy | B13: Chun Yin Ling | E13: Wendy Wong_1 | F13: Wong Lai Ying | G13: TW_2 Citistore | H13: 12 | I13: 60 | J13: 0 | K13: 0.02 | L13: {=_xlfn._xlws.FILTER(表格1[No.],(表格1[Name.]=表格4[[#This Row],[Name1]])+(表格1[Name.]&"_1"=表格4[[#This Row],[Name1]])+(表格1[Name.]&"_2"=表格4[[#This Row],[Name1]])+(表格1[Name.]&"_3"=表格4[[#This Row],[Name1]])+(表格1[Name.]&"_4"=表格4[[#This Row],[Name1]])+(表格1[Name.]&"_5"=表格4[[#This Row],[Name1]]))} -> 12 | M13: =IF(表格4[[#This Row],["Total" No.]]=表格4[[#This Row],[No]],表格4[[#This Row],[No]],"F") -> 12 | N13: =COUNTIF(表格1[No.],表格4[[#This Row],["Total" No.]]) -> 1
A14: Ho | B14: Kwan Tit Ho | E14: Mandy | F14: Ho Lai Sim | G14: TW_3 Citistore | H14: 13 | I14: 60 | J14: 0 | K14: 0.02 | L14: {=_xlfn._xlws.FILTER(表格1[No.],(表格1[Name.]=表格4[[#This Row],[Name1]])+(表格1[Name.]&"_1"=表格4[[#This Row],[Name1]])+(表格1[Name.]&"_2"=表格4[[#This Row],[Name1]])+(表格1[Name.]&"_3"=表格4[[#This Row],[Name1]])+(表格1[Name.]&"_4"=表格4[[#This Row],[Name1]])+(表格1[Name.]&"_5"=表格4[[#This Row],[Name1]]))} -> 13 | M14: =IF(表格4[[#This Row],["Total" No.]]=表格4[[#This Row],[No]],表格4[[#This Row],[No]],"F") -> 13 | N14: =COUNTIF(表格1[No.],表格4[[#This Row],["Total" No.]]) -> 1
A15: Hung | B15: Hui Man Hung | E15: Shan_2 | F15: Chiu Fung Shan | G15: TW RS_1 Citistore | H15: 14 | I15: 60 | J15: 0 | K15: 0.02 | L15: {=_xlfn._xlws.FILTER(表格1[No.],(表格1[Name.]=表格4[[#This Row],[Name1]])+(表格1[Name.]&"_1"=表格4[[#This Row],[Name1]])+(表格1[Name.]&"_2"=表格4[[#This Row],[Name1]])+(表格1[Name.]&"_3"=表格4[[#This Row],[Name1]])+(表格1[Name.]&"_4"=表格4[[#This Row],[Name1]])+(表格1[Name.]&"_5"=表格4[[#This Row],[Name1]]))} -> 14 | M15: =IF(表格4[[#This Row],["Total" No.]]=表格4[[#This Row],[No]],表格4[[#This Row],[No]],"F") -> 14 | N15: =COUNTIF(表格1[No.],表格4[[#This Row],["Total" No.]]) -> 1
A16: Iris | B16: Li Hang Yi | E16: Wendy Wong_2 | F16: Wong Lai Ying | G16: TW RS_2 Citistore | H16: 15 | I16: 60 | J16: 0 | K16: 0.01 | L16: {=_xlfn._xlws.FILTER(表格1[No.],(表格1[Name.]=表格4[[#This Row],[Name1]])+(表格1[Name.]&"_1"=表格4[[#This Row],[Name1]])+(表格1[Name.]&"_2"=表格4[[#This Row],[Name1]])+(表格1[Name.]&"_3"=表格4[[#This Row],[Name1]])+(表格1[Name.]&"_4"=表格4[[#This Row],[Name1]])+(表格1[Name.]&"_5"=表格4[[#This Row],[Name1]]))} -> 15 | M16: =IF(表格4[[#This Row],["Total" No.]]=表格4[[#This Row],[No]],表格4[[#This Row],[No]],"F") -> 15 | N16: =COUNTIF(表格1[No.],表格4[[#This Row],["Total" No.]]) -> 1
... A55: Pinky | B55: Cheung Yin Ping | E55: Ho_2 | F55: Kwan Tit Ho | G55: TC RS Tung Yuen | H55: 54 | I55: 60 | J55: 0 | K55: 0.02 | L55: {=_xlfn._xlws.FILTER(表格1[No.],(表格1[Name.]=表格4[[#This Row],[Name1]])+(表格1[Name.]&"_1"=表格4[[#This Row],[Name1]])+(表格1[Name.]&"_2"=表格4[[#This Row],[Name1]])+(表格1[Name.]&"_3"=表格4[[#This Row],[Name1]])+(表格1[Name.]&"_4"=表格4[[#This Row],[Name1]])+(表格1[Name.]&"_5"=表格4[[#This Row],[Name1]]))} -> 54 | M55: =IF(表格4[[#This Row],["Total" No.]]=表格4[[#This Row],[No]],表格4[[#This Row],[No]],"F") -> 54 | N55: =COUNTIF(表格1[No.],表格4[[#This Row],["Total" No.]]) -> 1
E56: Terence_2 | F56: Tsang Tak Kin | G56: TM RS Fortress | H56: 55 | I56: 60 | J56: 0 | K56: 0.01 | L56: {=_xlfn._xlws.FILTER(表格1[No.],(表格1[Name.]=表格4[[#This Row],[Name1]])+(表格1[Name.]&"_1"=表格4[[#This Row],[Name1]])+(表格1[Name.]&"_2"=表格4[[#This Row],[Name1]])+(表格1[Name.]&"_3"=表格4[[#This Row],[Name1]])+(表格1[Name.]&"_4"=表格4[[#This Row],[Name1]])+(表格1[Name.]&"_5"=表格4[[#This Row],[Name1]]))} -> 55 | M56: =IF(表格4[[#This Row],["Total" No.]]=表格4[[#This Row],[No]],表格4[[#This Row],[No]],"F") -> 55 | N56: =COUNTIF(表格1[No.],表格4[[#This Row],["Total" No.]]) -> 1
E57: Ho_1 | F57: Kwan Tit Ho | G57: Tsuen Wan Aeon | H57: 56 | I57: 60 | J57: 0 | K57: 0.02 | L57: {=_xlfn._xlws.FILTER(表格1[No.],(表格1[Name.]=表格4[[#This Row],[Name1]])+(表格1[Name.]&"_1"=表格4[[#This Row],[Name1]])+(表格1[Name.]&"_2"=表格4[[#This Row],[Name1]])+(表格1[Name.]&"_3"=表格4[[#This Row],[Name1]])+(表格1[Name.]&"_4"=表格4[[#This Row],[Name1]])+(表格1[Name.]&"_5"=表格4[[#This Row],[Name1]]))} -> 56 | M57: =IF(表格4[[#This Row],["Total" No.]]=表格4[[#This Row],[No]],表格4[[#This Row],[No]],"F") -> 56 | N57: =COUNTIF(表格1[No.],表格4[[#This Row],["Total" No.]]) -> 1
E58: Winnie | F58: Lee Yee Wan | G58: Panda Aeon | H58: 57 | I58: 60 | J58: 0 | K58: 0.02 | L58: {=_xlfn._xlws.FILTER(表格1[No.],(表格1[Name.]=表格4[[#This Row],[Name1]])+(表格1[Name.]&"_1"=表格4[[#This Row],[Name1]])+(表格1[Name.]&"_2"=表格4[[#This Row],[Name1]])+(表格1[Name.]&"_3"=表格4[[#This Row],[Name1]])+(表格1[Name.]&"_4"=表格4[[#This Row],[Name1]])+(表格1[Name.]&"_5"=表格4[[#This Row],[Name1]]))} -> 57 | M58: =IF(表格4[[#This Row],["Total" No.]]=表格4[[#This Row],[No]],表格4[[#This Row],[No]],"F") -> 57 | N58: =COUNTIF(表格1[No.],表格4[[#This Row],["Total" No.]]) -> 1
E59: Wendy Lau | F59: Lau Kwan Wai | G59: LCK Aeon | H59: 58 | I59: 60 | J59: 0 | K59: 0.02 | L59: {=_xlfn._xlws.FILTER(表格1[No.],(表格1[Name.]=表格4[[#This Row],[Name1]])+(表格1[Name.]&"_1"=表格4[[#This Row],[Name1]])+(表格1[Name.]&"_2"=表格4[[#This Row],[Name1]])+(表格1[Name.]&"_3"=表格4[[#This Row],[Name1]])+(表格1[Name.]&"_4"=表格4[[#This Row],[Name1]])+(表格1[Name.]&"_5"=表格4[[#This Row],[Name1]]))} -> 58 | M59: =IF(表格4[[#This Row],["Total" No.]]=表格4[[#This Row],[No]],表格4[[#This Row],[No]],"F") -> 58 | N59: =COUNTIF(表格1[No.],表格4[[#This Row],["Total" No.]]) -> 1
E60: Me | F60: Ngai Kong Ying | G60: Megabox Aeon | H60: 59 | I60: 60 | J60: 0 | K60: 0.02 | L60: {=_xlfn._xlws.FILTER(表格1[No.],(表格1[Name.]=表格4[[#This Row],[Name1]])+(表格1[Name.]&"_1"=表格4[[#This Row],[Name1]])+(表格1[Name.]&"_2"=表格4[[#This Row],[Name1]])+(表格1[Name.]&"_3"=表格4[[#This Row],[Name1]])+(表格1[Name.]&"_4"=表格4[[#This Row],[Name1]])+(表格1[Name.]&"_5"=表格4[[#This Row],[Name1]]))} -> 59 | M60: =IF(表格4[[#This Row],["Total" No.]]=表格4[[#This Row],[No]],表格4[[#This Row],[No]],"F") -> 59 | N60: =COUNTIF(表格1[No.],表格4[[#This Row],["Total" No.]]) -> 1
E61: Pinky | F61: Cheung Yin Ping | G61: Yau Tong Aeon | H61: 60 | I61: 60 | J61: 0 | K61: 0.02 | L61: {=_xlfn._xlws.FILTER(表格1[No.],(表格1[Name.]=表格4[[#This Row],[Name1]])+(表格1[Name.]&"_1"=表格4[[#This Row],[Name1]])+(表格1[Name.]&"_2"=表格4[[#This Row],[Name1]])+(表格1[Name.]&"_3"=表格4[[#This Row],[Name1]])+(表格1[Name.]&"_4"=表格4[[#This Row],[Name1]])+(表格1[Name.]&"_5"=表格4[[#This Row],[Name1]]))} -> 60 | M61: =IF(表格4[[#This Row],["Total" No.]]=表格4[[#This Row],[No]],表格4[[#This Row],[No]],"F") -> 60 | N61: =COUNTIF(表格1[No.],表格4[[#This Row],["Total" No.]]) -> 1
E62: Maggie Ho_1 | F62: Ho Lai Kuen | G62: TKO Aeon | H62: 61 | I62: 65 | J62: 0 | K62: 0.02 | L62: {=_xlfn._xlws.FILTER(表格1[No.],(表格1[Name.]=表格4[[#This Row],[Name1]])+(表格1[Name.]&"_1"=表格4[[#This Row],[Name1]])+(表格1[Name.]&"_2"=表格4[[#This Row],[Name1]])+(表格1[Name.]&"_3"=表格4[[#This Row],[Name1]])+(表格1[Name.]&"_4"=表格4[[#This Row],[Name1]])+(表格1[Name.]&"_5"=表格4[[#This Row],[Name1]]))} -> 61 | M62: =IF(表格4[[#This Row],["Total" No.]]=表格4[[#This Row],[No]],表格4[[#This Row],[No]],"F") -> 61 | N62: =COUNTIF(表格1[No.],表格4[[#This Row],["Total" No.]]) -> 1
E63: Eddy | F63: Chan Chi Tim | G63: Training_1 | H63: 62 | I63: 50 | J63: 0 | L63: {=_xlfn._xlws.FILTER(表格1[No.],(表格1[Name.]=表格4[[#This Row],[Name1]])+(表格1[Name.]&"_1"=表格4[[#This Row],[Name1]])+(表格1[Name.]&"_2"=表格4[[#This Row],[Name1]])+(表格1[Name.]&"_3"=表格4[[#This Row],[Name1]])+(表格1[Name.]&"_4"=表格4[[#This Row],[Name1]])+(表格1[Name.]&"_5"=表格4[[#This Row],[Name1]]))} -> 62 | M63: =IF(表格4[[#This Row],["Total" No.]]=表格4[[#This Row],[No]],表格4[[#This Row],[No]],"F") -> 62 | N63: =COUNTIF(表格1[No.],表格4[[#This Row],["Total" No.]]) -> 1
E64: Jenny | F64: Pang Kam Chun | G64: Training_2 | H64: 63 | I64: 50 | J64: 0 | L64: {=_xlfn._xlws.FILTER(表格1[No.],(表格1[Name.]=表格4[[#This Row],[Name1]])+(表格1[Name.]&"_1"=表格4[[#This Row],[Name1]])+(表格1[Name.]&"_2"=表格4[[#This Row],[Name1]])+(表格1[Name.]&"_3"=表格4[[#This Row],[Name1]])+(表格1[Name.]&"_4"=表格4[[#This Row],[Name1]])+(表格1[Name.]&"_5"=表格4[[#This Row],[Name1]]))} -> 63 | M64: =IF(表格4[[#This Row],["Total" No.]]=表格4[[#This Row],[No]],表格4[[#This Row],[No]],"F") -> 63 | N64: =COUNTIF(表格1[No.],表格4[[#This Row],["Total" No.]]) -> 1
E65: WanWah | F65: Chan Wan Wah | G65: Training_3 | H65: 64 | I65: 50 | J65: 0 | L65: {=_xlfn._xlws.FILTER(表格1[No.],(表格1[Name.]=表格4[[#This Row],[Name1]])+(表格1[Name.]&"_1"=表格4[[#This Row],[Name1]])+(表格1[Name.]&"_2"=表格4[[#This Row],[Name1]])+(表格1[Name.]&"_3"=表格4[[#This Row],[Name1]])+(表格1[Name.]&"_4"=表格4[[#This Row],[Name1]])+(表格1[Name.]&"_5"=表格4[[#This Row],[Name1]]))} -> 64 | M65: =IF(表格4[[#This Row],["Total" No.]]=表格4[[#This Row],[No]],表格4[[#This Row],[No]],"F") -> 64 | N65: =COUNTIF(表格1[No.],表格4[[#This Row],["Total" No.]]) -> 1
L66: {=_xlfn._xlws.FILTER(表格1[No.],(表格1[Name.]=表格4[[#This Row],[Name1]])+(表格1[Name.]&"_1"=表格4[[#This Row],[Name1]])+(表格1[Name.]&"_2"=表格4[[#This Row],[Name1]])+(表格1[Name.]&"_3"=表格4[[#This Row],[Name1]])+(表格1[Name.]&"_4"=表格4[[#This Row],[Name1]])+(表格1[Name.]&"_5"=表格4[[#This Row],[Name1]]))} -> #VALUE! | M66: =IF(表格4[[#This Row],["Total" No.]]=表格4[[#This Row],[No]],表格4[[#This Row],[No]],"F") -> #VALUE! | N66: =COUNTIF(表格1[No.],表格4[[#This Row],["Total" No.]]) -> 0
L67: {=_xlfn._xlws.FILTER(表格1[No.],(表格1[Name.]=表格4[[#This Row],[Name1]])+(表格1[Name.]&"_1"=表格4[[#This Row],[Name1]])+(表格1[Name.]&"_2"=表格4[[#This Row],[Name1]])+(表格1[Name.]&"_3"=表格4[[#This Row],[Name1]])+(表格1[Name.]&"_4"=表格4[[#This Row],[Name1]])+(表格1[Name.]&"_5"=表格4[[#This Row],[Name1]]))} -> #VALUE! | M67: =IF(表格4[[#This Row],["Total" No.]]=表格4[[#This Row],[No]],表格4[[#This Row],[No]],"F") -> #VALUE! | N67: =COUNTIF(表格1[No.],表格4[[#This Row],["Total" No.]]) -> 0
L68: {=_xlfn._xlws.FILTER(表格1[No.],(表格1[Name.]=表格4[[#This Row],[Name1]])+(表格1[Name.]&"_1"=表格4[[#This Row],[Name1]])+(表格1[Name.]&"_2"=表格4[[#This Row],[Name1]])+(表格1[Name.]&"_3"=表格4[[#This Row],[Name1]])+(表格1[Name.]&"_4"=表格4[[#This Row],[Name1]])+(表格1[Name.]&"_5"=表格4[[#This Row],[Name1]]))} -> #VALUE! | M68: =IF(表格4[[#This Row],["Total" No.]]=表格4[[#This Row],[No]],表格4[[#This Row],[No]],"F") -> #VALUE! | N68: =COUNTIF(表格1[No.],表格4[[#This Row],["Total" No.]]) -> 0
L69: {=_xlfn._xlws.FILTER(表格1[No.],(表格1[Name.]=表格4[[#This Row],[Name1]])+(表格1[Name.]&"_1"=表格4[[#This Row],[Name1]])+(表格1[Name.]&"_2"=表格4[[#This Row],[Name1]])+(表格1[Name.]&"_3"=表格4[[#This Row],[Name1]])+(表格1[Name.]&"_4"=表格4[[#This Row],[Name1]])+(表格1[Name.]&"_5"=表格4[[#This Row],[Name1]]))} -> #VALUE! | M69: =IF(表格4[[#This Row],["Total" No.]]=表格4[[#This Row],[No]],表格4[[#This Row],[No]],"F") -> #VALUE! | N69: =COUNTIF(表格1[No.],表格4[[#This Row],["Total" No.]]) -> 0
L70: {=_xlfn._xlws.FILTER(表格1[No.],(表格1[Name.]=表格4[[#This Row],[Name1]])+(表格1[Name.]&"_1"=表格4[[#This Row],[Name1]])+(表格1[Name.]&"_2"=表格4[[#This Row],[Name1]])+(表格1[Name.]&"_3"=表格4[[#This Row],[Name1]])+(表格1[Name.]&"_4"=表格4[[#This Row],[Name1]])+(表格1[Name.]&"_5"=表格4[[#This Row],[Name1]]))} -> #VALUE! | M70: =IF(表格4[[#This Row],["Total" No.]]=表格4[[#This Row],[No]],表格4[[#This Row],[No]],"F") -> #VALUE! | N70: =COUNTIF(表格1[No.],表格4[[#This Row],["Total" No.]]) -> 0
N71: =COUNTIF(表格1[No.],表格4[[#This Row],["Total" No.]]) -> 0
L72: {=_xlfn._xlws.FILTER(表格1[No.],(表格1[Name.]=表格4[[#This Row],[Name1]])+(表格1[Name.]&"_1"=表格4[[#This Row],[Name1]])+(表格1[Name.]&"_2"=表格4[[#This Row],[Name1]])+(表格1[Name.]&"_3"=表格4[[#This Row],[Name1]])+(表格1[Name.]&"_4"=表格4[[#This Row],[Name1]])+(表格1[Name.]&"_5"=表格4[[#This Row],[Name1]]))} -> #VALUE! | M72: =IF(表格4[[#This Row],["Total" No.]]=表格4[[#This Row],[No]],表格4[[#This Row],[No]],"F") -> #VALUE! | N72: =COUNTIF(表格1[No.],表格4[[#This Row],["Total" No.]]) -> 0
L73: {=_xlfn._xlws.FILTER(表格1[No.],(表格1[Name.]=表格4[[#This Row],[Name1]])+(表格1[Name.]&"_1"=表格4[[#This Row],[Name1]])+(表格1[Name.]&"_2"=表格4[[#This Row],[Name1]])+(表格1[Name.]&"_3"=表格4[[#This Row],[Name1]])+(表格1[Name.]&"_4"=表格4[[#This Row],[Name1]])+(表格1[Name.]&"_5"=表格4[[#This Row],[Name1]]))} -> #VALUE! | M73: =IF(表格4[[#This Row],["Total" No.]]=表格4[[#This Row],[No]],表格4[[#This Row],[No]],"F") -> #VALUE! | N73: =COUNTIF(表格1[No.],表格4[[#This Row],["Total" No.]]) -> 0
L74: {=_xlfn._xlws.FILTER(表格1[No.],(表格1[Name.]=表格4[[#This Row],[Name1]])+(表格1[Name.]&"_1"=表格4[[#This Row],[Name1]])+(表格1[Name.]&"_2"=表格4[[#This Row],[Name1]])+(表格1[Name.]&"_3"=表格4[[#This Row],[Name1]])+(表格1[Name.]&"_4"=表格4[[#This Row],[Name1]])+(表格1[Name.]&"_5"=表格4[[#This Row],[Name1]]))} -> #VALUE! | M74: =IF(表格4[[#This Row],["Total" No.]]=表格4[[#This Row],[No]],表格4[[#This Row],[No]],"F") -> #VALUE! | N74: =COUNTIF(表格1[No.],表格4[[#This Row],["Total" No.]]) -> 0
L75: {=_xlfn._xlws.FILTER(表格1[No.],(表格1[Name.]=表格4[[#This Row],[Name1]])+(表格1[Name.]&"_1"=表格4[[#This Row],[Name1]])+(表格1[Name.]&"_2"=表格4[[#This Row],[Name1]])+(表格1[Name.]&"_3"=表格4[[#This Row],[Name1]])+(表格1[Name.]&"_4"=表格4[[#This Row],[Name1]])+(表格1[Name.]&"_5"=表格4[[#This Row],[Name1]]))} -> #VALUE! | M75: =IF(表格4[[#This Row],["Total" No.]]=表格4[[#This Row],[No]],表格4[[#This Row],[No]],"F") -> #VALUE! | N75: =COUNTIF(表格1[No.],表格4[[#This Row],["Total" No.]]) -> 0
L76: {=_xlfn._xlws.FILTER(表格1[No.],(表格1[Name.]=表格4[[#This Row],[Name1]])+(表格1[Name.]&"_1"=表格4[[#This Row],[Name1]])+(表格1[Name.]&"_2"=表格4[[#This Row],[Name1]])+(表格1[Name.]&"_3"=表格4[[#This Row],[Name1]])+(表格1[Name.]&"_4"=表格4[[#This Row],[Name1]])+(表格1[Name.]&"_5"=表格4[[#This Row],[Name1]]))} -> #VALUE! | M76: =IF(表格4[[#This Row],["Total" No.]]=表格4[[#This Row],[No]],表格4[[#This Row],[No]],"F") -> #VALUE! | N76: =COUNTIF(表格1[No.],表格4[[#This Row],["Total" No.]]) -> 0
L77: {=_xlfn._xlws.FILTER(表格1[No.],(表格1[Name.]=表格4[[#This Row],[Name1]])+(表格1[Name.]&"_1"=表格4[[#This Row],[Name1]])+(表格1[Name.]&"_2"=表格4[[#This Row],[Name1]])+(表格1[Name.]&"_3"=表格4[[#This Row],[Name1]])+(表格1[Name.]&"_4"=表格4[[#This Row],[Name1]])+(表格1[Name.]&"_5"=表格4[[#This Row],[Name1]]))} -> #VALUE! | M77: =IF(表格4[[#This Row],["Total" No.]]=表格4[[#This Row],[No]],表格4[[#This Row],[No]],"F") -> #VALUE! | N77: =COUNTIF(表格1[No.],表格4[[#This Row],["Total" No.]]) -> 0
L78: {=_xlfn._xlws.FILTER(表格1[No.],(表格1[Name.]=表格4[[#This Row],[Name1]])+(表格1[Name.]&"_1"=表格4[[#This Row],[Name1]])+(表格1[Name.]&"_2"=表格4[[#This Row],[Name1]])+(表格1[Name.]&"_3"=表格4[[#This Row],[Name1]])+(表格1[Name.]&"_4"=表格4[[#This Row],[Name1]])+(表格1[Name.]&"_5"=表格4[[#This Row],[Name1]]))} -> #VALUE! | M78: =IF(表格4[[#This Row],["Total" No.]]=表格4[[#This Row],[No]],表格4[[#This Row],[No]],"F") -> #VALUE! | N78: =COUNTIF(表格1[No.],表格4[[#This Row],["Total" No.]]) -> 0
L79: {=_xlfn._xlws.FILTER(表格1[No.],(表格1[Name.]=表格4[[#This Row],[Name1]])+(表格1[Name.]&"_1"=表格4[[#This Row],[Name1]])+(表格1[Name.]&"_2"=表格4[[#This Row],[Name1]])+(表格1[Name.]&"_3"=表格4[[#This Row],[Name1]])+(表格1[Name.]&"_4"=表格4[[#This Row],[Name1]])+(表格1[Name.]&"_5"=表格4[[#This Row],[Name1]]))} -> #VALUE! | M79: =IF(表格4[[#This Row],["Total" No.]]=表格4[[#This Row],[No]],表格4[[#This Row],[No]],"F") -> #VALUE! | N79: =COUNTIF(表格1[No.],表格4[[#This Row],["Total" No.]]) -> 0
J80: - | M80: =IF(表格4[[#This Row],["Total" No.]]=表格4[[#This Row],[No]],表格4[[#This Row],[No]],"F") -> 0 | N80: =COUNTIF(表格1[No.],表格4[[#This Row],["Total" No.]]) -> 0

Sheet 工作表3
A1: No. | B1: 欄1 | C1: =Total!C7 -> Name. | D1: =Total!D7 -> Full Name. | E1: =Total!E7 -> CQ No. | F1: =Total!F7 -> Shop | G1: =Total!G7 -> Period | H1: =Total!H7 -> Days | I1: =Total!I7 -> Reg.Hrs | J1: =Total!J7 -> $ | ... O1: =Total!O7 -> Allowance | P1: A1 | Q1: A2 | R1: A3 | S1: A4 | T1: A5 | U1: A6 | V1: A7 | W1: A8 | X1: A9 | Y1: A10 | Z1: A11 | AA1: A12 | AB1: A13 | AC1: A14 | AD1: A15 | AE1: A16 | AF1: A17 | AG1: =Total!AG7 -> Total | AO1: B1 | AP1: B2 | AQ1: B3 | AR1: B4 | AS1: B5 | AT1: B6 | AU1: B7 | AV1: B8 | AW1: B9 | AX1: B10 | AY1: B11 | AZ1: B12 | BA1: B13 | BB1: B14 | BC1: B15 | BD1: B16 | BE1: B17
A2: 1 | B2: 2026-03 Toshiba | C2: =Total!C8 -> May C | D2: =Total!D8 -> Cheng Muk Kiu | E2: =Total!E8 -> 20850 | F2: =Total!F8 -> Kornhill Aeon | G2: =Total!G8 -> Mar/1-3,5-8,10-13,15-17,20-23,26-29 | H2: =Total!H8 -> 22 | I2: =Total!I8 -> 176 | J2: =Total!J8 -> 55 | ... AF2: =Total!AF8 -> 0 | AG2: =Total!AH8 -> 19745 | AO2: =表格1[[#Headers],[日本飯煲 RC-DS10K/18K]] -> 日本飯煲 RC-DS10K/18K | AP2: =表格1[[#Headers],[酵活炊電飯煲特佣 RC-18AMXH(W)]] -> 酵活炊電飯煲特佣 RC-18AMXH(W) | AQ2: =表格1[[#Headers],[嵌入式微波氣炸蒸焗爐特佣 EB-T500APW]] -> 嵌入式微波氣炸蒸焗爐特佣 EB-T500APW | AR2: =表格1[[#Headers],[蒸氣烤焗水波爐特佣 ER-VD7000HK(XK)]] -> 蒸氣烤焗水波爐特佣 ER-VD7000HK(XK) | AS2: =表格1[[#Headers],[TWDT21BU95 ]] -> TWDT21BU95 | AT2: =表格1[[#Headers],[日式洗衣機一特佣 AW-Q800APH(WW)]] -> 日式洗衣機一特佣 AW-Q800APH(WW) | AU2: =表格1[[#Headers],[日式洗衣機二特佣 AW-Q801APH(WW)]] -> 日式洗衣機二特佣 AW-Q801APH(WW) | AV2: =表格1[[#Headers],[三門雪櫃特佣 GR-RM469WE-PGA(B3)]] -> 三門雪櫃特佣 GR-RM469WE-PGA(B3) | AW2: =表格1[[#Headers],[雙門雪櫃一特佣 GR-RB449WE-PMA(57)]] -> 雙門雪櫃一特佣 GR-RB449WE-PMA(57) | AX2: =表格1[[#Headers],[雙門雪櫃一特佣 GR-RB410WE-PMA(06)]] -> 雙門雪櫃一特佣 GR-RB410WE-PMA(06) | AY2: =表格1[[#Headers],[十字門雪櫃 GR-RF698WI]] -> 十字門雪櫃 GR-RF698WI | AZ2: =表格1[[#Headers],[水機 TWP-W2265THK(W)]] -> 水機 TWP-W2265THK(W) | BA2: =表格1[[#Headers],[抽濕機特佣]] -> 抽濕機特佣 | BB2: =表格1[[#Headers],[(Fortress ONLY)TW-T25BZU115MWH(MG) ]] -> (Fortress ONLY)TW-T25BZU115MWH(MG) | BC2: =表格1[[#Headers],[開門紅(三月)]] -> 開門紅(三月) | BD2: =表格1[[#Headers],[開門紅(第一季)]] -> 開門紅(第一季) | BE2: =表格1[[#Headers],[酵活炊電飯煲特佣 RC-18AMXH(W)]] -> 酵活炊電飯煲特佣 RC-18AMXH(W)
A3: 4 | B3: =B2 -> 2026-03 Toshiba | C3: =Total!C11 -> Vicky L | D3: =Total!D11 -> Leung Ching | E3: =Total!E11 -> 20851 | F3: =Total!F11 -> Diamond Hill Fortress | G3: =Total!G11 -> Mar/1-2,4,6-8,13-19,21-31 | H3: =Total!H11 -> 24 | I3: =Total!I11 -> 192 | J3: =Total!J11 -> 60 | ... AF3: =Total!AF11 -> 0 | AG3: =Total!AH11 -> 23963 | AO3: =表格1[[#Headers],[日本飯煲 RC-DS10K/18K]] -> 日本飯煲 RC-DS10K/18K | AP3: =表格1[[#Headers],[酵活炊電飯煲特佣 RC-18AMXH(W)]] -> 酵活炊電飯煲特佣 RC-18AMXH(W) | AQ3: =表格1[[#Headers],[嵌入式微波氣炸蒸焗爐特佣 EB-T500APW]] -> 嵌入式微波氣炸蒸焗爐特佣 EB-T500APW | AR3: =表格1[[#Headers],[蒸氣烤焗水波爐特佣 ER-VD7000HK(XK)]] -> 蒸氣烤焗水波爐特佣 ER-VD7000HK(XK) | AS3: =表格1[[#Headers],[TWDT21BU95 ]] -> TWDT21BU95 | AT3: =表格1[[#Headers],[日式洗衣機一特佣 AW-Q800APH(WW)]] -> 日式洗衣機一特佣 AW-Q800APH(WW) | AU3: =表格1[[#Headers],[日式洗衣機二特佣 AW-Q801APH(WW)]] -> 日式洗衣機二特佣 AW-Q801APH(WW) | AV3: =表格1[[#Headers],[三門雪櫃特佣 GR-RM469WE-PGA(B3)]] -> 三門雪櫃特佣 GR-RM469WE-PGA(B3) | AW3: =表格1[[#Headers],[雙門雪櫃一特佣 GR-RB449WE-PMA(57)]] -> 雙門雪櫃一特佣 GR-RB449WE-PMA(57) | AX3: =表格1[[#Headers],[雙門雪櫃一特佣 GR-RB410WE-PMA(06)]] -> 雙門雪櫃一特佣 GR-RB410WE-PMA(06) | AY3: =表格1[[#Headers],[十字門雪櫃 GR-RF698WI]] -> 十字門雪櫃 GR-RF698WI | AZ3: =表格1[[#Headers],[水機 TWP-W2265THK(W)]] -> 水機 TWP-W2265THK(W) | BA3: =表格1[[#Headers],[抽濕機特佣]] -> 抽濕機特佣 | BB3: =表格1[[#Headers],[(Fortress ONLY)TW-T25BZU115MWH(MG) ]] -> (Fortress ONLY)TW-T25BZU115MWH(MG) | BC3: =表格1[[#Headers],[開門紅(三月)]] -> 開門紅(三月) | BD3: =表格1[[#Headers],[開門紅(第一季)]] -> 開門紅(第一季) | BE3: =表格1[[#Headers],[酵活炊電飯煲特佣 RC-18AMXH(W)]] -> 酵活炊電飯煲特佣 RC-18AMXH(W)
A4: 6 | B4: =B3 -> 2026-03 Toshiba | C4: =Total!C13 -> Jessica | D4: =Total!D13 -> Chiu Kan | E4: =Total!E13 -> 20852 | F4: =Total!F13 -> Whampoa Aeon | G4: =Total!G13 -> Mar/1-3,6-9,12-15,19-24,27-28,31 | H4: =Total!H13 -> 20 | I4: =Total!I13 -> 160 | J4: =Total!J13 -> 55 | ... AF4: =Total!AF13 -> 0 | AG4: =Total!AH13 -> 18982 | AO4: =表格1[[#Headers],[日本飯煲 RC-DS10K/18K]] -> 日本飯煲 RC-DS10K/18K | AP4: =表格1[[#Headers],[酵活炊電飯煲特佣 RC-18AMXH(W)]] -> 酵活炊電飯煲特佣 RC-18AMXH(W) | AQ4: =表格1[[#Headers],[嵌入式微波氣炸蒸焗爐特佣 EB-T500APW]] -> 嵌入式微波氣炸蒸焗爐特佣 EB-T500APW | AR4: =表格1[[#Headers],[蒸氣烤焗水波爐特佣 ER-VD7000HK(XK)]] -> 蒸氣烤焗水波爐特佣 ER-VD7000HK(XK) | AS4: =表格1[[#Headers],[TWDT21BU95 ]] -> TWDT21BU95 | AT4: =表格1[[#Headers],[日式洗衣機一特佣 AW-Q800APH(WW)]] -> 日式洗衣機一特佣 AW-Q800APH(WW) | AU4: =表格1[[#Headers],[日式洗衣機二特佣 AW-Q801APH(WW)]] -> 日式洗衣機二特佣 AW-Q801APH(WW) | AV4: =表格1[[#Headers],[三門雪櫃特佣 GR-RM469WE-PGA(B3)]] -> 三門雪櫃特佣 GR-RM469WE-PGA(B3) | AW4: =表格1[[#Headers],[雙門雪櫃一特佣 GR-RB449WE-PMA(57)]] -> 雙門雪櫃一特佣 GR-RB449WE-PMA(57) | AX4: =表格1[[#Headers],[雙門雪櫃一特佣 GR-RB410WE-PMA(06)]] -> 雙門雪櫃一特佣 GR-RB410WE-PMA(06) | AY4: =表格1[[#Headers],[十字門雪櫃 GR-RF698WI]] -> 十字門雪櫃 GR-RF698WI | AZ4: =表格1[[#Headers],[水機 TWP-W2265THK(W)]] -> 水機 TWP-W2265THK(W) | BA4: =表格1[[#Headers],[抽濕機特佣]] -> 抽濕機特佣 | BB4: =表格1[[#Headers],[(Fortress ONLY)TW-T25BZU115MWH(MG) ]] -> (Fortress ONLY)TW-T25BZU115MWH(MG) | BC4: =表格1[[#Headers],[開門紅(三月)]] -> 開門紅(三月) | BD4: =表格1[[#Headers],[開門紅(第一季)]] -> 開門紅(第一季) | BE4: =表格1[[#Headers],[酵活炊電飯煲特佣 RC-18AMXH(W)]] -> 酵活炊電飯煲特佣 RC-18AMXH(W)
A5: 7 | B5: =B4 -> 2026-03 Toshiba | C5: =Total!C14 -> Kitty Yeung | D5: =Total!D14 -> Yeung Lai Shan | E5: =Total!E14 -> 20853 | F5: =Total!F14 -> TKW Suning | G5: =Total!G14 -> Mar/1-4,7-11,14-17,21-25,28-31 | H5: =Total!H14 -> 22 | I5: =Total!I14 -> 176 | J5: =Total!J14 -> 60 | ... AF5: =Total!AF14 -> 0 | AG5: =Total!AH14 -> 15998 | AO5: =表格1[[#Headers],[日本飯煲 RC-DS10K/18K]] -> 日本飯煲 RC-DS10K/18K | AP5: =表格1[[#Headers],[酵活炊電飯煲特佣 RC-18AMXH(W)]] -> 酵活炊電飯煲特佣 RC-18AMXH(W) | AQ5: =表格1[[#Headers],[嵌入式微波氣炸蒸焗爐特佣 EB-T500APW]] -> 嵌入式微波氣炸蒸焗爐特佣 EB-T500APW | AR5: =表格1[[#Headers],[蒸氣烤焗水波爐特佣 ER-VD7000HK(XK)]] -> 蒸氣烤焗水波爐特佣 ER-VD7000HK(XK) | AS5: =表格1[[#Headers],[TWDT21BU95 ]] -> TWDT21BU95 | AT5: =表格1[[#Headers],[日式洗衣機一特佣 AW-Q800APH(WW)]] -> 日式洗衣機一特佣 AW-Q800APH(WW) | AU5: =表格1[[#Headers],[日式洗衣機二特佣 AW-Q801APH(WW)]] -> 日式洗衣機二特佣 AW-Q801APH(WW) | AV5: =表格1[[#Headers],[三門雪櫃特佣 GR-RM469WE-PGA(B3)]] -> 三門雪櫃特佣 GR-RM469WE-PGA(B3) | AW5: =表格1[[#Headers],[雙門雪櫃一特佣 GR-RB449WE-PMA(57)]] -> 雙門雪櫃一特佣 GR-RB449WE-PMA(57) | AX5: =表格1[[#Headers],[雙門雪櫃一特佣 GR-RB410WE-PMA(06)]] -> 雙門雪櫃一特佣 GR-RB410WE-PMA(06) | AY5: =表格1[[#Headers],[十字門雪櫃 GR-RF698WI]] -> 十字門雪櫃 GR-RF698WI | AZ5: =表格1[[#Headers],[水機 TWP-W2265THK(W)]] -> 水機 TWP-W2265THK(W) | BA5: =表格1[[#Headers],[抽濕機特佣]] -> 抽濕機特佣 | BB5: =表格1[[#Headers],[(Fortress ONLY)TW-T25BZU115MWH(MG) ]] -> (Fortress ONLY)TW-T25BZU115MWH(MG) | BC5: =表格1[[#Headers],[開門紅(三月)]] -> 開門紅(三月) | BD5: =表格1[[#Headers],[開門紅(第一季)]] -> 開門紅(第一季) | BE5: =表格1[[#Headers],[酵活炊電飯煲特佣 RC-18AMXH(W)]] -> 酵活炊電飯煲特佣 RC-18AMXH(W)
A6: 8 | B6: =B5 -> 2026-03 Toshiba | C6: =Total!C15 -> Amy Or_1 | D6: =Total!D15 -> Or Sim Kiu | E6: =Total!E15 -> 20854 | F6: =Total!F15 -> Tai koo Broadway | G6: =Total!G15 -> Mar/1,7,28-29 | H6: =Total!H15 -> 4 | I6: =Total!I15 -> 32 | J6: =Total!J15 -> 55 | ... AF6: =Total!AF15 -> 0 | AG6: =Total!AH15 -> 3763 | AO6: =表格1[[#Headers],[日本飯煲 RC-DS10K/18K]] -> 日本飯煲 RC-DS10K/18K | AP6: =表格1[[#Headers],[酵活炊電飯煲特佣 RC-18AMXH(W)]] -> 酵活炊電飯煲特佣 RC-18AMXH(W) | AQ6: =表格1[[#Headers],[嵌入式微波氣炸蒸焗爐特佣 EB-T500APW]] -> 嵌入式微波氣炸蒸焗爐特佣 EB-T500APW | AR6: =表格1[[#Headers],[蒸氣烤焗水波爐特佣 ER-VD7000HK(XK)]] -> 蒸氣烤焗水波爐特佣 ER-VD7000HK(XK) | AS6: =表格1[[#Headers],[TWDT21BU95 ]] -> TWDT21BU95 | AT6: =表格1[[#Headers],[日式洗衣機一特佣 AW-Q800APH(WW)]] -> 日式洗衣機一特佣 AW-Q800APH(WW) | AU6: =表格1[[#Headers],[日式洗衣機二特佣 AW-Q801APH(WW)]] -> 日式洗衣機二特佣 AW-Q801APH(WW) | AV6: =表格1[[#Headers],[三門雪櫃特佣 GR-RM469WE-PGA(B3)]] -> 三門雪櫃特佣 GR-RM469WE-PGA(B3) | AW6: =表格1[[#Headers],[雙門雪櫃一特佣 GR-RB449WE-PMA(57)]] -> 雙門雪櫃一特佣 GR-RB449WE-PMA(57) | AX6: =表格1[[#Headers],[雙門雪櫃一特佣 GR-RB410WE-PMA(06)]] -> 雙門雪櫃一特佣 GR-RB410WE-PMA(06) | AY6: =表格1[[#Headers],[十字門雪櫃 GR-RF698WI]] -> 十字門雪櫃 GR-RF698WI | AZ6: =表格1[[#Headers],[水機 TWP-W2265THK(W)]] -> 水機 TWP-W2265THK(W) | BA6: =表格1[[#Headers],[抽濕機特佣]] -> 抽濕機特佣 | BB6: =表格1[[#Headers],[(Fortress ONLY)TW-T25BZU115MWH(MG) ]] -> (Fortress ONLY)TW-T25BZU115MWH(MG) | BC6: =表格1[[#Headers],[開門紅(三月)]] -> 開門紅(三月) | BD6: =表格1[[#Headers],[開門紅(第一季)]] -> 開門紅(第一季) | BE6: =表格1[[#Headers],[酵活炊電飯煲特佣 RC-18AMXH(W)]] -> 酵活炊電飯煲特佣 RC-18AMXH(W)
A7: 11 | B7: =B6 -> 2026-03 Toshiba | C7: =Total!C18 -> Shan_1 | D7: =Total!D18 -> Chiu Fung Shan | E7: =Total!E18 -> 20855 | F7: =Total!F18 -> TW_1 Citistore | G7: =Total!G18 -> Mar/1-2,5-10,14-17,20-23 | H7: =Total!H18 -> 16 | I7: =Total!I18 -> 144 | J7: =Total!J18 -> 60 | ... AF7: =Total!AF18 -> 0 | AG7: =Total!AH18 -> 11331 | AO7: =表格1[[#Headers],[日本飯煲 RC-DS10K/18K]] -> 日本飯煲 RC-DS10K/18K | AP7: =表格1[[#Headers],[酵活炊電飯煲特佣 RC-18AMXH(W)]] -> 酵活炊電飯煲特佣 RC-18AMXH(W) | AQ7: =表格1[[#Headers],[嵌入式微波氣炸蒸焗爐特佣 EB-T500APW]] -> 嵌入式微波氣炸蒸焗爐特佣 EB-T500APW | AR7: =表格1[[#Headers],[蒸氣烤焗水波爐特佣 ER-VD7000HK(XK)]] -> 蒸氣烤焗水波爐特佣 ER-VD7000HK(XK) | AS7: =表格1[[#Headers],[TWDT21BU95 ]] -> TWDT21BU95 | AT7: =表格1[[#Headers],[日式洗衣機一特佣 AW-Q800APH(WW)]] -> 日式洗衣機一特佣 AW-Q800APH(WW) | AU7: =表格1[[#Headers],[日式洗衣機二特佣 AW-Q801APH(WW)]] -> 日式洗衣機二特佣 AW-Q801APH(WW) | AV7: =表格1[[#Headers],[三門雪櫃特佣 GR-RM469WE-PGA(B3)]] -> 三門雪櫃特佣 GR-RM469WE-PGA(B3) | AW7: =表格1[[#Headers],[雙門雪櫃一特佣 GR-RB449WE-PMA(57)]] -> 雙門雪櫃一特佣 GR-RB449WE-PMA(57) | AX7: =表格1[[#Headers],[雙門雪櫃一特佣 GR-RB410WE-PMA(06)]] -> 雙門雪櫃一特佣 GR-RB410WE-PMA(06) | AY7: =表格1[[#Headers],[十字門雪櫃 GR-RF698WI]] -> 十字門雪櫃 GR-RF698WI | AZ7: =表格1[[#Headers],[水機 TWP-W2265THK(W)]] -> 水機 TWP-W2265THK(W) | BA7: =表格1[[#Headers],[抽濕機特佣]] -> 抽濕機特佣 | BB7: =表格1[[#Headers],[(Fortress ONLY)TW-T25BZU115MWH(MG) ]] -> (Fortress ONLY)TW-T25BZU115MWH(MG) | BC7: =表格1[[#Headers],[開門紅(三月)]] -> 開門紅(三月) | BD7: =表格1[[#Headers],[開門紅(第一季)]] -> 開門紅(第一季) | BE7: =表格1[[#Headers],[酵活炊電飯煲特佣 RC-18AMXH(W)]] -> 酵活炊電飯煲特佣 RC-18AMXH(W)
A8: 14 | B8: =B7 -> 2026-03 Toshiba | C8: =Total!C21 -> Shan_2 | D8: =Total!D21 -> Chiu Fung Shan | E8: =Total!E21 -> 20856 | F8: =Total!F21 -> TW RS_1 Citistore | G8: =Total!G21 -> Mar/25-31 | H8: =Total!H21 -> 7 | I8: =Total!I21 -> 56 | J8: =Total!J21 -> 60 | ... AF8: =Total!AF21 -> 0 | AG8: =Total!AH21 -> 6389 | AO8: =表格1[[#Headers],[日本飯煲 RC-DS10K/18K]] -> 日本飯煲 RC-DS10K/18K | AP8: =表格1[[#Headers],[酵活炊電飯煲特佣 RC-18AMXH(W)]] -> 酵活炊電飯煲特佣 RC-18AMXH(W) | AQ8: =表格1[[#Headers],[嵌入式微波氣炸蒸焗爐特佣 EB-T500APW]] -> 嵌入式微波氣炸蒸焗爐特佣 EB-T500APW | AR8: =表格1[[#Headers],[蒸氣烤焗水波爐特佣 ER-VD7000HK(XK)]] -> 蒸氣烤焗水波爐特佣 ER-VD7000HK(XK) | AS8: =表格1[[#Headers],[TWDT21BU95 ]] -> TWDT21BU95 | AT8: =表格1[[#Headers],[日式洗衣機一特佣 AW-Q800APH(WW)]] -> 日式洗衣機一特佣 AW-Q800APH(WW) | AU8: =表格1[[#Headers],[日式洗衣機二特佣 AW-Q801APH(WW)]] -> 日式洗衣機二特佣 AW-Q801APH(WW) | AV8: =表格1[[#Headers],[三門雪櫃特佣 GR-RM469WE-PGA(B3)]] -> 三門雪櫃特佣 GR-RM469WE-PGA(B3) | AW8: =表格1[[#Headers],[雙門雪櫃一特佣 GR-RB449WE-PMA(57)]] -> 雙門雪櫃一特佣 GR-RB449WE-PMA(57) | AX8: =表格1[[#Headers],[雙門雪櫃一特佣 GR-RB410WE-PMA(06)]] -> 雙門雪櫃一特佣 GR-RB410WE-PMA(06) | AY8: =表格1[[#Headers],[十字門雪櫃 GR-RF698WI]] -> 十字門雪櫃 GR-RF698WI | AZ8: =表格1[[#Headers],[水機 TWP-W2265THK(W)]] -> 水機 TWP-W2265THK(W) | BA8: =表格1[[#Headers],[抽濕機特佣]] -> 抽濕機特佣 | BB8: =表格1[[#Headers],[(Fortress ONLY)TW-T25BZU115MWH(MG) ]] -> (Fortress ONLY)TW-T25BZU115MWH(MG) | BC8: =表格1[[#Headers],[開門紅(三月)]] -> 開門紅(三月) | BD8: =表格1[[#Headers],[開門紅(第一季)]] -> 開門紅(第一季) | BE8: =表格1[[#Headers],[酵活炊電飯煲特佣 RC-18AMXH(W)]] -> 酵活炊電飯煲特佣 RC-18AMXH(W)
A9: 17 | B9: =B8 -> 2026-03 Toshiba | C9: =Total!C24 -> Jaco | D9: =Total!D24 -> Ka Kui,Jaco | E9: =Total!E24 -> 20857 | F9: =Total!F24 -> Tung Chun Fortress | G9: =Total!G24 -> Mar/2-5,7-11,14-17,20-25,29-31 | H9: =Total!H24 -> 22 | I9: =Total!I24 -> 170 | J9: =Total!J24 -> 60 | ... AF9: =Total!AF24 -> 0 | AG9: =Total!AH24 -> 18102 | AO9: =表格1[[#Headers],[日本飯煲 RC-DS10K/18K]] -> 日本飯煲 RC-DS10K/18K | AP9: =表格1[[#Headers],[酵活炊電飯煲特佣 RC-18AMXH(W)]] -> 酵活炊電飯煲特佣 RC-18AMXH(W) | AQ9: =表格1[[#Headers],[嵌入式微波氣炸蒸焗爐特佣 EB-T500APW]] -> 嵌入式微波氣炸蒸焗爐特佣 EB-T500APW | AR9: =表格1[[#Headers],[蒸氣烤焗水波爐特佣 ER-VD7000HK(XK)]] -> 蒸氣烤焗水波爐特佣 ER-VD7000HK(XK) | AS9: =表格1[[#Headers],[TWDT21BU95 ]] -> TWDT21BU95 | AT9: =表格1[[#Headers],[日式洗衣機一特佣 AW-Q800APH(WW)]] -> 日式洗衣機一特佣 AW-Q800APH(WW) | AU9: =表格1[[#Headers],[日式洗衣機二特佣 AW-Q801APH(WW)]] -> 日式洗衣機二特佣 AW-Q801APH(WW) | AV9: =表格1[[#Headers],[三門雪櫃特佣 GR-RM469WE-PGA(B3)]] -> 三門雪櫃特佣 GR-RM469WE-PGA(B3) | AW9: =表格1[[#Headers],[雙門雪櫃一特佣 GR-RB449WE-PMA(57)]] -> 雙門雪櫃一特佣 GR-RB449WE-PMA(57) | AX9: =表格1[[#Headers],[雙門雪櫃一特佣 GR-RB410WE-PMA(06)]] -> 雙門雪櫃一特佣 GR-RB410WE-PMA(06) | AY9: =表格1[[#Headers],[十字門雪櫃 GR-RF698WI]] -> 十字門雪櫃 GR-RF698WI | AZ9: =表格1[[#Headers],[水機 TWP-W2265THK(W)]] -> 水機 TWP-W2265THK(W) | BA9: =表格1[[#Headers],[抽濕機特佣]] -> 抽濕機特佣 | BB9: =表格1[[#Headers],[(Fortress ONLY)TW-T25BZU115MWH(MG) ]] -> (Fortress ONLY)TW-T25BZU115MWH(MG) | BC9: =表格1[[#Headers],[開門紅(三月)]] -> 開門紅(三月) | BD9: =表格1[[#Headers],[開門紅(第一季)]] -> 開門紅(第一季) | BE9: =表格1[[#Headers],[酵活炊電飯煲特佣 RC-18AMXH(W)]] -> 酵活炊電飯煲特佣 RC-18AMXH(W)
A10: 21 | B10: =B9 -> 2026-03 Toshiba | C10: =Total!C28 -> Lily Hon | D10: =Total!D28 -> Hon Lily | E10: =Total!E28 -> 20858 | F10: =Total!F28 -> TM_1 Aeon | G10: =Total!G28 -> Mar/1-2,4,6,8-9,11,13,22-25,27-29,31 | H10: =Total!H28 -> 16 | I10: =Total!I28 -> 128 | J10: =Total!J28 -> 55 | ... AF10: =Total!AF28 -> 0 | AG10: =Total!AH28 -> 12093 | AO10: =表格1[[#Headers],[日本飯煲 RC-DS10K/18K]] -> 日本飯煲 RC-DS10K/18K | AP10: =表格1[[#Headers],[酵活炊電飯煲特佣 RC-18AMXH(W)]] -> 酵活炊電飯煲特佣 RC-18AMXH(W) | AQ10: =表格1[[#Headers],[嵌入式微波氣炸蒸焗爐特佣 EB-T500APW]] -> 嵌入式微波氣炸蒸焗爐特佣 EB-T500APW | AR10: =表格1[[#Headers],[蒸氣烤焗水波爐特佣 ER-VD7000HK(XK)]] -> 蒸氣烤焗水波爐特佣 ER-VD7000HK(XK) | AS10: =表格1[[#Headers],[TWDT21BU95 ]] -> TWDT21BU95 | AT10: =表格1[[#Headers],[日式洗衣機一特佣 AW-Q800APH(WW)]] -> 日式洗衣機一特佣 AW-Q800APH(WW) | AU10: =表格1[[#Headers],[日式洗衣機二特佣 AW-Q801APH(WW)]] -> 日式洗衣機二特佣 AW-Q801APH(WW) | AV10: =表格1[[#Headers],[三門雪櫃特佣 GR-RM469WE-PGA(B3)]] -> 三門雪櫃特佣 GR-RM469WE-PGA(B3) | AW10: =表格1[[#Headers],[雙門雪櫃一特佣 GR-RB449WE-PMA(57)]] -> 雙門雪櫃一特佣 GR-RB449WE-PMA(57) | AX10: =表格1[[#Headers],[雙門雪櫃一特佣 GR-RB410WE-PMA(06)]] -> 雙門雪櫃一特佣 GR-RB410WE-PMA(06) | AY10: =表格1[[#Headers],[十字門雪櫃 GR-RF698WI]] -> 十字門雪櫃 GR-RF698WI | AZ10: =表格1[[#Headers],[水機 TWP-W2265THK(W)]] -> 水機 TWP-W2265THK(W) | BA10: =表格1[[#Headers],[抽濕機特佣]] -> 抽濕機特佣 | BB10: =表格1[[#Headers],[(Fortress ONLY)TW-T25BZU115MWH(MG) ]] -> (Fortress ONLY)TW-T25BZU115MWH(MG) | BC10: =表格1[[#Headers],[開門紅(三月)]] -> 開門紅(三月) | BD10: =表格1[[#Headers],[開門紅(第一季)]] -> 開門紅(第一季) | BE10: =表格1[[#Headers],[酵活炊電飯煲特佣 RC-18AMXH(W)]] -> 酵活炊電飯煲特佣 RC-18AMXH(W)
A11: 22 | B11: =B10 -> 2026-03 Toshiba | C11: =Total!C29 -> Ho_3 | D11: =Total!D29 -> Kwan Tit Ho | E11: =Total!E29 -> 20859 | F11: =Total!F29 -> TM_2 Aeon | G11: =Total!G29 -> Mar/17-18,26,30 | H11: =Total!H29 -> 4 | I11: =Total!I29 -> 32 | J11: =Total!J29 -> 55 | ... AF11: =Total!AF29 -> 0 | AG11: =Total!AH29 -> 2382 | AO11: =表格1[[#Headers],[日本飯煲 RC-DS10K/18K]] -> 日本飯煲 RC-DS10K/18K | AP11: =表格1[[#Headers],[酵活炊電飯煲特佣 RC-18AMXH(W)]] -> 酵活炊電飯煲特佣 RC-18AMXH(W) | AQ11: =表格1[[#Headers],[嵌入式微波氣炸蒸焗爐特佣 EB-T500APW]] -> 嵌入式微波氣炸蒸焗爐特佣 EB-T500APW | AR11: =表格1[[#Headers],[蒸氣烤焗水波爐特佣 ER-VD7000HK(XK)]] -> 蒸氣烤焗水波爐特佣 ER-VD7000HK(XK) | AS11: =表格1[[#Headers],[TWDT21BU95 ]] -> TWDT21BU95 | AT11: =表格1[[#Headers],[日式洗衣機一特佣 AW-Q800APH(WW)]] -> 日式洗衣機一特佣 AW-Q800APH(WW) | AU11: =表格1[[#Headers],[日式洗衣機二特佣 AW-Q801APH(WW)]] -> 日式洗衣機二特佣 AW-Q801APH(WW) | AV11: =表格1[[#Headers],[三門雪櫃特佣 GR-RM469WE-PGA(B3)]] -> 三門雪櫃特佣 GR-RM469WE-PGA(B3) | AW11: =表格1[[#Headers],[雙門雪櫃一特佣 GR-RB449WE-PMA(57)]] -> 雙門雪櫃一特佣 GR-RB449WE-PMA(57) | AX11: =表格1[[#Headers],[雙門雪櫃一特佣 GR-RB410WE-PMA(06)]] -> 雙門雪櫃一特佣 GR-RB410WE-PMA(06) | AY11: =表格1[[#Headers],[十字門雪櫃 GR-RF698WI]] -> 十字門雪櫃 GR-RF698WI | AZ11: =表格1[[#Headers],[水機 TWP-W2265THK(W)]] -> 水機 TWP-W2265THK(W) | BA11: =表格1[[#Headers],[抽濕機特佣]] -> 抽濕機特佣 | BB11: =表格1[[#Headers],[(Fortress ONLY)TW-T25BZU115MWH(MG) ]] -> (Fortress ONLY)TW-T25BZU115MWH(MG) | BC11: =表格1[[#Headers],[開門紅(三月)]] -> 開門紅(三月) | BD11: =表格1[[#Headers],[開門紅(第一季)]] -> 開門紅(第一季) | BE11: =表格1[[#Headers],[酵活炊電飯煲特佣 RC-18AMXH(W)]] -> 酵活炊電飯煲特佣 RC-18AMXH(W)
A12: 23 | B12: =B11 -> 2026-03 Toshiba | C12: =Total!C30 -> Kandy | D12: =Total!D30 -> Sin Hoi Yam | E12: =Total!E30 -> 20860 | F12: =Total!F30 -> TW Fortress | G12: =Total!G30 -> Mar/1,7-8,21-22,28-29 | H12: =Total!H30 -> 7 | I12: =Total!I30 -> 56 | J12: =Total!J30 -> 55 | ... AF12: =Total!AF30 -> 0 | AG12: =Total!AH30 -> 6393 | AO12: =表格1[[#Headers],[日本飯煲 RC-DS10K/18K]] -> 日本飯煲 RC-DS10K/18K | AP12: =表格1[[#Headers],[酵活炊電飯煲特佣 RC-18AMXH(W)]] -> 酵活炊電飯煲特佣 RC-18AMXH(W) | AQ12: =表格1[[#Headers],[嵌入式微波氣炸蒸焗爐特佣 EB-T500APW]] -> 嵌入式微波氣炸蒸焗爐特佣 EB-T500APW | AR12: =表格1[[#Headers],[蒸氣烤焗水波爐特佣 ER-VD7000HK(XK)]] -> 蒸氣烤焗水波爐特佣 ER-VD7000HK(XK) | AS12: =表格1[[#Headers],[TWDT21BU95 ]] -> TWDT21BU95 | AT12: =表格1[[#Headers],[日式洗衣機一特佣 AW-Q800APH(WW)]] -> 日式洗衣機一特佣 AW-Q800APH(WW) | AU12: =表格1[[#Headers],[日式洗衣機二特佣 AW-Q801APH(WW)]] -> 日式洗衣機二特佣 AW-Q801APH(WW) | AV12: =表格1[[#Headers],[三門雪櫃特佣 GR-RM469WE-PGA(B3)]] -> 三門雪櫃特佣 GR-RM469WE-PGA(B3) | AW12: =表格1[[#Headers],[雙門雪櫃一特佣 GR-RB449WE-PMA(57)]] -> 雙門雪櫃一特佣 GR-RB449WE-PMA(57) | AX12: =表格1[[#Headers],[雙門雪櫃一特佣 GR-RB410WE-PMA(06)]] -> 雙門雪櫃一特佣 GR-RB410WE-PMA(06) | AY12: =表格1[[#Headers],[十字門雪櫃 GR-RF698WI]] -> 十字門雪櫃 GR-RF698WI | AZ12: =表格1[[#Headers],[水機 TWP-W2265THK(W)]] -> 水機 TWP-W2265THK(W) | BA12: =表格1[[#Headers],[抽濕機特佣]] -> 抽濕機特佣 | BB12: =表格1[[#Headers],[(Fortress ONLY)TW-T25BZU115MWH(MG) ]] -> (Fortress ONLY)TW-T25BZU115MWH(MG) | BC12: =表格1[[#Headers],[開門紅(三月)]] -> 開門紅(三月) | BD12: =表格1[[#Headers],[開門紅(第一季)]] -> 開門紅(第一季) | BE12: =表格1[[#Headers],[酵活炊電飯煲特佣 RC-18AMXH(W)]] -> 酵活炊電飯煲特佣 RC-18AMXH(W)
A13: 24 | B13: =B12 -> 2026-03 Toshiba | C13: =Total!C31 -> Hung | D13: =Total!D31 -> Hui Man Hung | E13: =Total!E31 -> 20861 | F13: =Total!F31 -> TW Suning | G13: =Total!G31 -> Mar/1-4,6-12,14-18,20-25 | H13: =Total!H31 -> 22 | I13: =Total!I31 -> 176 | J13: =Total!J31 -> 60 | ... AF13: =Total!AF31 -> 0 | AG13: =Total!AH31 -> 10560 | AO13: =表格1[[#Headers],[日本飯煲 RC-DS10K/18K]] -> 日本飯煲 RC-DS10K/18K | AP13: =表格1[[#Headers],[酵活炊電飯煲特佣 RC-18AMXH(W)]] -> 酵活炊電飯煲特佣 RC-18AMXH(W) | AQ13: =表格1[[#Headers],[嵌入式微波氣炸蒸焗爐特佣 EB-T500APW]] -> 嵌入式微波氣炸蒸焗爐特佣 EB-T500APW | AR13: =表格1[[#Headers],[蒸氣烤焗水波爐特佣 ER-VD7000HK(XK)]] -> 蒸氣烤焗水波爐特佣 ER-VD7000HK(XK) | AS13: =表格1[[#Headers],[TWDT21BU95 ]] -> TWDT21BU95 | AT13: =表格1[[#Headers],[日式洗衣機一特佣 AW-Q800APH(WW)]] -> 日式洗衣機一特佣 AW-Q800APH(WW) | AU13: =表格1[[#Headers],[日式洗衣機二特佣 AW-Q801APH(WW)]] -> 日式洗衣機二特佣 AW-Q801APH(WW) | AV13: =表格1[[#Headers],[三門雪櫃特佣 GR-RM469WE-PGA(B3)]] -> 三門雪櫃特佣 GR-RM469WE-PGA(B3) | AW13: =表格1[[#Headers],[雙門雪櫃一特佣 GR-RB449WE-PMA(57)]] -> 雙門雪櫃一特佣 GR-RB449WE-PMA(57) | AX13: =表格1[[#Headers],[雙門雪櫃一特佣 GR-RB410WE-PMA(06)]] -> 雙門雪櫃一特佣 GR-RB410WE-PMA(06) | AY13: =表格1[[#Headers],[十字門雪櫃 GR-RF698WI]] -> 十字門雪櫃 GR-RF698WI | AZ13: =表格1[[#Headers],[水機 TWP-W2265THK(W)]] -> 水機 TWP-W2265THK(W) | BA13: =表格1[[#Headers],[抽濕機特佣]] -> 抽濕機特佣 | BB13: =表格1[[#Headers],[(Fortress ONLY)TW-T25BZU115MWH(MG) ]] -> (Fortress ONLY)TW-T25BZU115MWH(MG) | BC13: =表格1[[#Headers],[開門紅(三月)]] -> 開門紅(三月) | BD13: =表格1[[#Headers],[開門紅(第一季)]] -> 開門紅(第一季) | BE13: =表格1[[#Headers],[酵活炊電飯煲特佣 RC-18AMXH(W)]] -> 酵活炊電飯煲特佣 RC-18AMXH(W)
A14: 26 | B14: =B13 -> 2026-03 Toshiba | C14: =Total!C33 -> Yee | D14: =Total!D33 -> Cheung Yu Wing Yee | E14: =Total!E33 -> 20862 | F14: =Total!F33 -> YL Citistore | G14: =Total!G33 -> Mar/1,5-9,12-16,19-22,26-30 | H14: =Total!H33 -> 20 | I14: =Total!I33 -> 160 | J14: =Total!J33 -> 60 | ... AF14: =Total!AF33 -> 0 | AG14: =Total!AH33 -> 12115 | AO14: =表格1[[#Headers],[日本飯煲 RC-DS10K/18K]] -> 日本飯煲 RC-DS10K/18K | AP14: =表格1[[#Headers],[酵活炊電飯煲特佣 RC-18AMXH(W)]] -> 酵活炊電飯煲特佣 RC-18AMXH(W) | AQ14: =表格1[[#Headers],[嵌入式微波氣炸蒸焗爐特佣 EB-T500APW]] -> 嵌入式微波氣炸蒸焗爐特佣 EB-T500APW | AR14: =表格1[[#Headers],[蒸氣烤焗水波爐特佣 ER-VD7000HK(XK)]] -> 蒸氣烤焗水波爐特佣 ER-VD7000HK(XK) | AS14: =表格1[[#Headers],[TWDT21BU95 ]] -> TWDT21BU95 | AT14: =表格1[[#Headers],[日式洗衣機一特佣 AW-Q800APH(WW)]] -> 日式洗衣機一特佣 AW-Q800APH(WW) | AU14: =表格1[[#Headers],[日式洗衣機二特佣 AW-Q801APH(WW)]] -> 日式洗衣機二特佣 AW-Q801APH(WW) | AV14: =表格1[[#Headers],[三門雪櫃特佣 GR-RM469WE-PGA(B3)]] -> 三門雪櫃特佣 GR-RM469WE-PGA(B3) | AW14: =表格1[[#Headers],[雙門雪櫃一特佣 GR-RB449WE-PMA(57)]] -> 雙門雪櫃一特佣 GR-RB449WE-PMA(57) | AX14: =表格1[[#Headers],[雙門雪櫃一特佣 GR-RB410WE-PMA(06)]] -> 雙門雪櫃一特佣 GR-RB410WE-PMA(06) | AY14: =表格1[[#Headers],[十字門雪櫃 GR-RF698WI]] -> 十字門雪櫃 GR-RF698WI | AZ14: =表格1[[#Headers],[水機 TWP-W2265THK(W)]] -> 水機 TWP-W2265THK(W) | BA14: =表格1[[#Headers],[抽濕機特佣]] -> 抽濕機特佣 | BB14: =表格1[[#Headers],[(Fortress ONLY)TW-T25BZU115MWH(MG) ]] -> (Fortress ONLY)TW-T25BZU115MWH(MG) | BC14: =表格1[[#Headers],[開門紅(三月)]] -> 開門紅(三月) | BD14: =表格1[[#Headers],[開門紅(第一季)]] -> 開門紅(第一季) | BE14: =表格1[[#Headers],[酵活炊電飯煲特佣 RC-18AMXH(W)]] -> 酵活炊電飯煲特佣 RC-18AMXH(W)
A15: 28 | B15: =B14 -> 2026-03 Toshiba | C15: =Total!C35 -> Happy | D15: =Total!D35 -> Chun Yin Ling | E15: =Total!E35 -> 20863 | F15: =Total!F35 -> APM Broadway | G15: =Total!G35 -> Mar/1,3-5,7-9,11-12,15-16,19-22,25-31 | H15: =Total!H35 -> 22 | I15: =Total!I35 -> 176 | J15: =Total!J35 -> 60 | ... AF15: =Total!AF35 -> 0 | AG15: =Total!AH35 -> 24676 | AO15: =表格1[[#Headers],[日本飯煲 RC-DS10K/18K]] -> 日本飯煲 RC-DS10K/18K | AP15: =表格1[[#Headers],[酵活炊電飯煲特佣 RC-18AMXH(W)]] -> 酵活炊電飯煲特佣 RC-18AMXH(W) | AQ15: =表格1[[#Headers],[嵌入式微波氣炸蒸焗爐特佣 EB-T500APW]] -> 嵌入式微波氣炸蒸焗爐特佣 EB-T500APW | AR15: =表格1[[#Headers],[蒸氣烤焗水波爐特佣 ER-VD7000HK(XK)]] -> 蒸氣烤焗水波爐特佣 ER-VD7000HK(XK) | AS15: =表格1[[#Headers],[TWDT21BU95 ]] -> TWDT21BU95 | AT15: =表格1[[#Headers],[日式洗衣機一特佣 AW-Q800APH(WW)]] -> 日式洗衣機一特佣 AW-Q800APH(WW) | AU15: =表格1[[#Headers],[日式洗衣機二特佣 AW-Q801APH(WW)]] -> 日式洗衣機二特佣 AW-Q801APH(WW) | AV15: =表格1[[#Headers],[三門雪櫃特佣 GR-RM469WE-PGA(B3)]] -> 三門雪櫃特佣 GR-RM469WE-PGA(B3) | AW15: =表格1[[#Headers],[雙門雪櫃一特佣 GR-RB449WE-PMA(57)]] -> 雙門雪櫃一特佣 GR-RB449WE-PMA(57) | AX15: =表格1[[#Headers],[雙門雪櫃一特佣 GR-RB410WE-PMA(06)]] -> 雙門雪櫃一特佣 GR-RB410WE-PMA(06) | AY15: =表格1[[#Headers],[十字門雪櫃 GR-RF698WI]] -> 十字門雪櫃 GR-RF698WI | AZ15: =表格1[[#Headers],[水機 TWP-W2265THK(W)]] -> 水機 TWP-W2265THK(W) | BA15: =表格1[[#Headers],[抽濕機特佣]] -> 抽濕機特佣 | BB15: =表格1[[#Headers],[(Fortress ONLY)TW-T25BZU115MWH(MG) ]] -> (Fortress ONLY)TW-T25BZU115MWH(MG) | BC15: =表格1[[#Headers],[開門紅(三月)]] -> 開門紅(三月) | BD15: =表格1[[#Headers],[開門紅(第一季)]] -> 開門紅(第一季) | BE15: =表格1[[#Headers],[酵活炊電飯煲特佣 RC-18AMXH(W)]] -> 酵活炊電飯煲特佣 RC-18AMXH(W)
A16: 30 | B16: =B15 -> 2026-03 Toshiba | C16: =Total!C37 -> Coco | D16: =Total!D37 -> Yuen Lai Ying | E16: =Total!E37 -> 20864 | F16: =Total!F37 -> TKO Suning | G16: =Total!G37 -> Mar/1,3-5,7-8,11-12,14-15,17-19,24-26,28-31 | H16: =Total!H37 -> 20 | I16: =Total!I37 -> 160 | J16: =Total!J37 -> 60 | ... AF16: =Total!AF37 -> 0 | AG16: =Total!AH37 -> 14185 | AO16: =表格1[[#Headers],[日本飯煲 RC-DS10K/18K]] -> 日本飯煲 RC-DS10K/18K | AP16: =表格1[[#Headers],[酵活炊電飯煲特佣 RC-18AMXH(W)]] -> 酵活炊電飯煲特佣 RC-18AMXH(W) | AQ16: =表格1[[#Headers],[嵌入式微波氣炸蒸焗爐特佣 EB-T500APW]] -> 嵌入式微波氣炸蒸焗爐特佣 EB-T500APW | AR16: =表格1[[#Headers],[蒸氣烤焗水波爐特佣 ER-VD7000HK(XK)]] -> 蒸氣烤焗水波爐特佣 ER-VD7000HK(XK) | AS16: =表格1[[#Headers],[TWDT21BU95 ]] -> TWDT21BU95 | AT16: =表格1[[#Headers],[日式洗衣機一特佣 AW-Q800APH(WW)]] -> 日式洗衣機一特佣 AW-Q800APH(WW) | AU16: =表格1[[#Headers],[日式洗衣機二特佣 AW-Q801APH(WW)]] -> 日式洗衣機二特佣 AW-Q801APH(WW) | AV16: =表格1[[#Headers],[三門雪櫃特佣 GR-RM469WE-PGA(B3)]] -> 三門雪櫃特佣 GR-RM469WE-PGA(B3) | AW16: =表格1[[#Headers],[雙門雪櫃一特佣 GR-RB449WE-PMA(57)]] -> 雙門雪櫃一特佣 GR-RB449WE-PMA(57) | AX16: =表格1[[#Headers],[雙門雪櫃一特佣 GR-RB410WE-PMA(06)]] -> 雙門雪櫃一特佣 GR-RB410WE-PMA(06) | AY16: =表格1[[#Headers],[十字門雪櫃 GR-RF698WI]] -> 十字門雪櫃 GR-RF698WI | AZ16: =表格1[[#Headers],[水機 TWP-W2265THK(W)]] -> 水機 TWP-W2265THK(W) | BA16: =表格1[[#Headers],[抽濕機特佣]] -> 抽濕機特佣 | BB16: =表格1[[#Headers],[(Fortress ONLY)TW-T25BZU115MWH(MG) ]] -> (Fortress ONLY)TW-T25BZU115MWH(MG) | BC16: =表格1[[#Headers],[開門紅(三月)]] -> 開門紅(三月) | BD16: =表格1[[#Headers],[開門紅(第一季)]] -> 開門紅(第一季) | BE16: =表格1[[#Headers],[酵活炊電飯煲特佣 RC-18AMXH(W)]] -> 酵活炊電飯煲特佣 RC-18AMXH(W)
A17: 31 | B17: =B16 -> 2026-03 Toshiba | C17: =Total!C38 -> Raymond | D17: =Total!D38 -> Kwok Chun Wah | E17: =Total!E38 -> 20865 | F17: =Total!F38 -> Times Fortress | G17: =Total!G38 -> Mar/1-5,7,9-12,15-18,21-26,28-31 | H17: =Total!H38 -> 24 | I17: =Total!I38 -> 192 | J17: =Total!J38 -> 60 | ... AF17: =Total!AF38 -> 0 | AG17: =Total!AH38 -> 18730 | AO17: =表格1[[#Headers],[日本飯煲 RC-DS10K/18K]] -> 日本飯煲 RC-DS10K/18K | AP17: =表格1[[#Headers],[酵活炊電飯煲特佣 RC-18AMXH(W)]] -> 酵活炊電飯煲特佣 RC-18AMXH(W) | AQ17: =表格1[[#Headers],[嵌入式微波氣炸蒸焗爐特佣 EB-T500APW]] -> 嵌入式微波氣炸蒸焗爐特佣 EB-T500APW | AR17: =表格1[[#Headers],[蒸氣烤焗水波爐特佣 ER-VD7000HK(XK)]] -> 蒸氣烤焗水波爐特佣 ER-VD7000HK(XK) | AS17: =表格1[[#Headers],[TWDT21BU95 ]] -> TWDT21BU95 | AT17: =表格1[[#Headers],[日式洗衣機一特佣 AW-Q800APH(WW)]] -> 日式洗衣機一特佣 AW-Q800APH(WW) | AU17: =表格1[[#Headers],[日式洗衣機二特佣 AW-Q801APH(WW)]] -> 日式洗衣機二特佣 AW-Q801APH(WW) | AV17: =表格1[[#Headers],[三門雪櫃特佣 GR-RM469WE-PGA(B3)]] -> 三門雪櫃特佣 GR-RM469WE-PGA(B3) | AW17: =表格1[[#Headers],[雙門雪櫃一特佣 GR-RB449WE-PMA(57)]] -> 雙門雪櫃一特佣 GR-RB449WE-PMA(57) | AX17: =表格1[[#Headers],[雙門雪櫃一特佣 GR-RB410WE-PMA(06)]] -> 雙門雪櫃一特佣 GR-RB410WE-PMA(06) | AY17: =表格1[[#Headers],[十字門雪櫃 GR-RF698WI]] -> 十字門雪櫃 GR-RF698WI | AZ17: =表格1[[#Headers],[水機 TWP-W2265THK(W)]] -> 水機 TWP-W2265THK(W) | BA17: =表格1[[#Headers],[抽濕機特佣]] -> 抽濕機特佣 | BB17: =表格1[[#Headers],[(Fortress ONLY)TW-T25BZU115MWH(MG) ]] -> (Fortress ONLY)TW-T25BZU115MWH(MG) | BC17: =表格1[[#Headers],[開門紅(三月)]] -> 開門紅(三月) | BD17: =表格1[[#Headers],[開門紅(第一季)]] -> 開門紅(第一季) | BE17: =表格1[[#Headers],[酵活炊電飯煲特佣 RC-18AMXH(W)]] -> 酵活炊電飯煲特佣 RC-18AMXH(W)
A18: 32 | B18: =B17 -> 2026-03 Toshiba | C18: =Total!C39 -> Maggie Yip | D18: =Total!D39 -> Yip Mei King | E18: =Total!E39 -> 20866 | F18: =Total!F39 -> Shatin_1 Yata | G18: =Total!G39 -> Mar/1-2,5-10,14-17,20-24,27-31 | H18: =Total!H39 -> 22 | I18: =Total!I39 -> 176 | J18: =Total!J39 -> 60 | ... AF18: =Total!AF39 -> 0 | AG18: =Total!AH39 -> 13026 | AO18: =表格1[[#Headers],[日本飯煲 RC-DS10K/18K]] -> 日本飯煲 RC-DS10K/18K | AP18: =表格1[[#Headers],[酵活炊電飯煲特佣 RC-18AMXH(W)]] -> 酵活炊電飯煲特佣 RC-18AMXH(W) | AQ18: =表格1[[#Headers],[嵌入式微波氣炸蒸焗爐特佣 EB-T500APW]] -> 嵌入式微波氣炸蒸焗爐特佣 EB-T500APW | AR18: =表格1[[#Headers],[蒸氣烤焗水波爐特佣 ER-VD7000HK(XK)]] -> 蒸氣烤焗水波爐特佣 ER-VD7000HK(XK) | AS18: =表格1[[#Headers],[TWDT21BU95 ]] -> TWDT21BU95 | AT18: =表格1[[#Headers],[日式洗衣機一特佣 AW-Q800APH(WW)]] -> 日式洗衣機一特佣 AW-Q800APH(WW) | AU18: =表格1[[#Headers],[日式洗衣機二特佣 AW-Q801APH(WW)]] -> 日式洗衣機二特佣 AW-Q801APH(WW) | AV18: =表格1[[#Headers],[三門雪櫃特佣 GR-RM469WE-PGA(B3)]] -> 三門雪櫃特佣 GR-RM469WE-PGA(B3) | AW18: =表格1[[#Headers],[雙門雪櫃一特佣 GR-RB449WE-PMA(57)]] -> 雙門雪櫃一特佣 GR-RB449WE-PMA(57) | AX18: =表格1[[#Headers],[雙門雪櫃一特佣 GR-RB410WE-PMA(06)]] -> 雙門雪櫃一特佣 GR-RB410WE-PMA(06) | AY18: =表格1[[#Headers],[十字門雪櫃 GR-RF698WI]] -> 十字門雪櫃 GR-RF698WI | AZ18: =表格1[[#Headers],[水機 TWP-W2265THK(W)]] -> 水機 TWP-W2265THK(W) | BA18: =表格1[[#Headers],[抽濕機特佣]] -> 抽濕機特佣 | BB18: =表格1[[#Headers],[(Fortress ONLY)TW-T25BZU115MWH(MG) ]] -> (Fortress ONLY)TW-T25BZU115MWH(MG) | BC18: =表格1[[#Headers],[開門紅(三月)]] -> 開門紅(三月) | BD18: =表格1[[#Headers],[開門紅(第一季)]] -> 開門紅(第一季) | BE18: =表格1[[#Headers],[酵活炊電飯煲特佣 RC-18AMXH(W)]] -> 酵活炊電飯煲特佣 RC-18AMXH(W)
A19: 36 | B19: =B18 -> 2026-03 Toshiba | C19: =Total!C43 -> Gloria | D19: =Total!D43 -> Yeung Chor Mui | E19: =Total!E43 -> 20867 | F19: =Total!F43 -> TP_1 Yata | G19: =Total!G43 -> Mar/1,4-8,11-15,18-22,25-29 | H19: =Total!H43 -> 21 | I19: =Total!I43 -> 168 | J19: =Total!J43 -> 60 | ... AF19: =Total!AF43 -> 0 | AG19: =Total!AH43 -> 13832 | AO19: =表格1[[#Headers],[日本飯煲 RC-DS10K/18K]] -> 日本飯煲 RC-DS10K/18K | AP19: =表格1[[#Headers],[酵活炊電飯煲特佣 RC-18AMXH(W)]] -> 酵活炊電飯煲特佣 RC-18AMXH(W) | AQ19: =表格1[[#Headers],[嵌入式微波氣炸蒸焗爐特佣 EB-T500APW]] -> 嵌入式微波氣炸蒸焗爐特佣 EB-T500APW | AR19: =表格1[[#Headers],[蒸氣烤焗水波爐特佣 ER-VD7000HK(XK)]] -> 蒸氣烤焗水波爐特佣 ER-VD7000HK(XK) | AS19: =表格1[[#Headers],[TWDT21BU95 ]] -> TWDT21BU95 | AT19: =表格1[[#Headers],[日式洗衣機一特佣 AW-Q800APH(WW)]] -> 日式洗衣機一特佣 AW-Q800APH(WW) | AU19: =表格1[[#Headers],[日式洗衣機二特佣 AW-Q801APH(WW)]] -> 日式洗衣機二特佣 AW-Q801APH(WW) | AV19: =表格1[[#Headers],[三門雪櫃特佣 GR-RM469WE-PGA(B3)]] -> 三門雪櫃特佣 GR-RM469WE-PGA(B3) | AW19: =表格1[[#Headers],[雙門雪櫃一特佣 GR-RB449WE-PMA(57)]] -> 雙門雪櫃一特佣 GR-RB449WE-PMA(57) | AX19: =表格1[[#Headers],[雙門雪櫃一特佣 GR-RB410WE-PMA(06)]] -> 雙門雪櫃一特佣 GR-RB410WE-PMA(06) | AY19: =表格1[[#Headers],[十字門雪櫃 GR-RF698WI]] -> 十字門雪櫃 GR-RF698WI | AZ19: =表格1[[#Headers],[水機 TWP-W2265THK(W)]] -> 水機 TWP-W2265THK(W) | BA19: =表格1[[#Headers],[抽濕機特佣]] -> 抽濕機特佣 | BB19: =表格1[[#Headers],[(Fortress ONLY)TW-T25BZU115MWH(MG) ]] -> (Fortress ONLY)TW-T25BZU115MWH(MG) | BC19: =表格1[[#Headers],[開門紅(三月)]] -> 開門紅(三月) | BD19: =表格1[[#Headers],[開門紅(第一季)]] -> 開門紅(第一季) | BE19: =表格1[[#Headers],[酵活炊電飯煲特佣 RC-18AMXH(W)]] -> 酵活炊電飯煲特佣 RC-18AMXH(W)
A20: 40 | B20: =B19 -> 2026-03 Toshiba | C20: =Total!C47 -> Hazel | D20: =Total!D47 -> Tan Xingfang | E20: =Total!E47 -> 20868 | F20: =Total!F47 -> Kai Tak_2 Sogo | G20: =Total!G47 -> Mar/1-4,7-8 | H20: =Total!H47 -> 6 | I20: =Total!I47 -> 48 | J20: =Total!J47 -> 65 | ... AF20: =Total!AF47 -> 0 | AG20: =Total!AH47 -> 3796 | AO20: =表格1[[#Headers],[日本飯煲 RC-DS10K/18K]] -> 日本飯煲 RC-DS10K/18K | AP20: =表格1[[#Headers],[酵活炊電飯煲特佣 RC-18AMXH(W)]] -> 酵活炊電飯煲特佣 RC-18AMXH(W) | AQ20: =表格1[[#Headers],[嵌入式微波氣炸蒸焗爐特佣 EB-T500APW]] -> 嵌入式微波氣炸蒸焗爐特佣 EB-T500APW | AR20: =表格1[[#Headers],[蒸氣烤焗水波爐特佣 ER-VD7000HK(XK)]] -> 蒸氣烤焗水波爐特佣 ER-VD7000HK(XK) | AS20: =表格1[[#Headers],[TWDT21BU95 ]] -> TWDT21BU95 | AT20: =表格1[[#Headers],[日式洗衣機一特佣 AW-Q800APH(WW)]] -> 日式洗衣機一特佣 AW-Q800APH(WW) | AU20: =表格1[[#Headers],[日式洗衣機二特佣 AW-Q801APH(WW)]] -> 日式洗衣機二特佣 AW-Q801APH(WW) | AV20: =表格1[[#Headers],[三門雪櫃特佣 GR-RM469WE-PGA(B3)]] -> 三門雪櫃特佣 GR-RM469WE-PGA(B3) | AW20: =表格1[[#Headers],[雙門雪櫃一特佣 GR-RB449WE-PMA(57)]] -> 雙門雪櫃一特佣 GR-RB449WE-PMA(57) | AX20: =表格1[[#Headers],[雙門雪櫃一特佣 GR-RB410WE-PMA(06)]] -> 雙門雪櫃一特佣 GR-RB410WE-PMA(06) | AY20: =表格1[[#Headers],[十字門雪櫃 GR-RF698WI]] -> 十字門雪櫃 GR-RF698WI | AZ20: =表格1[[#Headers],[水機 TWP-W2265THK(W)]] -> 水機 TWP-W2265THK(W) | BA20: =表格1[[#Headers],[抽濕機特佣]] -> 抽濕機特佣 | BB20: =表格1[[#Headers],[(Fortress ONLY)TW-T25BZU115MWH(MG) ]] -> (Fortress ONLY)TW-T25BZU115MWH(MG) | BC20: =表格1[[#Headers],[開門紅(三月)]] -> 開門紅(三月) | BD20: =表格1[[#Headers],[開門紅(第一季)]] -> 開門紅(第一季) | BE20: =表格1[[#Headers],[酵活炊電飯煲特佣 RC-18AMXH(W)]] -> 酵活炊電飯煲特佣 RC-18AMXH(W)
A21: 43 | B21: =B20 -> 2026-03 Toshiba | C21: =Total!C50 -> Shirley | D21: =Total!D50 -> Sit Kwok Fong | E21: =Total!E50 -> 20869 | F21: =Total!F50 -> Kai Tak_5 Sogo | G21: =Total!G50 -> Mar/28-29 | H21: =Total!H50 -> 2 | I21: =Total!I50 -> 16 | J21: =Total!J50 -> 60 | ... AF21: =Total!AF50 -> 0 | AG21: =Total!AH50 -> 1160 | AO21: =表格1[[#Headers],[日本飯煲 RC-DS10K/18K]] -> 日本飯煲 RC-DS10K/18K | AP21: =表格1[[#Headers],[酵活炊電飯煲特佣 RC-18AMXH(W)]] -> 酵活炊電飯煲特佣 RC-18AMXH(W) | AQ21: =表格1[[#Headers],[嵌入式微波氣炸蒸焗爐特佣 EB-T500APW]] -> 嵌入式微波氣炸蒸焗爐特佣 EB-T500APW | AR21: =表格1[[#Headers],[蒸氣烤焗水波爐特佣 ER-VD7000HK(XK)]] -> 蒸氣烤焗水波爐特佣 ER-VD7000HK(XK) | AS21: =表格1[[#Headers],[TWDT21BU95 ]] -> TWDT21BU95 | AT21: =表格1[[#Headers],[日式洗衣機一特佣 AW-Q800APH(WW)]] -> 日式洗衣機一特佣 AW-Q800APH(WW) | AU21: =表格1[[#Headers],[日式洗衣機二特佣 AW-Q801APH(WW)]] -> 日式洗衣機二特佣 AW-Q801APH(WW) | AV21: =表格1[[#Headers],[三門雪櫃特佣 GR-RM469WE-PGA(B3)]] -> 三門雪櫃特佣 GR-RM469WE-PGA(B3) | AW21: =表格1[[#Headers],[雙門雪櫃一特佣 GR-RB449WE-PMA(57)]] -> 雙門雪櫃一特佣 GR-RB449WE-PMA(57) | AX21: =表格1[[#Headers],[雙門雪櫃一特佣 GR-RB410WE-PMA(06)]] -> 雙門雪櫃一特佣 GR-RB410WE-PMA(06) | AY21: =表格1[[#Headers],[十字門雪櫃 GR-RF698WI]] -> 十字門雪櫃 GR-RF698WI | AZ21: =表格1[[#Headers],[水機 TWP-W2265THK(W)]] -> 水機 TWP-W2265THK(W) | BA21: =表格1[[#Headers],[抽濕機特佣]] -> 抽濕機特佣 | BB21: =表格1[[#Headers],[(Fortress ONLY)TW-T25BZU115MWH(MG) ]] -> (Fortress ONLY)TW-T25BZU115MWH(MG) | BC21: =表格1[[#Headers],[開門紅(三月)]] -> 開門紅(三月) | BD21: =表格1[[#Headers],[開門紅(第一季)]] -> 開門紅(第一季) | BE21: =表格1[[#Headers],[酵活炊電飯煲特佣 RC-18AMXH(W)]] -> 酵活炊電飯煲特佣 RC-18AMXH(W)
A22: 46 | B22: =B21 -> 2026-03 Toshiba | C22: =Total!C53 -> Connie | D22: =Total!D53 -> Chan Siu Mui | E22: =Total!E53 -> 20870 | F22: =Total!F53 -> Mongkok_1 BBE | G22: =Total!G53 -> Mar/26-29 | H22: =Total!H53 -> 4 | I22: =Total!I53 -> 32 | J22: =Total!J53 -> 60 | ... AF22: =Total!AF53 -> 0 | AG22: =Total!AH53 -> 1920 | AO22: =表格1[[#Headers],[日本飯煲 RC-DS10K/18K]] -> 日本飯煲 RC-DS10K/18K | AP22: =表格1[[#Headers],[酵活炊電飯煲特佣 RC-18AMXH(W)]] -> 酵活炊電飯煲特佣 RC-18AMXH(W) | AQ22: =表格1[[#Headers],[嵌入式微波氣炸蒸焗爐特佣 EB-T500APW]] -> 嵌入式微波氣炸蒸焗爐特佣 EB-T500APW | AR22: =表格1[[#Headers],[蒸氣烤焗水波爐特佣 ER-VD7000HK(XK)]] -> 蒸氣烤焗水波爐特佣 ER-VD7000HK(XK) | AS22: =表格1[[#Headers],[TWDT21BU95 ]] -> TWDT21BU95 | AT22: =表格1[[#Headers],[日式洗衣機一特佣 AW-Q800APH(WW)]] -> 日式洗衣機一特佣 AW-Q800APH(WW) | AU22: =表格1[[#Headers],[日式洗衣機二特佣 AW-Q801APH(WW)]] -> 日式洗衣機二特佣 AW-Q801APH(WW) | AV22: =表格1[[#Headers],[三門雪櫃特佣 GR-RM469WE-PGA(B3)]] -> 三門雪櫃特佣 GR-RM469WE-PGA(B3) | AW22: =表格1[[#Headers],[雙門雪櫃一特佣 GR-RB449WE-PMA(57)]] -> 雙門雪櫃一特佣 GR-RB449WE-PMA(57) | AX22: =表格1[[#Headers],[雙門雪櫃一特佣 GR-RB410WE-PMA(06)]] -> 雙門雪櫃一特佣 GR-RB410WE-PMA(06) | AY22: =表格1[[#Headers],[十字門雪櫃 GR-RF698WI]] -> 十字門雪櫃 GR-RF698WI | AZ22: =表格1[[#Headers],[水機 TWP-W2265THK(W)]] -> 水機 TWP-W2265THK(W) | BA22: =表格1[[#Headers],[抽濕機特佣]] -> 抽濕機特佣 | BB22: =表格1[[#Headers],[(Fortress ONLY)TW-T25BZU115MWH(MG) ]] -> (Fortress ONLY)TW-T25BZU115MWH(MG) | BC22: =表格1[[#Headers],[開門紅(三月)]] -> 開門紅(三月) | BD22: =表格1[[#Headers],[開門紅(第一季)]] -> 開門紅(第一季) | BE22: =表格1[[#Headers],[酵活炊電飯煲特佣 RC-18AMXH(W)]] -> 酵活炊電飯煲特佣 RC-18AMXH(W)
A23: 47 | B23: =B22 -> 2026-03 Toshiba | C23: =Total!C54 -> Amy Or_2 | D23: =Total!D54 -> Or Sim Kiu | E23: =Total!E54 -> 20871 | F23: =Total!F54 -> Mongkok_2 BBE | G23: =Total!G54 -> Mar/14-15,19-22 | H23: =Total!H54 -> 6 | I23: =Total!I54 -> 48 | J23: =Total!J54 -> 55 | ... AF23: =Total!AF54 -> 0 | AG23: =Total!AH54 -> 4732 | AO23: =表格1[[#Headers],[日本飯煲 RC-DS10K/18K]] -> 日本飯煲 RC-DS10K/18K | AP23: =表格1[[#Headers],[酵活炊電飯煲特佣 RC-18AMXH(W)]] -> 酵活炊電飯煲特佣 RC-18AMXH(W) | AQ23: =表格1[[#Headers],[嵌入式微波氣炸蒸焗爐特佣 EB-T500APW]] -> 嵌入式微波氣炸蒸焗爐特佣 EB-T500APW | AR23: =表格1[[#Headers],[蒸氣烤焗水波爐特佣 ER-VD7000HK(XK)]] -> 蒸氣烤焗水波爐特佣 ER-VD7000HK(XK) | AS23: =表格1[[#Headers],[TWDT21BU95 ]] -> TWDT21BU95 | AT23: =表格1[[#Headers],[日式洗衣機一特佣 AW-Q800APH(WW)]] -> 日式洗衣機一特佣 AW-Q800APH(WW) | AU23: =表格1[[#Headers],[日式洗衣機二特佣 AW-Q801APH(WW)]] -> 日式洗衣機二特佣 AW-Q801APH(WW) | AV23: =表格1[[#Headers],[三門雪櫃特佣 GR-RM469WE-PGA(B3)]] -> 三門雪櫃特佣 GR-RM469WE-PGA(B3) | AW23: =表格1[[#Headers],[雙門雪櫃一特佣 GR-RB449WE-PMA(57)]] -> 雙門雪櫃一特佣 GR-RB449WE-PMA(57) | AX23: =表格1[[#Headers],[雙門雪櫃一特佣 GR-RB410WE-PMA(06)]] -> 雙門雪櫃一特佣 GR-RB410WE-PMA(06) | AY23: =表格1[[#Headers],[十字門雪櫃 GR-RF698WI]] -> 十字門雪櫃 GR-RF698WI | AZ23: =表格1[[#Headers],[水機 TWP-W2265THK(W)]] -> 水機 TWP-W2265THK(W) | BA23: =表格1[[#Headers],[抽濕機特佣]] -> 抽濕機特佣 | BB23: =表格1[[#Headers],[(Fortress ONLY)TW-T25BZU115MWH(MG) ]] -> (Fortress ONLY)TW-T25BZU115MWH(MG) | BC23: =表格1[[#Headers],[開門紅(三月)]] -> 開門紅(三月) | BD23: =表格1[[#Headers],[開門紅(第一季)]] -> 開門紅(第一季) | BE23: =表格1[[#Headers],[酵活炊電飯煲特佣 RC-18AMXH(W)]] -> 酵活炊電飯煲特佣 RC-18AMXH(W)
A24: 50 | B24: =B23 -> 2026-03 Toshiba | C24: =Total!C57 -> Terence_1 | D24: =Total!D57 -> Tsang Tak Kin | E24: =Total!E57 -> 20872 | F24: =Total!F57 -> Tai Koo_3 Apita | G24: =Total!G57 -> Mar/19-20,25 | H24: =Total!H57 -> 3 | I24: =Total!I57 -> 24 | J24: =Total!J57 -> 60 | ... AF24: =Total!AF57 -> 0 | AG24: =Total!AH57 -> 1661 | AO24: =表格1[[#Headers],[日本飯煲 RC-DS10K/18K]] -> 日本飯煲 RC-DS10K/18K | AP24: =表格1[[#Headers],[酵活炊電飯煲特佣 RC-18AMXH(W)]] -> 酵活炊電飯煲特佣 RC-18AMXH(W) | AQ24: =表格1[[#Headers],[嵌入式微波氣炸蒸焗爐特佣 EB-T500APW]] -> 嵌入式微波氣炸蒸焗爐特佣 EB-T500APW | AR24: =表格1[[#Headers],[蒸氣烤焗水波爐特佣 ER-VD7000HK(XK)]] -> 蒸氣烤焗水波爐特佣 ER-VD7000HK(XK) | AS24: =表格1[[#Headers],[TWDT21BU95 ]] -> TWDT21BU95 | AT24: =表格1[[#Headers],[日式洗衣機一特佣 AW-Q800APH(WW)]] -> 日式洗衣機一特佣 AW-Q800APH(WW) | AU24: =表格1[[#Headers],[日式洗衣機二特佣 AW-Q801APH(WW)]] -> 日式洗衣機二特佣 AW-Q801APH(WW) | AV24: =表格1[[#Headers],[三門雪櫃特佣 GR-RM469WE-PGA(B3)]] -> 三門雪櫃特佣 GR-RM469WE-PGA(B3) | AW24: =表格1[[#Headers],[雙門雪櫃一特佣 GR-RB449WE-PMA(57)]] -> 雙門雪櫃一特佣 GR-RB449WE-PMA(57) | AX24: =表格1[[#Headers],[雙門雪櫃一特佣 GR-RB410WE-PMA(06)]] -> 雙門雪櫃一特佣 GR-RB410WE-PMA(06) | AY24: =表格1[[#Headers],[十字門雪櫃 GR-RF698WI]] -> 十字門雪櫃 GR-RF698WI | AZ24: =表格1[[#Headers],[水機 TWP-W2265THK(W)]] -> 水機 TWP-W2265THK(W) | BA24: =表格1[[#Headers],[抽濕機特佣]] -> 抽濕機特佣 | BB24: =表格1[[#Headers],[(Fortress ONLY)TW-T25BZU115MWH(MG) ]] -> (Fortress ONLY)TW-T25BZU115MWH(MG) | BC24: =表格1[[#Headers],[開門紅(三月)]] -> 開門紅(三月) | BD24: =表格1[[#Headers],[開門紅(第一季)]] -> 開門紅(第一季) | BE24: =表格1[[#Headers],[酵活炊電飯煲特佣 RC-18AMXH(W)]] -> 酵活炊電飯煲特佣 RC-18AMXH(W)
A25: 51 | B25: =B24 -> 2026-03 Toshiba | C25: =Total!C58 -> PoWan | D25: =Total!D58 -> Ng Po Wan | E25: =Total!E58 -> 20873 | F25: =Total!F58 -> Kln Bay Demo Broadway | G25: =Total!G58 -> Mar/1-9 | H25: =Total!H58 -> 9 | I25: =Total!I58 -> 72 | J25: =Total!J58 -> 80 | ... AF25: =Total!AF58 -> 1510 | AG25: =Total!AH58 -> 10722 | AO25: =表格1[[#Headers],[日本飯煲 RC-DS10K/18K]] -> 日本飯煲 RC-DS10K/18K | AP25: =表格1[[#Headers],[酵活炊電飯煲特佣 RC-18AMXH(W)]] -> 酵活炊電飯煲特佣 RC-18AMXH(W) | AQ25: =表格1[[#Headers],[嵌入式微波氣炸蒸焗爐特佣 EB-T500APW]] -> 嵌入式微波氣炸蒸焗爐特佣 EB-T500APW | AR25: =表格1[[#Headers],[蒸氣烤焗水波爐特佣 ER-VD7000HK(XK)]] -> 蒸氣烤焗水波爐特佣 ER-VD7000HK(XK) | AS25: =表格1[[#Headers],[TWDT21BU95 ]] -> TWDT21BU95 | AT25: =表格1[[#Headers],[日式洗衣機一特佣 AW-Q800APH(WW)]] -> 日式洗衣機一特佣 AW-Q800APH(WW) | AU25: =表格1[[#Headers],[日式洗衣機二特佣 AW-Q801APH(WW)]] -> 日式洗衣機二特佣 AW-Q801APH(WW) | AV25: =表格1[[#Headers],[三門雪櫃特佣 GR-RM469WE-PGA(B3)]] -> 三門雪櫃特佣 GR-RM469WE-PGA(B3) | AW25: =表格1[[#Headers],[雙門雪櫃一特佣 GR-RB449WE-PMA(57)]] -> 雙門雪櫃一特佣 GR-RB449WE-PMA(57) | AX25: =表格1[[#Headers],[雙門雪櫃一特佣 GR-RB410WE-PMA(06)]] -> 雙門雪櫃一特佣 GR-RB410WE-PMA(06) | AY25: =表格1[[#Headers],[十字門雪櫃 GR-RF698WI]] -> 十字門雪櫃 GR-RF698WI | AZ25: =表格1[[#Headers],[水機 TWP-W2265THK(W)]] -> 水機 TWP-W2265THK(W) | BA25: =表格1[[#Headers],[抽濕機特佣]] -> 抽濕機特佣 | BB25: =表格1[[#Headers],[(Fortress ONLY)TW-T25BZU115MWH(MG) ]] -> (Fortress ONLY)TW-T25BZU115MWH(MG) | BC25: =表格1[[#Headers],[開門紅(三月)]] -> 開門紅(三月) | BD25: =表格1[[#Headers],[開門紅(第一季)]] -> 開門紅(第一季) | BE25: =表格1[[#Headers],[酵活炊電飯煲特佣 RC-18AMXH(W)]] -> 酵活炊電飯煲特佣 RC-18AMXH(W)
A26: 52 | B26: =B25 -> 2026-03 Toshiba | C26: =Total!C59 -> Maggie Ho_2 | D26: =Total!D59 -> Ho Lai Kuen | E26: =Total!E59 -> 20874 | F26: =Total!F59 -> CWB Sogo | G26: =Total!G59 -> Mar/16-17,20-21,23-24,26-27 | H26: =Total!H59 -> 8 | I26: =Total!I59 -> 64 | J26: =Total!J59 -> 65 | ... AF26: =Total!AF59 -> 0 | AG26: =Total!AH59 -> 5596 | AO26: =表格1[[#Headers],[日本飯煲 RC-DS10K/18K]] -> 日本飯煲 RC-DS10K/18K | AP26: =表格1[[#Headers],[酵活炊電飯煲特佣 RC-18AMXH(W)]] -> 酵活炊電飯煲特佣 RC-18AMXH(W) | AQ26: =表格1[[#Headers],[嵌入式微波氣炸蒸焗爐特佣 EB-T500APW]] -> 嵌入式微波氣炸蒸焗爐特佣 EB-T500APW | AR26: =表格1[[#Headers],[蒸氣烤焗水波爐特佣 ER-VD7000HK(XK)]] -> 蒸氣烤焗水波爐特佣 ER-VD7000HK(XK) | AS26: =表格1[[#Headers],[TWDT21BU95 ]] -> TWDT21BU95 | AT26: =表格1[[#Headers],[日式洗衣機一特佣 AW-Q800APH(WW)]] -> 日式洗衣機一特佣 AW-Q800APH(WW) | AU26: =表格1[[#Headers],[日式洗衣機二特佣 AW-Q801APH(WW)]] -> 日式洗衣機二特佣 AW-Q801APH(WW) | AV26: =表格1[[#Headers],[三門雪櫃特佣 GR-RM469WE-PGA(B3)]] -> 三門雪櫃特佣 GR-RM469WE-PGA(B3) | AW26: =表格1[[#Headers],[雙門雪櫃一特佣 GR-RB449WE-PMA(57)]] -> 雙門雪櫃一特佣 GR-RB449WE-PMA(57) | AX26: =表格1[[#Headers],[雙門雪櫃一特佣 GR-RB410WE-PMA(06)]] -> 雙門雪櫃一特佣 GR-RB410WE-PMA(06) | AY26: =表格1[[#Headers],[十字門雪櫃 GR-RF698WI]] -> 十字門雪櫃 GR-RF698WI | AZ26: =表格1[[#Headers],[水機 TWP-W2265THK(W)]] -> 水機 TWP-W2265THK(W) | BA26: =表格1[[#Headers],[抽濕機特佣]] -> 抽濕機特佣 | BB26: =表格1[[#Headers],[(Fortress ONLY)TW-T25BZU115MWH(MG) ]] -> (Fortress ONLY)TW-T25BZU115MWH(MG) | BC26: =表格1[[#Headers],[開門紅(三月)]] -> 開門紅(三月) | BD26: =表格1[[#Headers],[開門紅(第一季)]] -> 開門紅(第一季) | BE26: =表格1[[#Headers],[酵活炊電飯煲特佣 RC-18AMXH(W)]] -> 酵活炊電飯煲特佣 RC-18AMXH(W)
A27: 54 | B27: =B26 -> 2026-03 Toshiba | C27: =Total!C61 -> Ho_2 | D27: =Total!D61 -> Kwan Tit Ho | E27: =Total!E61 -> 20875 | F27: =Total!F61 -> TC RS Tung Yuen | G27: =Total!G61 -> Mar/20-23 | H27: =Total!H61 -> 4 | I27: =Total!I61 -> 32 | J27: =Total!J61 -> 60 | ... AF27: =Total!AF61 -> 0 | AG27: =Total!AH61 -> 3425 | AO27: =表格1[[#Headers],[日本飯煲 RC-DS10K/18K]] -> 日本飯煲 RC-DS10K/18K | AP27: =表格1[[#Headers],[酵活炊電飯煲特佣 RC-18AMXH(W)]] -> 酵活炊電飯煲特佣 RC-18AMXH(W) | AQ27: =表格1[[#Headers],[嵌入式微波氣炸蒸焗爐特佣 EB-T500APW]] -> 嵌入式微波氣炸蒸焗爐特佣 EB-T500APW | AR27: =表格1[[#Headers],[蒸氣烤焗水波爐特佣 ER-VD7000HK(XK)]] -> 蒸氣烤焗水波爐特佣 ER-VD7000HK(XK) | AS27: =表格1[[#Headers],[TWDT21BU95 ]] -> TWDT21BU95 | AT27: =表格1[[#Headers],[日式洗衣機一特佣 AW-Q800APH(WW)]] -> 日式洗衣機一特佣 AW-Q800APH(WW) | AU27: =表格1[[#Headers],[日式洗衣機二特佣 AW-Q801APH(WW)]] -> 日式洗衣機二特佣 AW-Q801APH(WW) | AV27: =表格1[[#Headers],[三門雪櫃特佣 GR-RM469WE-PGA(B3)]] -> 三門雪櫃特佣 GR-RM469WE-PGA(B3) | AW27: =表格1[[#Headers],[雙門雪櫃一特佣 GR-RB449WE-PMA(57)]] -> 雙門雪櫃一特佣 GR-RB449WE-PMA(57) | AX27: =表格1[[#Headers],[雙門雪櫃一特佣 GR-RB410WE-PMA(06)]] -> 雙門雪櫃一特佣 GR-RB410WE-PMA(06) | AY27: =表格1[[#Headers],[十字門雪櫃 GR-RF698WI]] -> 十字門雪櫃 GR-RF698WI | AZ27: =表格1[[#Headers],[水機 TWP-W2265THK(W)]] -> 水機 TWP-W2265THK(W) | BA27: =表格1[[#Headers],[抽濕機特佣]] -> 抽濕機特佣 | BB27: =表格1[[#Headers],[(Fortress ONLY)TW-T25BZU115MWH(MG) ]] -> (Fortress ONLY)TW-T25BZU115MWH(MG) | BC27: =表格1[[#Headers],[開門紅(三月)]] -> 開門紅(三月) | BD27: =表格1[[#Headers],[開門紅(第一季)]] -> 開門紅(第一季) | BE27: =表格1[[#Headers],[酵活炊電飯煲特佣 RC-18AMXH(W)]] -> 酵活炊電飯煲特佣 RC-18AMXH(W)
A28: 55 | B28: =B27 -> 2026-03 Toshiba | C28: =Total!C62 -> Terence_2 | D28: =Total!D62 -> Tsang Tak Kin | E28: =Total!E62 -> 20876 | F28: =Total!F62 -> TM RS Fortress | G28: =Total!G62 -> Mar/27-30 | H28: =Total!H62 -> 4 | I28: =Total!I62 -> 40 | J28: =Total!J62 -> 60 | ... AF28: =Total!AF62 -> 0 | AG28: =Total!AH62 -> 7822 | AO28: =表格1[[#Headers],[日本飯煲 RC-DS10K/18K]] -> 日本飯煲 RC-DS10K/18K | AP28: =表格1[[#Headers],[酵活炊電飯煲特佣 RC-18AMXH(W)]] -> 酵活炊電飯煲特佣 RC-18AMXH(W) | AQ28: =表格1[[#Headers],[嵌入式微波氣炸蒸焗爐特佣 EB-T500APW]] -> 嵌入式微波氣炸蒸焗爐特佣 EB-T500APW | AR28: =表格1[[#Headers],[蒸氣烤焗水波爐特佣 ER-VD7000HK(XK)]] -> 蒸氣烤焗水波爐特佣 ER-VD7000HK(XK) | AS28: =表格1[[#Headers],[TWDT21BU95 ]] -> TWDT21BU95 | AT28: =表格1[[#Headers],[日式洗衣機一特佣 AW-Q800APH(WW)]] -> 日式洗衣機一特佣 AW-Q800APH(WW) | AU28: =表格1[[#Headers],[日式洗衣機二特佣 AW-Q801APH(WW)]] -> 日式洗衣機二特佣 AW-Q801APH(WW) | AV28: =表格1[[#Headers],[三門雪櫃特佣 GR-RM469WE-PGA(B3)]] -> 三門雪櫃特佣 GR-RM469WE-PGA(B3) | AW28: =表格1[[#Headers],[雙門雪櫃一特佣 GR-RB449WE-PMA(57)]] -> 雙門雪櫃一特佣 GR-RB449WE-PMA(57) | AX28: =表格1[[#Headers],[雙門雪櫃一特佣 GR-RB410WE-PMA(06)]] -> 雙門雪櫃一特佣 GR-RB410WE-PMA(06) | AY28: =表格1[[#Headers],[十字門雪櫃 GR-RF698WI]] -> 十字門雪櫃 GR-RF698WI | AZ28: =表格1[[#Headers],[水機 TWP-W2265THK(W)]] -> 水機 TWP-W2265THK(W) | BA28: =表格1[[#Headers],[抽濕機特佣]] -> 抽濕機特佣 | BB28: =表格1[[#Headers],[(Fortress ONLY)TW-T25BZU115MWH(MG) ]] -> (Fortress ONLY)TW-T25BZU115MWH(MG) | BC28: =表格1[[#Headers],[開門紅(三月)]] -> 開門紅(三月) | BD28: =表格1[[#Headers],[開門紅(第一季)]] -> 開門紅(第一季) | BE28: =表格1[[#Headers],[酵活炊電飯煲特佣 RC-18AMXH(W)]] -> 酵活炊電飯煲特佣 RC-18AMXH(W)
A29: 56 | B29: =B28 -> 2026-03 Toshiba | C29: =Total!C63 -> Ho_1 | D29: =Total!D63 -> Kwan Tit Ho | E29: =Total!E63 -> 20877 | F29: =Total!F63 -> Tsuen Wan Aeon | G29: =Total!G63 -> Mar/1-3,5-12,14-15 | H29: =Total!H63 -> 13 | I29: =Total!I63 -> 104 | J29: =Total!J63 -> 60 | ... AF29: =Total!AF63 -> 0 | AG29: =Total!AH63 -> 8466 | AO29: =表格1[[#Headers],[日本飯煲 RC-DS10K/18K]] -> 日本飯煲 RC-DS10K/18K | AP29: =表格1[[#Headers],[酵活炊電飯煲特佣 RC-18AMXH(W)]] -> 酵活炊電飯煲特佣 RC-18AMXH(W) | AQ29: =表格1[[#Headers],[嵌入式微波氣炸蒸焗爐特佣 EB-T500APW]] -> 嵌入式微波氣炸蒸焗爐特佣 EB-T500APW | AR29: =表格1[[#Headers],[蒸氣烤焗水波爐特佣 ER-VD7000HK(XK)]] -> 蒸氣烤焗水波爐特佣 ER-VD7000HK(XK) | AS29: =表格1[[#Headers],[TWDT21BU95 ]] -> TWDT21BU95 | AT29: =表格1[[#Headers],[日式洗衣機一特佣 AW-Q800APH(WW)]] -> 日式洗衣機一特佣 AW-Q800APH(WW) | AU29: =表格1[[#Headers],[日式洗衣機二特佣 AW-Q801APH(WW)]] -> 日式洗衣機二特佣 AW-Q801APH(WW) | AV29: =表格1[[#Headers],[三門雪櫃特佣 GR-RM469WE-PGA(B3)]] -> 三門雪櫃特佣 GR-RM469WE-PGA(B3) | AW29: =表格1[[#Headers],[雙門雪櫃一特佣 GR-RB449WE-PMA(57)]] -> 雙門雪櫃一特佣 GR-RB449WE-PMA(57) | AX29: =表格1[[#Headers],[雙門雪櫃一特佣 GR-RB410WE-PMA(06)]] -> 雙門雪櫃一特佣 GR-RB410WE-PMA(06) | AY29: =表格1[[#Headers],[十字門雪櫃 GR-RF698WI]] -> 十字門雪櫃 GR-RF698WI | AZ29: =表格1[[#Headers],[水機 TWP-W2265THK(W)]] -> 水機 TWP-W2265THK(W) | BA29: =表格1[[#Headers],[抽濕機特佣]] -> 抽濕機特佣 | BB29: =表格1[[#Headers],[(Fortress ONLY)TW-T25BZU115MWH(MG) ]] -> (Fortress ONLY)TW-T25BZU115MWH(MG) | BC29: =表格1[[#Headers],[開門紅(三月)]] -> 開門紅(三月) | BD29: =表格1[[#Headers],[開門紅(第一季)]] -> 開門紅(第一季) | BE29: =表格1[[#Headers],[酵活炊電飯煲特佣 RC-18AMXH(W)]] -> 酵活炊電飯煲特佣 RC-18AMXH(W)
A30: 57 | B30: =B29 -> 2026-03 Toshiba | C30: =Total!C64 -> Winnie | D30: =Total!D64 -> Lee Yee Wan | E30: =Total!E64 -> 20878 | F30: =Total!F64 -> Panda Aeon | G30: =Total!G64 -> Mar/1,7-8,14-15 | H30: =Total!H64 -> 5 | I30: =Total!I64 -> 40 | J30: =Total!J64 -> 60 | ... AF30: =Total!AF64 -> 0 | AG30: =Total!AH64 -> 3727 | AO30: =表格1[[#Headers],[日本飯煲 RC-DS10K/18K]] -> 日本飯煲 RC-DS10K/18K | AP30: =表格1[[#Headers],[酵活炊電飯煲特佣 RC-18AMXH(W)]] -> 酵活炊電飯煲特佣 RC-18AMXH(W) | AQ30: =表格1[[#Headers],[嵌入式微波氣炸蒸焗爐特佣 EB-T500APW]] -> 嵌入式微波氣炸蒸焗爐特佣 EB-T500APW | AR30: =表格1[[#Headers],[蒸氣烤焗水波爐特佣 ER-VD7000HK(XK)]] -> 蒸氣烤焗水波爐特佣 ER-VD7000HK(XK) | AS30: =表格1[[#Headers],[TWDT21BU95 ]] -> TWDT21BU95 | AT30: =表格1[[#Headers],[日式洗衣機一特佣 AW-Q800APH(WW)]] -> 日式洗衣機一特佣 AW-Q800APH(WW) | AU30: =表格1[[#Headers],[日式洗衣機二特佣 AW-Q801APH(WW)]] -> 日式洗衣機二特佣 AW-Q801APH(WW) | AV30: =表格1[[#Headers],[三門雪櫃特佣 GR-RM469WE-PGA(B3)]] -> 三門雪櫃特佣 GR-RM469WE-PGA(B3) | AW30: =表格1[[#Headers],[雙門雪櫃一特佣 GR-RB449WE-PMA(57)]] -> 雙門雪櫃一特佣 GR-RB449WE-PMA(57) | AX30: =表格1[[#Headers],[雙門雪櫃一特佣 GR-RB410WE-PMA(06)]] -> 雙門雪櫃一特佣 GR-RB410WE-PMA(06) | AY30: =表格1[[#Headers],[十字門雪櫃 GR-RF698WI]] -> 十字門雪櫃 GR-RF698WI | AZ30: =表格1[[#Headers],[水機 TWP-W2265THK(W)]] -> 水機 TWP-W2265THK(W) | BA30: =表格1[[#Headers],[抽濕機特佣]] -> 抽濕機特佣 | BB30: =表格1[[#Headers],[(Fortress ONLY)TW-T25BZU115MWH(MG) ]] -> (Fortress ONLY)TW-T25BZU115MWH(MG) | BC30: =表格1[[#Headers],[開門紅(三月)]] -> 開門紅(三月) | BD30: =表格1[[#Headers],[開門紅(第一季)]] -> 開門紅(第一季) | BE30: =表格1[[#Headers],[酵活炊電飯煲特佣 RC-18AMXH(W)]] -> 酵活炊電飯煲特佣 RC-18AMXH(W)
A31: 58 | B31: =B30 -> 2026-03 Toshiba | C31: =Total!C65 -> Wendy Lau | D31: =Total!D65 -> Lau Kwan Wai | E31: =Total!E65 -> 20879 | F31: =Total!F65 -> LCK Aeon | G31: =Total!G65 -> Mar/1,7-8,14-15 | H31: =Total!H65 -> 5 | I31: =Total!I65 -> 40 | J31: =Total!J65 -> 60 | ... AF31: =Total!AF65 -> 0 | AG31: =Total!AH65 -> 3980 | AO31: =表格1[[#Headers],[日本飯煲 RC-DS10K/18K]] -> 日本飯煲 RC-DS10K/18K | AP31: =表格1[[#Headers],[酵活炊電飯煲特佣 RC-18AMXH(W)]] -> 酵活炊電飯煲特佣 RC-18AMXH(W) | AQ31: =表格1[[#Headers],[嵌入式微波氣炸蒸焗爐特佣 EB-T500APW]] -> 嵌入式微波氣炸蒸焗爐特佣 EB-T500APW | AR31: =表格1[[#Headers],[蒸氣烤焗水波爐特佣 ER-VD7000HK(XK)]] -> 蒸氣烤焗水波爐特佣 ER-VD7000HK(XK) | AS31: =表格1[[#Headers],[TWDT21BU95 ]] -> TWDT21BU95 | AT31: =表格1[[#Headers],[日式洗衣機一特佣 AW-Q800APH(WW)]] -> 日式洗衣機一特佣 AW-Q800APH(WW) | AU31: =表格1[[#Headers],[日式洗衣機二特佣 AW-Q801APH(WW)]] -> 日式洗衣機二特佣 AW-Q801APH(WW) | AV31: =表格1[[#Headers],[三門雪櫃特佣 GR-RM469WE-PGA(B3)]] -> 三門雪櫃特佣 GR-RM469WE-PGA(B3) | AW31: =表格1[[#Headers],[雙門雪櫃一特佣 GR-RB449WE-PMA(57)]] -> 雙門雪櫃一特佣 GR-RB449WE-PMA(57) | AX31: =表格1[[#Headers],[雙門雪櫃一特佣 GR-RB410WE-PMA(06)]] -> 雙門雪櫃一特佣 GR-RB410WE-PMA(06) | AY31: =表格1[[#Headers],[十字門雪櫃 GR-RF698WI]] -> 十字門雪櫃 GR-RF698WI | AZ31: =表格1[[#Headers],[水機 TWP-W2265THK(W)]] -> 水機 TWP-W2265THK(W) | BA31: =表格1[[#Headers],[抽濕機特佣]] -> 抽濕機特佣 | BB31: =表格1[[#Headers],[(Fortress ONLY)TW-T25BZU115MWH(MG) ]] -> (Fortress ONLY)TW-T25BZU115MWH(MG) | BC31: =表格1[[#Headers],[開門紅(三月)]] -> 開門紅(三月) | BD31: =表格1[[#Headers],[開門紅(第一季)]] -> 開門紅(第一季) | BE31: =表格1[[#Headers],[酵活炊電飯煲特佣 RC-18AMXH(W)]] -> 酵活炊電飯煲特佣 RC-18AMXH(W)
A32: 61 | B32: =B31 -> 2026-03 Toshiba | C32: =Total!C68 -> Maggie Ho_1 | D32: =Total!D68 -> Ho Lai Kuen | E32: =Total!E68 -> 20880 | F32: =Total!F68 -> TKO Aeon | G32: =Total!G68 -> Mar/1,7-8,14-15 | H32: =Total!H68 -> 5 | I32: =Total!I68 -> 40 | J32: =Total!J68 -> 65 | ... AF32: =Total!AF68 -> 0 | AG32: =Total!AH68 -> 4375 | AO32: =表格1[[#Headers],[日本飯煲 RC-DS10K/18K]] -> 日本飯煲 RC-DS10K/18K | AP32: =表格1[[#Headers],[酵活炊電飯煲特佣 RC-18AMXH(W)]] -> 酵活炊電飯煲特佣 RC-18AMXH(W) | AQ32: =表格1[[#Headers],[嵌入式微波氣炸蒸焗爐特佣 EB-T500APW]] -> 嵌入式微波氣炸蒸焗爐特佣 EB-T500APW | AR32: =表格1[[#Headers],[蒸氣烤焗水波爐特佣 ER-VD7000HK(XK)]] -> 蒸氣烤焗水波爐特佣 ER-VD7000HK(XK) | AS32: =表格1[[#Headers],[TWDT21BU95 ]] -> TWDT21BU95 | AT32: =表格1[[#Headers],[日式洗衣機一特佣 AW-Q800APH(WW)]] -> 日式洗衣機一特佣 AW-Q800APH(WW) | AU32: =表格1[[#Headers],[日式洗衣機二特佣 AW-Q801APH(WW)]] -> 日式洗衣機二特佣 AW-Q801APH(WW) | AV32: =表格1[[#Headers],[三門雪櫃特佣 GR-RM469WE-PGA(B3)]] -> 三門雪櫃特佣 GR-RM469WE-PGA(B3) | AW32: =表格1[[#Headers],[雙門雪櫃一特佣 GR-RB449WE-PMA(57)]] -> 雙門雪櫃一特佣 GR-RB449WE-PMA(57) | AX32: =表格1[[#Headers],[雙門雪櫃一特佣 GR-RB410WE-PMA(06)]] -> 雙門雪櫃一特佣 GR-RB410WE-PMA(06) | AY32: =表格1[[#Headers],[十字門雪櫃 GR-RF698WI]] -> 十字門雪櫃 GR-RF698WI | AZ32: =表格1[[#Headers],[水機 TWP-W2265THK(W)]] -> 水機 TWP-W2265THK(W) | BA32: =表格1[[#Headers],[抽濕機特佣]] -> 抽濕機特佣 | BB32: =表格1[[#Headers],[(Fortress ONLY)TW-T25BZU115MWH(MG) ]] -> (Fortress ONLY)TW-T25BZU115MWH(MG) | BC32: =表格1[[#Headers],[開門紅(三月)]] -> 開門紅(三月) | BD32: =表格1[[#Headers],[開門紅(第一季)]] -> 開門紅(第一季) | BE32: =表格1[[#Headers],[酵活炊電飯煲特佣 RC-18AMXH(W)]] -> 酵活炊電飯煲特佣 RC-18AMXH(W)
A33: 62 | B33: =B32 -> 2026-03 Toshiba | C33: =Total!C69 -> Eddy | D33: =Total!D69 -> Chan Chi Tim | E33: =Total!E69 -> 20881 | F33: =Total!F69 -> Training_1 | G33: =Total!G69 -> Mar/24 | H33: =Total!H69 -> 1 | I33: =Total!I69 -> 7 | J33: =Total!J69 -> 50 | ... AF33: =Total!AF69 -> 0 | AG33: =Total!AH69 -> 350 | AO33: =表格1[[#Headers],[日本飯煲 RC-DS10K/18K]] -> 日本飯煲 RC-DS10K/18K | AP33: =表格1[[#Headers],[酵活炊電飯煲特佣 RC-18AMXH(W)]] -> 酵活炊電飯煲特佣 RC-18AMXH(W) | AQ33: =表格1[[#Headers],[嵌入式微波氣炸蒸焗爐特佣 EB-T500APW]] -> 嵌入式微波氣炸蒸焗爐特佣 EB-T500APW | AR33: =表格1[[#Headers],[蒸氣烤焗水波爐特佣 ER-VD7000HK(XK)]] -> 蒸氣烤焗水波爐特佣 ER-VD7000HK(XK) | AS33: =表格1[[#Headers],[TWDT21BU95 ]] -> TWDT21BU95 | AT33: =表格1[[#Headers],[日式洗衣機一特佣 AW-Q800APH(WW)]] -> 日式洗衣機一特佣 AW-Q800APH(WW) | AU33: =表格1[[#Headers],[日式洗衣機二特佣 AW-Q801APH(WW)]] -> 日式洗衣機二特佣 AW-Q801APH(WW) | AV33: =表格1[[#Headers],[三門雪櫃特佣 GR-RM469WE-PGA(B3)]] -> 三門雪櫃特佣 GR-RM469WE-PGA(B3) | AW33: =表格1[[#Headers],[雙門雪櫃一特佣 GR-RB449WE-PMA(57)]] -> 雙門雪櫃一特佣 GR-RB449WE-PMA(57) | AX33: =表格1[[#Headers],[雙門雪櫃一特佣 GR-RB410WE-PMA(06)]] -> 雙門雪櫃一特佣 GR-RB410WE-PMA(06) | AY33: =表格1[[#Headers],[十字門雪櫃 GR-RF698WI]] -> 十字門雪櫃 GR-RF698WI | AZ33: =表格1[[#Headers],[水機 TWP-W2265THK(W)]] -> 水機 TWP-W2265THK(W) | BA33: =表格1[[#Headers],[抽濕機特佣]] -> 抽濕機特佣 | BB33: =表格1[[#Headers],[(Fortress ONLY)TW-T25BZU115MWH(MG) ]] -> (Fortress ONLY)TW-T25BZU115MWH(MG) | BC33: =表格1[[#Headers],[開門紅(三月)]] -> 開門紅(三月) | BD33: =表格1[[#Headers],[開門紅(第一季)]] -> 開門紅(第一季) | BE33: =表格1[[#Headers],[酵活炊電飯煲特佣 RC-18AMXH(W)]] -> 酵活炊電飯煲特佣 RC-18AMXH(W)
A34: 64 | B34: =B33 -> 2026-03 Toshiba | C34: =Total!C71 -> WanWah | D34: =Total!D71 -> Chan Wan Wah | E34: =Total!E71 -> 20882 | F34: =Total!F71 -> Training_3 | G34: =Total!G71 -> Mar/24 | H34: =Total!H71 -> 1 | I34: =Total!I71 -> 7 | J34: =Total!J71 -> 50 | ... AF34: =Total!AF71 -> 0 | AG34: =Total!AH71 -> 350 | AO34: =表格1[[#Headers],[日本飯煲 RC-DS10K/18K]] -> 日本飯煲 RC-DS10K/18K | AP34: =表格1[[#Headers],[酵活炊電飯煲特佣 RC-18AMXH(W)]] -> 酵活炊電飯煲特佣 RC-18AMXH(W) | AQ34: =表格1[[#Headers],[嵌入式微波氣炸蒸焗爐特佣 EB-T500APW]] -> 嵌入式微波氣炸蒸焗爐特佣 EB-T500APW | AR34: =表格1[[#Headers],[蒸氣烤焗水波爐特佣 ER-VD7000HK(XK)]] -> 蒸氣烤焗水波爐特佣 ER-VD7000HK(XK) | AS34: =表格1[[#Headers],[TWDT21BU95 ]] -> TWDT21BU95 | AT34: =表格1[[#Headers],[日式洗衣機一特佣 AW-Q800APH(WW)]] -> 日式洗衣機一特佣 AW-Q800APH(WW) | AU34: =表格1[[#Headers],[日式洗衣機二特佣 AW-Q801APH(WW)]] -> 日式洗衣機二特佣 AW-Q801APH(WW) | AV34: =表格1[[#Headers],[三門雪櫃特佣 GR-RM469WE-PGA(B3)]] -> 三門雪櫃特佣 GR-RM469WE-PGA(B3) | AW34: =表格1[[#Headers],[雙門雪櫃一特佣 GR-RB449WE-PMA(57)]] -> 雙門雪櫃一特佣 GR-RB449WE-PMA(57) | AX34: =表格1[[#Headers],[雙門雪櫃一特佣 GR-RB410WE-PMA(06)]] -> 雙門雪櫃一特佣 GR-RB410WE-PMA(06) | AY34: =表格1[[#Headers],[十字門雪櫃 GR-RF698WI]] -> 十字門雪櫃 GR-RF698WI | AZ34: =表格1[[#Headers],[水機 TWP-W2265THK(W)]] -> 水機 TWP-W2265THK(W) | BA34: =表格1[[#Headers],[抽濕機特佣]] -> 抽濕機特佣 | BB34: =表格1[[#Headers],[(Fortress ONLY)TW-T25BZU115MWH(MG) ]] -> (Fortress ONLY)TW-T25BZU115MWH(MG) | BC34: =表格1[[#Headers],[開門紅(三月)]] -> 開門紅(三月) | BD34: =表格1[[#Headers],[開門紅(第一季)]] -> 開門紅(第一季) | BE34: =表格1[[#Headers],[酵活炊電飯煲特佣 RC-18AMXH(W)]] -> 酵活炊電飯煲特佣 RC-18AMXH(W)
A35: 2 | B35: =B34 -> 2026-03 Toshiba | C35: =Total!C9 -> Ivy Wong_1 | D35: =Total!D9 -> Wong Wai Chu | E35: =Total!E9 -> Autopay | F35: =Total!F9 -> Vcity_1 Fortress | G35: =Total!G9 -> Mar/1,14-15,21-22,25,28 | H35: =Total!H9 -> 7 | I35: =Total!I9 -> 56 | J35: =Total!J9 -> 60 | ... AF35: =Total!AF9 -> 0 | AG35: =Total!AH9 -> 8607 | AO35: =表格1[[#Headers],[日本飯煲 RC-DS10K/18K]] -> 日本飯煲 RC-DS10K/18K | AP35: =表格1[[#Headers],[酵活炊電飯煲特佣 RC-18AMXH(W)]] -> 酵活炊電飯煲特佣 RC-18AMXH(W) | AQ35: =表格1[[#Headers],[嵌入式微波氣炸蒸焗爐特佣 EB-T500APW]] -> 嵌入式微波氣炸蒸焗爐特佣 EB-T500APW | AR35: =表格1[[#Headers],[蒸氣烤焗水波爐特佣 ER-VD7000HK(XK)]] -> 蒸氣烤焗水波爐特佣 ER-VD7000HK(XK) | AS35: =表格1[[#Headers],[TWDT21BU95 ]] -> TWDT21BU95 | AT35: =表格1[[#Headers],[日式洗衣機一特佣 AW-Q800APH(WW)]] -> 日式洗衣機一特佣 AW-Q800APH(WW) | AU35: =表格1[[#Headers],[日式洗衣機二特佣 AW-Q801APH(WW)]] -> 日式洗衣機二特佣 AW-Q801APH(WW) | AV35: =表格1[[#Headers],[三門雪櫃特佣 GR-RM469WE-PGA(B3)]] -> 三門雪櫃特佣 GR-RM469WE-PGA(B3) | AW35: =表格1[[#Headers],[雙門雪櫃一特佣 GR-RB449WE-PMA(57)]] -> 雙門雪櫃一特佣 GR-RB449WE-PMA(57) | AX35: =表格1[[#Headers],[雙門雪櫃一特佣 GR-RB410WE-PMA(06)]] -> 雙門雪櫃一特佣 GR-RB410WE-PMA(06) | AY35: =表格1[[#Headers],[十字門雪櫃 GR-RF698WI]] -> 十字門雪櫃 GR-RF698WI | AZ35: =表格1[[#Headers],[水機 TWP-W2265THK(W)]] -> 水機 TWP-W2265THK(W) | BA35: =表格1[[#Headers],[抽濕機特佣]] -> 抽濕機特佣 | BB35: =表格1[[#Headers],[(Fortress ONLY)TW-T25BZU115MWH(MG) ]] -> (Fortress ONLY)TW-T25BZU115MWH(MG) | BC35: =表格1[[#Headers],[開門紅(三月)]] -> 開門紅(三月) | BD35: =表格1[[#Headers],[開門紅(第一季)]] -> 開門紅(第一季) | BE35: =表格1[[#Headers],[酵活炊電飯煲特佣 RC-18AMXH(W)]] -> 酵活炊電飯煲特佣 RC-18AMXH(W)
A36: 3 | B36: =B35 -> 2026-03 Toshiba | C36: =Total!C10 -> Kit_3 | D36: =Total!D10 -> Li Wenjie | E36: =Total!E10 -> Autopay | F36: =Total!F10 -> Vcity_2 Fortress | G36: =Total!G10 -> Mar/7-8 | H36: =Total!H10 -> 2 | I36: =Total!I10 -> 16 | J36: =Total!J10 -> 60 | ... AF36: =Total!AF10 -> 0 | AG36: =Total!AH10 -> 1118 | AO36: =表格1[[#Headers],[日本飯煲 RC-DS10K/18K]] -> 日本飯煲 RC-DS10K/18K | AP36: =表格1[[#Headers],[酵活炊電飯煲特佣 RC-18AMXH(W)]] -> 酵活炊電飯煲特佣 RC-18AMXH(W) | AQ36: =表格1[[#Headers],[嵌入式微波氣炸蒸焗爐特佣 EB-T500APW]] -> 嵌入式微波氣炸蒸焗爐特佣 EB-T500APW | AR36: =表格1[[#Headers],[蒸氣烤焗水波爐特佣 ER-VD7000HK(XK)]] -> 蒸氣烤焗水波爐特佣 ER-VD7000HK(XK) | AS36: =表格1[[#Headers],[TWDT21BU95 ]] -> TWDT21BU95 | AT36: =表格1[[#Headers],[日式洗衣機一特佣 AW-Q800APH(WW)]] -> 日式洗衣機一特佣 AW-Q800APH(WW) | AU36: =表格1[[#Headers],[日式洗衣機二特佣 AW-Q801APH(WW)]] -> 日式洗衣機二特佣 AW-Q801APH(WW) | AV36: =表格1[[#Headers],[三門雪櫃特佣 GR-RM469WE-PGA(B3)]] -> 三門雪櫃特佣 GR-RM469WE-PGA(B3) | AW36: =表格1[[#Headers],[雙門雪櫃一特佣 GR-RB449WE-PMA(57)]] -> 雙門雪櫃一特佣 GR-RB449WE-PMA(57) | AX36: =表格1[[#Headers],[雙門雪櫃一特佣 GR-RB410WE-PMA(06)]] -> 雙門雪櫃一特佣 GR-RB410WE-PMA(06) | AY36: =表格1[[#Headers],[十字門雪櫃 GR-RF698WI]] -> 十字門雪櫃 GR-RF698WI | AZ36: =表格1[[#Headers],[水機 TWP-W2265THK(W)]] -> 水機 TWP-W2265THK(W) | BA36: =表格1[[#Headers],[抽濕機特佣]] -> 抽濕機特佣 | BB36: =表格1[[#Headers],[(Fortress ONLY)TW-T25BZU115MWH(MG) ]] -> (Fortress ONLY)TW-T25BZU115MWH(MG) | BC36: =表格1[[#Headers],[開門紅(三月)]] -> 開門紅(三月) | BD36: =表格1[[#Headers],[開門紅(第一季)]] -> 開門紅(第一季) | BE36: =表格1[[#Headers],[酵活炊電飯煲特佣 RC-18AMXH(W)]] -> 酵活炊電飯煲特佣 RC-18AMXH(W)
A37: 5 | B37: =B36 -> 2026-03 Toshiba | C37: =Total!C12 -> Michelle | D37: =Total!D12 -> Lo Muk Chun | E37: =Total!E12 -> Autopay | F37: =Total!F12 -> Good Hope Fortress | G37: =Total!G12 -> Mar/1,5-8,11-15,17-22,25-29,31 | H37: =Total!H12 -> 22 | I37: =Total!I12 -> 176 | J37: =Total!J12 -> 60 | ... AF37: =Total!AF12 -> 0 | AG37: =Total!AH12 -> 20397 | AO37: =表格1[[#Headers],[日本飯煲 RC-DS10K/18K]] -> 日本飯煲 RC-DS10K/18K | AP37: =表格1[[#Headers],[酵活炊電飯煲特佣 RC-18AMXH(W)]] -> 酵活炊電飯煲特佣 RC-18AMXH(W) | AQ37: =表格1[[#Headers],[嵌入式微波氣炸蒸焗爐特佣 EB-T500APW]] -> 嵌入式微波氣炸蒸焗爐特佣 EB-T500APW | AR37: =表格1[[#Headers],[蒸氣烤焗水波爐特佣 ER-VD7000HK(XK)]] -> 蒸氣烤焗水波爐特佣 ER-VD7000HK(XK) | AS37: =表格1[[#Headers],[TWDT21BU95 ]] -> TWDT21BU95 | AT37: =表格1[[#Headers],[日式洗衣機一特佣 AW-Q800APH(WW)]] -> 日式洗衣機一特佣 AW-Q800APH(WW) | AU37: =表格1[[#Headers],[日式洗衣機二特佣 AW-Q801APH(WW)]] -> 日式洗衣機二特佣 AW-Q801APH(WW) | AV37: =表格1[[#Headers],[三門雪櫃特佣 GR-RM469WE-PGA(B3)]] -> 三門雪櫃特佣 GR-RM469WE-PGA(B3) | AW37: =表格1[[#Headers],[雙門雪櫃一特佣 GR-RB449WE-PMA(57)]] -> 雙門雪櫃一特佣 GR-RB449WE-PMA(57) | AX37: =表格1[[#Headers],[雙門雪櫃一特佣 GR-RB410WE-PMA(06)]] -> 雙門雪櫃一特佣 GR-RB410WE-PMA(06) | AY37: =表格1[[#Headers],[十字門雪櫃 GR-RF698WI]] -> 十字門雪櫃 GR-RF698WI | AZ37: =表格1[[#Headers],[水機 TWP-W2265THK(W)]] -> 水機 TWP-W2265THK(W) | BA37: =表格1[[#Headers],[抽濕機特佣]] -> 抽濕機特佣 | BB37: =表格1[[#Headers],[(Fortress ONLY)TW-T25BZU115MWH(MG) ]] -> (Fortress ONLY)TW-T25BZU115MWH(MG) | BC37: =表格1[[#Headers],[開門紅(三月)]] -> 開門紅(三月) | BD37: =表格1[[#Headers],[開門紅(第一季)]] -> 開門紅(第一季) | BE37: =表格1[[#Headers],[酵活炊電飯煲特佣 RC-18AMXH(W)]] -> 酵活炊電飯煲特佣 RC-18AMXH(W)
A38: 9 | B38: =B37 -> 2026-03 Toshiba | C38: =Total!C16 -> Fong_1 | D38: =Total!D16 -> Ng Nga Fong | E38: =Total!E16 -> Autopay | F38: =Total!F16 -> Diamond Hill_1 Broadway | G38: =Total!G16 -> Mar/1,7-8,14-15,28-29 | H38: =Total!H16 -> 7 | I38: =Total!I16 -> 56 | J38: =Total!J16 -> 60 | ... AF38: =Total!AF16 -> 0 | AG38: =Total!AH16 -> 4712 | AO38: =表格1[[#Headers],[日本飯煲 RC-DS10K/18K]] -> 日本飯煲 RC-DS10K/18K | AP38: =表格1[[#Headers],[酵活炊電飯煲特佣 RC-18AMXH(W)]] -> 酵活炊電飯煲特佣 RC-18AMXH(W) | AQ38: =表格1[[#Headers],[嵌入式微波氣炸蒸焗爐特佣 EB-T500APW]] -> 嵌入式微波氣炸蒸焗爐特佣 EB-T500APW | AR38: =表格1[[#Headers],[蒸氣烤焗水波爐特佣 ER-VD7000HK(XK)]] -> 蒸氣烤焗水波爐特佣 ER-VD7000HK(XK) | AS38: =表格1[[#Headers],[TWDT21BU95 ]] -> TWDT21BU95 | AT38: =表格1[[#Headers],[日式洗衣機一特佣 AW-Q800APH(WW)]] -> 日式洗衣機一特佣 AW-Q800APH(WW) | AU38: =表格1[[#Headers],[日式洗衣機二特佣 AW-Q801APH(WW)]] -> 日式洗衣機二特佣 AW-Q801APH(WW) | AV38: =表格1[[#Headers],[三門雪櫃特佣 GR-RM469WE-PGA(B3)]] -> 三門雪櫃特佣 GR-RM469WE-PGA(B3) | AW38: =表格1[[#Headers],[雙門雪櫃一特佣 GR-RB449WE-PMA(57)]] -> 雙門雪櫃一特佣 GR-RB449WE-PMA(57) | AX38: =表格1[[#Headers],[雙門雪櫃一特佣 GR-RB410WE-PMA(06)]] -> 雙門雪櫃一特佣 GR-RB410WE-PMA(06) | AY38: =表格1[[#Headers],[十字門雪櫃 GR-RF698WI]] -> 十字門雪櫃 GR-RF698WI | AZ38: =表格1[[#Headers],[水機 TWP-W2265THK(W)]] -> 水機 TWP-W2265THK(W) | BA38: =表格1[[#Headers],[抽濕機特佣]] -> 抽濕機特佣 | BB38: =表格1[[#Headers],[(Fortress ONLY)TW-T25BZU115MWH(MG) ]] -> (Fortress ONLY)TW-T25BZU115MWH(MG) | BC38: =表格1[[#Headers],[開門紅(三月)]] -> 開門紅(三月) | BD38: =表格1[[#Headers],[開門紅(第一季)]] -> 開門紅(第一季) | BE38: =表格1[[#Headers],[酵活炊電飯煲特佣 RC-18AMXH(W)]] -> 酵活炊電飯煲特佣 RC-18AMXH(W)
A39: 10 | B39: =B38 -> 2026-03 Toshiba | C39: =Total!C17 -> Mui Chan_2 | D39: =Total!D17 -> Chan So Mui | E39: =Total!E17 -> Autopay | F39: =Total!F17 -> Diamond Hill_2 Broadway | G39: =Total!G17 -> Mar/21-22 | H39: =Total!H17 -> 2 | I39: =Total!I17 -> 16 | J39: =Total!J17 -> 60 | ... AF39: =Total!AF17 -> 30 | AG39: =Total!AH17 -> 1336 | AO39: =表格1[[#Headers],[日本飯煲 RC-DS10K/18K]] -> 日本飯煲 RC-DS10K/18K | AP39: =表格1[[#Headers],[酵活炊電飯煲特佣 RC-18AMXH(W)]] -> 酵活炊電飯煲特佣 RC-18AMXH(W) | AQ39: =表格1[[#Headers],[嵌入式微波氣炸蒸焗爐特佣 EB-T500APW]] -> 嵌入式微波氣炸蒸焗爐特佣 EB-T500APW | AR39: =表格1[[#Headers],[蒸氣烤焗水波爐特佣 ER-VD7000HK(XK)]] -> 蒸氣烤焗水波爐特佣 ER-VD7000HK(XK) | AS39: =表格1[[#Headers],[TWDT21BU95 ]] -> TWDT21BU95 | AT39: =表格1[[#Headers],[日式洗衣機一特佣 AW-Q800APH(WW)]] -> 日式洗衣機一特佣 AW-Q800APH(WW) | AU39: =表格1[[#Headers],[日式洗衣機二特佣 AW-Q801APH(WW)]] -> 日式洗衣機二特佣 AW-Q801APH(WW) | AV39: =表格1[[#Headers],[三門雪櫃特佣 GR-RM469WE-PGA(B3)]] -> 三門雪櫃特佣 GR-RM469WE-PGA(B3) | AW39: =表格1[[#Headers],[雙門雪櫃一特佣 GR-RB449WE-PMA(57)]] -> 雙門雪櫃一特佣 GR-RB449WE-PMA(57) | AX39: =表格1[[#Headers],[雙門雪櫃一特佣 GR-RB410WE-PMA(06)]] -> 雙門雪櫃一特佣 GR-RB410WE-PMA(06) | AY39: =表格1[[#Headers],[十字門雪櫃 GR-RF698WI]] -> 十字門雪櫃 GR-RF698WI | AZ39: =表格1[[#Headers],[水機 TWP-W2265THK(W)]] -> 水機 TWP-W2265THK(W) | BA39: =表格1[[#Headers],[抽濕機特佣]] -> 抽濕機特佣 | BB39: =表格1[[#Headers],[(Fortress ONLY)TW-T25BZU115MWH(MG) ]] -> (Fortress ONLY)TW-T25BZU115MWH(MG) | BC39: =表格1[[#Headers],[開門紅(三月)]] -> 開門紅(三月) | BD39: =表格1[[#Headers],[開門紅(第一季)]] -> 開門紅(第一季) | BE39: =表格1[[#Headers],[酵活炊電飯煲特佣 RC-18AMXH(W)]] -> 酵活炊電飯煲特佣 RC-18AMXH(W)
A40: 12 | B40: =B39 -> 2026-03 Toshiba | C40: =Total!C19 -> Wendy Wong_1 | D40: =Total!D19 -> Wong Lai Ying | E40: =Total!E19 -> Autopay | F40: =Total!F19 -> TW_2 Citistore | G40: =Total!G19 -> Mar/3-4,11,13,18-19,24 | H40: =Total!H19 -> 7 | I40: =Total!I19 -> 63 | J40: =Total!J19 -> 60 | ... AF40: =Total!AF19 -> 0 | AG40: =Total!AH19 -> 4344 | AO40: =表格1[[#Headers],[日本飯煲 RC-DS10K/18K]] -> 日本飯煲 RC-DS10K/18K | AP40: =表格1[[#Headers],[酵活炊電飯煲特佣 RC-18AMXH(W)]] -> 酵活炊電飯煲特佣 RC-18AMXH(W) | AQ40: =表格1[[#Headers],[嵌入式微波氣炸蒸焗爐特佣 EB-T500APW]] -> 嵌入式微波氣炸蒸焗爐特佣 EB-T500APW | AR40: =表格1[[#Headers],[蒸氣烤焗水波爐特佣 ER-VD7000HK(XK)]] -> 蒸氣烤焗水波爐特佣 ER-VD7000HK(XK) | AS40: =表格1[[#Headers],[TWDT21BU95 ]] -> TWDT21BU95 | AT40: =表格1[[#Headers],[日式洗衣機一特佣 AW-Q800APH(WW)]] -> 日式洗衣機一特佣 AW-Q800APH(WW) | AU40: =表格1[[#Headers],[日式洗衣機二特佣 AW-Q801APH(WW)]] -> 日式洗衣機二特佣 AW-Q801APH(WW) | AV40: =表格1[[#Headers],[三門雪櫃特佣 GR-RM469WE-PGA(B3)]] -> 三門雪櫃特佣 GR-RM469WE-PGA(B3) | AW40: =表格1[[#Headers],[雙門雪櫃一特佣 GR-RB449WE-PMA(57)]] -> 雙門雪櫃一特佣 GR-RB449WE-PMA(57) | AX40: =表格1[[#Headers],[雙門雪櫃一特佣 GR-RB410WE-PMA(06)]] -> 雙門雪櫃一特佣 GR-RB410WE-PMA(06) | AY40: =表格1[[#Headers],[十字門雪櫃 GR-RF698WI]] -> 十字門雪櫃 GR-RF698WI | AZ40: =表格1[[#Headers],[水機 TWP-W2265THK(W)]] -> 水機 TWP-W2265THK(W) | BA40: =表格1[[#Headers],[抽濕機特佣]] -> 抽濕機特佣 | BB40: =表格1[[#Headers],[(Fortress ONLY)TW-T25BZU115MWH(MG) ]] -> (Fortress ONLY)TW-T25BZU115MWH(MG) | BC40: =表格1[[#Headers],[開門紅(三月)]] -> 開門紅(三月) | BD40: =表格1[[#Headers],[開門紅(第一季)]] -> 開門紅(第一季) | BE40: =表格1[[#Headers],[酵活炊電飯煲特佣 RC-18AMXH(W)]] -> 酵活炊電飯煲特佣 RC-18AMXH(W)
A41: 13 | B41: =B40 -> 2026-03 Toshiba | C41: =Total!C20 -> Mandy | D41: =Total!D20 -> Ho Lai Sim | E41: =Total!E20 -> Autopay | F41: =Total!F20 -> TW_3 Citistore | G41: =Total!G20 -> Mar/12 | H41: =Total!H20 -> 1 | I41: =Total!I20 -> 9 | J41: =Total!J20 -> 60 | ... AF41: =Total!AF20 -> 0 | AG41: =Total!AH20 -> 633 | AO41: =表格1[[#Headers],[日本飯煲 RC-DS10K/18K]] -> 日本飯煲 RC-DS10K/18K | AP41: =表格1[[#Headers],[酵活炊電飯煲特佣 RC-18AMXH(W)]] -> 酵活炊電飯煲特佣 RC-18AMXH(W) | AQ41: =表格1[[#Headers],[嵌入式微波氣炸蒸焗爐特佣 EB-T500APW]] -> 嵌入式微波氣炸蒸焗爐特佣 EB-T500APW | AR41: =表格1[[#Headers],[蒸氣烤焗水波爐特佣 ER-VD7000HK(XK)]] -> 蒸氣烤焗水波爐特佣 ER-VD7000HK(XK) | AS41: =表格1[[#Headers],[TWDT21BU95 ]] -> TWDT21BU95 | AT41: =表格1[[#Headers],[日式洗衣機一特佣 AW-Q800APH(WW)]] -> 日式洗衣機一特佣 AW-Q800APH(WW) | AU41: =表格1[[#Headers],[日式洗衣機二特佣 AW-Q801APH(WW)]] -> 日式洗衣機二特佣 AW-Q801APH(WW) | AV41: =表格1[[#Headers],[三門雪櫃特佣 GR-RM469WE-PGA(B3)]] -> 三門雪櫃特佣 GR-RM469WE-PGA(B3) | AW41: =表格1[[#Headers],[雙門雪櫃一特佣 GR-RB449WE-PMA(57)]] -> 雙門雪櫃一特佣 GR-RB449WE-PMA(57) | AX41: =表格1[[#Headers],[雙門雪櫃一特佣 GR-RB410WE-PMA(06)]] -> 雙門雪櫃一特佣 GR-RB410WE-PMA(06) | AY41: =表格1[[#Headers],[十字門雪櫃 GR-RF698WI]] -> 十字門雪櫃 GR-RF698WI | AZ41: =表格1[[#Headers],[水機 TWP-W2265THK(W)]] -> 水機 TWP-W2265THK(W) | BA41: =表格1[[#Headers],[抽濕機特佣]] -> 抽濕機特佣 | BB41: =表格1[[#Headers],[(Fortress ONLY)TW-T25BZU115MWH(MG) ]] -> (Fortress ONLY)TW-T25BZU115MWH(MG) | BC41: =表格1[[#Headers],[開門紅(三月)]] -> 開門紅(三月) | BD41: =表格1[[#Headers],[開門紅(第一季)]] -> 開門紅(第一季) | BE41: =表格1[[#Headers],[酵活炊電飯煲特佣 RC-18AMXH(W)]] -> 酵活炊電飯煲特佣 RC-18AMXH(W)
A42: 15 | B42: =B41 -> 2026-03 Toshiba | C42: =Total!C22 -> Wendy Wong_2 | D42: =Total!D22 -> Wong Lai Ying | E42: =Total!E22 -> Autopay | F42: =Total!F22 -> TW RS_2 Citistore | G42: =Total!G22 -> Mar/27-29 | H42: =Total!H22 -> 3 | I42: =Total!I22 -> 24 | J42: =Total!J22 -> 60 | ... AF42: =Total!AF22 -> 0 | AG42: =Total!AH22 -> 2238 | AO42: =表格1[[#Headers],[日本飯煲 RC-DS10K/18K]] -> 日本飯煲 RC-DS10K/18K | AP42: =表格1[[#Headers],[酵活炊電飯煲特佣 RC-18AMXH(W)]] -> 酵活炊電飯煲特佣 RC-18AMXH(W) | AQ42: =表格1[[#Headers],[嵌入式微波氣炸蒸焗爐特佣 EB-T500APW]] -> 嵌入式微波氣炸蒸焗爐特佣 EB-T500APW | AR42: =表格1[[#Headers],[蒸氣烤焗水波爐特佣 ER-VD7000HK(XK)]] -> 蒸氣烤焗水波爐特佣 ER-VD7000HK(XK) | AS42: =表格1[[#Headers],[TWDT21BU95 ]] -> TWDT21BU95 | AT42: =表格1[[#Headers],[日式洗衣機一特佣 AW-Q800APH(WW)]] -> 日式洗衣機一特佣 AW-Q800APH(WW) | AU42: =表格1[[#Headers],[日式洗衣機二特佣 AW-Q801APH(WW)]] -> 日式洗衣機二特佣 AW-Q801APH(WW) | AV42: =表格1[[#Headers],[三門雪櫃特佣 GR-RM469WE-PGA(B3)]] -> 三門雪櫃特佣 GR-RM469WE-PGA(B3) | AW42: =表格1[[#Headers],[雙門雪櫃一特佣 GR-RB449WE-PMA(57)]] -> 雙門雪櫃一特佣 GR-RB449WE-PMA(57) | AX42: =表格1[[#Headers],[雙門雪櫃一特佣 GR-RB410WE-PMA(06)]] -> 雙門雪櫃一特佣 GR-RB410WE-PMA(06) | AY42: =表格1[[#Headers],[十字門雪櫃 GR-RF698WI]] -> 十字門雪櫃 GR-RF698WI | AZ42: =表格1[[#Headers],[水機 TWP-W2265THK(W)]] -> 水機 TWP-W2265THK(W) | BA42: =表格1[[#Headers],[抽濕機特佣]] -> 抽濕機特佣 | BB42: =表格1[[#Headers],[(Fortress ONLY)TW-T25BZU115MWH(MG) ]] -> (Fortress ONLY)TW-T25BZU115MWH(MG) | BC42: =表格1[[#Headers],[開門紅(三月)]] -> 開門紅(三月) | BD42: =表格1[[#Headers],[開門紅(第一季)]] -> 開門紅(第一季) | BE42: =表格1[[#Headers],[酵活炊電飯煲特佣 RC-18AMXH(W)]] -> 酵活炊電飯煲特佣 RC-18AMXH(W)
A43: 16 | B43: =B42 -> 2026-03 Toshiba | C43: =Total!C23 -> Kiko | D43: =Total!D23 -> Chan Mei Sim | E43: =Total!E23 -> Autopay | F43: =Total!F23 -> Tai Koo Fortress | G43: =Total!G23 -> Mar/1-3,7-11,14-18,21-25,28-31 | H43: =Total!H23 -> 22 | I43: =Total!I23 -> 176 | J43: =Total!J23 -> 60 | ... AF43: =Total!AF23 -> 0 | AG43: =Total!AH23 -> 22132 | AO43: =表格1[[#Headers],[日本飯煲 RC-DS10K/18K]] -> 日本飯煲 RC-DS10K/18K | AP43: =表格1[[#Headers],[酵活炊電飯煲特佣 RC-18AMXH(W)]] -> 酵活炊電飯煲特佣 RC-18AMXH(W) | AQ43: =表格1[[#Headers],[嵌入式微波氣炸蒸焗爐特佣 EB-T500APW]] -> 嵌入式微波氣炸蒸焗爐特佣 EB-T500APW | AR43: =表格1[[#Headers],[蒸氣烤焗水波爐特佣 ER-VD7000HK(XK)]] -> 蒸氣烤焗水波爐特佣 ER-VD7000HK(XK) | AS43: =表格1[[#Headers],[TWDT21BU95 ]] -> TWDT21BU95 | AT43: =表格1[[#Headers],[日式洗衣機一特佣 AW-Q800APH(WW)]] -> 日式洗衣機一特佣 AW-Q800APH(WW) | AU43: =表格1[[#Headers],[日式洗衣機二特佣 AW-Q801APH(WW)]] -> 日式洗衣機二特佣 AW-Q801APH(WW) | AV43: =表格1[[#Headers],[三門雪櫃特佣 GR-RM469WE-PGA(B3)]] -> 三門雪櫃特佣 GR-RM469WE-PGA(B3) | AW43: =表格1[[#Headers],[雙門雪櫃一特佣 GR-RB449WE-PMA(57)]] -> 雙門雪櫃一特佣 GR-RB449WE-PMA(57) | AX43: =表格1[[#Headers],[雙門雪櫃一特佣 GR-RB410WE-PMA(06)]] -> 雙門雪櫃一特佣 GR-RB410WE-PMA(06) | AY43: =表格1[[#Headers],[十字門雪櫃 GR-RF698WI]] -> 十字門雪櫃 GR-RF698WI | AZ43: =表格1[[#Headers],[水機 TWP-W2265THK(W)]] -> 水機 TWP-W2265THK(W) | BA43: =表格1[[#Headers],[抽濕機特佣]] -> 抽濕機特佣 | BB43: =表格1[[#Headers],[(Fortress ONLY)TW-T25BZU115MWH(MG) ]] -> (Fortress ONLY)TW-T25BZU115MWH(MG) | BC43: =表格1[[#Headers],[開門紅(三月)]] -> 開門紅(三月) | BD43: =表格1[[#Headers],[開門紅(第一季)]] -> 開門紅(第一季) | BE43: =表格1[[#Headers],[酵活炊電飯煲特佣 RC-18AMXH(W)]] -> 酵活炊電飯煲特佣 RC-18AMXH(W)
A44: 18 | B44: =B43 -> 2026-03 Toshiba | C44: =Total!C25 -> Daisy | D44: =Total!D25 -> Yeung Kwai Lin | E44: =Total!E25 -> Autopay | F44: =Total!F25 -> TM Suning | G44: =Total!G25 -> Mar/1-4,7-10,14-18,20-25,28-31 | H44: =Total!H25 -> 23 | I44: =Total!I25 -> 184 | J44: =Total!J25 -> 60 | ... AF44: =Total!AF25 -> 0 | AG44: =Total!AH25 -> 18146 | AO44: =表格1[[#Headers],[日本飯煲 RC-DS10K/18K]] -> 日本飯煲 RC-DS10K/18K | AP44: =表格1[[#Headers],[酵活炊電飯煲特佣 RC-18AMXH(W)]] -> 酵活炊電飯煲特佣 RC-18AMXH(W) | AQ44: =表格1[[#Headers],[嵌入式微波氣炸蒸焗爐特佣 EB-T500APW]] -> 嵌入式微波氣炸蒸焗爐特佣 EB-T500APW | AR44: =表格1[[#Headers],[蒸氣烤焗水波爐特佣 ER-VD7000HK(XK)]] -> 蒸氣烤焗水波爐特佣 ER-VD7000HK(XK) | AS44: =表格1[[#Headers],[TWDT21BU95 ]] -> TWDT21BU95 | AT44: =表格1[[#Headers],[日式洗衣機一特佣 AW-Q800APH(WW)]] -> 日式洗衣機一特佣 AW-Q800APH(WW) | AU44: =表格1[[#Headers],[日式洗衣機二特佣 AW-Q801APH(WW)]] -> 日式洗衣機二特佣 AW-Q801APH(WW) | AV44: =表格1[[#Headers],[三門雪櫃特佣 GR-RM469WE-PGA(B3)]] -> 三門雪櫃特佣 GR-RM469WE-PGA(B3) | AW44: =表格1[[#Headers],[雙門雪櫃一特佣 GR-RB449WE-PMA(57)]] -> 雙門雪櫃一特佣 GR-RB449WE-PMA(57) | AX44: =表格1[[#Headers],[雙門雪櫃一特佣 GR-RB410WE-PMA(06)]] -> 雙門雪櫃一特佣 GR-RB410WE-PMA(06) | AY44: =表格1[[#Headers],[十字門雪櫃 GR-RF698WI]] -> 十字門雪櫃 GR-RF698WI | AZ44: =表格1[[#Headers],[水機 TWP-W2265THK(W)]] -> 水機 TWP-W2265THK(W) | BA44: =表格1[[#Headers],[抽濕機特佣]] -> 抽濕機特佣 | BB44: =表格1[[#Headers],[(Fortress ONLY)TW-T25BZU115MWH(MG) ]] -> (Fortress ONLY)TW-T25BZU115MWH(MG) | BC44: =表格1[[#Headers],[開門紅(三月)]] -> 開門紅(三月) | BD44: =表格1[[#Headers],[開門紅(第一季)]] -> 開門紅(第一季) | BE44: =表格1[[#Headers],[酵活炊電飯煲特佣 RC-18AMXH(W)]] -> 酵活炊電飯煲特佣 RC-18AMXH(W)
A45: 19 | B45: =B44 -> 2026-03 Toshiba | C45: =Total!C26 -> Pam | D45: =Total!D26 -> Tam Wing Lam | E45: =Total!E26 -> Autopay | F45: =Total!F26 -> Mos_1 Citistore | G45: =Total!G26 -> Mar/1,3-5,7-10,12-16,18,24-26,28-31 | H45: =Total!H26 -> 21 | I45: =Total!I26 -> 168 | J45: =Total!J26 -> 55 | ... AF45: =Total!AF26 -> 0 | AG45: =Total!AH26 -> 11624 | AO45: =表格1[[#Headers],[日本飯煲 RC-DS10K/18K]] -> 日本飯煲 RC-DS10K/18K | AP45: =表格1[[#Headers],[酵活炊電飯煲特佣 RC-18AMXH(W)]] -> 酵活炊電飯煲特佣 RC-18AMXH(W) | AQ45: =表格1[[#Headers],[嵌入式微波氣炸蒸焗爐特佣 EB-T500APW]] -> 嵌入式微波氣炸蒸焗爐特佣 EB-T500APW | AR45: =表格1[[#Headers],[蒸氣烤焗水波爐特佣 ER-VD7000HK(XK)]] -> 蒸氣烤焗水波爐特佣 ER-VD7000HK(XK) | AS45: =表格1[[#Headers],[TWDT21BU95 ]] -> TWDT21BU95 | AT45: =表格1[[#Headers],[日式洗衣機一特佣 AW-Q800APH(WW)]] -> 日式洗衣機一特佣 AW-Q800APH(WW) | AU45: =表格1[[#Headers],[日式洗衣機二特佣 AW-Q801APH(WW)]] -> 日式洗衣機二特佣 AW-Q801APH(WW) | AV45: =表格1[[#Headers],[三門雪櫃特佣 GR-RM469WE-PGA(B3)]] -> 三門雪櫃特佣 GR-RM469WE-PGA(B3) | AW45: =表格1[[#Headers],[雙門雪櫃一特佣 GR-RB449WE-PMA(57)]] -> 雙門雪櫃一特佣 GR-RB449WE-PMA(57) | AX45: =表格1[[#Headers],[雙門雪櫃一特佣 GR-RB410WE-PMA(06)]] -> 雙門雪櫃一特佣 GR-RB410WE-PMA(06) | AY45: =表格1[[#Headers],[十字門雪櫃 GR-RF698WI]] -> 十字門雪櫃 GR-RF698WI | AZ45: =表格1[[#Headers],[水機 TWP-W2265THK(W)]] -> 水機 TWP-W2265THK(W) | BA45: =表格1[[#Headers],[抽濕機特佣]] -> 抽濕機特佣 | BB45: =表格1[[#Headers],[(Fortress ONLY)TW-T25BZU115MWH(MG) ]] -> (Fortress ONLY)TW-T25BZU115MWH(MG) | BC45: =表格1[[#Headers],[開門紅(三月)]] -> 開門紅(三月) | BD45: =表格1[[#Headers],[開門紅(第一季)]] -> 開門紅(第一季) | BE45: =表格1[[#Headers],[酵活炊電飯煲特佣 RC-18AMXH(W)]] -> 酵活炊電飯煲特佣 RC-18AMXH(W)
A46: 20 | B46: =B45 -> 2026-03 Toshiba | C46: =Total!C27 -> Tony_4 | D46: =Total!D27 -> Wong Tak Chung | E46: =Total!E27 -> Autopay | F46: =Total!F27 -> Mos_2 Citistore | G46: =Total!G27 -> Mar/21-22 | H46: =Total!H27 -> 2 | I46: =Total!I27 -> 16 | J46: =Total!J27 -> 60 | ... AF46: =Total!AF27 -> 0 | AG46: =Total!AH27 -> 1313 | AO46: =表格1[[#Headers],[日本飯煲 RC-DS10K/18K]] -> 日本飯煲 RC-DS10K/18K | AP46: =表格1[[#Headers],[酵活炊電飯煲特佣 RC-18AMXH(W)]] -> 酵活炊電飯煲特佣 RC-18AMXH(W) | AQ46: =表格1[[#Headers],[嵌入式微波氣炸蒸焗爐特佣 EB-T500APW]] -> 嵌入式微波氣炸蒸焗爐特佣 EB-T500APW | AR46: =表格1[[#Headers],[蒸氣烤焗水波爐特佣 ER-VD7000HK(XK)]] -> 蒸氣烤焗水波爐特佣 ER-VD7000HK(XK) | AS46: =表格1[[#Headers],[TWDT21BU95 ]] -> TWDT21BU95 | AT46: =表格1[[#Headers],[日式洗衣機一特佣 AW-Q800APH(WW)]] -> 日式洗衣機一特佣 AW-Q800APH(WW) | AU46: =表格1[[#Headers],[日式洗衣機二特佣 AW-Q801APH(WW)]] -> 日式洗衣機二特佣 AW-Q801APH(WW) | AV46: =表格1[[#Headers],[三門雪櫃特佣 GR-RM469WE-PGA(B3)]] -> 三門雪櫃特佣 GR-RM469WE-PGA(B3) | AW46: =表格1[[#Headers],[雙門雪櫃一特佣 GR-RB449WE-PMA(57)]] -> 雙門雪櫃一特佣 GR-RB449WE-PMA(57) | AX46: =表格1[[#Headers],[雙門雪櫃一特佣 GR-RB410WE-PMA(06)]] -> 雙門雪櫃一特佣 GR-RB410WE-PMA(06) | AY46: =表格1[[#Headers],[十字門雪櫃 GR-RF698WI]] -> 十字門雪櫃 GR-RF698WI | AZ46: =表格1[[#Headers],[水機 TWP-W2265THK(W)]] -> 水機 TWP-W2265THK(W) | BA46: =表格1[[#Headers],[抽濕機特佣]] -> 抽濕機特佣 | BB46: =表格1[[#Headers],[(Fortress ONLY)TW-T25BZU115MWH(MG) ]] -> (Fortress ONLY)TW-T25BZU115MWH(MG) | BC46: =表格1[[#Headers],[開門紅(三月)]] -> 開門紅(三月) | BD46: =表格1[[#Headers],[開門紅(第一季)]] -> 開門紅(第一季) | BE46: =表格1[[#Headers],[酵活炊電飯煲特佣 RC-18AMXH(W)]] -> 酵活炊電飯煲特佣 RC-18AMXH(W)
A47: 25 | B47: =B46 -> 2026-03 Toshiba | C47: =Total!C32 -> Leo | D47: =Total!D32 -> Lam King Chung | E47: =Total!E32 -> Autopay | F47: =Total!F32 -> Yoho Suning | G47: =Total!G32 -> Mar/2-3,5,7-10,12-17,19-24,26,29-31 | H47: =Total!H32 -> 23 | I47: =Total!I32 -> 184 | J47: =Total!J32 -> 55 | ... AF47: =Total!AF32 -> 0 | AG47: =Total!AH32 -> 17812 | AO47: =表格1[[#Headers],[日本飯煲 RC-DS10K/18K]] -> 日本飯煲 RC-DS10K/18K | AP47: =表格1[[#Headers],[酵活炊電飯煲特佣 RC-18AMXH(W)]] -> 酵活炊電飯煲特佣 RC-18AMXH(W) | AQ47: =表格1[[#Headers],[嵌入式微波氣炸蒸焗爐特佣 EB-T500APW]] -> 嵌入式微波氣炸蒸焗爐特佣 EB-T500APW | AR47: =表格1[[#Headers],[蒸氣烤焗水波爐特佣 ER-VD7000HK(XK)]] -> 蒸氣烤焗水波爐特佣 ER-VD7000HK(XK) | AS47: =表格1[[#Headers],[TWDT21BU95 ]] -> TWDT21BU95 | AT47: =表格1[[#Headers],[日式洗衣機一特佣 AW-Q800APH(WW)]] -> 日式洗衣機一特佣 AW-Q800APH(WW) | AU47: =表格1[[#Headers],[日式洗衣機二特佣 AW-Q801APH(WW)]] -> 日式洗衣機二特佣 AW-Q801APH(WW) | AV47: =表格1[[#Headers],[三門雪櫃特佣 GR-RM469WE-PGA(B3)]] -> 三門雪櫃特佣 GR-RM469WE-PGA(B3) | AW47: =表格1[[#Headers],[雙門雪櫃一特佣 GR-RB449WE-PMA(57)]] -> 雙門雪櫃一特佣 GR-RB449WE-PMA(57) | AX47: =表格1[[#Headers],[雙門雪櫃一特佣 GR-RB410WE-PMA(06)]] -> 雙門雪櫃一特佣 GR-RB410WE-PMA(06) | AY47: =表格1[[#Headers],[十字門雪櫃 GR-RF698WI]] -> 十字門雪櫃 GR-RF698WI | AZ47: =表格1[[#Headers],[水機 TWP-W2265THK(W)]] -> 水機 TWP-W2265THK(W) | BA47: =表格1[[#Headers],[抽濕機特佣]] -> 抽濕機特佣 | BB47: =表格1[[#Headers],[(Fortress ONLY)TW-T25BZU115MWH(MG) ]] -> (Fortress ONLY)TW-T25BZU115MWH(MG) | BC47: =表格1[[#Headers],[開門紅(三月)]] -> 開門紅(三月) | BD47: =表格1[[#Headers],[開門紅(第一季)]] -> 開門紅(第一季) | BE47: =表格1[[#Headers],[酵活炊電飯煲特佣 RC-18AMXH(W)]] -> 酵活炊電飯煲特佣 RC-18AMXH(W)
A48: 27 | B48: =B47 -> 2026-03 Toshiba | C48: =Total!C34 -> Ling Ho | D48: =Total!D34 -> Ho Wai Ling | E48: =Total!E34 -> Autopay | F48: =Total!F34 -> TM Citistore | G48: =Total!G34 -> Mar/1,3-4,6-9,11-12,14-17,20-24,26-31 | H48: =Total!H34 -> 24 | I48: =Total!I34 -> 192 | J48: =Total!J34 -> 60 | ... AF48: =Total!AF34 -> 0 | AG48: =Total!AH34 -> 14596 | AO48: =表格1[[#Headers],[日本飯煲 RC-DS10K/18K]] -> 日本飯煲 RC-DS10K/18K | AP48: =表格1[[#Headers],[酵活炊電飯煲特佣 RC-18AMXH(W)]] -> 酵活炊電飯煲特佣 RC-18AMXH(W) | AQ48: =表格1[[#Headers],[嵌入式微波氣炸蒸焗爐特佣 EB-T500APW]] -> 嵌入式微波氣炸蒸焗爐特佣 EB-T500APW | AR48: =表格1[[#Headers],[蒸氣烤焗水波爐特佣 ER-VD7000HK(XK)]] -> 蒸氣烤焗水波爐特佣 ER-VD7000HK(XK) | AS48: =表格1[[#Headers],[TWDT21BU95 ]] -> TWDT21BU95 | AT48: =表格1[[#Headers],[日式洗衣機一特佣 AW-Q800APH(WW)]] -> 日式洗衣機一特佣 AW-Q800APH(WW) | AU48: =表格1[[#Headers],[日式洗衣機二特佣 AW-Q801APH(WW)]] -> 日式洗衣機二特佣 AW-Q801APH(WW) | AV48: =表格1[[#Headers],[三門雪櫃特佣 GR-RM469WE-PGA(B3)]] -> 三門雪櫃特佣 GR-RM469WE-PGA(B3) | AW48: =表格1[[#Headers],[雙門雪櫃一特佣 GR-RB449WE-PMA(57)]] -> 雙門雪櫃一特佣 GR-RB449WE-PMA(57) | AX48: =表格1[[#Headers],[雙門雪櫃一特佣 GR-RB410WE-PMA(06)]] -> 雙門雪櫃一特佣 GR-RB410WE-PMA(06) | AY48: =表格1[[#Headers],[十字門雪櫃 GR-RF698WI]] -> 十字門雪櫃 GR-RF698WI | AZ48: =表格1[[#Headers],[水機 TWP-W2265THK(W)]] -> 水機 TWP-W2265THK(W) | BA48: =表格1[[#Headers],[抽濕機特佣]] -> 抽濕機特佣 | BB48: =表格1[[#Headers],[(Fortress ONLY)TW-T25BZU115MWH(MG) ]] -> (Fortress ONLY)TW-T25BZU115MWH(MG) | BC48: =表格1[[#Headers],[開門紅(三月)]] -> 開門紅(三月) | BD48: =表格1[[#Headers],[開門紅(第一季)]] -> 開門紅(第一季) | BE48: =表格1[[#Headers],[酵活炊電飯煲特佣 RC-18AMXH(W)]] -> 酵活炊電飯煲特佣 RC-18AMXH(W)
A49: 29 | B49: =B48 -> 2026-03 Toshiba | C49: =Total!C36 -> Tiffany | D49: =Total!D36 -> Man Wai Han | E49: =Total!E36 -> Autopay | F49: =Total!F36 -> APM Fortress | G49: =Total!G36 -> Mar/1,5-6,8-9,11-12,14,16,19-22,24-26,29,31 | H49: =Total!H36 -> 18 | I49: =Total!I36 -> 144 | J49: =Total!J36 -> 60 | ... AF49: =Total!AF36 -> 0 | AG49: =Total!AH36 -> 22983 | AO49: =表格1[[#Headers],[日本飯煲 RC-DS10K/18K]] -> 日本飯煲 RC-DS10K/18K | AP49: =表格1[[#Headers],[酵活炊電飯煲特佣 RC-18AMXH(W)]] -> 酵活炊電飯煲特佣 RC-18AMXH(W) | AQ49: =表格1[[#Headers],[嵌入式微波氣炸蒸焗爐特佣 EB-T500APW]] -> 嵌入式微波氣炸蒸焗爐特佣 EB-T500APW | AR49: =表格1[[#Headers],[蒸氣烤焗水波爐特佣 ER-VD7000HK(XK)]] -> 蒸氣烤焗水波爐特佣 ER-VD7000HK(XK) | AS49: =表格1[[#Headers],[TWDT21BU95 ]] -> TWDT21BU95 | AT49: =表格1[[#Headers],[日式洗衣機一特佣 AW-Q800APH(WW)]] -> 日式洗衣機一特佣 AW-Q800APH(WW) | AU49: =表格1[[#Headers],[日式洗衣機二特佣 AW-Q801APH(WW)]] -> 日式洗衣機二特佣 AW-Q801APH(WW) | AV49: =表格1[[#Headers],[三門雪櫃特佣 GR-RM469WE-PGA(B3)]] -> 三門雪櫃特佣 GR-RM469WE-PGA(B3) | AW49: =表格1[[#Headers],[雙門雪櫃一特佣 GR-RB449WE-PMA(57)]] -> 雙門雪櫃一特佣 GR-RB449WE-PMA(57) | AX49: =表格1[[#Headers],[雙門雪櫃一特佣 GR-RB410WE-PMA(06)]] -> 雙門雪櫃一特佣 GR-RB410WE-PMA(06) | AY49: =表格1[[#Headers],[十字門雪櫃 GR-RF698WI]] -> 十字門雪櫃 GR-RF698WI | AZ49: =表格1[[#Headers],[水機 TWP-W2265THK(W)]] -> 水機 TWP-W2265THK(W) | BA49: =表格1[[#Headers],[抽濕機特佣]] -> 抽濕機特佣 | BB49: =表格1[[#Headers],[(Fortress ONLY)TW-T25BZU115MWH(MG) ]] -> (Fortress ONLY)TW-T25BZU115MWH(MG) | BC49: =表格1[[#Headers],[開門紅(三月)]] -> 開門紅(三月) | BD49: =表格1[[#Headers],[開門紅(第一季)]] -> 開門紅(第一季) | BE49: =表格1[[#Headers],[酵活炊電飯煲特佣 RC-18AMXH(W)]] -> 酵活炊電飯煲特佣 RC-18AMXH(W)
A50: 33 | B50: =B49 -> 2026-03 Toshiba | C50: =Total!C40 -> Emma | D50: =Total!D40 -> Ng Yuk Ying | E50: =Total!E40 -> Autopay | F50: =Total!F40 -> Shatin_2 Yata | G50: =Total!G40 -> Mar/3-4,18-19 | H50: =Total!H40 -> 4 | I50: =Total!I40 -> 32 | J50: =Total!J40 -> 60 | ... AF50: =Total!AF40 -> 45 | AG50: =Total!AH40 -> 2281 | AO50: =表格1[[#Headers],[日本飯煲 RC-DS10K/18K]] -> 日本飯煲 RC-DS10K/18K | AP50: =表格1[[#Headers],[酵活炊電飯煲特佣 RC-18AMXH(W)]] -> 酵活炊電飯煲特佣 RC-18AMXH(W) | AQ50: =表格1[[#Headers],[嵌入式微波氣炸蒸焗爐特佣 EB-T500APW]] -> 嵌入式微波氣炸蒸焗爐特佣 EB-T500APW | AR50: =表格1[[#Headers],[蒸氣烤焗水波爐特佣 ER-VD7000HK(XK)]] -> 蒸氣烤焗水波爐特佣 ER-VD7000HK(XK) | AS50: =表格1[[#Headers],[TWDT21BU95 ]] -> TWDT21BU95 | AT50: =表格1[[#Headers],[日式洗衣機一特佣 AW-Q800APH(WW)]] -> 日式洗衣機一特佣 AW-Q800APH(WW) | AU50: =表格1[[#Headers],[日式洗衣機二特佣 AW-Q801APH(WW)]] -> 日式洗衣機二特佣 AW-Q801APH(WW) | AV50: =表格1[[#Headers],[三門雪櫃特佣 GR-RM469WE-PGA(B3)]] -> 三門雪櫃特佣 GR-RM469WE-PGA(B3) | AW50: =表格1[[#Headers],[雙門雪櫃一特佣 GR-RB449WE-PMA(57)]] -> 雙門雪櫃一特佣 GR-RB449WE-PMA(57) | AX50: =表格1[[#Headers],[雙門雪櫃一特佣 GR-RB410WE-PMA(06)]] -> 雙門雪櫃一特佣 GR-RB410WE-PMA(06) | AY50: =表格1[[#Headers],[十字門雪櫃 GR-RF698WI]] -> 十字門雪櫃 GR-RF698WI | AZ50: =表格1[[#Headers],[水機 TWP-W2265THK(W)]] -> 水機 TWP-W2265THK(W) | BA50: =表格1[[#Headers],[抽濕機特佣]] -> 抽濕機特佣 | BB50: =表格1[[#Headers],[(Fortress ONLY)TW-T25BZU115MWH(MG) ]] -> (Fortress ONLY)TW-T25BZU115MWH(MG) | BC50: =表格1[[#Headers],[開門紅(三月)]] -> 開門紅(三月) | BD50: =表格1[[#Headers],[開門紅(第一季)]] -> 開門紅(第一季) | BE50: =表格1[[#Headers],[酵活炊電飯煲特佣 RC-18AMXH(W)]] -> 酵活炊電飯煲特佣 RC-18AMXH(W)
A51: 34 | B51: =B50 -> 2026-03 Toshiba | C51: =Total!C41 -> Tony_1 | D51: =Total!D41 -> Wong Tak Chung | E51: =Total!E41 -> Autopay | F51: =Total!F41 -> Shatin_3 Yata | G51: =Total!G41 -> Mar/25-26 | H51: =Total!H41 -> 2 | I51: =Total!I41 -> 16 | J51: =Total!J41 -> 60 | ... AF51: =Total!AF41 -> 0 | AG51: =Total!AH41 -> 1074 | AO51: =表格1[[#Headers],[日本飯煲 RC-DS10K/18K]] -> 日本飯煲 RC-DS10K/18K | AP51: =表格1[[#Headers],[酵活炊電飯煲特佣 RC-18AMXH(W)]] -> 酵活炊電飯煲特佣 RC-18AMXH(W) | AQ51: =表格1[[#Headers],[嵌入式微波氣炸蒸焗爐特佣 EB-T500APW]] -> 嵌入式微波氣炸蒸焗爐特佣 EB-T500APW | AR51: =表格1[[#Headers],[蒸氣烤焗水波爐特佣 ER-VD7000HK(XK)]] -> 蒸氣烤焗水波爐特佣 ER-VD7000HK(XK) | AS51: =表格1[[#Headers],[TWDT21BU95 ]] -> TWDT21BU95 | AT51: =表格1[[#Headers],[日式洗衣機一特佣 AW-Q800APH(WW)]] -> 日式洗衣機一特佣 AW-Q800APH(WW) | AU51: =表格1[[#Headers],[日式洗衣機二特佣 AW-Q801APH(WW)]] -> 日式洗衣機二特佣 AW-Q801APH(WW) | AV51: =表格1[[#Headers],[三門雪櫃特佣 GR-RM469WE-PGA(B3)]] -> 三門雪櫃特佣 GR-RM469WE-PGA(B3) | AW51: =表格1[[#Headers],[雙門雪櫃一特佣 GR-RB449WE-PMA(57)]] -> 雙門雪櫃一特佣 GR-RB449WE-PMA(57) | AX51: =表格1[[#Headers],[雙門雪櫃一特佣 GR-RB410WE-PMA(06)]] -> 雙門雪櫃一特佣 GR-RB410WE-PMA(06) | AY51: =表格1[[#Headers],[十字門雪櫃 GR-RF698WI]] -> 十字門雪櫃 GR-RF698WI | AZ51: =表格1[[#Headers],[水機 TWP-W2265THK(W)]] -> 水機 TWP-W2265THK(W) | BA51: =表格1[[#Headers],[抽濕機特佣]] -> 抽濕機特佣 | BB51: =表格1[[#Headers],[(Fortress ONLY)TW-T25BZU115MWH(MG) ]] -> (Fortress ONLY)TW-T25BZU115MWH(MG) | BC51: =表格1[[#Headers],[開門紅(三月)]] -> 開門紅(三月) | BD51: =表格1[[#Headers],[開門紅(第一季)]] -> 開門紅(第一季) | BE51: =表格1[[#Headers],[酵活炊電飯煲特佣 RC-18AMXH(W)]] -> 酵活炊電飯煲特佣 RC-18AMXH(W)
A52: 35 | B52: =B51 -> 2026-03 Toshiba | C52: =Total!C42 -> Kit_1 | D52: =Total!D42 -> Li Wenjie | E52: =Total!E42 -> Autopay | F52: =Total!F42 -> Shatin_4 Yata | G52: =Total!G42 -> Mar/11-13 | H52: =Total!H42 -> 3 | I52: =Total!I42 -> 24 | J52: =Total!J42 -> 60 | ... AF52: =Total!AF42 -> 0 | AG52: =Total!AH42 -> 1840 | AO52: =表格1[[#Headers],[日本飯煲 RC-DS10K/18K]] -> 日本飯煲 RC-DS10K/18K | AP52: =表格1[[#Headers],[酵活炊電飯煲特佣 RC-18AMXH(W)]] -> 酵活炊電飯煲特佣 RC-18AMXH(W) | AQ52: =表格1[[#Headers],[嵌入式微波氣炸蒸焗爐特佣 EB-T500APW]] -> 嵌入式微波氣炸蒸焗爐特佣 EB-T500APW | AR52: =表格1[[#Headers],[蒸氣烤焗水波爐特佣 ER-VD7000HK(XK)]] -> 蒸氣烤焗水波爐特佣 ER-VD7000HK(XK) | AS52: =表格1[[#Headers],[TWDT21BU95 ]] -> TWDT21BU95 | AT52: =表格1[[#Headers],[日式洗衣機一特佣 AW-Q800APH(WW)]] -> 日式洗衣機一特佣 AW-Q800APH(WW) | AU52: =表格1[[#Headers],[日式洗衣機二特佣 AW-Q801APH(WW)]] -> 日式洗衣機二特佣 AW-Q801APH(WW) | AV52: =表格1[[#Headers],[三門雪櫃特佣 GR-RM469WE-PGA(B3)]] -> 三門雪櫃特佣 GR-RM469WE-PGA(B3) | AW52: =表格1[[#Headers],[雙門雪櫃一特佣 GR-RB449WE-PMA(57)]] -> 雙門雪櫃一特佣 GR-RB449WE-PMA(57) | AX52: =表格1[[#Headers],[雙門雪櫃一特佣 GR-RB410WE-PMA(06)]] -> 雙門雪櫃一特佣 GR-RB410WE-PMA(06) | AY52: =表格1[[#Headers],[十字門雪櫃 GR-RF698WI]] -> 十字門雪櫃 GR-RF698WI | AZ52: =表格1[[#Headers],[水機 TWP-W2265THK(W)]] -> 水機 TWP-W2265THK(W) | BA52: =表格1[[#Headers],[抽濕機特佣]] -> 抽濕機特佣 | BB52: =表格1[[#Headers],[(Fortress ONLY)TW-T25BZU115MWH(MG) ]] -> (Fortress ONLY)TW-T25BZU115MWH(MG) | BC52: =表格1[[#Headers],[開門紅(三月)]] -> 開門紅(三月) | BD52: =表格1[[#Headers],[開門紅(第一季)]] -> 開門紅(第一季) | BE52: =表格1[[#Headers],[酵活炊電飯煲特佣 RC-18AMXH(W)]] -> 酵活炊電飯煲特佣 RC-18AMXH(W)
A53: 37 | B53: =B52 -> 2026-03 Toshiba | C53: =Total!C44 -> Tony_2 | D53: =Total!D44 -> Wong Tak Chung | E53: =Total!E44 -> Autopay | F53: =Total!F44 -> TP_2 Yata | G53: =Total!G44 -> Mar/9-10,23-24,30-31 | H53: =Total!H44 -> 6 | I53: =Total!I44 -> 48 | J53: =Total!J44 -> 60 | ... AF53: =Total!AF44 -> 0 | AG53: =Total!AH44 -> 3539 | AO53: =表格1[[#Headers],[日本飯煲 RC-DS10K/18K]] -> 日本飯煲 RC-DS10K/18K | AP53: =表格1[[#Headers],[酵活炊電飯煲特佣 RC-18AMXH(W)]] -> 酵活炊電飯煲特佣 RC-18AMXH(W) | AQ53: =表格1[[#Headers],[嵌入式微波氣炸蒸焗爐特佣 EB-T500APW]] -> 嵌入式微波氣炸蒸焗爐特佣 EB-T500APW | AR53: =表格1[[#Headers],[蒸氣烤焗水波爐特佣 ER-VD7000HK(XK)]] -> 蒸氣烤焗水波爐特佣 ER-VD7000HK(XK) | AS53: =表格1[[#Headers],[TWDT21BU95 ]] -> TWDT21BU95 | AT53: =表格1[[#Headers],[日式洗衣機一特佣 AW-Q800APH(WW)]] -> 日式洗衣機一特佣 AW-Q800APH(WW) | AU53: =表格1[[#Headers],[日式洗衣機二特佣 AW-Q801APH(WW)]] -> 日式洗衣機二特佣 AW-Q801APH(WW) | AV53: =表格1[[#Headers],[三門雪櫃特佣 GR-RM469WE-PGA(B3)]] -> 三門雪櫃特佣 GR-RM469WE-PGA(B3) | AW53: =表格1[[#Headers],[雙門雪櫃一特佣 GR-RB449WE-PMA(57)]] -> 雙門雪櫃一特佣 GR-RB449WE-PMA(57) | AX53: =表格1[[#Headers],[雙門雪櫃一特佣 GR-RB410WE-PMA(06)]] -> 雙門雪櫃一特佣 GR-RB410WE-PMA(06) | AY53: =表格1[[#Headers],[十字門雪櫃 GR-RF698WI]] -> 十字門雪櫃 GR-RF698WI | AZ53: =表格1[[#Headers],[水機 TWP-W2265THK(W)]] -> 水機 TWP-W2265THK(W) | BA53: =表格1[[#Headers],[抽濕機特佣]] -> 抽濕機特佣 | BB53: =表格1[[#Headers],[(Fortress ONLY)TW-T25BZU115MWH(MG) ]] -> (Fortress ONLY)TW-T25BZU115MWH(MG) | BC53: =表格1[[#Headers],[開門紅(三月)]] -> 開門紅(三月) | BD53: =表格1[[#Headers],[開門紅(第一季)]] -> 開門紅(第一季) | BE53: =表格1[[#Headers],[酵活炊電飯煲特佣 RC-18AMXH(W)]] -> 酵活炊電飯煲特佣 RC-18AMXH(W)
A54: 38 | B54: =B53 -> 2026-03 Toshiba | C54: =Total!C45 -> Kit_2 | D54: =Total!D45 -> Li Wenjie | E54: =Total!E45 -> Autopay | F54: =Total!F45 -> TP_3 Yata | G54: =Total!G45 -> Mar/2-3,16-17 | H54: =Total!H45 -> 4 | I54: =Total!I45 -> 32 | J54: =Total!J45 -> 60 | ... AF54: =Total!AF45 -> 0 | AG54: =Total!AH45 -> 2091 | AO54: =表格1[[#Headers],[日本飯煲 RC-DS10K/18K]] -> 日本飯煲 RC-DS10K/18K | AP54: =表格1[[#Headers],[酵活炊電飯煲特佣 RC-18AMXH(W)]] -> 酵活炊電飯煲特佣 RC-18AMXH(W) | AQ54: =表格1[[#Headers],[嵌入式微波氣炸蒸焗爐特佣 EB-T500APW]] -> 嵌入式微波氣炸蒸焗爐特佣 EB-T500APW | AR54: =表格1[[#Headers],[蒸氣烤焗水波爐特佣 ER-VD7000HK(XK)]] -> 蒸氣烤焗水波爐特佣 ER-VD7000HK(XK) | AS54: =表格1[[#Headers],[TWDT21BU95 ]] -> TWDT21BU95 | AT54: =表格1[[#Headers],[日式洗衣機一特佣 AW-Q800APH(WW)]] -> 日式洗衣機一特佣 AW-Q800APH(WW) | AU54: =表格1[[#Headers],[日式洗衣機二特佣 AW-Q801APH(WW)]] -> 日式洗衣機二特佣 AW-Q801APH(WW) | AV54: =表格1[[#Headers],[三門雪櫃特佣 GR-RM469WE-PGA(B3)]] -> 三門雪櫃特佣 GR-RM469WE-PGA(B3) | AW54: =表格1[[#Headers],[雙門雪櫃一特佣 GR-RB449WE-PMA(57)]] -> 雙門雪櫃一特佣 GR-RB449WE-PMA(57) | AX54: =表格1[[#Headers],[雙門雪櫃一特佣 GR-RB410WE-PMA(06)]] -> 雙門雪櫃一特佣 GR-RB410WE-PMA(06) | AY54: =表格1[[#Headers],[十字門雪櫃 GR-RF698WI]] -> 十字門雪櫃 GR-RF698WI | AZ54: =表格1[[#Headers],[水機 TWP-W2265THK(W)]] -> 水機 TWP-W2265THK(W) | BA54: =表格1[[#Headers],[抽濕機特佣]] -> 抽濕機特佣 | BB54: =表格1[[#Headers],[(Fortress ONLY)TW-T25BZU115MWH(MG) ]] -> (Fortress ONLY)TW-T25BZU115MWH(MG) | BC54: =表格1[[#Headers],[開門紅(三月)]] -> 開門紅(三月) | BD54: =表格1[[#Headers],[開門紅(第一季)]] -> 開門紅(第一季) | BE54: =表格1[[#Headers],[酵活炊電飯煲特佣 RC-18AMXH(W)]] -> 酵活炊電飯煲特佣 RC-18AMXH(W)
A55: 39 | B55: =B54 -> 2026-03 Toshiba | C55: =Total!C46 -> Anita_1 | D55: =Total!D46 -> Chan Siu Kuen | E55: =Total!E46 -> Autopay | F55: =Total!F46 -> Kai Tak_1 Sogo | G55: =Total!G46 -> Mar/21-22,31 | H55: =Total!H46 -> 3 | I55: =Total!I46 -> 24 | J55: =Total!J46 -> 60 | ... AF55: =Total!AF46 -> 0 | AG55: =Total!AH46 -> 1554 | AO55: =表格1[[#Headers],[日本飯煲 RC-DS10K/18K]] -> 日本飯煲 RC-DS10K/18K | AP55: =表格1[[#Headers],[酵活炊電飯煲特佣 RC-18AMXH(W)]] -> 酵活炊電飯煲特佣 RC-18AMXH(W) | AQ55: =表格1[[#Headers],[嵌入式微波氣炸蒸焗爐特佣 EB-T500APW]] -> 嵌入式微波氣炸蒸焗爐特佣 EB-T500APW | AR55: =表格1[[#Headers],[蒸氣烤焗水波爐特佣 ER-VD7000HK(XK)]] -> 蒸氣烤焗水波爐特佣 ER-VD7000HK(XK) | AS55: =表格1[[#Headers],[TWDT21BU95 ]] -> TWDT21BU95 | AT55: =表格1[[#Headers],[日式洗衣機一特佣 AW-Q800APH(WW)]] -> 日式洗衣機一特佣 AW-Q800APH(WW) | AU55: =表格1[[#Headers],[日式洗衣機二特佣 AW-Q801APH(WW)]] -> 日式洗衣機二特佣 AW-Q801APH(WW) | AV55: =表格1[[#Headers],[三門雪櫃特佣 GR-RM469WE-PGA(B3)]] -> 三門雪櫃特佣 GR-RM469WE-PGA(B3) | AW55: =表格1[[#Headers],[雙門雪櫃一特佣 GR-RB449WE-PMA(57)]] -> 雙門雪櫃一特佣 GR-RB449WE-PMA(57) | AX55: =表格1[[#Headers],[雙門雪櫃一特佣 GR-RB410WE-PMA(06)]] -> 雙門雪櫃一特佣 GR-RB410WE-PMA(06) | AY55: =表格1[[#Headers],[十字門雪櫃 GR-RF698WI]] -> 十字門雪櫃 GR-RF698WI | AZ55: =表格1[[#Headers],[水機 TWP-W2265THK(W)]] -> 水機 TWP-W2265THK(W) | BA55: =表格1[[#Headers],[抽濕機特佣]] -> 抽濕機特佣 | BB55: =表格1[[#Headers],[(Fortress ONLY)TW-T25BZU115MWH(MG) ]] -> (Fortress ONLY)TW-T25BZU115MWH(MG) | BC55: =表格1[[#Headers],[開門紅(三月)]] -> 開門紅(三月) | BD55: =表格1[[#Headers],[開門紅(第一季)]] -> 開門紅(第一季) | BE55: =表格1[[#Headers],[酵活炊電飯煲特佣 RC-18AMXH(W)]] -> 酵活炊電飯煲特佣 RC-18AMXH(W)
A56: 41 | B56: =B55 -> 2026-03 Toshiba | C56: =Total!C48 -> Mui Chan_1 | D56: =Total!D48 -> Chan So Mui | E56: =Total!E48 -> Autopay | F56: =Total!F48 -> Kai Tak_3 Sogo | G56: =Total!G48 -> Mar/5,9-19,24-26 | H56: =Total!H48 -> 15 | I56: =Total!I48 -> 120 | J56: =Total!J48 -> 60 | ... AF56: =Total!AF48 -> 0 | AG56: =Total!AH48 -> 11885 | AO56: =表格1[[#Headers],[日本飯煲 RC-DS10K/18K]] -> 日本飯煲 RC-DS10K/18K | AP56: =表格1[[#Headers],[酵活炊電飯煲特佣 RC-18AMXH(W)]] -> 酵活炊電飯煲特佣 RC-18AMXH(W) | AQ56: =表格1[[#Headers],[嵌入式微波氣炸蒸焗爐特佣 EB-T500APW]] -> 嵌入式微波氣炸蒸焗爐特佣 EB-T500APW | AR56: =表格1[[#Headers],[蒸氣烤焗水波爐特佣 ER-VD7000HK(XK)]] -> 蒸氣烤焗水波爐特佣 ER-VD7000HK(XK) | AS56: =表格1[[#Headers],[TWDT21BU95 ]] -> TWDT21BU95 | AT56: =表格1[[#Headers],[日式洗衣機一特佣 AW-Q800APH(WW)]] -> 日式洗衣機一特佣 AW-Q800APH(WW) | AU56: =表格1[[#Headers],[日式洗衣機二特佣 AW-Q801APH(WW)]] -> 日式洗衣機二特佣 AW-Q801APH(WW) | AV56: =表格1[[#Headers],[三門雪櫃特佣 GR-RM469WE-PGA(B3)]] -> 三門雪櫃特佣 GR-RM469WE-PGA(B3) | AW56: =表格1[[#Headers],[雙門雪櫃一特佣 GR-RB449WE-PMA(57)]] -> 雙門雪櫃一特佣 GR-RB449WE-PMA(57) | AX56: =表格1[[#Headers],[雙門雪櫃一特佣 GR-RB410WE-PMA(06)]] -> 雙門雪櫃一特佣 GR-RB410WE-PMA(06) | AY56: =表格1[[#Headers],[十字門雪櫃 GR-RF698WI]] -> 十字門雪櫃 GR-RF698WI | AZ56: =表格1[[#Headers],[水機 TWP-W2265THK(W)]] -> 水機 TWP-W2265THK(W) | BA56: =表格1[[#Headers],[抽濕機特佣]] -> 抽濕機特佣 | BB56: =表格1[[#Headers],[(Fortress ONLY)TW-T25BZU115MWH(MG) ]] -> (Fortress ONLY)TW-T25BZU115MWH(MG) | BC56: =表格1[[#Headers],[開門紅(三月)]] -> 開門紅(三月) | BD56: =表格1[[#Headers],[開門紅(第一季)]] -> 開門紅(第一季) | BE56: =表格1[[#Headers],[酵活炊電飯煲特佣 RC-18AMXH(W)]] -> 酵活炊電飯煲特佣 RC-18AMXH(W)
A57: 42 | B57: =B56 -> 2026-03 Toshiba | C57: =Total!C49 -> Fong_2 | D57: =Total!D49 -> Ng Nga Fong | E57: =Total!E49 -> Autopay | F57: =Total!F49 -> Kai Tak_4 Sogo | G57: =Total!G49 -> Mar/6 | H57: =Total!H49 -> 1 | I57: =Total!I49 -> 8 | J57: =Total!J49 -> 60 | ... AF57: =Total!AF49 -> 0 | AG57: =Total!AH49 -> 554 | AO57: =表格1[[#Headers],[日本飯煲 RC-DS10K/18K]] -> 日本飯煲 RC-DS10K/18K | AP57: =表格1[[#Headers],[酵活炊電飯煲特佣 RC-18AMXH(W)]] -> 酵活炊電飯煲特佣 RC-18AMXH(W) | AQ57: =表格1[[#Headers],[嵌入式微波氣炸蒸焗爐特佣 EB-T500APW]] -> 嵌入式微波氣炸蒸焗爐特佣 EB-T500APW | AR57: =表格1[[#Headers],[蒸氣烤焗水波爐特佣 ER-VD7000HK(XK)]] -> 蒸氣烤焗水波爐特佣 ER-VD7000HK(XK) | AS57: =表格1[[#Headers],[TWDT21BU95 ]] -> TWDT21BU95 | AT57: =表格1[[#Headers],[日式洗衣機一特佣 AW-Q800APH(WW)]] -> 日式洗衣機一特佣 AW-Q800APH(WW) | AU57: =表格1[[#Headers],[日式洗衣機二特佣 AW-Q801APH(WW)]] -> 日式洗衣機二特佣 AW-Q801APH(WW) | AV57: =表格1[[#Headers],[三門雪櫃特佣 GR-RM469WE-PGA(B3)]] -> 三門雪櫃特佣 GR-RM469WE-PGA(B3) | AW57: =表格1[[#Headers],[雙門雪櫃一特佣 GR-RB449WE-PMA(57)]] -> 雙門雪櫃一特佣 GR-RB449WE-PMA(57) | AX57: =表格1[[#Headers],[雙門雪櫃一特佣 GR-RB410WE-PMA(06)]] -> 雙門雪櫃一特佣 GR-RB410WE-PMA(06) | AY57: =表格1[[#Headers],[十字門雪櫃 GR-RF698WI]] -> 十字門雪櫃 GR-RF698WI | AZ57: =表格1[[#Headers],[水機 TWP-W2265THK(W)]] -> 水機 TWP-W2265THK(W) | BA57: =表格1[[#Headers],[抽濕機特佣]] -> 抽濕機特佣 | BB57: =表格1[[#Headers],[(Fortress ONLY)TW-T25BZU115MWH(MG) ]] -> (Fortress ONLY)TW-T25BZU115MWH(MG) | BC57: =表格1[[#Headers],[開門紅(三月)]] -> 開門紅(三月) | BD57: =表格1[[#Headers],[開門紅(第一季)]] -> 開門紅(第一季) | BE57: =表格1[[#Headers],[酵活炊電飯煲特佣 RC-18AMXH(W)]] -> 酵活炊電飯煲特佣 RC-18AMXH(W)
A58: 44 | B58: =B57 -> 2026-03 Toshiba | C58: =Total!C51 -> Wendy Wong_3 | D58: =Total!D51 -> Wong Lai Ying | E58: =Total!E51 -> Autopay | F58: =Total!F51 -> Kai Tak RS_1 Sogo | G58: =Total!G51 -> Mar/1,7-8 | H58: =Total!H51 -> 3 | I58: =Total!I51 -> 24 | J58: =Total!J51 -> 60 | ... AF58: =Total!AF51 -> 0 | AG58: =Total!AH51 -> 1753 | AO58: =表格1[[#Headers],[日本飯煲 RC-DS10K/18K]] -> 日本飯煲 RC-DS10K/18K | AP58: =表格1[[#Headers],[酵活炊電飯煲特佣 RC-18AMXH(W)]] -> 酵活炊電飯煲特佣 RC-18AMXH(W) | AQ58: =表格1[[#Headers],[嵌入式微波氣炸蒸焗爐特佣 EB-T500APW]] -> 嵌入式微波氣炸蒸焗爐特佣 EB-T500APW | AR58: =表格1[[#Headers],[蒸氣烤焗水波爐特佣 ER-VD7000HK(XK)]] -> 蒸氣烤焗水波爐特佣 ER-VD7000HK(XK) | AS58: =表格1[[#Headers],[TWDT21BU95 ]] -> TWDT21BU95 | AT58: =表格1[[#Headers],[日式洗衣機一特佣 AW-Q800APH(WW)]] -> 日式洗衣機一特佣 AW-Q800APH(WW) | AU58: =表格1[[#Headers],[日式洗衣機二特佣 AW-Q801APH(WW)]] -> 日式洗衣機二特佣 AW-Q801APH(WW) | AV58: =表格1[[#Headers],[三門雪櫃特佣 GR-RM469WE-PGA(B3)]] -> 三門雪櫃特佣 GR-RM469WE-PGA(B3) | AW58: =表格1[[#Headers],[雙門雪櫃一特佣 GR-RB449WE-PMA(57)]] -> 雙門雪櫃一特佣 GR-RB449WE-PMA(57) | AX58: =表格1[[#Headers],[雙門雪櫃一特佣 GR-RB410WE-PMA(06)]] -> 雙門雪櫃一特佣 GR-RB410WE-PMA(06) | AY58: =表格1[[#Headers],[十字門雪櫃 GR-RF698WI]] -> 十字門雪櫃 GR-RF698WI | AZ58: =表格1[[#Headers],[水機 TWP-W2265THK(W)]] -> 水機 TWP-W2265THK(W) | BA58: =表格1[[#Headers],[抽濕機特佣]] -> 抽濕機特佣 | BB58: =表格1[[#Headers],[(Fortress ONLY)TW-T25BZU115MWH(MG) ]] -> (Fortress ONLY)TW-T25BZU115MWH(MG) | BC58: =表格1[[#Headers],[開門紅(三月)]] -> 開門紅(三月) | BD58: =表格1[[#Headers],[開門紅(第一季)]] -> 開門紅(第一季) | BE58: =表格1[[#Headers],[酵活炊電飯煲特佣 RC-18AMXH(W)]] -> 酵活炊電飯煲特佣 RC-18AMXH(W)
A59: 45 | B59: =B58 -> 2026-03 Toshiba | C59: =Total!C52 -> Anita_2 | D59: =Total!D52 -> Chan Siu Kuen | E59: =Total!E52 -> Autopay | F59: =Total!F52 -> Kai Tak RS_2 Sogo | G59: =Total!G52 -> Mar/14-15 | H59: =Total!H52 -> 2 | I59: =Total!I52 -> 16 | J59: =Total!J52 -> 60 | ... AF59: =Total!AF52 -> 0 | AG59: =Total!AH52 -> 1603 | AO59: =表格1[[#Headers],[日本飯煲 RC-DS10K/18K]] -> 日本飯煲 RC-DS10K/18K | AP59: =表格1[[#Headers],[酵活炊電飯煲特佣 RC-18AMXH(W)]] -> 酵活炊電飯煲特佣 RC-18AMXH(W) | AQ59: =表格1[[#Headers],[嵌入式微波氣炸蒸焗爐特佣 EB-T500APW]] -> 嵌入式微波氣炸蒸焗爐特佣 EB-T500APW | AR59: =表格1[[#Headers],[蒸氣烤焗水波爐特佣 ER-VD7000HK(XK)]] -> 蒸氣烤焗水波爐特佣 ER-VD7000HK(XK) | AS59: =表格1[[#Headers],[TWDT21BU95 ]] -> TWDT21BU95 | AT59: =表格1[[#Headers],[日式洗衣機一特佣 AW-Q800APH(WW)]] -> 日式洗衣機一特佣 AW-Q800APH(WW) | AU59: =表格1[[#Headers],[日式洗衣機二特佣 AW-Q801APH(WW)]] -> 日式洗衣機二特佣 AW-Q801APH(WW) | AV59: =表格1[[#Headers],[三門雪櫃特佣 GR-RM469WE-PGA(B3)]] -> 三門雪櫃特佣 GR-RM469WE-PGA(B3) | AW59: =表格1[[#Headers],[雙門雪櫃一特佣 GR-RB449WE-PMA(57)]] -> 雙門雪櫃一特佣 GR-RB449WE-PMA(57) | AX59: =表格1[[#Headers],[雙門雪櫃一特佣 GR-RB410WE-PMA(06)]] -> 雙門雪櫃一特佣 GR-RB410WE-PMA(06) | AY59: =表格1[[#Headers],[十字門雪櫃 GR-RF698WI]] -> 十字門雪櫃 GR-RF698WI | AZ59: =表格1[[#Headers],[水機 TWP-W2265THK(W)]] -> 水機 TWP-W2265THK(W) | BA59: =表格1[[#Headers],[抽濕機特佣]] -> 抽濕機特佣 | BB59: =表格1[[#Headers],[(Fortress ONLY)TW-T25BZU115MWH(MG) ]] -> (Fortress ONLY)TW-T25BZU115MWH(MG) | BC59: =表格1[[#Headers],[開門紅(三月)]] -> 開門紅(三月) | BD59: =表格1[[#Headers],[開門紅(第一季)]] -> 開門紅(第一季) | BE59: =表格1[[#Headers],[酵活炊電飯煲特佣 RC-18AMXH(W)]] -> 酵活炊電飯煲特佣 RC-18AMXH(W)
A60: 48 | B60: =B59 -> 2026-03 Toshiba | C60: =Total!C55 -> SK | D60: =Total!D55 -> Ip Sau King | E60: =Total!E55 -> Autopay | F60: =Total!F55 -> Tai Koo_1 Apita | G60: =Total!G55 -> Mar/1,7-8,14,21-24,28-29 | H60: =Total!H55 -> 10 | I60: =Total!I55 -> 80 | J60: =Total!J55 -> 60 | ... AF60: =Total!AF55 -> 0 | AG60: =Total!AH55 -> 5744 | AO60: =表格1[[#Headers],[日本飯煲 RC-DS10K/18K]] -> 日本飯煲 RC-DS10K/18K | AP60: =表格1[[#Headers],[酵活炊電飯煲特佣 RC-18AMXH(W)]] -> 酵活炊電飯煲特佣 RC-18AMXH(W) | AQ60: =表格1[[#Headers],[嵌入式微波氣炸蒸焗爐特佣 EB-T500APW]] -> 嵌入式微波氣炸蒸焗爐特佣 EB-T500APW | AR60: =表格1[[#Headers],[蒸氣烤焗水波爐特佣 ER-VD7000HK(XK)]] -> 蒸氣烤焗水波爐特佣 ER-VD7000HK(XK) | AS60: =表格1[[#Headers],[TWDT21BU95 ]] -> TWDT21BU95 | AT60: =表格1[[#Headers],[日式洗衣機一特佣 AW-Q800APH(WW)]] -> 日式洗衣機一特佣 AW-Q800APH(WW) | AU60: =表格1[[#Headers],[日式洗衣機二特佣 AW-Q801APH(WW)]] -> 日式洗衣機二特佣 AW-Q801APH(WW) | AV60: =表格1[[#Headers],[三門雪櫃特佣 GR-RM469WE-PGA(B3)]] -> 三門雪櫃特佣 GR-RM469WE-PGA(B3) | AW60: =表格1[[#Headers],[雙門雪櫃一特佣 GR-RB449WE-PMA(57)]] -> 雙門雪櫃一特佣 GR-RB449WE-PMA(57) | AX60: =表格1[[#Headers],[雙門雪櫃一特佣 GR-RB410WE-PMA(06)]] -> 雙門雪櫃一特佣 GR-RB410WE-PMA(06) | AY60: =表格1[[#Headers],[十字門雪櫃 GR-RF698WI]] -> 十字門雪櫃 GR-RF698WI | AZ60: =表格1[[#Headers],[水機 TWP-W2265THK(W)]] -> 水機 TWP-W2265THK(W) | BA60: =表格1[[#Headers],[抽濕機特佣]] -> 抽濕機特佣 | BB60: =表格1[[#Headers],[(Fortress ONLY)TW-T25BZU115MWH(MG) ]] -> (Fortress ONLY)TW-T25BZU115MWH(MG) | BC60: =表格1[[#Headers],[開門紅(三月)]] -> 開門紅(三月) | BD60: =表格1[[#Headers],[開門紅(第一季)]] -> 開門紅(第一季) | BE60: =表格1[[#Headers],[酵活炊電飯煲特佣 RC-18AMXH(W)]] -> 酵活炊電飯煲特佣 RC-18AMXH(W)
A61: 49 | B61: =B60 -> 2026-03 Toshiba | C61: =Total!C56 -> Tony_3 | D61: =Total!D56 -> Wong Tak Chung | E61: =Total!E56 -> Autopay | F61: =Total!F56 -> Tai Koo_2 Apita | G61: =Total!G56 -> Mar/15 | H61: =Total!H56 -> 1 | I61: =Total!I56 -> 8 | J61: =Total!J56 -> 60 | ... AF61: =Total!AF56 -> 0 | AG61: =Total!AH56 -> 605 | AO61: =表格1[[#Headers],[日本飯煲 RC-DS10K/18K]] -> 日本飯煲 RC-DS10K/18K | AP61: =表格1[[#Headers],[酵活炊電飯煲特佣 RC-18AMXH(W)]] -> 酵活炊電飯煲特佣 RC-18AMXH(W) | AQ61: =表格1[[#Headers],[嵌入式微波氣炸蒸焗爐特佣 EB-T500APW]] -> 嵌入式微波氣炸蒸焗爐特佣 EB-T500APW | AR61: =表格1[[#Headers],[蒸氣烤焗水波爐特佣 ER-VD7000HK(XK)]] -> 蒸氣烤焗水波爐特佣 ER-VD7000HK(XK) | AS61: =表格1[[#Headers],[TWDT21BU95 ]] -> TWDT21BU95 | AT61: =表格1[[#Headers],[日式洗衣機一特佣 AW-Q800APH(WW)]] -> 日式洗衣機一特佣 AW-Q800APH(WW) | AU61: =表格1[[#Headers],[日式洗衣機二特佣 AW-Q801APH(WW)]] -> 日式洗衣機二特佣 AW-Q801APH(WW) | AV61: =表格1[[#Headers],[三門雪櫃特佣 GR-RM469WE-PGA(B3)]] -> 三門雪櫃特佣 GR-RM469WE-PGA(B3) | AW61: =表格1[[#Headers],[雙門雪櫃一特佣 GR-RB449WE-PMA(57)]] -> 雙門雪櫃一特佣 GR-RB449WE-PMA(57) | AX61: =表格1[[#Headers],[雙門雪櫃一特佣 GR-RB410WE-PMA(06)]] -> 雙門雪櫃一特佣 GR-RB410WE-PMA(06) | AY61: =表格1[[#Headers],[十字門雪櫃 GR-RF698WI]] -> 十字門雪櫃 GR-RF698WI | AZ61: =表格1[[#Headers],[水機 TWP-W2265THK(W)]] -> 水機 TWP-W2265THK(W) | BA61: =表格1[[#Headers],[抽濕機特佣]] -> 抽濕機特佣 | BB61: =表格1[[#Headers],[(Fortress ONLY)TW-T25BZU115MWH(MG) ]] -> (Fortress ONLY)TW-T25BZU115MWH(MG) | BC61: =表格1[[#Headers],[開門紅(三月)]] -> 開門紅(三月) | BD61: =表格1[[#Headers],[開門紅(第一季)]] -> 開門紅(第一季) | BE61: =表格1[[#Headers],[酵活炊電飯煲特佣 RC-18AMXH(W)]] -> 酵活炊電飯煲特佣 RC-18AMXH(W)
A62: 53 | B62: =B61 -> 2026-03 Toshiba | C62: =Total!C60 -> Ivy Wong_2 | D62: =Total!D60 -> Wong Wai Chu | E62: =Total!E60 -> Autopay | F62: =Total!F60 -> TSW RS Tung Yuen | G62: =Total!G60 -> Mar/6-9 | H62: =Total!H60 -> 4 | I62: =Total!I60 -> 35.5 | J62: =Total!J60 -> 60 | ... AF62: =Total!AF60 -> 0 | AG62: =Total!AH60 -> 3806 | AO62: =表格1[[#Headers],[日本飯煲 RC-DS10K/18K]] -> 日本飯煲 RC-DS10K/18K | AP62: =表格1[[#Headers],[酵活炊電飯煲特佣 RC-18AMXH(W)]] -> 酵活炊電飯煲特佣 RC-18AMXH(W) | AQ62: =表格1[[#Headers],[嵌入式微波氣炸蒸焗爐特佣 EB-T500APW]] -> 嵌入式微波氣炸蒸焗爐特佣 EB-T500APW | AR62: =表格1[[#Headers],[蒸氣烤焗水波爐特佣 ER-VD7000HK(XK)]] -> 蒸氣烤焗水波爐特佣 ER-VD7000HK(XK) | AS62: =表格1[[#Headers],[TWDT21BU95 ]] -> TWDT21BU95 | AT62: =表格1[[#Headers],[日式洗衣機一特佣 AW-Q800APH(WW)]] -> 日式洗衣機一特佣 AW-Q800APH(WW) | AU62: =表格1[[#Headers],[日式洗衣機二特佣 AW-Q801APH(WW)]] -> 日式洗衣機二特佣 AW-Q801APH(WW) | AV62: =表格1[[#Headers],[三門雪櫃特佣 GR-RM469WE-PGA(B3)]] -> 三門雪櫃特佣 GR-RM469WE-PGA(B3) | AW62: =表格1[[#Headers],[雙門雪櫃一特佣 GR-RB449WE-PMA(57)]] -> 雙門雪櫃一特佣 GR-RB449WE-PMA(57) | AX62: =表格1[[#Headers],[雙門雪櫃一特佣 GR-RB410WE-PMA(06)]] -> 雙門雪櫃一特佣 GR-RB410WE-PMA(06) | AY62: =表格1[[#Headers],[十字門雪櫃 GR-RF698WI]] -> 十字門雪櫃 GR-RF698WI | AZ62: =表格1[[#Headers],[水機 TWP-W2265THK(W)]] -> 水機 TWP-W2265THK(W) | BA62: =表格1[[#Headers],[抽濕機特佣]] -> 抽濕機特佣 | BB62: =表格1[[#Headers],[(Fortress ONLY)TW-T25BZU115MWH(MG) ]] -> (Fortress ONLY)TW-T25BZU115MWH(MG) | BC62: =表格1[[#Headers],[開門紅(三月)]] -> 開門紅(三月) | BD62: =表格1[[#Headers],[開門紅(第一季)]] -> 開門紅(第一季) | BE62: =表格1[[#Headers],[酵活炊電飯煲特佣 RC-18AMXH(W)]] -> 酵活炊電飯煲特佣 RC-18AMXH(W)
A63: 59 | B63: =B62 -> 2026-03 Toshiba | C63: =Total!C66 -> Me | D63: =Total!D66 -> Ngai Kong Ying | E63: =Total!E66 -> Autopay | F63: =Total!F66 -> Megabox Aeon | G63: =Total!G66 -> Mar/1-4,6-10,12-15 | H63: =Total!H66 -> 13 | I63: =Total!I66 -> 104 | J63: =Total!J66 -> 60 | ... AF63: =Total!AF66 -> 0 | AG63: =Total!AH66 -> 11982 | AO63: =表格1[[#Headers],[日本飯煲 RC-DS10K/18K]] -> 日本飯煲 RC-DS10K/18K | AP63: =表格1[[#Headers],[酵活炊電飯煲特佣 RC-18AMXH(W)]] -> 酵活炊電飯煲特佣 RC-18AMXH(W) | AQ63: =表格1[[#Headers],[嵌入式微波氣炸蒸焗爐特佣 EB-T500APW]] -> 嵌入式微波氣炸蒸焗爐特佣 EB-T500APW | AR63: =表格1[[#Headers],[蒸氣烤焗水波爐特佣 ER-VD7000HK(XK)]] -> 蒸氣烤焗水波爐特佣 ER-VD7000HK(XK) | AS63: =表格1[[#Headers],[TWDT21BU95 ]] -> TWDT21BU95 | AT63: =表格1[[#Headers],[日式洗衣機一特佣 AW-Q800APH(WW)]] -> 日式洗衣機一特佣 AW-Q800APH(WW) | AU63: =表格1[[#Headers],[日式洗衣機二特佣 AW-Q801APH(WW)]] -> 日式洗衣機二特佣 AW-Q801APH(WW) | AV63: =表格1[[#Headers],[三門雪櫃特佣 GR-RM469WE-PGA(B3)]] -> 三門雪櫃特佣 GR-RM469WE-PGA(B3) | AW63: =表格1[[#Headers],[雙門雪櫃一特佣 GR-RB449WE-PMA(57)]] -> 雙門雪櫃一特佣 GR-RB449WE-PMA(57) | AX63: =表格1[[#Headers],[雙門雪櫃一特佣 GR-RB410WE-PMA(06)]] -> 雙門雪櫃一特佣 GR-RB410WE-PMA(06) | AY63: =表格1[[#Headers],[十字門雪櫃 GR-RF698WI]] -> 十字門雪櫃 GR-RF698WI | AZ63: =表格1[[#Headers],[水機 TWP-W2265THK(W)]] -> 水機 TWP-W2265THK(W) | BA63: =表格1[[#Headers],[抽濕機特佣]] -> 抽濕機特佣 | BB63: =表格1[[#Headers],[(Fortress ONLY)TW-T25BZU115MWH(MG) ]] -> (Fortress ONLY)TW-T25BZU115MWH(MG) | BC63: =表格1[[#Headers],[開門紅(三月)]] -> 開門紅(三月) | BD63: =表格1[[#Headers],[開門紅(第一季)]] -> 開門紅(第一季) | BE63: =表格1[[#Headers],[酵活炊電飯煲特佣 RC-18AMXH(W)]] -> 酵活炊電飯煲特佣 RC-18AMXH(W)
A64: 60 | B64: =B63 -> 2026-03 Toshiba | C64: =Total!C67 -> Pinky | D64: =Total!D67 -> Cheung Yin Ping | E64: =Total!E67 -> Autopay | F64: =Total!F67 -> Yau Tong Aeon | G64: =Total!G67 -> Mar/1,7-8,14-15 | H64: =Total!H67 -> 5 | I64: =Total!I67 -> 40 | J64: =Total!J67 -> 60 | ... AF64: =Total!AF67 -> 0 | AG64: =Total!AH67 -> 2612 | AO64: =表格1[[#Headers],[日本飯煲 RC-DS10K/18K]] -> 日本飯煲 RC-DS10K/18K | AP64: =表格1[[#Headers],[酵活炊電飯煲特佣 RC-18AMXH(W)]] -> 酵活炊電飯煲特佣 RC-18AMXH(W) | AQ64: =表格1[[#Headers],[嵌入式微波氣炸蒸焗爐特佣 EB-T500APW]] -> 嵌入式微波氣炸蒸焗爐特佣 EB-T500APW | AR64: =表格1[[#Headers],[蒸氣烤焗水波爐特佣 ER-VD7000HK(XK)]] -> 蒸氣烤焗水波爐特佣 ER-VD7000HK(XK) | AS64: =表格1[[#Headers],[TWDT21BU95 ]] -> TWDT21BU95 | AT64: =表格1[[#Headers],[日式洗衣機一特佣 AW-Q800APH(WW)]] -> 日式洗衣機一特佣 AW-Q800APH(WW) | AU64: =表格1[[#Headers],[日式洗衣機二特佣 AW-Q801APH(WW)]] -> 日式洗衣機二特佣 AW-Q801APH(WW) | AV64: =表格1[[#Headers],[三門雪櫃特佣 GR-RM469WE-PGA(B3)]] -> 三門雪櫃特佣 GR-RM469WE-PGA(B3) | AW64: =表格1[[#Headers],[雙門雪櫃一特佣 GR-RB449WE-PMA(57)]] -> 雙門雪櫃一特佣 GR-RB449WE-PMA(57) | AX64: =表格1[[#Headers],[雙門雪櫃一特佣 GR-RB410WE-PMA(06)]] -> 雙門雪櫃一特佣 GR-RB410WE-PMA(06) | AY64: =表格1[[#Headers],[十字門雪櫃 GR-RF698WI]] -> 十字門雪櫃 GR-RF698WI | AZ64: =表格1[[#Headers],[水機 TWP-W2265THK(W)]] -> 水機 TWP-W2265THK(W) | BA64: =表格1[[#Headers],[抽濕機特佣]] -> 抽濕機特佣 | BB64: =表格1[[#Headers],[(Fortress ONLY)TW-T25BZU115MWH(MG) ]] -> (Fortress ONLY)TW-T25BZU115MWH(MG) | BC64: =表格1[[#Headers],[開門紅(三月)]] -> 開門紅(三月) | BD64: =表格1[[#Headers],[開門紅(第一季)]] -> 開門紅(第一季) | BE64: =表格1[[#Headers],[酵活炊電飯煲特佣 RC-18AMXH(W)]] -> 酵活炊電飯煲特佣 RC-18AMXH(W)
A65: 63 | B65: =B64 -> 2026-03 Toshiba | C65: =Total!C70 -> Jenny | D65: =Total!D70 -> Pang Kam Chun | E65: =Total!E70 -> Autopay | F65: =Total!F70 -> Training_2 | G65: =Total!G70 -> Mar/24 | H65: =Total!H70 -> 1 | I65: =Total!I70 -> 7 | J65: =Total!J70 -> 50 | ... AF65: =Total!AF70 -> 0 | AG65: =Total!AH70 -> 350 | AO65: =表格1[[#Headers],[日本飯煲 RC-DS10K/18K]] -> 日本飯煲 RC-DS10K/18K | AP65: =表格1[[#Headers],[酵活炊電飯煲特佣 RC-18AMXH(W)]] -> 酵活炊電飯煲特佣 RC-18AMXH(W) | AQ65: =表格1[[#Headers],[嵌入式微波氣炸蒸焗爐特佣 EB-T500APW]] -> 嵌入式微波氣炸蒸焗爐特佣 EB-T500APW | AR65: =表格1[[#Headers],[蒸氣烤焗水波爐特佣 ER-VD7000HK(XK)]] -> 蒸氣烤焗水波爐特佣 ER-VD7000HK(XK) | AS65: =表格1[[#Headers],[TWDT21BU95 ]] -> TWDT21BU95 | AT65: =表格1[[#Headers],[日式洗衣機一特佣 AW-Q800APH(WW)]] -> 日式洗衣機一特佣 AW-Q800APH(WW) | AU65: =表格1[[#Headers],[日式洗衣機二特佣 AW-Q801APH(WW)]] -> 日式洗衣機二特佣 AW-Q801APH(WW) | AV65: =表格1[[#Headers],[三門雪櫃特佣 GR-RM469WE-PGA(B3)]] -> 三門雪櫃特佣 GR-RM469WE-PGA(B3) | AW65: =表格1[[#Headers],[雙門雪櫃一特佣 GR-RB449WE-PMA(57)]] -> 雙門雪櫃一特佣 GR-RB449WE-PMA(57) | AX65: =表格1[[#Headers],[雙門雪櫃一特佣 GR-RB410WE-PMA(06)]] -> 雙門雪櫃一特佣 GR-RB410WE-PMA(06) | AY65: =表格1[[#Headers],[十字門雪櫃 GR-RF698WI]] -> 十字門雪櫃 GR-RF698WI | AZ65: =表格1[[#Headers],[水機 TWP-W2265THK(W)]] -> 水機 TWP-W2265THK(W) | BA65: =表格1[[#Headers],[抽濕機特佣]] -> 抽濕機特佣 | BB65: =表格1[[#Headers],[(Fortress ONLY)TW-T25BZU115MWH(MG) ]] -> (Fortress ONLY)TW-T25BZU115MWH(MG) | BC65: =表格1[[#Headers],[開門紅(三月)]] -> 開門紅(三月) | BD65: =表格1[[#Headers],[開門紅(第一季)]] -> 開門紅(第一季) | BE65: =表格1[[#Headers],[酵活炊電飯煲特佣 RC-18AMXH(W)]] -> 酵活炊電飯煲特佣 RC-18AMXH(W)
